Workbook
Name anno_CORRENTE: COPIA!$AP$1
Name anno_inizio: COPIA!$AP$1
Name ANNO_SELEZIONATO: COPIA!$AR$1
Name ATTIVO: COPIA!$CD$3:$CI$103
Name AVERE: COPIA!$BE$3:$BE$400
Name avere_grezzo: COPIA!$AP$3:$AP$400
Name bilancio: COPIA!$AJ$3:$AJ$400
Name CLASSIFICAZIONE: COPIA!$AF$3:$AF$400
Name CODICE: COPIA!$AB$3:$AB$400
Name CODICE_BILANCIO: COPIA!$DY$3:$DY$400
Name CONTI_APERTI: COPIA!$CV$2:$CV$401
Name DARE: COPIA!$BD$3:$BD$400
Name dare_grezzo: COPIA!$AO$3:$AO$400
Name DATA: COPIA!$BA$3:$BA$400
Name data_grezzo: COPIA!$AL$3:$AL$400
Name DEN_G: COPIA!$BB$3:$BB$400
Name den_grezzo: COPIA!$AM$3:$AM$400
Name DEN_PDC: COPIA!$AC$3:$AC$400
Name DESCRIZIONE: COPIA!$BC$3:$BC$400
Name dest_grezzo: COPIA!$AK$3:$AK$400
Name DESTINAZIONE: COPIA!$AG$3:$AG$400
Name ECCEDENZA: COPIA!$AE$3:$AE$400
Name ECONOMICO: COPIA!$CD$191:$CI$247
Name ELENCO_CONTI: COPIA!$U$3:$U$401
Name FINE_A_PC: COPIA!$AM$2
Name FINE_AC: COPIA!$AR$2
Name FINE_ANNO_PREC: COPIA!$AJ$2
Name FINE_PERIODO: COPIA!$AP$2
Name FOCUS: OFFSET(COPIA!$CV$2,,,COPIA!$DB$1+1,1)
Name giornale_grezzo: COPIA!$AL$3:$AP$400
Name GIORNI: COPIA!$BF$15:$BF$45
Name INIZIO_A_PC: COPIA!$AO$2
Name INIZIO_AC: COPIA!$AQ$2
Name INIZIO_ANNO_PREC: COPIA!$AI$2
Name LIBRO_GIORNALE: COPIA!$AZ$3:$BE$400
Name MESI: COPIA!$BF$15:$BF$26
Name NASCONDI_RIGHE: COPIA!$BF$200:$BF$400
Name NATURA: COPIA!$AD$3:$AD$400
Name Num._riga: COPIA!$AZ$3:$AZ$400
Name PASSIVO: COPIA!$CD$105:$CI$189
Name PATRIMONIO_REDDITO: COPIA!$AH$3:$AH$400
Name PDC: COPIA!$AB$3:$AJ$400
Name progressivo: COPIA!$EP$3:$EP$400
Name RAGRUPPAMENTO: COPIA!$AI$3:$AI$400
Name RIGHE_TRA_I_PROSPETTI: COPIA!$BF$102:$BF$142
Name TENDINA_GIORNALE: OFFSET(COPIA!$U$3,,,COPIA!$V$1)
Name VALORI_INIZIALI: VALORI_INIZIALI!$B$9:$I$108

Sheet PIANO_DEI_CONTI
D1: PIANO DEI CONTI
D3: FORMA SOCIETARIA | F3: MODALITÀ DI CALCOLO DEL RISULTATO ECONOMICO | I3: RINOMINA I CONTI CON DENOMINAZIONE GENERICA
D4: SOCIETÀ PER AZIONI | F4: CALCOLO AUTOMATICO | I4: =IF(COPIA!A1=1,"1.BANCA X C/C - 2.BANCA Y C/C - 3.BANCA Z C/C","1.BANCA X C/C - 2.BANCA Y C/C - 3.BANCA Z C/C - 4.BANCA X C/VINCOLATO") -> 1.BANCA X C/C - 2.BANCA Y C/C - 3.BANCA Z C/C - 4.BANCA X C/VINCOLATO
D7: =CONCATENATE(B8," - DAL FASCICOLO ALLEGATO AL LIBRO DI TESTO Futuro impresa smart 4 - TE214FA TRAMONTANA") -> QUADRO DEI CONTI DI UN'IMPRESA INDUSTRIALE IN FORMA DI SPA - DAL FASCICOLO ALLEGATO AL LIBRO DI TESTO Futuro impresa smart 4 - TE214FA TRAMONTANA
B8: =IF(COPIA!A1=1," QUADRO DEI CONTI DI UN'IMPRESA COMMERCIALE IN FORMA DI SNC "," QUADRO DEI CONTI DI UN'IMPRESA INDUSTRIALE IN FORMA DI SPA ") -> QUADRO DEI CONTI DI UN'IMPRESA INDUSTRIALE IN FORMA DI SPA | D8: CODICE | E8: DENOMINANZIONE DEL CONTO | F8: NATURA | G8: ECCEDENZA | H8: CLASSIFICAZIONE | I8: DESTINAZIONE | J8: 1
D9: =IFERROR(IF(COPIA!A3<>0,COPIA!A3,""),"") -> 00.00 | E9: =IFERROR(IF(COPIA!B3<>0,COPIA!B3,""),"") -> CREDITI V/SOCI | F9: =IFERROR(IF(COPIA!C3<>0,COPIA!C3,""),"") | G9: =IFERROR(IF(COPIA!D3<>0,COPIA!D3,""),"") | H9: =IF(E9="FONDO SVALUTAZIONE CREDITI","RETTIFICA CREDITI",IFERROR(IF(COPIA!E3<>0,COPIA!E3,""),"")) | I9: =IFERROR(IF(COPIA!F3<>0,COPIA!F3,""),"") | J9: 2
D10: =IFERROR(IF(COPIA!A4<>0,COPIA!A4,""),"") -> 00.01 | E10: =IFERROR(IF(COPIA!B4<>0,COPIA!B4,""),"") -> AZIONISTI C/SOTTOSCRIZIONE | F10: =IFERROR(IF(COPIA!C4<>0,COPIA!C4,""),"") -> F | G10: =IFERROR(IF(COPIA!D4<>0,COPIA!D4,""),"") -> D | H10: =IF(E10="FONDO SVALUTAZIONE CREDITI","RETTIFICA CREDITI",IFERROR(IF(COPIA!E4<>0,COPIA!E4,""),"")) -> CREDITI | I10: =IFERROR(IF(COPIA!F4<>0,COPIA!F4,""),"") -> SP DARE | J10: 3
D11: =IFERROR(IF(COPIA!A5<>0,COPIA!A5,""),"") -> 00.02 | E11: =IFERROR(IF(COPIA!B5<>0,COPIA!B5,""),"") -> AZIONISTI C/VERSAMENTI RICHIAMATI | F11: =IFERROR(IF(COPIA!C5<>0,COPIA!C5,""),"") -> F | G11: =IFERROR(IF(COPIA!D5<>0,COPIA!D5,""),"") -> D | H11: =IF(E11="FONDO SVALUTAZIONE CREDITI","RETTIFICA CREDITI",IFERROR(IF(COPIA!E5<>0,COPIA!E5,""),"")) -> CREDITI | I11: =IFERROR(IF(COPIA!F5<>0,COPIA!F5,""),"") -> SP DARE | J11: =IF(COPIA!A1=1,"",4) -> 4
D12: =IFERROR(IF(COPIA!A6<>0,COPIA!A6,""),"") -> 00.03 | E12: =IFERROR(IF(COPIA!B6<>0,COPIA!B6,""),"") -> AZIONISTI C/REINTEGRO | F12: =IFERROR(IF(COPIA!C6<>0,COPIA!C6,""),"") -> F | G12: =IFERROR(IF(COPIA!D6<>0,COPIA!D6,""),"") -> D | H12: =IF(E12="FONDO SVALUTAZIONE CREDITI","RETTIFICA CREDITI",IFERROR(IF(COPIA!E6<>0,COPIA!E6,""),"")) -> CREDITI | I12: =IFERROR(IF(COPIA!F6<>0,COPIA!F6,""),"") -> SP DARE | K12: NOME DEI SOCI
D13: =IFERROR(IF(COPIA!A7<>0,COPIA!A7,""),"") -> 01.00 | E13: =IFERROR(IF(COPIA!B7<>0,COPIA!B7,""),"") -> IMMOBILIZZAZIONI IMMATERIALI | F13: =IFERROR(IF(COPIA!C7<>0,COPIA!C7,""),"") | G13: =IFERROR(IF(COPIA!D7<>0,COPIA!D7,""),"") | H13: =IF(E13="FONDO SVALUTAZIONE CREDITI","RETTIFICA CREDITI",IFERROR(IF(COPIA!E7<>0,COPIA!E7,""),"")) | I13: =IFERROR(IF(COPIA!F7<>0,COPIA!F7,""),"") | J13: A
D14: =IFERROR(IF(COPIA!A8<>0,COPIA!A8,""),"") -> 01.01 | E14: =IFERROR(IF(COPIA!B8<>0,COPIA!B8,""),"") -> COSTI DI IMPIANTO | F14: =IFERROR(IF(COPIA!C8<>0,COPIA!C8,""),"") -> E | G14: =IFERROR(IF(COPIA!D8<>0,COPIA!D8,""),"") -> D | H14: =IF(E14="FONDO SVALUTAZIONE CREDITI","RETTIFICA CREDITI",IFERROR(IF(COPIA!E8<>0,COPIA!E8,""),"")) -> COSTI PLURIENNALI | I14: =IFERROR(IF(COPIA!F8<>0,COPIA!F8,""),"") -> SP DARE | J14: B
D15: =IFERROR(IF(COPIA!A9<>0,COPIA!A9,""),"") -> 01.02 | E15: =IFERROR(IF(COPIA!B9<>0,COPIA!B9,""),"") -> COSTI DI AMPLIAMENTO | F15: =IFERROR(IF(COPIA!C9<>0,COPIA!C9,""),"") -> E | G15: =IFERROR(IF(COPIA!D9<>0,COPIA!D9,""),"") -> D | H15: =IF(E15="FONDO SVALUTAZIONE CREDITI","RETTIFICA CREDITI",IFERROR(IF(COPIA!E9<>0,COPIA!E9,""),"")) -> COSTI PLURIENNALI | I15: =IFERROR(IF(COPIA!F9<>0,COPIA!F9,""),"") -> SP DARE | J15: C
D16: =IFERROR(IF(COPIA!A10<>0,COPIA!A10,""),"") -> 01.03 | E16: =IFERROR(IF(COPIA!B10<>0,COPIA!B10,""),"") -> COSTI DI SVILUPPO | F16: =IFERROR(IF(COPIA!C10<>0,COPIA!C10,""),"") -> E | G16: =IFERROR(IF(COPIA!D10<>0,COPIA!D10,""),"") -> D | H16: =IF(E16="FONDO SVALUTAZIONE CREDITI","RETTIFICA CREDITI",IFERROR(IF(COPIA!E10<>0,COPIA!E10,""),"")) -> COSTI PLURIENNALI | I16: =IFERROR(IF(COPIA!F10<>0,COPIA!F10,""),"") -> SP DARE | J16: D
D17: =IFERROR(IF(COPIA!A11<>0,COPIA!A11,""),"") -> 01.04 | E17: =IFERROR(IF(COPIA!B11<>0,COPIA!B11,""),"") -> BREVETTI | F17: =IFERROR(IF(COPIA!C11<>0,COPIA!C11,""),"") -> E | G17: =IFERROR(IF(COPIA!D11<>0,COPIA!D11,""),"") -> D | H17: =IF(E17="FONDO SVALUTAZIONE CREDITI","RETTIFICA CREDITI",IFERROR(IF(COPIA!E11<>0,COPIA!E11,""),"")) -> COSTI PLURIENNALI | I17: =IFERROR(IF(COPIA!F11<>0,COPIA!F11,""),"") -> SP DARE
D18: =IFERROR(IF(COPIA!A12<>0,COPIA!A12,""),"") -> 01.05 | E18: =IFERROR(IF(COPIA!B12<>0,COPIA!B12,""),"") -> SOFTWARE | F18: =IFERROR(IF(COPIA!C12<>0,COPIA!C12,""),"") -> E | G18: =IFERROR(IF(COPIA!D12<>0,COPIA!D12,""),"") -> D | H18: =IF(E18="FONDO SVALUTAZIONE CREDITI","RETTIFICA CREDITI",IFERROR(IF(COPIA!E12<>0,COPIA!E12,""),"")) -> COSTI PLURIENNALI | I18: =IFERROR(IF(COPIA!F12<>0,COPIA!F12,""),"") -> SP DARE
D19: =IFERROR(IF(COPIA!A13<>0,COPIA!A13,""),"") -> 01.06 | E19: =IFERROR(IF(COPIA!B13<>0,COPIA!B13,""),"") -> AVVIAMENTO | F19: =IFERROR(IF(COPIA!C13<>0,COPIA!C13,""),"") -> E | G19: =IFERROR(IF(COPIA!D13<>0,COPIA!D13,""),"") -> D | H19: =IF(E19="FONDO SVALUTAZIONE CREDITI","RETTIFICA CREDITI",IFERROR(IF(COPIA!E13<>0,COPIA!E13,""),"")) -> COSTI PLURIENNALI | I19: =IFERROR(IF(COPIA!F13<>0,COPIA!F13,""),"") -> SP DARE
D20: =IFERROR(IF(COPIA!A14<>0,COPIA!A14,""),"") -> 01.11 | E20: =IFERROR(IF(COPIA!B14<>0,COPIA!B14,""),"") -> FONDO AMMORTAMENTO COSTI DI IMPIANTO | F20: =IFERROR(IF(COPIA!C14<>0,COPIA!C14,""),"") -> E | G20: =IFERROR(IF(COPIA!D14<>0,COPIA!D14,""),"") -> A | H20: =IF(E20="FONDO SVALUTAZIONE CREDITI","RETTIFICA CREDITI",IFERROR(IF(COPIA!E14<>0,COPIA!E14,""),"")) -> RETTIFICHE COSTI PLURIENNALI | I20: =IFERROR(IF(COPIA!F14<>0,COPIA!F14,""),"") -> SP AVERE
D21: =IFERROR(IF(COPIA!A15<>0,COPIA!A15,""),"") -> 01.12 | E21: =IFERROR(IF(COPIA!B15<>0,COPIA!B15,""),"") -> FONDO AMMORTAMENTO COSTI DI AMPLIAMENTO | F21: =IFERROR(IF(COPIA!C15<>0,COPIA!C15,""),"") -> E | G21: =IFERROR(IF(COPIA!D15<>0,COPIA!D15,""),"") -> A | H21: =IF(E21="FONDO SVALUTAZIONE CREDITI","RETTIFICA CREDITI",IFERROR(IF(COPIA!E15<>0,COPIA!E15,""),"")) -> RETTIFICHE COSTI PLURIENNALI | I21: =IFERROR(IF(COPIA!F15<>0,COPIA!F15,""),"") -> SP AVERE
D22: =IFERROR(IF(COPIA!A16<>0,COPIA!A16,""),"") -> 01.13 | E22: =IFERROR(IF(COPIA!B16<>0,COPIA!B16,""),"") -> FONDO AMMORTAMENTO COSTI DI SVILUPPO | F22: =IFERROR(IF(COPIA!C16<>0,COPIA!C16,""),"") -> E | G22: =IFERROR(IF(COPIA!D16<>0,COPIA!D16,""),"") -> A | H22: =IF(E22="FONDO SVALUTAZIONE CREDITI","RETTIFICA CREDITI",IFERROR(IF(COPIA!E16<>0,COPIA!E16,""),"")) -> RETTIFICHE COSTI PLURIENNALI | I22: =IFERROR(IF(COPIA!F16<>0,COPIA!F16,""),"") -> SP AVERE
D23: =IFERROR(IF(COPIA!A17<>0,COPIA!A17,""),"") -> 01.14 | E23: =IFERROR(IF(COPIA!B17<>0,COPIA!B17,""),"") -> FONDO AMMORTAMENTO BREVETTI | F23: =IFERROR(IF(COPIA!C17<>0,COPIA!C17,""),"") -> E | G23: =IFERROR(IF(COPIA!D17<>0,COPIA!D17,""),"") -> A | H23: =IF(E23="FONDO SVALUTAZIONE CREDITI","RETTIFICA CREDITI",IFERROR(IF(COPIA!E17<>0,COPIA!E17,""),"")) -> RETTIFICHE COSTI PLURIENNALI | I23: =IFERROR(IF(COPIA!F17<>0,COPIA!F17,""),"") -> SP AVERE
D24: =IFERROR(IF(COPIA!A18<>0,COPIA!A18,""),"") -> 01.15 | E24: =IFERROR(IF(COPIA!B18<>0,COPIA!B18,""),"") -> FONDO AMMORTAMENTO SOFTWARE | F24: =IFERROR(IF(COPIA!C18<>0,COPIA!C18,""),"") -> E | G24: =IFERROR(IF(COPIA!D18<>0,COPIA!D18,""),"") -> A | H24: =IF(E24="FONDO SVALUTAZIONE CREDITI","RETTIFICA CREDITI",IFERROR(IF(COPIA!E18<>0,COPIA!E18,""),"")) -> RETTIFICHE COSTI PLURIENNALI | I24: =IFERROR(IF(COPIA!F18<>0,COPIA!F18,""),"") -> SP AVERE
D25: =IFERROR(IF(COPIA!A19<>0,COPIA!A19,""),"") -> 01.16 | E25: =IFERROR(IF(COPIA!B19<>0,COPIA!B19,""),"") -> FONDO AMMORTAMENTO AVVIAMENTO | F25: =IFERROR(IF(COPIA!C19<>0,COPIA!C19,""),"") -> E | G25: =IFERROR(IF(COPIA!D19<>0,COPIA!D19,""),"") -> A | H25: =IF(E25="FONDO SVALUTAZIONE CREDITI","RETTIFICA CREDITI",IFERROR(IF(COPIA!E19<>0,COPIA!E19,""),"")) -> RETTIFICHE COSTI PLURIENNALI | I25: =IFERROR(IF(COPIA!F19<>0,COPIA!F19,""),"") -> SP AVERE
D26: =IFERROR(IF(COPIA!A20<>0,COPIA!A20,""),"") -> 01.30 | E26: =IFERROR(IF(COPIA!B20<>0,COPIA!B20,""),"") -> IMMOBILIZZAZIONI IMMATERIALI IN CORSO | F26: =IFERROR(IF(COPIA!C20<>0,COPIA!C20,""),"") -> E | G26: =IFERROR(IF(COPIA!D20<>0,COPIA!D20,""),"") -> D | H26: =IF(E26="FONDO SVALUTAZIONE CREDITI","RETTIFICA CREDITI",IFERROR(IF(COPIA!E20<>0,COPIA!E20,""),"")) -> COSTI PLURIENNALI | I26: =IFERROR(IF(COPIA!F20<>0,COPIA!F20,""),"") -> SP DARE
D27: =IFERROR(IF(COPIA!A21<>0,COPIA!A21,""),"") -> 01.31 | E27: =IFERROR(IF(COPIA!B21<>0,COPIA!B21,""),"") -> FORNITORI IMMOBILIZZAZIONI IMMATERIALI C/ACCONTI | F27: =IFERROR(IF(COPIA!C21<>0,COPIA!C21,""),"") -> F | G27: =IFERROR(IF(COPIA!D21<>0,COPIA!D21,""),"") -> D | H27: =IF(E27="FONDO SVALUTAZIONE CREDITI","RETTIFICA CREDITI",IFERROR(IF(COPIA!E21<>0,COPIA!E21,""),"")) -> CREDITI | I27: =IFERROR(IF(COPIA!F21<>0,COPIA!F21,""),"") -> SP DARE
D28: =IFERROR(IF(COPIA!A22<>0,COPIA!A22,""),"") -> 02.00 | E28: =IFERROR(IF(COPIA!B22<>0,COPIA!B22,""),"") -> IMMOBILIZZAZIONI MATERIALI | F28: =IFERROR(IF(COPIA!C22<>0,COPIA!C22,""),"") | G28: =IFERROR(IF(COPIA!D22<>0,COPIA!D22,""),"") | H28: =IF(E28="FONDO SVALUTAZIONE CREDITI","RETTIFICA CREDITI",IFERROR(IF(COPIA!E22<>0,COPIA!E22,""),"")) | I28: =IFERROR(IF(COPIA!F22<>0,COPIA!F22,""),"")
... D220: =IFERROR(IF(COPIA!A214<>0,COPIA!A214,""),"") -> 21.12 | E220: =IFERROR(IF(COPIA!B214<>0,COPIA!B214,""),"") -> PRODOTTI FINITI C/RIMANENZE FINALI | F220: =IFERROR(IF(COPIA!C214<>0,COPIA!C214,""),"") -> E | G220: =IFERROR(IF(COPIA!D214<>0,COPIA!D214,""),"") -> A | H220: =IF(E220="FONDO SVALUTAZIONE CREDITI","RETTIFICA CREDITI",IFERROR(IF(COPIA!E214<>0,COPIA!E214,""),"")) -> RETTIFICHE COSTI D'ESERCIZIO | I220: =IFERROR(IF(COPIA!F214<>0,COPIA!F214,""),"") -> SE AVERE
D221: =IFERROR(IF(COPIA!A215<>0,COPIA!A215,""),"") -> 30.00 | E221: =IFERROR(IF(COPIA!B215<>0,COPIA!B215,""),"") -> COSTI DELLE MATERIE | F221: =IFERROR(IF(COPIA!C215<>0,COPIA!C215,""),"") | G221: =IFERROR(IF(COPIA!D215<>0,COPIA!D215,""),"") | H221: =IF(E221="FONDO SVALUTAZIONE CREDITI","RETTIFICA CREDITI",IFERROR(IF(COPIA!E215<>0,COPIA!E215,""),"")) | I221: =IFERROR(IF(COPIA!F215<>0,COPIA!F215,""),"") | K221: 3
D222: =IFERROR(IF(COPIA!A216<>0,COPIA!A216,""),"") -> 30.01 | E222: =IFERROR(IF(COPIA!B216<>0,COPIA!B216,""),"") -> MATERIE PRIME C/ACQUISTI | F222: =IFERROR(IF(COPIA!C216<>0,COPIA!C216,""),"") -> E | G222: =IFERROR(IF(COPIA!D216<>0,COPIA!D216,""),"") -> D | H222: =IF(E222="FONDO SVALUTAZIONE CREDITI","RETTIFICA CREDITI",IFERROR(IF(COPIA!E216<>0,COPIA!E216,""),"")) -> COSTI D'ESERCIZIO | I222: =IFERROR(IF(COPIA!F216<>0,COPIA!F216,""),"") -> SE DARE
D223: =IFERROR(IF(COPIA!A217<>0,COPIA!A217,""),"") -> 30.02 | E223: =IFERROR(IF(COPIA!B217<>0,COPIA!B217,""),"") -> MATERIE SUSSIDIARIE C/ACQUISTI | F223: =IFERROR(IF(COPIA!C217<>0,COPIA!C217,""),"") -> E | G223: =IFERROR(IF(COPIA!D217<>0,COPIA!D217,""),"") -> D | H223: =IF(E223="FONDO SVALUTAZIONE CREDITI","RETTIFICA CREDITI",IFERROR(IF(COPIA!E217<>0,COPIA!E217,""),"")) -> COSTI D'ESERCIZIO | I223: =IFERROR(IF(COPIA!F217<>0,COPIA!F217,""),"") -> SE DARE
D224: =IFERROR(IF(COPIA!A218<>0,COPIA!A218,""),"") -> 30.03 | E224: =IFERROR(IF(COPIA!B218<>0,COPIA!B218,""),"") -> MATERIE DI CONSUMO C/ACQUISTI | F224: =IFERROR(IF(COPIA!C218<>0,COPIA!C218,""),"") -> E | G224: =IFERROR(IF(COPIA!D218<>0,COPIA!D218,""),"") -> D | H224: =IF(E224="FONDO SVALUTAZIONE CREDITI","RETTIFICA CREDITI",IFERROR(IF(COPIA!E218<>0,COPIA!E218,""),"")) -> COSTI D'ESERCIZIO | I224: =IFERROR(IF(COPIA!F218<>0,COPIA!F218,""),"") -> SE DARE
D225: =IFERROR(IF(COPIA!A219<>0,COPIA!A219,""),"") -> 30.04 | E225: =IFERROR(IF(COPIA!B219<>0,COPIA!B219,""),"") -> MATERIE C/APPORTI | F225: =IFERROR(IF(COPIA!C219<>0,COPIA!C219,""),"") -> E | G225: =IFERROR(IF(COPIA!D219<>0,COPIA!D219,""),"") -> D | H225: =IF(E225="FONDO SVALUTAZIONE CREDITI","RETTIFICA CREDITI",IFERROR(IF(COPIA!E219<>0,COPIA!E219,""),"")) -> COSTI D'ESERCIZIO | I225: =IFERROR(IF(COPIA!F219<>0,COPIA!F219,""),"") -> SE DARE
D226: =IFERROR(IF(COPIA!A220<>0,COPIA!A220,""),"") -> 30.10 | E226: =IFERROR(IF(COPIA!B220<>0,COPIA!B220,""),"") -> RESI SU ACQUISTI | F226: =IFERROR(IF(COPIA!C220<>0,COPIA!C220,""),"") -> E | G226: =IFERROR(IF(COPIA!D220<>0,COPIA!D220,""),"") -> A | H226: =IF(E226="FONDO SVALUTAZIONE CREDITI","RETTIFICA CREDITI",IFERROR(IF(COPIA!E220<>0,COPIA!E220,""),"")) -> RETTIFICHE COSTI D'ESERCIZIO | I226: =IFERROR(IF(COPIA!F220<>0,COPIA!F220,""),"") -> SE AVERE
D227: =IFERROR(IF(COPIA!A221<>0,COPIA!A221,""),"") -> 30.11 | E227: =IFERROR(IF(COPIA!B221<>0,COPIA!B221,""),"") -> RIBASSI E ABBUONI ATTIVI | F227: =IFERROR(IF(COPIA!C221<>0,COPIA!C221,""),"") -> E | G227: =IFERROR(IF(COPIA!D221<>0,COPIA!D221,""),"") -> A | H227: =IF(E227="FONDO SVALUTAZIONE CREDITI","RETTIFICA CREDITI",IFERROR(IF(COPIA!E221<>0,COPIA!E221,""),"")) -> RETTIFICHE COSTI D'ESERCIZIO | I227: =IFERROR(IF(COPIA!F221<>0,COPIA!F221,""),"") -> SE AVERE
D228: =IFERROR(IF(COPIA!A222<>0,COPIA!A222,""),"") -> 30.12 | E228: =IFERROR(IF(COPIA!B222<>0,COPIA!B222,""),"") -> PREMI SU ACQUISTI | F228: =IFERROR(IF(COPIA!C222<>0,COPIA!C222,""),"") -> E | G228: =IFERROR(IF(COPIA!D222<>0,COPIA!D222,""),"") -> A | H228: =IF(E228="FONDO SVALUTAZIONE CREDITI","RETTIFICA CREDITI",IFERROR(IF(COPIA!E222<>0,COPIA!E222,""),"")) -> RETTIFICHE COSTI D'ESERCIZIO | I228: =IFERROR(IF(COPIA!F222<>0,COPIA!F222,""),"") -> SE AVERE
D229: =IFERROR(IF(COPIA!A223<>0,COPIA!A223,""),"") -> 31.00 | E229: =IFERROR(IF(COPIA!B223<>0,COPIA!B223,""),"") -> COSTI PER SERVIZI | F229: =IFERROR(IF(COPIA!C223<>0,COPIA!C223,""),"") | G229: =IFERROR(IF(COPIA!D223<>0,COPIA!D223,""),"") | H229: =IF(E229="FONDO SVALUTAZIONE CREDITI","RETTIFICA CREDITI",IFERROR(IF(COPIA!E223<>0,COPIA!E223,""),"")) | I229: =IFERROR(IF(COPIA!F223<>0,COPIA!F223,""),"")
D230: =IFERROR(IF(COPIA!A224<>0,COPIA!A224,""),"") -> 31.01 | E230: =IFERROR(IF(COPIA!B224<>0,COPIA!B224,""),"") -> COSTI DI TRASPORTO | F230: =IFERROR(IF(COPIA!C224<>0,COPIA!C224,""),"") -> E | G230: =IFERROR(IF(COPIA!D224<>0,COPIA!D224,""),"") -> D | H230: =IF(E230="FONDO SVALUTAZIONE CREDITI","RETTIFICA CREDITI",IFERROR(IF(COPIA!E224<>0,COPIA!E224,""),"")) -> COSTI D'ESERCIZIO | I230: =IFERROR(IF(COPIA!F224<>0,COPIA!F224,""),"") -> SE DARE
D231: =IFERROR(IF(COPIA!A225<>0,COPIA!A225,""),"") -> 31.02 | E231: =IFERROR(IF(COPIA!B225<>0,COPIA!B225,""),"") -> COSTI PER ENERGIA | F231: =IFERROR(IF(COPIA!C225<>0,COPIA!C225,""),"") -> E | G231: =IFERROR(IF(COPIA!D225<>0,COPIA!D225,""),"") -> D | H231: =IF(E231="FONDO SVALUTAZIONE CREDITI","RETTIFICA CREDITI",IFERROR(IF(COPIA!E225<>0,COPIA!E225,""),"")) -> COSTI D'ESERCIZIO | I231: =IFERROR(IF(COPIA!F225<>0,COPIA!F225,""),"") -> SE DARE
D232: =IFERROR(IF(COPIA!A226<>0,COPIA!A226,""),"") -> 31.03 | E232: =IFERROR(IF(COPIA!B226<>0,COPIA!B226,""),"") -> PUBBLICITÀ | F232: =IFERROR(IF(COPIA!C226<>0,COPIA!C226,""),"") -> E | G232: =IFERROR(IF(COPIA!D226<>0,COPIA!D226,""),"") -> D | H232: =IF(E232="FONDO SVALUTAZIONE CREDITI","RETTIFICA CREDITI",IFERROR(IF(COPIA!E226<>0,COPIA!E226,""),"")) -> COSTI D'ESERCIZIO | I232: =IFERROR(IF(COPIA!F226<>0,COPIA!F226,""),"") -> SE DARE
D233: =IFERROR(IF(COPIA!A227<>0,COPIA!A227,""),"") -> 31.04 | E233: =IFERROR(IF(COPIA!B227<>0,COPIA!B227,""),"") -> CONSULENZE | F233: =IFERROR(IF(COPIA!C227<>0,COPIA!C227,""),"") -> E | G233: =IFERROR(IF(COPIA!D227<>0,COPIA!D227,""),"") -> D | H233: =IF(E233="FONDO SVALUTAZIONE CREDITI","RETTIFICA CREDITI",IFERROR(IF(COPIA!E227<>0,COPIA!E227,""),"")) -> COSTI D'ESERCIZIO | I233: =IFERROR(IF(COPIA!F227<>0,COPIA!F227,""),"") -> SE DARE
... D399: =IFERROR(IF(COPIA!A393<>0,COPIA!A393,""),"") | E399: =IFERROR(IF(COPIA!B393<>0,COPIA!B393,""),"") | F399: =IFERROR(IF(COPIA!C393<>0,COPIA!C393,""),"") | G399: =IFERROR(IF(COPIA!D393<>0,COPIA!D393,""),"") | H399: =IF(E399="FONDO SVALUTAZIONE CREDITI","RETTIFICA CREDITI",IFERROR(IF(COPIA!E393<>0,COPIA!E393,""),"")) | I399: =IFERROR(IF(COPIA!F393<>0,COPIA!F393,""),"")

Sheet LIBRO_GIORNALE
B1: LIBRO GIORNALE | K1: =IF(COPIA!AL1=1,"esercizio n",IF(COPIA!AL1=2,"esercizio n+1",IF(COPIA!AL1=3,"esercizio n+2",IF(COPIA!AL1=4,"esercizio n+3",IF(COPIA!AL1=5,"esercizio n+4",IF(COPIA!AL1=6,"esercizio n+5","")))))) -> esercizio n | O1: =INDEX($M$11:$N$210,MATCH(MAX($M$11:$M$308),$M$11:$M$210,0),2) -> 0
B2: SCEGLI LA VERSIONE | E2: CONTI SUDDIVISI PER RAGGRUPPAMENTO | F2: =IF(COPIA!CO1=0,"",CONCATENATE("Articoli registrati: ",COUNTIFS(K11:K308,"="&0))) | G2: TOT. DARE | H2: TOT.AVERE | K2: =IF(COPIA!CO1=0,"",IF(AND(COPIA!$I$1=1,VALORI_INIZIALI!H4<>VALORI_INIZIALI!I4),"I valori inziali non bilanciano.",IF(AND(COPIA!$I$1=1,VALORI_INIZIALI!H4=VALORI_INIZIALI!I4,VALORI_INIZIALI!$H$4>0,VALORI_INIZIALI!$I$4>0),"Sono presenti valori iniziali.",IF(AND(COPIA!$I$1=2,OR(VALORI_INIZIALI!$H$4>0,VALORI_INIZIALI!$I$4>0)),"Sono presenti valori iniziali.","Non sono presenti valori iniziali.")))) | O2: =IFERROR(INDEX($M$11:$N$210,MATCH(MAX($M$11:$M$308)-1,$M$11:$M$210,0),2),0) -> 0
B3: Desktop: Office | E3: =IF(INDIRECT(ADDRESS(3,2,,,))="Cloud: Office 365","VERSIONE OFFICE 365","") | F3: =COPIA!FG1 | G3: =K1 -> esercizio n
B4: Periodo di riferimento dei prospetti | F4: =K2 | G4: =ROUND(SUMIFS(INDIRECT(CONCATENATE(ADDRESS(11,7,,,),":",ADDRESS(210,7,,,))),INDIRECT(CONCATENATE(ADDRESS(11,4,,,),":",ADDRESS(210,4,,,))),"<="&FINE_AC,INDIRECT(CONCATENATE(ADDRESS(11,4,,,),":",ADDRESS(210,4,,,))),">="&INIZIO_AC),2) -> 0 | H4: =ROUND(SUMIFS(INDIRECT(CONCATENATE(ADDRESS(11,8,,,),":",ADDRESS(210,8,,,))),INDIRECT(CONCATENATE(ADDRESS(11,4,,,),":",ADDRESS(210,4,,,))),"<="&FINE_AC,INDIRECT(CONCATENATE(ADDRESS(11,4,,,),":",ADDRESS(210,4,,,))),">="&INIZIO_AC),2) -> 0
B5: 31 | C5: 12 | D5: N | E5: =IF(INDIRECT(ADDRESS(3,2,,,))<>"Cloud: Office 365","ATTIVA LA VERSIONE ONLINE","") -> ATTIVA LA VERSIONE ONLINE
B6: gg | C6: mm | D6: aa | F6: DELIMITAZIONE ARTICOLO ATTIVATA | G6: Nascondi riga dalla n. | H6: ATTIVA
B7: PIANO DEI CONTI SELEZIONATO | F7: STUDENTE | G7: ATTIVITÀ
B8: =IF(INDIRECT(ADDRESS(4,4,,,"PIANO_DEI_CONTI"))="Adatta ad una S.r.l. solo alcuni dei conti della S.p.A.","Società a responsabilità limitata",INDIRECT(ADDRESS(4,4,,,"PIANO_DEI_CONTI"))) -> SOCIETÀ PER AZIONI
E9: . | L9: =L10+5 -> 2031
B10: Codice | C10: Nr. riga | D10: DATA | E10: DENOMINAZIONE DEI CONTI | F10: DESCRIZIONE | G10: DARE | H10: AVERE | L10: =COPIA!$AP$1 -> 2026
B11: =IF(INDIRECT(ADDRESS(ROW(),4,,,))="","",IFERROR(INDEX(PDC,MATCH(INDIRECT(ADDRESS(ROW(),5,,,)),DEN_PDC,0),1),0)) | C11: =IF(INDIRECT(ADDRESS(ROW(),5,,,))<>"",ROW()-10,"") | K11: =IF(IF(COPIA!$R$1=TRUE,IF(OR(G11<>0,H11<>0),ROUND(SUM(G$11:G11),2)-ROUND(SUM(H$11:H11),2),""),"")<>0,"",0) | L11: =IF(INDIRECT(ADDRESS(ROW(),4,4,,))<>"",YEAR(INDIRECT(ADDRESS(ROW(),4,4,,))),0) -> 0 | M11: =IFERROR(IF(AND(INDIRECT(ADDRESS(ROW(),4,,,))<=COPIA!$DA$1,K11=0,COPIA!$BF$1>1,ROW()-10<COPIA!$BF$1-1),MAX($M$10:M10)+1,IF(AND(INDIRECT(ADDRESS(ROW(),4,,,))<=COPIA!$DA$1,K11=0,COPIA!$BF$1=1),MAX($M$10:M10)+1,0)),0) -> 0 | N11: =IF(AND(COPIA!$BF$1=1,M11<>0),ROW()-10,IF(AND(COPIA!$BF$1>1,ROW()-10>COPIA!$BF$1,M11<>0),0,IF(AND(COPIA!$BF$1>1,ROW()-10<=COPIA!$BF$1,M11<>0),ROW()-10,0))) -> 0 | O11: =IF(AND($O$1=0,ROW()-10<=$O$2),MAX($O$10:O10)+1,IF(AND(ROW()-10>$O$2,ROW()-10<=$O$1),ROW()-10,0)) -> 0 | P11: =IF(O11>0,MAX($P$10:P10)+1,0) -> 0
B12: =IF(INDIRECT(ADDRESS(ROW(),4,,,))="","",IFERROR(INDEX(PDC,MATCH(INDIRECT(ADDRESS(ROW(),5,,,)),DEN_PDC,0),1),0)) | C12: =IF(INDIRECT(ADDRESS(ROW(),5,,,))<>"",ROW()-10,"") | K12: =IF(IF(COPIA!$R$1=TRUE,IF(OR(G12<>0,H12<>0),ROUND(SUM(G$11:G12),2)-ROUND(SUM(H$11:H12),2),""),"")<>0,"",0) | L12: =IF(INDIRECT(ADDRESS(ROW(),4,4,,))<>"",YEAR(INDIRECT(ADDRESS(ROW(),4,4,,))),0) -> 0 | M12: =IFERROR(IF(AND(INDIRECT(ADDRESS(ROW(),4,,,))<=COPIA!$DA$1,K12=0,COPIA!$BF$1>1,ROW()-10<COPIA!$BF$1-1),MAX($M$10:M11)+1,IF(AND(INDIRECT(ADDRESS(ROW(),4,,,))<=COPIA!$DA$1,K12=0,COPIA!$BF$1=1),MAX($M$10:M11)+1,0)),0) -> 0 | N12: =IF(AND(COPIA!$BF$1=1,M12<>0),ROW()-10,IF(AND(COPIA!$BF$1>1,ROW()-10>COPIA!$BF$1,M12<>0),0,IF(AND(COPIA!$BF$1>1,ROW()-10<=COPIA!$BF$1,M12<>0),ROW()-10,0))) -> 0 | O12: =IF(AND($O$1=0,ROW()-10<=$O$2),MAX($O$10:O11)+1,IF(AND(ROW()-10>$O$2,ROW()-10<=$O$1),ROW()-10,0)) -> 0 | P12: =IF(O12>0,MAX($P$10:P11)+1,0) -> 0
B13: =IF(INDIRECT(ADDRESS(ROW(),4,,,))="","",IFERROR(INDEX(PDC,MATCH(INDIRECT(ADDRESS(ROW(),5,,,)),DEN_PDC,0),1),0)) | C13: =IF(INDIRECT(ADDRESS(ROW(),5,,,))<>"",ROW()-10,"") | K13: =IF(IF(COPIA!$R$1=TRUE,IF(OR(G13<>0,H13<>0),ROUND(SUM(G$11:G13),2)-ROUND(SUM(H$11:H13),2),""),"")<>0,"",0) | L13: =IF(INDIRECT(ADDRESS(ROW(),4,4,,))<>"",YEAR(INDIRECT(ADDRESS(ROW(),4,4,,))),0) -> 0 | M13: =IFERROR(IF(AND(INDIRECT(ADDRESS(ROW(),4,,,))<=COPIA!$DA$1,K13=0,COPIA!$BF$1>1,ROW()-10<COPIA!$BF$1-1),MAX($M$10:M12)+1,IF(AND(INDIRECT(ADDRESS(ROW(),4,,,))<=COPIA!$DA$1,K13=0,COPIA!$BF$1=1),MAX($M$10:M12)+1,0)),0) -> 0 | N13: =IF(AND(COPIA!$BF$1=1,M13<>0),ROW()-10,IF(AND(COPIA!$BF$1>1,ROW()-10>COPIA!$BF$1,M13<>0),0,IF(AND(COPIA!$BF$1>1,ROW()-10<=COPIA!$BF$1,M13<>0),ROW()-10,0))) -> 0 | O13: =IF(AND($O$1=0,ROW()-10<=$O$2),MAX($O$10:O12)+1,IF(AND(ROW()-10>$O$2,ROW()-10<=$O$1),ROW()-10,0)) -> 0 | P13: =IF(O13>0,MAX($P$10:P12)+1,0) -> 0
B14: =IF(INDIRECT(ADDRESS(ROW(),4,,,))="","",IFERROR(INDEX(PDC,MATCH(INDIRECT(ADDRESS(ROW(),5,,,)),DEN_PDC,0),1),0)) | C14: =IF(INDIRECT(ADDRESS(ROW(),5,,,))<>"",ROW()-10,"") | K14: =IF(IF(COPIA!$R$1=TRUE,IF(OR(G14<>0,H14<>0),ROUND(SUM(G$11:G14),2)-ROUND(SUM(H$11:H14),2),""),"")<>0,"",0) | L14: =IF(INDIRECT(ADDRESS(ROW(),4,4,,))<>"",YEAR(INDIRECT(ADDRESS(ROW(),4,4,,))),0) -> 0 | M14: =IFERROR(IF(AND(INDIRECT(ADDRESS(ROW(),4,,,))<=COPIA!$DA$1,K14=0,COPIA!$BF$1>1,ROW()-10<COPIA!$BF$1-1),MAX($M$10:M13)+1,IF(AND(INDIRECT(ADDRESS(ROW(),4,,,))<=COPIA!$DA$1,K14=0,COPIA!$BF$1=1),MAX($M$10:M13)+1,0)),0) -> 0 | N14: =IF(AND(COPIA!$BF$1=1,M14<>0),ROW()-10,IF(AND(COPIA!$BF$1>1,ROW()-10>COPIA!$BF$1,M14<>0),0,IF(AND(COPIA!$BF$1>1,ROW()-10<=COPIA!$BF$1,M14<>0),ROW()-10,0))) -> 0 | O14: =IF(AND($O$1=0,ROW()-10<=$O$2),MAX($O$10:O13)+1,IF(AND(ROW()-10>$O$2,ROW()-10<=$O$1),ROW()-10,0)) -> 0 | P14: =IF(O14>0,MAX($P$10:P13)+1,0) -> 0
B15: =IF(INDIRECT(ADDRESS(ROW(),4,,,))="","",IFERROR(INDEX(PDC,MATCH(INDIRECT(ADDRESS(ROW(),5,,,)),DEN_PDC,0),1),0)) | C15: =IF(INDIRECT(ADDRESS(ROW(),5,,,))<>"",ROW()-10,"") | K15: =IF(IF(COPIA!$R$1=TRUE,IF(OR(G15<>0,H15<>0),ROUND(SUM(G$11:G15),2)-ROUND(SUM(H$11:H15),2),""),"")<>0,"",0) | L15: =IF(INDIRECT(ADDRESS(ROW(),4,4,,))<>"",YEAR(INDIRECT(ADDRESS(ROW(),4,4,,))),0) -> 0 | M15: =IFERROR(IF(AND(INDIRECT(ADDRESS(ROW(),4,,,))<=COPIA!$DA$1,K15=0,COPIA!$BF$1>1,ROW()-10<COPIA!$BF$1-1),MAX($M$10:M14)+1,IF(AND(INDIRECT(ADDRESS(ROW(),4,,,))<=COPIA!$DA$1,K15=0,COPIA!$BF$1=1),MAX($M$10:M14)+1,0)),0) -> 0 | N15: =IF(AND(COPIA!$BF$1=1,M15<>0),ROW()-10,IF(AND(COPIA!$BF$1>1,ROW()-10>COPIA!$BF$1,M15<>0),0,IF(AND(COPIA!$BF$1>1,ROW()-10<=COPIA!$BF$1,M15<>0),ROW()-10,0))) -> 0 | O15: =IF(AND($O$1=0,ROW()-10<=$O$2),MAX($O$10:O14)+1,IF(AND(ROW()-10>$O$2,ROW()-10<=$O$1),ROW()-10,0)) -> 0 | P15: =IF(O15>0,MAX($P$10:P14)+1,0) -> 0
B16: =IF(INDIRECT(ADDRESS(ROW(),4,,,))="","",IFERROR(INDEX(PDC,MATCH(INDIRECT(ADDRESS(ROW(),5,,,)),DEN_PDC,0),1),0)) | C16: =IF(INDIRECT(ADDRESS(ROW(),5,,,))<>"",ROW()-10,"") | K16: =IF(IF(COPIA!$R$1=TRUE,IF(OR(G16<>0,H16<>0),ROUND(SUM(G$11:G16),2)-ROUND(SUM(H$11:H16),2),""),"")<>0,"",0) | L16: =IF(INDIRECT(ADDRESS(ROW(),4,4,,))<>"",YEAR(INDIRECT(ADDRESS(ROW(),4,4,,))),0) -> 0 | M16: =IFERROR(IF(AND(INDIRECT(ADDRESS(ROW(),4,,,))<=COPIA!$DA$1,K16=0,COPIA!$BF$1>1,ROW()-10<COPIA!$BF$1-1),MAX($M$10:M15)+1,IF(AND(INDIRECT(ADDRESS(ROW(),4,,,))<=COPIA!$DA$1,K16=0,COPIA!$BF$1=1),MAX($M$10:M15)+1,0)),0) -> 0 | N16: =IF(AND(COPIA!$BF$1=1,M16<>0),ROW()-10,IF(AND(COPIA!$BF$1>1,ROW()-10>COPIA!$BF$1,M16<>0),0,IF(AND(COPIA!$BF$1>1,ROW()-10<=COPIA!$BF$1,M16<>0),ROW()-10,0))) -> 0 | O16: =IF(AND($O$1=0,ROW()-10<=$O$2),MAX($O$10:O15)+1,IF(AND(ROW()-10>$O$2,ROW()-10<=$O$1),ROW()-10,0)) -> 0 | P16: =IF(O16>0,MAX($P$10:P15)+1,0) -> 0
B17: =IF(INDIRECT(ADDRESS(ROW(),4,,,))="","",IFERROR(INDEX(PDC,MATCH(INDIRECT(ADDRESS(ROW(),5,,,)),DEN_PDC,0),1),0)) | C17: =IF(INDIRECT(ADDRESS(ROW(),5,,,))<>"",ROW()-10,"") | K17: =IF(IF(COPIA!$R$1=TRUE,IF(OR(G17<>0,H17<>0),ROUND(SUM(G$11:G17),2)-ROUND(SUM(H$11:H17),2),""),"")<>0,"",0) | L17: =IF(INDIRECT(ADDRESS(ROW(),4,4,,))<>"",YEAR(INDIRECT(ADDRESS(ROW(),4,4,,))),0) -> 0 | M17: =IFERROR(IF(AND(INDIRECT(ADDRESS(ROW(),4,,,))<=COPIA!$DA$1,K17=0,COPIA!$BF$1>1,ROW()-10<COPIA!$BF$1-1),MAX($M$10:M16)+1,IF(AND(INDIRECT(ADDRESS(ROW(),4,,,))<=COPIA!$DA$1,K17=0,COPIA!$BF$1=1),MAX($M$10:M16)+1,0)),0) -> 0 | N17: =IF(AND(COPIA!$BF$1=1,M17<>0),ROW()-10,IF(AND(COPIA!$BF$1>1,ROW()-10>COPIA!$BF$1,M17<>0),0,IF(AND(COPIA!$BF$1>1,ROW()-10<=COPIA!$BF$1,M17<>0),ROW()-10,0))) -> 0 | O17: =IF(AND($O$1=0,ROW()-10<=$O$2),MAX($O$10:O16)+1,IF(AND(ROW()-10>$O$2,ROW()-10<=$O$1),ROW()-10,0)) -> 0 | P17: =IF(O17>0,MAX($P$10:P16)+1,0) -> 0
B18: =IF(INDIRECT(ADDRESS(ROW(),4,,,))="","",IFERROR(INDEX(PDC,MATCH(INDIRECT(ADDRESS(ROW(),5,,,)),DEN_PDC,0),1),0)) | C18: =IF(INDIRECT(ADDRESS(ROW(),5,,,))<>"",ROW()-10,"") | K18: =IF(IF(COPIA!$R$1=TRUE,IF(OR(G18<>0,H18<>0),ROUND(SUM(G$11:G18),2)-ROUND(SUM(H$11:H18),2),""),"")<>0,"",0) | L18: =IF(INDIRECT(ADDRESS(ROW(),4,4,,))<>"",YEAR(INDIRECT(ADDRESS(ROW(),4,4,,))),0) -> 0 | M18: =IFERROR(IF(AND(INDIRECT(ADDRESS(ROW(),4,,,))<=COPIA!$DA$1,K18=0,COPIA!$BF$1>1,ROW()-10<COPIA!$BF$1-1),MAX($M$10:M17)+1,IF(AND(INDIRECT(ADDRESS(ROW(),4,,,))<=COPIA!$DA$1,K18=0,COPIA!$BF$1=1),MAX($M$10:M17)+1,0)),0) -> 0 | N18: =IF(AND(COPIA!$BF$1=1,M18<>0),ROW()-10,IF(AND(COPIA!$BF$1>1,ROW()-10>COPIA!$BF$1,M18<>0),0,IF(AND(COPIA!$BF$1>1,ROW()-10<=COPIA!$BF$1,M18<>0),ROW()-10,0))) -> 0 | O18: =IF(AND($O$1=0,ROW()-10<=$O$2),MAX($O$10:O17)+1,IF(AND(ROW()-10>$O$2,ROW()-10<=$O$1),ROW()-10,0)) -> 0 | P18: =IF(O18>0,MAX($P$10:P17)+1,0) -> 0
B19: =IF(INDIRECT(ADDRESS(ROW(),4,,,))="","",IFERROR(INDEX(PDC,MATCH(INDIRECT(ADDRESS(ROW(),5,,,)),DEN_PDC,0),1),0)) | C19: =IF(INDIRECT(ADDRESS(ROW(),5,,,))<>"",ROW()-10,"") | K19: =IF(IF(COPIA!$R$1=TRUE,IF(OR(G19<>0,H19<>0),ROUND(SUM(G$11:G19),2)-ROUND(SUM(H$11:H19),2),""),"")<>0,"",0) | L19: =IF(INDIRECT(ADDRESS(ROW(),4,4,,))<>"",YEAR(INDIRECT(ADDRESS(ROW(),4,4,,))),0) -> 0 | M19: =IFERROR(IF(AND(INDIRECT(ADDRESS(ROW(),4,,,))<=COPIA!$DA$1,K19=0,COPIA!$BF$1>1,ROW()-10<COPIA!$BF$1-1),MAX($M$10:M18)+1,IF(AND(INDIRECT(ADDRESS(ROW(),4,,,))<=COPIA!$DA$1,K19=0,COPIA!$BF$1=1),MAX($M$10:M18)+1,0)),0) -> 0 | N19: =IF(AND(COPIA!$BF$1=1,M19<>0),ROW()-10,IF(AND(COPIA!$BF$1>1,ROW()-10>COPIA!$BF$1,M19<>0),0,IF(AND(COPIA!$BF$1>1,ROW()-10<=COPIA!$BF$1,M19<>0),ROW()-10,0))) -> 0 | O19: =IF(AND($O$1=0,ROW()-10<=$O$2),MAX($O$10:O18)+1,IF(AND(ROW()-10>$O$2,ROW()-10<=$O$1),ROW()-10,0)) -> 0 | P19: =IF(O19>0,MAX($P$10:P18)+1,0) -> 0
B20: =IF(INDIRECT(ADDRESS(ROW(),4,,,))="","",IFERROR(INDEX(PDC,MATCH(INDIRECT(ADDRESS(ROW(),5,,,)),DEN_PDC,0),1),0)) | C20: =IF(INDIRECT(ADDRESS(ROW(),5,,,))<>"",ROW()-10,"") | K20: =IF(IF(COPIA!$R$1=TRUE,IF(OR(G20<>0,H20<>0),ROUND(SUM(G$11:G20),2)-ROUND(SUM(H$11:H20),2),""),"")<>0,"",0) | L20: =IF(INDIRECT(ADDRESS(ROW(),4,4,,))<>"",YEAR(INDIRECT(ADDRESS(ROW(),4,4,,))),0) -> 0 | M20: =IFERROR(IF(AND(INDIRECT(ADDRESS(ROW(),4,,,))<=COPIA!$DA$1,K20=0,COPIA!$BF$1>1,ROW()-10<COPIA!$BF$1-1),MAX($M$10:M19)+1,IF(AND(INDIRECT(ADDRESS(ROW(),4,,,))<=COPIA!$DA$1,K20=0,COPIA!$BF$1=1),MAX($M$10:M19)+1,0)),0) -> 0 | N20: =IF(AND(COPIA!$BF$1=1,M20<>0),ROW()-10,IF(AND(COPIA!$BF$1>1,ROW()-10>COPIA!$BF$1,M20<>0),0,IF(AND(COPIA!$BF$1>1,ROW()-10<=COPIA!$BF$1,M20<>0),ROW()-10,0))) -> 0 | O20: =IF(AND($O$1=0,ROW()-10<=$O$2),MAX($O$10:O19)+1,IF(AND(ROW()-10>$O$2,ROW()-10<=$O$1),ROW()-10,0)) -> 0 | P20: =IF(O20>0,MAX($P$10:P19)+1,0) -> 0
B21: =IF(INDIRECT(ADDRESS(ROW(),4,,,))="","",IFERROR(INDEX(PDC,MATCH(INDIRECT(ADDRESS(ROW(),5,,,)),DEN_PDC,0),1),0)) | C21: =IF(INDIRECT(ADDRESS(ROW(),5,,,))<>"",ROW()-10,"") | K21: =IF(IF(COPIA!$R$1=TRUE,IF(OR(G21<>0,H21<>0),ROUND(SUM(G$11:G21),2)-ROUND(SUM(H$11:H21),2),""),"")<>0,"",0) | L21: =IF(INDIRECT(ADDRESS(ROW(),4,4,,))<>"",YEAR(INDIRECT(ADDRESS(ROW(),4,4,,))),0) -> 0 | M21: =IFERROR(IF(AND(INDIRECT(ADDRESS(ROW(),4,,,))<=COPIA!$DA$1,K21=0,COPIA!$BF$1>1,ROW()-10<COPIA!$BF$1-1),MAX($M$10:M20)+1,IF(AND(INDIRECT(ADDRESS(ROW(),4,,,))<=COPIA!$DA$1,K21=0,COPIA!$BF$1=1),MAX($M$10:M20)+1,0)),0) -> 0 | N21: =IF(AND(COPIA!$BF$1=1,M21<>0),ROW()-10,IF(AND(COPIA!$BF$1>1,ROW()-10>COPIA!$BF$1,M21<>0),0,IF(AND(COPIA!$BF$1>1,ROW()-10<=COPIA!$BF$1,M21<>0),ROW()-10,0))) -> 0 | O21: =IF(AND($O$1=0,ROW()-10<=$O$2),MAX($O$10:O20)+1,IF(AND(ROW()-10>$O$2,ROW()-10<=$O$1),ROW()-10,0)) -> 0 | P21: =IF(O21>0,MAX($P$10:P20)+1,0) -> 0
B22: =IF(INDIRECT(ADDRESS(ROW(),4,,,))="","",IFERROR(INDEX(PDC,MATCH(INDIRECT(ADDRESS(ROW(),5,,,)),DEN_PDC,0),1),0)) | C22: =IF(INDIRECT(ADDRESS(ROW(),5,,,))<>"",ROW()-10,"") | K22: =IF(IF(COPIA!$R$1=TRUE,IF(OR(G22<>0,H22<>0),ROUND(SUM(G$11:G22),2)-ROUND(SUM(H$11:H22),2),""),"")<>0,"",0) | L22: =IF(INDIRECT(ADDRESS(ROW(),4,4,,))<>"",YEAR(INDIRECT(ADDRESS(ROW(),4,4,,))),0) -> 0 | M22: =IFERROR(IF(AND(INDIRECT(ADDRESS(ROW(),4,,,))<=COPIA!$DA$1,K22=0,COPIA!$BF$1>1,ROW()-10<COPIA!$BF$1-1),MAX($M$10:M21)+1,IF(AND(INDIRECT(ADDRESS(ROW(),4,,,))<=COPIA!$DA$1,K22=0,COPIA!$BF$1=1),MAX($M$10:M21)+1,0)),0) -> 0 | N22: =IF(AND(COPIA!$BF$1=1,M22<>0),ROW()-10,IF(AND(COPIA!$BF$1>1,ROW()-10>COPIA!$BF$1,M22<>0),0,IF(AND(COPIA!$BF$1>1,ROW()-10<=COPIA!$BF$1,M22<>0),ROW()-10,0))) -> 0 | O22: =IF(AND($O$1=0,ROW()-10<=$O$2),MAX($O$10:O21)+1,IF(AND(ROW()-10>$O$2,ROW()-10<=$O$1),ROW()-10,0)) -> 0 | P22: =IF(O22>0,MAX($P$10:P21)+1,0) -> 0
... B210: =IF(INDIRECT(ADDRESS(ROW(),4,,,))="","",IFERROR(INDEX(PDC,MATCH(INDIRECT(ADDRESS(ROW(),5,,,)),DEN_PDC,0),1),0)) | C210: =IF(INDIRECT(ADDRESS(ROW(),5,,,))<>"",ROW()-10,"") | K210: =IF(IF(COPIA!$R$1=TRUE,IF(OR(G210<>0,H210<>0),ROUND(SUM(G$11:G210),2)-ROUND(SUM(H$11:H210),2),""),"")<>0,"",0) | L210: =IF(INDIRECT(ADDRESS(ROW(),4,4,,))<>"",YEAR(INDIRECT(ADDRESS(ROW(),4,4,,))),0) -> 0 | M210: =IFERROR(IF(AND(INDIRECT(ADDRESS(ROW(),4,,,))<=COPIA!$DA$1,K210=0,COPIA!$BF$1>1,ROW()-10<COPIA!$BF$1-1),MAX($M$10:M209)+1,IF(AND(INDIRECT(ADDRESS(ROW(),4,,,))<=COPIA!$DA$1,K210=0,COPIA!$BF$1=1),MAX($M$10:M209)+1,0)),0) -> 0 | N210: =IF(AND(COPIA!$BF$1=1,M210<>0),ROW()-10,IF(AND(COPIA!$BF$1>1,ROW()-10>COPIA!$BF$1,M210<>0),0,IF(AND(COPIA!$BF$1>1,ROW()-10<=COPIA!$BF$1,M210<>0),ROW()-10,0))) -> 0 | O210: =IF(AND($O$1=0,ROW()-10<=$O$2),MAX($O$10:O209)+1,IF(AND(ROW()-10>$O$2,ROW()-10<=$O$1),ROW()-10,0)) -> 0 | P210: =IF(O210>0,MAX($P$10:P209)+1,0) -> 0
C211: =IF(INDIRECT(ADDRESS(ROW(),5,,,))<>"",ROW()-10,"") | K211: =IF(IF(COPIA!$R$1=TRUE,IF(OR(G211<>0,H211<>0),ROUND(SUM(G$11:G211),2)-ROUND(SUM(H$11:H211),2),""),"")<>0,"",0)
C212: =IF(INDIRECT(ADDRESS(ROW(),5,,,))<>"",ROW()-10,"") | K212: =IF(IF(COPIA!$R$1=TRUE,IF(OR(G212<>0,H212<>0),ROUND(SUM(G$11:G212),2)-ROUND(SUM(H$11:H212),2),""),"")<>0,"",0) | L212: =IF(D212<>"",YEAR(D212),0) -> 0

Sheet CONTI_DI_MASTRO
B1: CONTI DI MASTRO
B2: =L7 | E2: Riquadro di controllo: DENOMINAZIONE | H2: Riquadro di controllo: ECCEDENZA
D3: =IF(COPIA!CO1=0,"",CONCATENATE("Numero dei conti con denominazione errata: ",COPIA!ES1)) | E3: =IF(COPIA!ET3<>"",COPIA!ET3,"") | H3: =IF(COPIA!EO3<>"",COPIA!EO3,"")
D4: =IF(COPIA!CO1=0,"",CONCATENATE("Numero dei conti con eccedenza errata: ",COPIA!EN2))
B6: OPZIONI DI VISUALIZZAZIONE | D6: MOSTRA UN CONTO IN EVIDENZA | E6: VISUALIZZA PRIMA I CONTI DELL'ULTIMO ARTICOLO | H6: VISUALIZZA I MOVIMENTI E IL SALDO
L7: =IF(COPIA!CO1=0,"",CONCATENATE("Numero dei conti visualizzati: ",COPIA!$DE$1))
B8: =IF(INDIRECT(ADDRESS(8,6,,,"LIBRO_GIORNALE"))="","",INDIRECT(ADDRESS(8,6,,,"LIBRO_GIORNALE"))) | E8: =IF(INDIRECT(ADDRESS(8,7,,,"LIBRO_GIORNALE"))="","",INDIRECT(ADDRESS(8,7,,,"LIBRO_GIORNALE")))
B9: =IF(COPIA!CO1=0,"",CONCATENATE("CONTI DI MASTRO dal 1/1/",COPIA!AW1," al ",COPIA!AS1,"/",COPIA!AT1,"/",COPIA!AW1)) | K9: =MAX(COPIA!DF3:DF1339)+3 -> 3
A10: =COPIA!AC3 -> AZIONISTI C/SOTTOSCRIZIONE | B10: =IF(IFERROR(INDEX((COPIA!$DA$3:$DE$1339),MATCH(ROWS(B$10:B10),COPIA!$DF$3:$DF$1339,0),COLUMN()-1),"")>=1,IFERROR(INDEX((COPIA!$DA$3:$DE$1339),MATCH(ROWS(B$10:B10),COPIA!$DF$3:$DF$1339,0),COLUMN()-1),""),"") | C10: =SUBSTITUTE(IFERROR(INDEX((COPIA!$DA$3:$DE$1339),MATCH(ROWS(C$10:C10),COPIA!$DF$3:$DF$1339,0),COLUMN()-1),""),"MASTRO","") | D10: =IF(IFERROR(INDEX((COPIA!$DA$3:$DE$1339),MATCH(ROWS(D$10:D10),COPIA!$DF$3:$DF$1339,0),COLUMN()-1),"")=0,"",IFERROR(INDEX((COPIA!$DA$3:$DE$1339),MATCH(ROWS(D$10:D10),COPIA!$DF$3:$DF$1339,0),COLUMN()-1),"")) | E10: =IF(IFERROR(INDEX((COPIA!$DA$3:$DE$1339),MATCH(ROWS(E$10:E10),COPIA!$DF$3:$DF$1339,0),COLUMN()-1),"")=0,"",IFERROR(INDEX((COPIA!$DA$3:$DE$1339),MATCH(ROWS(E$10:E10),COPIA!$DF$3:$DF$1339,0),COLUMN()-1),"")) | F10: =IF(IFERROR(INDEX((COPIA!$DA$3:$DE$1339),MATCH(ROWS(F$10:F10),COPIA!$DF$3:$DF$1339,0),COLUMN()-1),"")=0,"",IFERROR(INDEX((COPIA!$DA$3:$DE$1339),MATCH(ROWS(F$10:F10),COPIA!$DF$3:$DF$1339,0),COLUMN()-1),""))
A11: =COPIA!AC4 -> AZIONISTI C/VERSAMENTI RICHIAMATI | B11: =IF(IFERROR(INDEX((COPIA!$DA$3:$DE$1339),MATCH(ROWS(B$10:B11),COPIA!$DF$3:$DF$1339,0),COLUMN()-1),"")>=1,IFERROR(INDEX((COPIA!$DA$3:$DE$1339),MATCH(ROWS(B$10:B11),COPIA!$DF$3:$DF$1339,0),COLUMN()-1),""),"") | C11: =SUBSTITUTE(IFERROR(INDEX((COPIA!$DA$3:$DE$1339),MATCH(ROWS(C$10:C11),COPIA!$DF$3:$DF$1339,0),COLUMN()-1),""),"MASTRO","") | D11: =IF(IFERROR(INDEX((COPIA!$DA$3:$DE$1339),MATCH(ROWS(D$10:D11),COPIA!$DF$3:$DF$1339,0),COLUMN()-1),"")=0,"",IFERROR(INDEX((COPIA!$DA$3:$DE$1339),MATCH(ROWS(D$10:D11),COPIA!$DF$3:$DF$1339,0),COLUMN()-1),"")) | E11: =IF(IFERROR(INDEX((COPIA!$DA$3:$DE$1339),MATCH(ROWS(E$10:E11),COPIA!$DF$3:$DF$1339,0),COLUMN()-1),"")=0,"",IFERROR(INDEX((COPIA!$DA$3:$DE$1339),MATCH(ROWS(E$10:E11),COPIA!$DF$3:$DF$1339,0),COLUMN()-1),"")) | F11: =IF(IFERROR(INDEX((COPIA!$DA$3:$DE$1339),MATCH(ROWS(F$10:F11),COPIA!$DF$3:$DF$1339,0),COLUMN()-1),"")=0,"",IFERROR(INDEX((COPIA!$DA$3:$DE$1339),MATCH(ROWS(F$10:F11),COPIA!$DF$3:$DF$1339,0),COLUMN()-1),""))
A12: =COPIA!AC5 -> AZIONISTI C/REINTEGRO | B12: =IF(IFERROR(INDEX((COPIA!$DA$3:$DE$1339),MATCH(ROWS(B$10:B12),COPIA!$DF$3:$DF$1339,0),COLUMN()-1),"")>=1,IFERROR(INDEX((COPIA!$DA$3:$DE$1339),MATCH(ROWS(B$10:B12),COPIA!$DF$3:$DF$1339,0),COLUMN()-1),""),"") | C12: =SUBSTITUTE(IFERROR(INDEX((COPIA!$DA$3:$DE$1339),MATCH(ROWS(C$10:C12),COPIA!$DF$3:$DF$1339,0),COLUMN()-1),""),"MASTRO","") | D12: =IF(IFERROR(INDEX((COPIA!$DA$3:$DE$1339),MATCH(ROWS(D$10:D12),COPIA!$DF$3:$DF$1339,0),COLUMN()-1),"")=0,"",IFERROR(INDEX((COPIA!$DA$3:$DE$1339),MATCH(ROWS(D$10:D12),COPIA!$DF$3:$DF$1339,0),COLUMN()-1),"")) | E12: =IF(IFERROR(INDEX((COPIA!$DA$3:$DE$1339),MATCH(ROWS(E$10:E12),COPIA!$DF$3:$DF$1339,0),COLUMN()-1),"")=0,"",IFERROR(INDEX((COPIA!$DA$3:$DE$1339),MATCH(ROWS(E$10:E12),COPIA!$DF$3:$DF$1339,0),COLUMN()-1),"")) | F12: =IF(IFERROR(INDEX((COPIA!$DA$3:$DE$1339),MATCH(ROWS(F$10:F12),COPIA!$DF$3:$DF$1339,0),COLUMN()-1),"")=0,"",IFERROR(INDEX((COPIA!$DA$3:$DE$1339),MATCH(ROWS(F$10:F12),COPIA!$DF$3:$DF$1339,0),COLUMN()-1),""))
A13: =COPIA!AC6 -> COSTI DI IMPIANTO | B13: =IF(IFERROR(INDEX((COPIA!$DA$3:$DE$1339),MATCH(ROWS(B$10:B13),COPIA!$DF$3:$DF$1339,0),COLUMN()-1),"")>=1,IFERROR(INDEX((COPIA!$DA$3:$DE$1339),MATCH(ROWS(B$10:B13),COPIA!$DF$3:$DF$1339,0),COLUMN()-1),""),"") | C13: =SUBSTITUTE(IFERROR(INDEX((COPIA!$DA$3:$DE$1339),MATCH(ROWS(C$10:C13),COPIA!$DF$3:$DF$1339,0),COLUMN()-1),""),"MASTRO","") | D13: =IF(IFERROR(INDEX((COPIA!$DA$3:$DE$1339),MATCH(ROWS(D$10:D13),COPIA!$DF$3:$DF$1339,0),COLUMN()-1),"")=0,"",IFERROR(INDEX((COPIA!$DA$3:$DE$1339),MATCH(ROWS(D$10:D13),COPIA!$DF$3:$DF$1339,0),COLUMN()-1),"")) | E13: =IF(IFERROR(INDEX((COPIA!$DA$3:$DE$1339),MATCH(ROWS(E$10:E13),COPIA!$DF$3:$DF$1339,0),COLUMN()-1),"")=0,"",IFERROR(INDEX((COPIA!$DA$3:$DE$1339),MATCH(ROWS(E$10:E13),COPIA!$DF$3:$DF$1339,0),COLUMN()-1),"")) | F13: =IF(IFERROR(INDEX((COPIA!$DA$3:$DE$1339),MATCH(ROWS(F$10:F13),COPIA!$DF$3:$DF$1339,0),COLUMN()-1),"")=0,"",IFERROR(INDEX((COPIA!$DA$3:$DE$1339),MATCH(ROWS(F$10:F13),COPIA!$DF$3:$DF$1339,0),COLUMN()-1),""))
A14: =COPIA!AC7 -> COSTI DI AMPLIAMENTO | B14: =IF(IFERROR(INDEX((COPIA!$DA$3:$DE$1339),MATCH(ROWS(B$10:B14),COPIA!$DF$3:$DF$1339,0),COLUMN()-1),"")>=1,IFERROR(INDEX((COPIA!$DA$3:$DE$1339),MATCH(ROWS(B$10:B14),COPIA!$DF$3:$DF$1339,0),COLUMN()-1),""),"") | C14: =SUBSTITUTE(IFERROR(INDEX((COPIA!$DA$3:$DE$1339),MATCH(ROWS(C$10:C14),COPIA!$DF$3:$DF$1339,0),COLUMN()-1),""),"MASTRO","") | D14: =IF(IFERROR(INDEX((COPIA!$DA$3:$DE$1339),MATCH(ROWS(D$10:D14),COPIA!$DF$3:$DF$1339,0),COLUMN()-1),"")=0,"",IFERROR(INDEX((COPIA!$DA$3:$DE$1339),MATCH(ROWS(D$10:D14),COPIA!$DF$3:$DF$1339,0),COLUMN()-1),"")) | E14: =IF(IFERROR(INDEX((COPIA!$DA$3:$DE$1339),MATCH(ROWS(E$10:E14),COPIA!$DF$3:$DF$1339,0),COLUMN()-1),"")=0,"",IFERROR(INDEX((COPIA!$DA$3:$DE$1339),MATCH(ROWS(E$10:E14),COPIA!$DF$3:$DF$1339,0),COLUMN()-1),"")) | F14: =IF(IFERROR(INDEX((COPIA!$DA$3:$DE$1339),MATCH(ROWS(F$10:F14),COPIA!$DF$3:$DF$1339,0),COLUMN()-1),"")=0,"",IFERROR(INDEX((COPIA!$DA$3:$DE$1339),MATCH(ROWS(F$10:F14),COPIA!$DF$3:$DF$1339,0),COLUMN()-1),""))
A15: =COPIA!AC8 -> COSTI DI SVILUPPO | B15: =IF(IFERROR(INDEX((COPIA!$DA$3:$DE$1339),MATCH(ROWS(B$10:B15),COPIA!$DF$3:$DF$1339,0),COLUMN()-1),"")>=1,IFERROR(INDEX((COPIA!$DA$3:$DE$1339),MATCH(ROWS(B$10:B15),COPIA!$DF$3:$DF$1339,0),COLUMN()-1),""),"") | C15: =SUBSTITUTE(IFERROR(INDEX((COPIA!$DA$3:$DE$1339),MATCH(ROWS(C$10:C15),COPIA!$DF$3:$DF$1339,0),COLUMN()-1),""),"MASTRO","") | D15: =IF(IFERROR(INDEX((COPIA!$DA$3:$DE$1339),MATCH(ROWS(D$10:D15),COPIA!$DF$3:$DF$1339,0),COLUMN()-1),"")=0,"",IFERROR(INDEX((COPIA!$DA$3:$DE$1339),MATCH(ROWS(D$10:D15),COPIA!$DF$3:$DF$1339,0),COLUMN()-1),"")) | E15: =IF(IFERROR(INDEX((COPIA!$DA$3:$DE$1339),MATCH(ROWS(E$10:E15),COPIA!$DF$3:$DF$1339,0),COLUMN()-1),"")=0,"",IFERROR(INDEX((COPIA!$DA$3:$DE$1339),MATCH(ROWS(E$10:E15),COPIA!$DF$3:$DF$1339,0),COLUMN()-1),"")) | F15: =IF(IFERROR(INDEX((COPIA!$DA$3:$DE$1339),MATCH(ROWS(F$10:F15),COPIA!$DF$3:$DF$1339,0),COLUMN()-1),"")=0,"",IFERROR(INDEX((COPIA!$DA$3:$DE$1339),MATCH(ROWS(F$10:F15),COPIA!$DF$3:$DF$1339,0),COLUMN()-1),""))
A16: =COPIA!AC9 -> BREVETTI | B16: =IF(IFERROR(INDEX((COPIA!$DA$3:$DE$1339),MATCH(ROWS(B$10:B16),COPIA!$DF$3:$DF$1339,0),COLUMN()-1),"")>=1,IFERROR(INDEX((COPIA!$DA$3:$DE$1339),MATCH(ROWS(B$10:B16),COPIA!$DF$3:$DF$1339,0),COLUMN()-1),""),"") | C16: =SUBSTITUTE(IFERROR(INDEX((COPIA!$DA$3:$DE$1339),MATCH(ROWS(C$10:C16),COPIA!$DF$3:$DF$1339,0),COLUMN()-1),""),"MASTRO","") | D16: =IF(IFERROR(INDEX((COPIA!$DA$3:$DE$1339),MATCH(ROWS(D$10:D16),COPIA!$DF$3:$DF$1339,0),COLUMN()-1),"")=0,"",IFERROR(INDEX((COPIA!$DA$3:$DE$1339),MATCH(ROWS(D$10:D16),COPIA!$DF$3:$DF$1339,0),COLUMN()-1),"")) | E16: =IF(IFERROR(INDEX((COPIA!$DA$3:$DE$1339),MATCH(ROWS(E$10:E16),COPIA!$DF$3:$DF$1339,0),COLUMN()-1),"")=0,"",IFERROR(INDEX((COPIA!$DA$3:$DE$1339),MATCH(ROWS(E$10:E16),COPIA!$DF$3:$DF$1339,0),COLUMN()-1),"")) | F16: =IF(IFERROR(INDEX((COPIA!$DA$3:$DE$1339),MATCH(ROWS(F$10:F16),COPIA!$DF$3:$DF$1339,0),COLUMN()-1),"")=0,"",IFERROR(INDEX((COPIA!$DA$3:$DE$1339),MATCH(ROWS(F$10:F16),COPIA!$DF$3:$DF$1339,0),COLUMN()-1),""))
A17: =COPIA!AC10 -> SOFTWARE | B17: =IF(IFERROR(INDEX((COPIA!$DA$3:$DE$1339),MATCH(ROWS(B$10:B17),COPIA!$DF$3:$DF$1339,0),COLUMN()-1),"")>=1,IFERROR(INDEX((COPIA!$DA$3:$DE$1339),MATCH(ROWS(B$10:B17),COPIA!$DF$3:$DF$1339,0),COLUMN()-1),""),"") | C17: =SUBSTITUTE(IFERROR(INDEX((COPIA!$DA$3:$DE$1339),MATCH(ROWS(C$10:C17),COPIA!$DF$3:$DF$1339,0),COLUMN()-1),""),"MASTRO","") | D17: =IF(IFERROR(INDEX((COPIA!$DA$3:$DE$1339),MATCH(ROWS(D$10:D17),COPIA!$DF$3:$DF$1339,0),COLUMN()-1),"")=0,"",IFERROR(INDEX((COPIA!$DA$3:$DE$1339),MATCH(ROWS(D$10:D17),COPIA!$DF$3:$DF$1339,0),COLUMN()-1),"")) | E17: =IF(IFERROR(INDEX((COPIA!$DA$3:$DE$1339),MATCH(ROWS(E$10:E17),COPIA!$DF$3:$DF$1339,0),COLUMN()-1),"")=0,"",IFERROR(INDEX((COPIA!$DA$3:$DE$1339),MATCH(ROWS(E$10:E17),COPIA!$DF$3:$DF$1339,0),COLUMN()-1),"")) | F17: =IF(IFERROR(INDEX((COPIA!$DA$3:$DE$1339),MATCH(ROWS(F$10:F17),COPIA!$DF$3:$DF$1339,0),COLUMN()-1),"")=0,"",IFERROR(INDEX((COPIA!$DA$3:$DE$1339),MATCH(ROWS(F$10:F17),COPIA!$DF$3:$DF$1339,0),COLUMN()-1),""))
A18: =COPIA!AC11 -> AVVIAMENTO | B18: =IF(IFERROR(INDEX((COPIA!$DA$3:$DE$1339),MATCH(ROWS(B$10:B18),COPIA!$DF$3:$DF$1339,0),COLUMN()-1),"")>=1,IFERROR(INDEX((COPIA!$DA$3:$DE$1339),MATCH(ROWS(B$10:B18),COPIA!$DF$3:$DF$1339,0),COLUMN()-1),""),"") | C18: =SUBSTITUTE(IFERROR(INDEX((COPIA!$DA$3:$DE$1339),MATCH(ROWS(C$10:C18),COPIA!$DF$3:$DF$1339,0),COLUMN()-1),""),"MASTRO","") | D18: =IF(IFERROR(INDEX((COPIA!$DA$3:$DE$1339),MATCH(ROWS(D$10:D18),COPIA!$DF$3:$DF$1339,0),COLUMN()-1),"")=0,"",IFERROR(INDEX((COPIA!$DA$3:$DE$1339),MATCH(ROWS(D$10:D18),COPIA!$DF$3:$DF$1339,0),COLUMN()-1),"")) | E18: =IF(IFERROR(INDEX((COPIA!$DA$3:$DE$1339),MATCH(ROWS(E$10:E18),COPIA!$DF$3:$DF$1339,0),COLUMN()-1),"")=0,"",IFERROR(INDEX((COPIA!$DA$3:$DE$1339),MATCH(ROWS(E$10:E18),COPIA!$DF$3:$DF$1339,0),COLUMN()-1),"")) | F18: =IF(IFERROR(INDEX((COPIA!$DA$3:$DE$1339),MATCH(ROWS(F$10:F18),COPIA!$DF$3:$DF$1339,0),COLUMN()-1),"")=0,"",IFERROR(INDEX((COPIA!$DA$3:$DE$1339),MATCH(ROWS(F$10:F18),COPIA!$DF$3:$DF$1339,0),COLUMN()-1),""))
A19: =COPIA!AC12 -> FONDO AMMORTAMENTO COSTI DI IMPIANTO | B19: =IF(IFERROR(INDEX((COPIA!$DA$3:$DE$1339),MATCH(ROWS(B$10:B19),COPIA!$DF$3:$DF$1339,0),COLUMN()-1),"")>=1,IFERROR(INDEX((COPIA!$DA$3:$DE$1339),MATCH(ROWS(B$10:B19),COPIA!$DF$3:$DF$1339,0),COLUMN()-1),""),"") | C19: =SUBSTITUTE(IFERROR(INDEX((COPIA!$DA$3:$DE$1339),MATCH(ROWS(C$10:C19),COPIA!$DF$3:$DF$1339,0),COLUMN()-1),""),"MASTRO","") | D19: =IF(IFERROR(INDEX((COPIA!$DA$3:$DE$1339),MATCH(ROWS(D$10:D19),COPIA!$DF$3:$DF$1339,0),COLUMN()-1),"")=0,"",IFERROR(INDEX((COPIA!$DA$3:$DE$1339),MATCH(ROWS(D$10:D19),COPIA!$DF$3:$DF$1339,0),COLUMN()-1),"")) | E19: =IF(IFERROR(INDEX((COPIA!$DA$3:$DE$1339),MATCH(ROWS(E$10:E19),COPIA!$DF$3:$DF$1339,0),COLUMN()-1),"")=0,"",IFERROR(INDEX((COPIA!$DA$3:$DE$1339),MATCH(ROWS(E$10:E19),COPIA!$DF$3:$DF$1339,0),COLUMN()-1),"")) | F19: =IF(IFERROR(INDEX((COPIA!$DA$3:$DE$1339),MATCH(ROWS(F$10:F19),COPIA!$DF$3:$DF$1339,0),COLUMN()-1),"")=0,"",IFERROR(INDEX((COPIA!$DA$3:$DE$1339),MATCH(ROWS(F$10:F19),COPIA!$DF$3:$DF$1339,0),COLUMN()-1),""))
A20: =COPIA!AC13 -> FONDO AMMORTAMENTO COSTI DI AMPLIAMENTO | B20: =IF(IFERROR(INDEX((COPIA!$DA$3:$DE$1339),MATCH(ROWS(B$10:B20),COPIA!$DF$3:$DF$1339,0),COLUMN()-1),"")>=1,IFERROR(INDEX((COPIA!$DA$3:$DE$1339),MATCH(ROWS(B$10:B20),COPIA!$DF$3:$DF$1339,0),COLUMN()-1),""),"") | C20: =SUBSTITUTE(IFERROR(INDEX((COPIA!$DA$3:$DE$1339),MATCH(ROWS(C$10:C20),COPIA!$DF$3:$DF$1339,0),COLUMN()-1),""),"MASTRO","") | D20: =IF(IFERROR(INDEX((COPIA!$DA$3:$DE$1339),MATCH(ROWS(D$10:D20),COPIA!$DF$3:$DF$1339,0),COLUMN()-1),"")=0,"",IFERROR(INDEX((COPIA!$DA$3:$DE$1339),MATCH(ROWS(D$10:D20),COPIA!$DF$3:$DF$1339,0),COLUMN()-1),"")) | E20: =IF(IFERROR(INDEX((COPIA!$DA$3:$DE$1339),MATCH(ROWS(E$10:E20),COPIA!$DF$3:$DF$1339,0),COLUMN()-1),"")=0,"",IFERROR(INDEX((COPIA!$DA$3:$DE$1339),MATCH(ROWS(E$10:E20),COPIA!$DF$3:$DF$1339,0),COLUMN()-1),"")) | F20: =IF(IFERROR(INDEX((COPIA!$DA$3:$DE$1339),MATCH(ROWS(F$10:F20),COPIA!$DF$3:$DF$1339,0),COLUMN()-1),"")=0,"",IFERROR(INDEX((COPIA!$DA$3:$DE$1339),MATCH(ROWS(F$10:F20),COPIA!$DF$3:$DF$1339,0),COLUMN()-1),""))
A21: =COPIA!AC14 -> FONDO AMMORTAMENTO COSTI DI SVILUPPO | B21: =IF(IFERROR(INDEX((COPIA!$DA$3:$DE$1339),MATCH(ROWS(B$10:B21),COPIA!$DF$3:$DF$1339,0),COLUMN()-1),"")>=1,IFERROR(INDEX((COPIA!$DA$3:$DE$1339),MATCH(ROWS(B$10:B21),COPIA!$DF$3:$DF$1339,0),COLUMN()-1),""),"") | C21: =SUBSTITUTE(IFERROR(INDEX((COPIA!$DA$3:$DE$1339),MATCH(ROWS(C$10:C21),COPIA!$DF$3:$DF$1339,0),COLUMN()-1),""),"MASTRO","") | D21: =IF(IFERROR(INDEX((COPIA!$DA$3:$DE$1339),MATCH(ROWS(D$10:D21),COPIA!$DF$3:$DF$1339,0),COLUMN()-1),"")=0,"",IFERROR(INDEX((COPIA!$DA$3:$DE$1339),MATCH(ROWS(D$10:D21),COPIA!$DF$3:$DF$1339,0),COLUMN()-1),"")) | E21: =IF(IFERROR(INDEX((COPIA!$DA$3:$DE$1339),MATCH(ROWS(E$10:E21),COPIA!$DF$3:$DF$1339,0),COLUMN()-1),"")=0,"",IFERROR(INDEX((COPIA!$DA$3:$DE$1339),MATCH(ROWS(E$10:E21),COPIA!$DF$3:$DF$1339,0),COLUMN()-1),"")) | F21: =IF(IFERROR(INDEX((COPIA!$DA$3:$DE$1339),MATCH(ROWS(F$10:F21),COPIA!$DF$3:$DF$1339,0),COLUMN()-1),"")=0,"",IFERROR(INDEX((COPIA!$DA$3:$DE$1339),MATCH(ROWS(F$10:F21),COPIA!$DF$3:$DF$1339,0),COLUMN()-1),""))
... A407: =COPIA!AC400 | B407: =IF(IFERROR(INDEX((COPIA!$DA$3:$DE$1339),MATCH(ROWS(B$10:B407),COPIA!$DF$3:$DF$1339,0),COLUMN()-1),"")>=1,IFERROR(INDEX((COPIA!$DA$3:$DE$1339),MATCH(ROWS(B$10:B407),COPIA!$DF$3:$DF$1339,0),COLUMN()-1),""),"") | C407: =SUBSTITUTE(IFERROR(INDEX((COPIA!$DA$3:$DE$1339),MATCH(ROWS(C$10:C407),COPIA!$DF$3:$DF$1339,0),COLUMN()-1),""),"MASTRO","") | D407: =IF(IFERROR(INDEX((COPIA!$DA$3:$DE$1339),MATCH(ROWS(D$10:D407),COPIA!$DF$3:$DF$1339,0),COLUMN()-1),"")=0,"",IFERROR(INDEX((COPIA!$DA$3:$DE$1339),MATCH(ROWS(D$10:D407),COPIA!$DF$3:$DF$1339,0),COLUMN()-1),"")) | E407: =IF(IFERROR(INDEX((COPIA!$DA$3:$DE$1339),MATCH(ROWS(E$10:E407),COPIA!$DF$3:$DF$1339,0),COLUMN()-1),"")=0,"",IFERROR(INDEX((COPIA!$DA$3:$DE$1339),MATCH(ROWS(E$10:E407),COPIA!$DF$3:$DF$1339,0),COLUMN()-1),"")) | F407: =IF(IFERROR(INDEX((COPIA!$DA$3:$DE$1339),MATCH(ROWS(F$10:F407),COPIA!$DF$3:$DF$1339,0),COLUMN()-1),"")=0,"",IFERROR(INDEX((COPIA!$DA$3:$DE$1339),MATCH(ROWS(F$10:F407),COPIA!$DF$3:$DF$1339,0),COLUMN()-1),""))
B408: =IF(IFERROR(INDEX((COPIA!$DA$3:$DE$1339),MATCH(ROWS(B$10:B408),COPIA!$DF$3:$DF$1339,0),COLUMN()-1),"")>=1,IFERROR(INDEX((COPIA!$DA$3:$DE$1339),MATCH(ROWS(B$10:B408),COPIA!$DF$3:$DF$1339,0),COLUMN()-1),""),"") | C408: =SUBSTITUTE(IFERROR(INDEX((COPIA!$DA$3:$DE$1339),MATCH(ROWS(C$10:C408),COPIA!$DF$3:$DF$1339,0),COLUMN()-1),""),"MASTRO","") | D408: =IF(IFERROR(INDEX((COPIA!$DA$3:$DE$1339),MATCH(ROWS(D$10:D408),COPIA!$DF$3:$DF$1339,0),COLUMN()-1),"")=0,"",IFERROR(INDEX((COPIA!$DA$3:$DE$1339),MATCH(ROWS(D$10:D408),COPIA!$DF$3:$DF$1339,0),COLUMN()-1),"")) | E408: =IF(IFERROR(INDEX((COPIA!$DA$3:$DE$1339),MATCH(ROWS(E$10:E408),COPIA!$DF$3:$DF$1339,0),COLUMN()-1),"")=0,"",IFERROR(INDEX((COPIA!$DA$3:$DE$1339),MATCH(ROWS(E$10:E408),COPIA!$DF$3:$DF$1339,0),COLUMN()-1),"")) | F408: =IF(IFERROR(INDEX((COPIA!$DA$3:$DE$1339),MATCH(ROWS(F$10:F408),COPIA!$DF$3:$DF$1339,0),COLUMN()-1),"")=0,"",IFERROR(INDEX((COPIA!$DA$3:$DE$1339),MATCH(ROWS(F$10:F408),COPIA!$DF$3:$DF$1339,0),COLUMN()-1),""))
B409: =IF(IFERROR(INDEX((COPIA!$DA$3:$DE$1339),MATCH(ROWS(B$10:B409),COPIA!$DF$3:$DF$1339,0),COLUMN()-1),"")>=1,IFERROR(INDEX((COPIA!$DA$3:$DE$1339),MATCH(ROWS(B$10:B409),COPIA!$DF$3:$DF$1339,0),COLUMN()-1),""),"") | C409: =SUBSTITUTE(IFERROR(INDEX((COPIA!$DA$3:$DE$1339),MATCH(ROWS(C$10:C409),COPIA!$DF$3:$DF$1339,0),COLUMN()-1),""),"MASTRO","") | D409: =IF(IFERROR(INDEX((COPIA!$DA$3:$DE$1339),MATCH(ROWS(D$10:D409),COPIA!$DF$3:$DF$1339,0),COLUMN()-1),"")=0,"",IFERROR(INDEX((COPIA!$DA$3:$DE$1339),MATCH(ROWS(D$10:D409),COPIA!$DF$3:$DF$1339,0),COLUMN()-1),"")) | E409: =IF(IFERROR(INDEX((COPIA!$DA$3:$DE$1339),MATCH(ROWS(E$10:E409),COPIA!$DF$3:$DF$1339,0),COLUMN()-1),"")=0,"",IFERROR(INDEX((COPIA!$DA$3:$DE$1339),MATCH(ROWS(E$10:E409),COPIA!$DF$3:$DF$1339,0),COLUMN()-1),"")) | F409: =IF(IFERROR(INDEX((COPIA!$DA$3:$DE$1339),MATCH(ROWS(F$10:F409),COPIA!$DF$3:$DF$1339,0),COLUMN()-1),"")=0,"",IFERROR(INDEX((COPIA!$DA$3:$DE$1339),MATCH(ROWS(F$10:F409),COPIA!$DF$3:$DF$1339,0),COLUMN()-1),""))
B410: =IF(IFERROR(INDEX((COPIA!$DA$3:$DE$1339),MATCH(ROWS(B$10:B410),COPIA!$DF$3:$DF$1339,0),COLUMN()-1),"")>=1,IFERROR(INDEX((COPIA!$DA$3:$DE$1339),MATCH(ROWS(B$10:B410),COPIA!$DF$3:$DF$1339,0),COLUMN()-1),""),"") | C410: =SUBSTITUTE(IFERROR(INDEX((COPIA!$DA$3:$DE$1339),MATCH(ROWS(C$10:C410),COPIA!$DF$3:$DF$1339,0),COLUMN()-1),""),"MASTRO","") | D410: =IF(IFERROR(INDEX((COPIA!$DA$3:$DE$1339),MATCH(ROWS(D$10:D410),COPIA!$DF$3:$DF$1339,0),COLUMN()-1),"")=0,"",IFERROR(INDEX((COPIA!$DA$3:$DE$1339),MATCH(ROWS(D$10:D410),COPIA!$DF$3:$DF$1339,0),COLUMN()-1),"")) | E410: =IF(IFERROR(INDEX((COPIA!$DA$3:$DE$1339),MATCH(ROWS(E$10:E410),COPIA!$DF$3:$DF$1339,0),COLUMN()-1),"")=0,"",IFERROR(INDEX((COPIA!$DA$3:$DE$1339),MATCH(ROWS(E$10:E410),COPIA!$DF$3:$DF$1339,0),COLUMN()-1),"")) | F410: =IF(IFERROR(INDEX((COPIA!$DA$3:$DE$1339),MATCH(ROWS(F$10:F410),COPIA!$DF$3:$DF$1339,0),COLUMN()-1),"")=0,"",IFERROR(INDEX((COPIA!$DA$3:$DE$1339),MATCH(ROWS(F$10:F410),COPIA!$DF$3:$DF$1339,0),COLUMN()-1),""))
B411: =IF(IFERROR(INDEX((COPIA!$DA$3:$DE$1339),MATCH(ROWS(B$10:B411),COPIA!$DF$3:$DF$1339,0),COLUMN()-1),"")>=1,IFERROR(INDEX((COPIA!$DA$3:$DE$1339),MATCH(ROWS(B$10:B411),COPIA!$DF$3:$DF$1339,0),COLUMN()-1),""),"") | C411: =SUBSTITUTE(IFERROR(INDEX((COPIA!$DA$3:$DE$1339),MATCH(ROWS(C$10:C411),COPIA!$DF$3:$DF$1339,0),COLUMN()-1),""),"MASTRO","") | D411: =IF(IFERROR(INDEX((COPIA!$DA$3:$DE$1339),MATCH(ROWS(D$10:D411),COPIA!$DF$3:$DF$1339,0),COLUMN()-1),"")=0,"",IFERROR(INDEX((COPIA!$DA$3:$DE$1339),MATCH(ROWS(D$10:D411),COPIA!$DF$3:$DF$1339,0),COLUMN()-1),"")) | E411: =IF(IFERROR(INDEX((COPIA!$DA$3:$DE$1339),MATCH(ROWS(E$10:E411),COPIA!$DF$3:$DF$1339,0),COLUMN()-1),"")=0,"",IFERROR(INDEX((COPIA!$DA$3:$DE$1339),MATCH(ROWS(E$10:E411),COPIA!$DF$3:$DF$1339,0),COLUMN()-1),"")) | F411: =IF(IFERROR(INDEX((COPIA!$DA$3:$DE$1339),MATCH(ROWS(F$10:F411),COPIA!$DF$3:$DF$1339,0),COLUMN()-1),"")=0,"",IFERROR(INDEX((COPIA!$DA$3:$DE$1339),MATCH(ROWS(F$10:F411),COPIA!$DF$3:$DF$1339,0),COLUMN()-1),""))
B412: =IF(IFERROR(INDEX((COPIA!$DA$3:$DE$1339),MATCH(ROWS(B$10:B412),COPIA!$DF$3:$DF$1339,0),COLUMN()-1),"")>=1,IFERROR(INDEX((COPIA!$DA$3:$DE$1339),MATCH(ROWS(B$10:B412),COPIA!$DF$3:$DF$1339,0),COLUMN()-1),""),"") | C412: =SUBSTITUTE(IFERROR(INDEX((COPIA!$DA$3:$DE$1339),MATCH(ROWS(C$10:C412),COPIA!$DF$3:$DF$1339,0),COLUMN()-1),""),"MASTRO","") | D412: =IF(IFERROR(INDEX((COPIA!$DA$3:$DE$1339),MATCH(ROWS(D$10:D412),COPIA!$DF$3:$DF$1339,0),COLUMN()-1),"")=0,"",IFERROR(INDEX((COPIA!$DA$3:$DE$1339),MATCH(ROWS(D$10:D412),COPIA!$DF$3:$DF$1339,0),COLUMN()-1),"")) | E412: =IF(IFERROR(INDEX((COPIA!$DA$3:$DE$1339),MATCH(ROWS(E$10:E412),COPIA!$DF$3:$DF$1339,0),COLUMN()-1),"")=0,"",IFERROR(INDEX((COPIA!$DA$3:$DE$1339),MATCH(ROWS(E$10:E412),COPIA!$DF$3:$DF$1339,0),COLUMN()-1),"")) | F412: =IF(IFERROR(INDEX((COPIA!$DA$3:$DE$1339),MATCH(ROWS(F$10:F412),COPIA!$DF$3:$DF$1339,0),COLUMN()-1),"")=0,"",IFERROR(INDEX((COPIA!$DA$3:$DE$1339),MATCH(ROWS(F$10:F412),COPIA!$DF$3:$DF$1339,0),COLUMN()-1),""))
B413: =IF(IFERROR(INDEX((COPIA!$DA$3:$DE$1339),MATCH(ROWS(B$10:B413),COPIA!$DF$3:$DF$1339,0),COLUMN()-1),"")>=1,IFERROR(INDEX((COPIA!$DA$3:$DE$1339),MATCH(ROWS(B$10:B413),COPIA!$DF$3:$DF$1339,0),COLUMN()-1),""),"") | C413: =SUBSTITUTE(IFERROR(INDEX((COPIA!$DA$3:$DE$1339),MATCH(ROWS(C$10:C413),COPIA!$DF$3:$DF$1339,0),COLUMN()-1),""),"MASTRO","") | D413: =IF(IFERROR(INDEX((COPIA!$DA$3:$DE$1339),MATCH(ROWS(D$10:D413),COPIA!$DF$3:$DF$1339,0),COLUMN()-1),"")=0,"",IFERROR(INDEX((COPIA!$DA$3:$DE$1339),MATCH(ROWS(D$10:D413),COPIA!$DF$3:$DF$1339,0),COLUMN()-1),"")) | E413: =IF(IFERROR(INDEX((COPIA!$DA$3:$DE$1339),MATCH(ROWS(E$10:E413),COPIA!$DF$3:$DF$1339,0),COLUMN()-1),"")=0,"",IFERROR(INDEX((COPIA!$DA$3:$DE$1339),MATCH(ROWS(E$10:E413),COPIA!$DF$3:$DF$1339,0),COLUMN()-1),"")) | F413: =IF(IFERROR(INDEX((COPIA!$DA$3:$DE$1339),MATCH(ROWS(F$10:F413),COPIA!$DF$3:$DF$1339,0),COLUMN()-1),"")=0,"",IFERROR(INDEX((COPIA!$DA$3:$DE$1339),MATCH(ROWS(F$10:F413),COPIA!$DF$3:$DF$1339,0),COLUMN()-1),""))
B414: =IF(IFERROR(INDEX((COPIA!$DA$3:$DE$1339),MATCH(ROWS(B$10:B414),COPIA!$DF$3:$DF$1339,0),COLUMN()-1),"")>=1,IFERROR(INDEX((COPIA!$DA$3:$DE$1339),MATCH(ROWS(B$10:B414),COPIA!$DF$3:$DF$1339,0),COLUMN()-1),""),"") | C414: =SUBSTITUTE(IFERROR(INDEX((COPIA!$DA$3:$DE$1339),MATCH(ROWS(C$10:C414),COPIA!$DF$3:$DF$1339,0),COLUMN()-1),""),"MASTRO","") | D414: =IF(IFERROR(INDEX((COPIA!$DA$3:$DE$1339),MATCH(ROWS(D$10:D414),COPIA!$DF$3:$DF$1339,0),COLUMN()-1),"")=0,"",IFERROR(INDEX((COPIA!$DA$3:$DE$1339),MATCH(ROWS(D$10:D414),COPIA!$DF$3:$DF$1339,0),COLUMN()-1),"")) | E414: =IF(IFERROR(INDEX((COPIA!$DA$3:$DE$1339),MATCH(ROWS(E$10:E414),COPIA!$DF$3:$DF$1339,0),COLUMN()-1),"")=0,"",IFERROR(INDEX((COPIA!$DA$3:$DE$1339),MATCH(ROWS(E$10:E414),COPIA!$DF$3:$DF$1339,0),COLUMN()-1),"")) | F414: =IF(IFERROR(INDEX((COPIA!$DA$3:$DE$1339),MATCH(ROWS(F$10:F414),COPIA!$DF$3:$DF$1339,0),COLUMN()-1),"")=0,"",IFERROR(INDEX((COPIA!$DA$3:$DE$1339),MATCH(ROWS(F$10:F414),COPIA!$DF$3:$DF$1339,0),COLUMN()-1),""))
B415: =IF(IFERROR(INDEX((COPIA!$DA$3:$DE$1339),MATCH(ROWS(B$10:B415),COPIA!$DF$3:$DF$1339,0),COLUMN()-1),"")>=1,IFERROR(INDEX((COPIA!$DA$3:$DE$1339),MATCH(ROWS(B$10:B415),COPIA!$DF$3:$DF$1339,0),COLUMN()-1),""),"") | C415: =SUBSTITUTE(IFERROR(INDEX((COPIA!$DA$3:$DE$1339),MATCH(ROWS(C$10:C415),COPIA!$DF$3:$DF$1339,0),COLUMN()-1),""),"MASTRO","") | D415: =IF(IFERROR(INDEX((COPIA!$DA$3:$DE$1339),MATCH(ROWS(D$10:D415),COPIA!$DF$3:$DF$1339,0),COLUMN()-1),"")=0,"",IFERROR(INDEX((COPIA!$DA$3:$DE$1339),MATCH(ROWS(D$10:D415),COPIA!$DF$3:$DF$1339,0),COLUMN()-1),"")) | E415: =IF(IFERROR(INDEX((COPIA!$DA$3:$DE$1339),MATCH(ROWS(E$10:E415),COPIA!$DF$3:$DF$1339,0),COLUMN()-1),"")=0,"",IFERROR(INDEX((COPIA!$DA$3:$DE$1339),MATCH(ROWS(E$10:E415),COPIA!$DF$3:$DF$1339,0),COLUMN()-1),"")) | F415: =IF(IFERROR(INDEX((COPIA!$DA$3:$DE$1339),MATCH(ROWS(F$10:F415),COPIA!$DF$3:$DF$1339,0),COLUMN()-1),"")=0,"",IFERROR(INDEX((COPIA!$DA$3:$DE$1339),MATCH(ROWS(F$10:F415),COPIA!$DF$3:$DF$1339,0),COLUMN()-1),""))
B416: =IF(IFERROR(INDEX((COPIA!$DA$3:$DE$1339),MATCH(ROWS(B$10:B416),COPIA!$DF$3:$DF$1339,0),COLUMN()-1),"")>=1,IFERROR(INDEX((COPIA!$DA$3:$DE$1339),MATCH(ROWS(B$10:B416),COPIA!$DF$3:$DF$1339,0),COLUMN()-1),""),"") | C416: =SUBSTITUTE(IFERROR(INDEX((COPIA!$DA$3:$DE$1339),MATCH(ROWS(C$10:C416),COPIA!$DF$3:$DF$1339,0),COLUMN()-1),""),"MASTRO","") | D416: =IF(IFERROR(INDEX((COPIA!$DA$3:$DE$1339),MATCH(ROWS(D$10:D416),COPIA!$DF$3:$DF$1339,0),COLUMN()-1),"")=0,"",IFERROR(INDEX((COPIA!$DA$3:$DE$1339),MATCH(ROWS(D$10:D416),COPIA!$DF$3:$DF$1339,0),COLUMN()-1),"")) | E416: =IF(IFERROR(INDEX((COPIA!$DA$3:$DE$1339),MATCH(ROWS(E$10:E416),COPIA!$DF$3:$DF$1339,0),COLUMN()-1),"")=0,"",IFERROR(INDEX((COPIA!$DA$3:$DE$1339),MATCH(ROWS(E$10:E416),COPIA!$DF$3:$DF$1339,0),COLUMN()-1),"")) | F416: =IF(IFERROR(INDEX((COPIA!$DA$3:$DE$1339),MATCH(ROWS(F$10:F416),COPIA!$DF$3:$DF$1339,0),COLUMN()-1),"")=0,"",IFERROR(INDEX((COPIA!$DA$3:$DE$1339),MATCH(ROWS(F$10:F416),COPIA!$DF$3:$DF$1339,0),COLUMN()-1),""))
B417: =IF(IFERROR(INDEX((COPIA!$DA$3:$DE$1339),MATCH(ROWS(B$10:B417),COPIA!$DF$3:$DF$1339,0),COLUMN()-1),"")>=1,IFERROR(INDEX((COPIA!$DA$3:$DE$1339),MATCH(ROWS(B$10:B417),COPIA!$DF$3:$DF$1339,0),COLUMN()-1),""),"") | C417: =SUBSTITUTE(IFERROR(INDEX((COPIA!$DA$3:$DE$1339),MATCH(ROWS(C$10:C417),COPIA!$DF$3:$DF$1339,0),COLUMN()-1),""),"MASTRO","") | D417: =IF(IFERROR(INDEX((COPIA!$DA$3:$DE$1339),MATCH(ROWS(D$10:D417),COPIA!$DF$3:$DF$1339,0),COLUMN()-1),"")=0,"",IFERROR(INDEX((COPIA!$DA$3:$DE$1339),MATCH(ROWS(D$10:D417),COPIA!$DF$3:$DF$1339,0),COLUMN()-1),"")) | E417: =IF(IFERROR(INDEX((COPIA!$DA$3:$DE$1339),MATCH(ROWS(E$10:E417),COPIA!$DF$3:$DF$1339,0),COLUMN()-1),"")=0,"",IFERROR(INDEX((COPIA!$DA$3:$DE$1339),MATCH(ROWS(E$10:E417),COPIA!$DF$3:$DF$1339,0),COLUMN()-1),"")) | F417: =IF(IFERROR(INDEX((COPIA!$DA$3:$DE$1339),MATCH(ROWS(F$10:F417),COPIA!$DF$3:$DF$1339,0),COLUMN()-1),"")=0,"",IFERROR(INDEX((COPIA!$DA$3:$DE$1339),MATCH(ROWS(F$10:F417),COPIA!$DF$3:$DF$1339,0),COLUMN()-1),""))
B418: =IF(IFERROR(INDEX((COPIA!$DA$3:$DE$1339),MATCH(ROWS(B$10:B418),COPIA!$DF$3:$DF$1339,0),COLUMN()-1),"")>=1,IFERROR(INDEX((COPIA!$DA$3:$DE$1339),MATCH(ROWS(B$10:B418),COPIA!$DF$3:$DF$1339,0),COLUMN()-1),""),"") | C418: =SUBSTITUTE(IFERROR(INDEX((COPIA!$DA$3:$DE$1339),MATCH(ROWS(C$10:C418),COPIA!$DF$3:$DF$1339,0),COLUMN()-1),""),"MASTRO","") | D418: =IF(IFERROR(INDEX((COPIA!$DA$3:$DE$1339),MATCH(ROWS(D$10:D418),COPIA!$DF$3:$DF$1339,0),COLUMN()-1),"")=0,"",IFERROR(INDEX((COPIA!$DA$3:$DE$1339),MATCH(ROWS(D$10:D418),COPIA!$DF$3:$DF$1339,0),COLUMN()-1),"")) | E418: =IF(IFERROR(INDEX((COPIA!$DA$3:$DE$1339),MATCH(ROWS(E$10:E418),COPIA!$DF$3:$DF$1339,0),COLUMN()-1),"")=0,"",IFERROR(INDEX((COPIA!$DA$3:$DE$1339),MATCH(ROWS(E$10:E418),COPIA!$DF$3:$DF$1339,0),COLUMN()-1),"")) | F418: =IF(IFERROR(INDEX((COPIA!$DA$3:$DE$1339),MATCH(ROWS(F$10:F418),COPIA!$DF$3:$DF$1339,0),COLUMN()-1),"")=0,"",IFERROR(INDEX((COPIA!$DA$3:$DE$1339),MATCH(ROWS(F$10:F418),COPIA!$DF$3:$DF$1339,0),COLUMN()-1),""))
B419: =IF(IFERROR(INDEX((COPIA!$DA$3:$DE$1339),MATCH(ROWS(B$10:B419),COPIA!$DF$3:$DF$1339,0),COLUMN()-1),"")>=1,IFERROR(INDEX((COPIA!$DA$3:$DE$1339),MATCH(ROWS(B$10:B419),COPIA!$DF$3:$DF$1339,0),COLUMN()-1),""),"") | C419: =SUBSTITUTE(IFERROR(INDEX((COPIA!$DA$3:$DE$1339),MATCH(ROWS(C$10:C419),COPIA!$DF$3:$DF$1339,0),COLUMN()-1),""),"MASTRO","") | D419: =IF(IFERROR(INDEX((COPIA!$DA$3:$DE$1339),MATCH(ROWS(D$10:D419),COPIA!$DF$3:$DF$1339,0),COLUMN()-1),"")=0,"",IFERROR(INDEX((COPIA!$DA$3:$DE$1339),MATCH(ROWS(D$10:D419),COPIA!$DF$3:$DF$1339,0),COLUMN()-1),"")) | E419: =IF(IFERROR(INDEX((COPIA!$DA$3:$DE$1339),MATCH(ROWS(E$10:E419),COPIA!$DF$3:$DF$1339,0),COLUMN()-1),"")=0,"",IFERROR(INDEX((COPIA!$DA$3:$DE$1339),MATCH(ROWS(E$10:E419),COPIA!$DF$3:$DF$1339,0),COLUMN()-1),"")) | F419: =IF(IFERROR(INDEX((COPIA!$DA$3:$DE$1339),MATCH(ROWS(F$10:F419),COPIA!$DF$3:$DF$1339,0),COLUMN()-1),"")=0,"",IFERROR(INDEX((COPIA!$DA$3:$DE$1339),MATCH(ROWS(F$10:F419),COPIA!$DF$3:$DF$1339,0),COLUMN()-1),""))
... B879: =IF(IFERROR(INDEX((COPIA!$DA$3:$DE$1339),MATCH(ROWS(B$10:B879),COPIA!$DF$3:$DF$1339,0),COLUMN()-1),"")>=1,IFERROR(INDEX((COPIA!$DA$3:$DE$1339),MATCH(ROWS(B$10:B879),COPIA!$DF$3:$DF$1339,0),COLUMN()-1),""),"") | C879: =SUBSTITUTE(IFERROR(INDEX((COPIA!$DA$3:$DE$1339),MATCH(ROWS(C$10:C879),COPIA!$DF$3:$DF$1339,0),COLUMN()-1),""),"MASTRO","") | D879: =IF(IFERROR(INDEX((COPIA!$DA$3:$DE$1339),MATCH(ROWS(D$10:D879),COPIA!$DF$3:$DF$1339,0),COLUMN()-1),"")=0,"",IFERROR(INDEX((COPIA!$DA$3:$DE$1339),MATCH(ROWS(D$10:D879),COPIA!$DF$3:$DF$1339,0),COLUMN()-1),"")) | E879: =IF(IFERROR(INDEX((COPIA!$DA$3:$DE$1339),MATCH(ROWS(E$10:E879),COPIA!$DF$3:$DF$1339,0),COLUMN()-1),"")=0,"",IFERROR(INDEX((COPIA!$DA$3:$DE$1339),MATCH(ROWS(E$10:E879),COPIA!$DF$3:$DF$1339,0),COLUMN()-1),"")) | F879: =IF(IFERROR(INDEX((COPIA!$DA$3:$DE$1339),MATCH(ROWS(F$10:F879),COPIA!$DF$3:$DF$1339,0),COLUMN()-1),"")=0,"",IFERROR(INDEX((COPIA!$DA$3:$DE$1339),MATCH(ROWS(F$10:F879),COPIA!$DF$3:$DF$1339,0),COLUMN()-1),""))

Sheet SIT._CONTABILE
B1: SITUAZIONE CONTABILE
C3: OPZIONI DI VISUALIZZAZIONE | D3: =COPIA!CS3
C4: PER TOTALI ED ECCEDENZE
A6: =COPIA!BU1 -> 3 | B6: =IF(INDIRECT(ADDRESS(8,6,,,"LIBRO_GIORNALE"))="","",INDIRECT(ADDRESS(8,6,,,"LIBRO_GIORNALE"))) | D6: =IF(INDIRECT(ADDRESS(8,7,,,"LIBRO_GIORNALE"))="","",INDIRECT(ADDRESS(8,7,,,"LIBRO_GIORNALE")))
C7: =IF(COPIA!CO1=0,"",IF(COPIA!$I$1=1,IFERROR(CONCATENATE("Situazione contabile per ",LOWER(COPIA!BV1)," al ",COPIA!AS1,"/",COPIA!AT1,"/",UPPER(COPIA!AW1)),""),IF(COPIA!$I$1=2,IFERROR(CONCATENATE("Stralcio di Situazione contabile per ",LOWER(COPIA!BV1)," al ",COPIA!AS1,"/",COPIA!AT1,"/",COPIA!AW1),""),"")))
B8: =IF($H$9=0,"","CODICE") | C8: =IF($H$9=0,"","DENOMINAZIONE DEI CONTI") | D8: =IF($H$9=0,"",IF(COPIA!BU1=3,"TOTALI",IF(COPIA!BU1=2,"ECCEDENZE","TOTALI"))) | F8: =IF($H$9=0,"",IF(COPIA!BU1=3,"ECCEDENZE","")) | H8: =COPIA!BU1 -> 3
D9: =IF($H$9=0,"","DARE") | E9: =IF($H$9=0,"","AVERE") | F9: =IF(H9=0,"",IF(COPIA!$BU$1=3,"DARE","")) | G9: =IF(H9=0,"",IF(COPIA!$BU$1=3,"AVERE","")) | H9: =MAX(H10:H233) -> 0
B10: =IF(C10=" …………….","……",IFERROR(INDEX(PDC,MATCH(C10,DEN_PDC,0),1),0)) | C10: =IF(OR(COPIA!$BU$1=1,COPIA!$BU$1=3),COPIA!CO3,IF(COPIA!$BU$1=2,COPIA!BZ3,IF(ROW()=COPIA!$BT$1,"TOTALE",""))) | D10: =IF(AND(OR(COPIA!$BU$1=1,COPIA!$BU$1=3),INDEX(COPIA!$BT$3:$BV$400,MATCH($C10,COPIA!$BT$3:$BT$400,0),2)<>0),INDEX(COPIA!$BT$3:$BV$400,MATCH($C10,COPIA!$BT$3:$BT$400,0),2),IF(AND(COPIA!$BU$1=2,INDEX(COPIA!$BZ$3:$CB$400,MATCH($C10,COPIA!$BZ$3:$BZ$400,0),2)<>0),INDEX(COPIA!$BZ$3:$CB$400,MATCH($C10,COPIA!$BZ$3:$BZ$400,0),2),"")) | E10: =IF(AND(OR(COPIA!$BU$1=1,COPIA!$BU$1=3),INDEX(COPIA!$BT$3:$BV$400,MATCH($C10,COPIA!$BT$3:$BT$400,0),3)<>0),INDEX(COPIA!$BT$3:$BV$400,MATCH($C10,COPIA!$BT$3:$BT$400,0),3),IF(AND(COPIA!$BU$1=2,INDEX(COPIA!$BZ$3:$CB$400,MATCH($C10,COPIA!$BZ$3:$BZ$400,0),3)<>0),INDEX(COPIA!$BZ$3:$CB$400,MATCH($C10,COPIA!$BZ$3:$BZ$400,0),3),"")) | F10: =IFERROR(IF(AND(COPIA!$BU$1=3,INDEX(COPIA!$BZ$3:$CB$400,MATCH($C10,COPIA!$BZ$3:$BZ$400,0),2)<>0),INDEX(COPIA!$BZ$3:$CB$400,MATCH($C10,COPIA!$BZ$3:$BZ$400,0),2),""),"") | G10: =IFERROR(IF(AND(COPIA!$BU$1=3,INDEX(COPIA!$BZ$3:$CB$400,MATCH($C10,COPIA!$BZ$3:$BZ$400,0),3)<>0),INDEX(COPIA!$BZ$3:$CB$400,MATCH($C10,COPIA!$BZ$3:$BZ$400,0),3),""),"") | H10: =IF(C10<>"",ROW(),"")
B11: =IF(C11=" …………….","……",IFERROR(INDEX(PDC,MATCH(C11,DEN_PDC,0),1),0)) | C11: =IF(OR(COPIA!$BU$1=1,COPIA!$BU$1=3),COPIA!CO4,IF(COPIA!$BU$1=2,COPIA!BZ4,IF(ROW()=COPIA!$BT$1,"TOTALE",""))) | D11: =IF(AND(OR(COPIA!$BU$1=1,COPIA!$BU$1=3),INDEX(COPIA!$BT$3:$BV$400,MATCH($C11,COPIA!$BT$3:$BT$400,0),2)<>0),INDEX(COPIA!$BT$3:$BV$400,MATCH($C11,COPIA!$BT$3:$BT$400,0),2),IF(AND(COPIA!$BU$1=2,INDEX(COPIA!$BZ$3:$CB$400,MATCH($C11,COPIA!$BZ$3:$BZ$400,0),2)<>0),INDEX(COPIA!$BZ$3:$CB$400,MATCH($C11,COPIA!$BZ$3:$BZ$400,0),2),"")) | E11: =IF(AND(OR(COPIA!$BU$1=1,COPIA!$BU$1=3),INDEX(COPIA!$BT$3:$BV$400,MATCH($C11,COPIA!$BT$3:$BT$400,0),3)<>0),INDEX(COPIA!$BT$3:$BV$400,MATCH($C11,COPIA!$BT$3:$BT$400,0),3),IF(AND(COPIA!$BU$1=2,INDEX(COPIA!$BZ$3:$CB$400,MATCH($C11,COPIA!$BZ$3:$BZ$400,0),3)<>0),INDEX(COPIA!$BZ$3:$CB$400,MATCH($C11,COPIA!$BZ$3:$BZ$400,0),3),"")) | F11: =IFERROR(IF(AND(COPIA!$BU$1=3,INDEX(COPIA!$BZ$3:$CB$400,MATCH($C11,COPIA!$BZ$3:$BZ$400,0),2)<>0),INDEX(COPIA!$BZ$3:$CB$400,MATCH($C11,COPIA!$BZ$3:$BZ$400,0),2),""),"") | G11: =IFERROR(IF(AND(COPIA!$BU$1=3,INDEX(COPIA!$BZ$3:$CB$400,MATCH($C11,COPIA!$BZ$3:$BZ$400,0),3)<>0),INDEX(COPIA!$BZ$3:$CB$400,MATCH($C11,COPIA!$BZ$3:$BZ$400,0),3),""),"") | H11: =IF(C11<>"",ROW(),"")
B12: =IF(C12=" …………….","……",IFERROR(INDEX(PDC,MATCH(C12,DEN_PDC,0),1),0)) | C12: =IF(OR(COPIA!$BU$1=1,COPIA!$BU$1=3),COPIA!CO5,IF(COPIA!$BU$1=2,COPIA!BZ5,IF(ROW()=COPIA!$BT$1,"TOTALE",""))) | D12: =IF(AND(OR(COPIA!$BU$1=1,COPIA!$BU$1=3),INDEX(COPIA!$BT$3:$BV$400,MATCH($C12,COPIA!$BT$3:$BT$400,0),2)<>0),INDEX(COPIA!$BT$3:$BV$400,MATCH($C12,COPIA!$BT$3:$BT$400,0),2),IF(AND(COPIA!$BU$1=2,INDEX(COPIA!$BZ$3:$CB$400,MATCH($C12,COPIA!$BZ$3:$BZ$400,0),2)<>0),INDEX(COPIA!$BZ$3:$CB$400,MATCH($C12,COPIA!$BZ$3:$BZ$400,0),2),"")) | E12: =IF(AND(OR(COPIA!$BU$1=1,COPIA!$BU$1=3),INDEX(COPIA!$BT$3:$BV$400,MATCH($C12,COPIA!$BT$3:$BT$400,0),3)<>0),INDEX(COPIA!$BT$3:$BV$400,MATCH($C12,COPIA!$BT$3:$BT$400,0),3),IF(AND(COPIA!$BU$1=2,INDEX(COPIA!$BZ$3:$CB$400,MATCH($C12,COPIA!$BZ$3:$BZ$400,0),3)<>0),INDEX(COPIA!$BZ$3:$CB$400,MATCH($C12,COPIA!$BZ$3:$BZ$400,0),3),"")) | F12: =IFERROR(IF(AND(COPIA!$BU$1=3,INDEX(COPIA!$BZ$3:$CB$400,MATCH($C12,COPIA!$BZ$3:$BZ$400,0),2)<>0),INDEX(COPIA!$BZ$3:$CB$400,MATCH($C12,COPIA!$BZ$3:$BZ$400,0),2),""),"") | G12: =IFERROR(IF(AND(COPIA!$BU$1=3,INDEX(COPIA!$BZ$3:$CB$400,MATCH($C12,COPIA!$BZ$3:$BZ$400,0),3)<>0),INDEX(COPIA!$BZ$3:$CB$400,MATCH($C12,COPIA!$BZ$3:$BZ$400,0),3),""),"") | H12: =IF(C12<>"",ROW(),"")
B13: =IF(C13=" …………….","……",IFERROR(INDEX(PDC,MATCH(C13,DEN_PDC,0),1),0)) | C13: =IF(OR(COPIA!$BU$1=1,COPIA!$BU$1=3),COPIA!CO6,IF(COPIA!$BU$1=2,COPIA!BZ6,IF(ROW()=COPIA!$BT$1,"TOTALE",""))) | D13: =IF(AND(OR(COPIA!$BU$1=1,COPIA!$BU$1=3),INDEX(COPIA!$BT$3:$BV$400,MATCH($C13,COPIA!$BT$3:$BT$400,0),2)<>0),INDEX(COPIA!$BT$3:$BV$400,MATCH($C13,COPIA!$BT$3:$BT$400,0),2),IF(AND(COPIA!$BU$1=2,INDEX(COPIA!$BZ$3:$CB$400,MATCH($C13,COPIA!$BZ$3:$BZ$400,0),2)<>0),INDEX(COPIA!$BZ$3:$CB$400,MATCH($C13,COPIA!$BZ$3:$BZ$400,0),2),"")) | E13: =IF(AND(OR(COPIA!$BU$1=1,COPIA!$BU$1=3),INDEX(COPIA!$BT$3:$BV$400,MATCH($C13,COPIA!$BT$3:$BT$400,0),3)<>0),INDEX(COPIA!$BT$3:$BV$400,MATCH($C13,COPIA!$BT$3:$BT$400,0),3),IF(AND(COPIA!$BU$1=2,INDEX(COPIA!$BZ$3:$CB$400,MATCH($C13,COPIA!$BZ$3:$BZ$400,0),3)<>0),INDEX(COPIA!$BZ$3:$CB$400,MATCH($C13,COPIA!$BZ$3:$BZ$400,0),3),"")) | F13: =IFERROR(IF(AND(COPIA!$BU$1=3,INDEX(COPIA!$BZ$3:$CB$400,MATCH($C13,COPIA!$BZ$3:$BZ$400,0),2)<>0),INDEX(COPIA!$BZ$3:$CB$400,MATCH($C13,COPIA!$BZ$3:$BZ$400,0),2),""),"") | G13: =IFERROR(IF(AND(COPIA!$BU$1=3,INDEX(COPIA!$BZ$3:$CB$400,MATCH($C13,COPIA!$BZ$3:$BZ$400,0),3)<>0),INDEX(COPIA!$BZ$3:$CB$400,MATCH($C13,COPIA!$BZ$3:$BZ$400,0),3),""),"") | H13: =IF(C13<>"",ROW(),"")
B14: =IF(C14=" …………….","……",IFERROR(INDEX(PDC,MATCH(C14,DEN_PDC,0),1),0)) | C14: =IF(OR(COPIA!$BU$1=1,COPIA!$BU$1=3),COPIA!CO7,IF(COPIA!$BU$1=2,COPIA!BZ7,IF(ROW()=COPIA!$BT$1,"TOTALE",""))) | D14: =IF(AND(OR(COPIA!$BU$1=1,COPIA!$BU$1=3),INDEX(COPIA!$BT$3:$BV$400,MATCH($C14,COPIA!$BT$3:$BT$400,0),2)<>0),INDEX(COPIA!$BT$3:$BV$400,MATCH($C14,COPIA!$BT$3:$BT$400,0),2),IF(AND(COPIA!$BU$1=2,INDEX(COPIA!$BZ$3:$CB$400,MATCH($C14,COPIA!$BZ$3:$BZ$400,0),2)<>0),INDEX(COPIA!$BZ$3:$CB$400,MATCH($C14,COPIA!$BZ$3:$BZ$400,0),2),"")) | E14: =IF(AND(OR(COPIA!$BU$1=1,COPIA!$BU$1=3),INDEX(COPIA!$BT$3:$BV$400,MATCH($C14,COPIA!$BT$3:$BT$400,0),3)<>0),INDEX(COPIA!$BT$3:$BV$400,MATCH($C14,COPIA!$BT$3:$BT$400,0),3),IF(AND(COPIA!$BU$1=2,INDEX(COPIA!$BZ$3:$CB$400,MATCH($C14,COPIA!$BZ$3:$BZ$400,0),3)<>0),INDEX(COPIA!$BZ$3:$CB$400,MATCH($C14,COPIA!$BZ$3:$BZ$400,0),3),"")) | F14: =IFERROR(IF(AND(COPIA!$BU$1=3,INDEX(COPIA!$BZ$3:$CB$400,MATCH($C14,COPIA!$BZ$3:$BZ$400,0),2)<>0),INDEX(COPIA!$BZ$3:$CB$400,MATCH($C14,COPIA!$BZ$3:$BZ$400,0),2),""),"") | G14: =IFERROR(IF(AND(COPIA!$BU$1=3,INDEX(COPIA!$BZ$3:$CB$400,MATCH($C14,COPIA!$BZ$3:$BZ$400,0),3)<>0),INDEX(COPIA!$BZ$3:$CB$400,MATCH($C14,COPIA!$BZ$3:$BZ$400,0),3),""),"") | H14: =IF(C14<>"",ROW(),"")
B15: =IF(C15=" …………….","……",IFERROR(INDEX(PDC,MATCH(C15,DEN_PDC,0),1),0)) | C15: =IF(OR(COPIA!$BU$1=1,COPIA!$BU$1=3),COPIA!CO8,IF(COPIA!$BU$1=2,COPIA!BZ8,IF(ROW()=COPIA!$BT$1,"TOTALE",""))) | D15: =IF(AND(OR(COPIA!$BU$1=1,COPIA!$BU$1=3),INDEX(COPIA!$BT$3:$BV$400,MATCH($C15,COPIA!$BT$3:$BT$400,0),2)<>0),INDEX(COPIA!$BT$3:$BV$400,MATCH($C15,COPIA!$BT$3:$BT$400,0),2),IF(AND(COPIA!$BU$1=2,INDEX(COPIA!$BZ$3:$CB$400,MATCH($C15,COPIA!$BZ$3:$BZ$400,0),2)<>0),INDEX(COPIA!$BZ$3:$CB$400,MATCH($C15,COPIA!$BZ$3:$BZ$400,0),2),"")) | E15: =IF(AND(OR(COPIA!$BU$1=1,COPIA!$BU$1=3),INDEX(COPIA!$BT$3:$BV$400,MATCH($C15,COPIA!$BT$3:$BT$400,0),3)<>0),INDEX(COPIA!$BT$3:$BV$400,MATCH($C15,COPIA!$BT$3:$BT$400,0),3),IF(AND(COPIA!$BU$1=2,INDEX(COPIA!$BZ$3:$CB$400,MATCH($C15,COPIA!$BZ$3:$BZ$400,0),3)<>0),INDEX(COPIA!$BZ$3:$CB$400,MATCH($C15,COPIA!$BZ$3:$BZ$400,0),3),"")) | F15: =IFERROR(IF(AND(COPIA!$BU$1=3,INDEX(COPIA!$BZ$3:$CB$400,MATCH($C15,COPIA!$BZ$3:$BZ$400,0),2)<>0),INDEX(COPIA!$BZ$3:$CB$400,MATCH($C15,COPIA!$BZ$3:$BZ$400,0),2),""),"") | G15: =IFERROR(IF(AND(COPIA!$BU$1=3,INDEX(COPIA!$BZ$3:$CB$400,MATCH($C15,COPIA!$BZ$3:$BZ$400,0),3)<>0),INDEX(COPIA!$BZ$3:$CB$400,MATCH($C15,COPIA!$BZ$3:$BZ$400,0),3),""),"") | H15: =IF(C15<>"",ROW(),"")
B16: =IF(C16=" …………….","……",IFERROR(INDEX(PDC,MATCH(C16,DEN_PDC,0),1),0)) | C16: =IF(OR(COPIA!$BU$1=1,COPIA!$BU$1=3),COPIA!CO9,IF(COPIA!$BU$1=2,COPIA!BZ9,IF(ROW()=COPIA!$BT$1,"TOTALE",""))) | D16: =IF(AND(OR(COPIA!$BU$1=1,COPIA!$BU$1=3),INDEX(COPIA!$BT$3:$BV$400,MATCH($C16,COPIA!$BT$3:$BT$400,0),2)<>0),INDEX(COPIA!$BT$3:$BV$400,MATCH($C16,COPIA!$BT$3:$BT$400,0),2),IF(AND(COPIA!$BU$1=2,INDEX(COPIA!$BZ$3:$CB$400,MATCH($C16,COPIA!$BZ$3:$BZ$400,0),2)<>0),INDEX(COPIA!$BZ$3:$CB$400,MATCH($C16,COPIA!$BZ$3:$BZ$400,0),2),"")) | E16: =IF(AND(OR(COPIA!$BU$1=1,COPIA!$BU$1=3),INDEX(COPIA!$BT$3:$BV$400,MATCH($C16,COPIA!$BT$3:$BT$400,0),3)<>0),INDEX(COPIA!$BT$3:$BV$400,MATCH($C16,COPIA!$BT$3:$BT$400,0),3),IF(AND(COPIA!$BU$1=2,INDEX(COPIA!$BZ$3:$CB$400,MATCH($C16,COPIA!$BZ$3:$BZ$400,0),3)<>0),INDEX(COPIA!$BZ$3:$CB$400,MATCH($C16,COPIA!$BZ$3:$BZ$400,0),3),"")) | F16: =IFERROR(IF(AND(COPIA!$BU$1=3,INDEX(COPIA!$BZ$3:$CB$400,MATCH($C16,COPIA!$BZ$3:$BZ$400,0),2)<>0),INDEX(COPIA!$BZ$3:$CB$400,MATCH($C16,COPIA!$BZ$3:$BZ$400,0),2),""),"") | G16: =IFERROR(IF(AND(COPIA!$BU$1=3,INDEX(COPIA!$BZ$3:$CB$400,MATCH($C16,COPIA!$BZ$3:$BZ$400,0),3)<>0),INDEX(COPIA!$BZ$3:$CB$400,MATCH($C16,COPIA!$BZ$3:$BZ$400,0),3),""),"") | H16: =IF(C16<>"",ROW(),"")
B17: =IF(C17=" …………….","……",IFERROR(INDEX(PDC,MATCH(C17,DEN_PDC,0),1),0)) | C17: =IF(OR(COPIA!$BU$1=1,COPIA!$BU$1=3),COPIA!CO10,IF(COPIA!$BU$1=2,COPIA!BZ10,IF(ROW()=COPIA!$BT$1,"TOTALE",""))) | D17: =IF(AND(OR(COPIA!$BU$1=1,COPIA!$BU$1=3),INDEX(COPIA!$BT$3:$BV$400,MATCH($C17,COPIA!$BT$3:$BT$400,0),2)<>0),INDEX(COPIA!$BT$3:$BV$400,MATCH($C17,COPIA!$BT$3:$BT$400,0),2),IF(AND(COPIA!$BU$1=2,INDEX(COPIA!$BZ$3:$CB$400,MATCH($C17,COPIA!$BZ$3:$BZ$400,0),2)<>0),INDEX(COPIA!$BZ$3:$CB$400,MATCH($C17,COPIA!$BZ$3:$BZ$400,0),2),"")) | E17: =IF(AND(OR(COPIA!$BU$1=1,COPIA!$BU$1=3),INDEX(COPIA!$BT$3:$BV$400,MATCH($C17,COPIA!$BT$3:$BT$400,0),3)<>0),INDEX(COPIA!$BT$3:$BV$400,MATCH($C17,COPIA!$BT$3:$BT$400,0),3),IF(AND(COPIA!$BU$1=2,INDEX(COPIA!$BZ$3:$CB$400,MATCH($C17,COPIA!$BZ$3:$BZ$400,0),3)<>0),INDEX(COPIA!$BZ$3:$CB$400,MATCH($C17,COPIA!$BZ$3:$BZ$400,0),3),"")) | F17: =IFERROR(IF(AND(COPIA!$BU$1=3,INDEX(COPIA!$BZ$3:$CB$400,MATCH($C17,COPIA!$BZ$3:$BZ$400,0),2)<>0),INDEX(COPIA!$BZ$3:$CB$400,MATCH($C17,COPIA!$BZ$3:$BZ$400,0),2),""),"") | G17: =IFERROR(IF(AND(COPIA!$BU$1=3,INDEX(COPIA!$BZ$3:$CB$400,MATCH($C17,COPIA!$BZ$3:$BZ$400,0),3)<>0),INDEX(COPIA!$BZ$3:$CB$400,MATCH($C17,COPIA!$BZ$3:$BZ$400,0),3),""),"") | H17: =IF(C17<>"",ROW(),"")
B18: =IF(C18=" …………….","……",IFERROR(INDEX(PDC,MATCH(C18,DEN_PDC,0),1),0)) | C18: =IF(OR(COPIA!$BU$1=1,COPIA!$BU$1=3),COPIA!CO11,IF(COPIA!$BU$1=2,COPIA!BZ11,IF(ROW()=COPIA!$BT$1,"TOTALE",""))) | D18: =IF(AND(OR(COPIA!$BU$1=1,COPIA!$BU$1=3),INDEX(COPIA!$BT$3:$BV$400,MATCH($C18,COPIA!$BT$3:$BT$400,0),2)<>0),INDEX(COPIA!$BT$3:$BV$400,MATCH($C18,COPIA!$BT$3:$BT$400,0),2),IF(AND(COPIA!$BU$1=2,INDEX(COPIA!$BZ$3:$CB$400,MATCH($C18,COPIA!$BZ$3:$BZ$400,0),2)<>0),INDEX(COPIA!$BZ$3:$CB$400,MATCH($C18,COPIA!$BZ$3:$BZ$400,0),2),"")) | E18: =IF(AND(OR(COPIA!$BU$1=1,COPIA!$BU$1=3),INDEX(COPIA!$BT$3:$BV$400,MATCH($C18,COPIA!$BT$3:$BT$400,0),3)<>0),INDEX(COPIA!$BT$3:$BV$400,MATCH($C18,COPIA!$BT$3:$BT$400,0),3),IF(AND(COPIA!$BU$1=2,INDEX(COPIA!$BZ$3:$CB$400,MATCH($C18,COPIA!$BZ$3:$BZ$400,0),3)<>0),INDEX(COPIA!$BZ$3:$CB$400,MATCH($C18,COPIA!$BZ$3:$BZ$400,0),3),"")) | F18: =IFERROR(IF(AND(COPIA!$BU$1=3,INDEX(COPIA!$BZ$3:$CB$400,MATCH($C18,COPIA!$BZ$3:$BZ$400,0),2)<>0),INDEX(COPIA!$BZ$3:$CB$400,MATCH($C18,COPIA!$BZ$3:$BZ$400,0),2),""),"") | G18: =IFERROR(IF(AND(COPIA!$BU$1=3,INDEX(COPIA!$BZ$3:$CB$400,MATCH($C18,COPIA!$BZ$3:$BZ$400,0),3)<>0),INDEX(COPIA!$BZ$3:$CB$400,MATCH($C18,COPIA!$BZ$3:$BZ$400,0),3),""),"") | H18: =IF(C18<>"",ROW(),"")
B19: =IF(C19=" …………….","……",IFERROR(INDEX(PDC,MATCH(C19,DEN_PDC,0),1),0)) | C19: =IF(OR(COPIA!$BU$1=1,COPIA!$BU$1=3),COPIA!CO12,IF(COPIA!$BU$1=2,COPIA!BZ12,IF(ROW()=COPIA!$BT$1,"TOTALE",""))) | D19: =IF(AND(OR(COPIA!$BU$1=1,COPIA!$BU$1=3),INDEX(COPIA!$BT$3:$BV$400,MATCH($C19,COPIA!$BT$3:$BT$400,0),2)<>0),INDEX(COPIA!$BT$3:$BV$400,MATCH($C19,COPIA!$BT$3:$BT$400,0),2),IF(AND(COPIA!$BU$1=2,INDEX(COPIA!$BZ$3:$CB$400,MATCH($C19,COPIA!$BZ$3:$BZ$400,0),2)<>0),INDEX(COPIA!$BZ$3:$CB$400,MATCH($C19,COPIA!$BZ$3:$BZ$400,0),2),"")) | E19: =IF(AND(OR(COPIA!$BU$1=1,COPIA!$BU$1=3),INDEX(COPIA!$BT$3:$BV$400,MATCH($C19,COPIA!$BT$3:$BT$400,0),3)<>0),INDEX(COPIA!$BT$3:$BV$400,MATCH($C19,COPIA!$BT$3:$BT$400,0),3),IF(AND(COPIA!$BU$1=2,INDEX(COPIA!$BZ$3:$CB$400,MATCH($C19,COPIA!$BZ$3:$BZ$400,0),3)<>0),INDEX(COPIA!$BZ$3:$CB$400,MATCH($C19,COPIA!$BZ$3:$BZ$400,0),3),"")) | F19: =IFERROR(IF(AND(COPIA!$BU$1=3,INDEX(COPIA!$BZ$3:$CB$400,MATCH($C19,COPIA!$BZ$3:$BZ$400,0),2)<>0),INDEX(COPIA!$BZ$3:$CB$400,MATCH($C19,COPIA!$BZ$3:$BZ$400,0),2),""),"") | G19: =IFERROR(IF(AND(COPIA!$BU$1=3,INDEX(COPIA!$BZ$3:$CB$400,MATCH($C19,COPIA!$BZ$3:$BZ$400,0),3)<>0),INDEX(COPIA!$BZ$3:$CB$400,MATCH($C19,COPIA!$BZ$3:$BZ$400,0),3),""),"") | H19: =IF(C19<>"",ROW(),"")
B20: =IF(C20=" …………….","……",IFERROR(INDEX(PDC,MATCH(C20,DEN_PDC,0),1),0)) | C20: =IF(OR(COPIA!$BU$1=1,COPIA!$BU$1=3),COPIA!CO13,IF(COPIA!$BU$1=2,COPIA!BZ13,IF(ROW()=COPIA!$BT$1,"TOTALE",""))) | D20: =IF(AND(OR(COPIA!$BU$1=1,COPIA!$BU$1=3),INDEX(COPIA!$BT$3:$BV$400,MATCH($C20,COPIA!$BT$3:$BT$400,0),2)<>0),INDEX(COPIA!$BT$3:$BV$400,MATCH($C20,COPIA!$BT$3:$BT$400,0),2),IF(AND(COPIA!$BU$1=2,INDEX(COPIA!$BZ$3:$CB$400,MATCH($C20,COPIA!$BZ$3:$BZ$400,0),2)<>0),INDEX(COPIA!$BZ$3:$CB$400,MATCH($C20,COPIA!$BZ$3:$BZ$400,0),2),"")) | E20: =IF(AND(OR(COPIA!$BU$1=1,COPIA!$BU$1=3),INDEX(COPIA!$BT$3:$BV$400,MATCH($C20,COPIA!$BT$3:$BT$400,0),3)<>0),INDEX(COPIA!$BT$3:$BV$400,MATCH($C20,COPIA!$BT$3:$BT$400,0),3),IF(AND(COPIA!$BU$1=2,INDEX(COPIA!$BZ$3:$CB$400,MATCH($C20,COPIA!$BZ$3:$BZ$400,0),3)<>0),INDEX(COPIA!$BZ$3:$CB$400,MATCH($C20,COPIA!$BZ$3:$BZ$400,0),3),"")) | F20: =IFERROR(IF(AND(COPIA!$BU$1=3,INDEX(COPIA!$BZ$3:$CB$400,MATCH($C20,COPIA!$BZ$3:$BZ$400,0),2)<>0),INDEX(COPIA!$BZ$3:$CB$400,MATCH($C20,COPIA!$BZ$3:$BZ$400,0),2),""),"") | G20: =IFERROR(IF(AND(COPIA!$BU$1=3,INDEX(COPIA!$BZ$3:$CB$400,MATCH($C20,COPIA!$BZ$3:$BZ$400,0),3)<>0),INDEX(COPIA!$BZ$3:$CB$400,MATCH($C20,COPIA!$BZ$3:$BZ$400,0),3),""),"") | H20: =IF(C20<>"",ROW(),"")
B21: =IF(C21=" …………….","……",IFERROR(INDEX(PDC,MATCH(C21,DEN_PDC,0),1),0)) | C21: =IF(OR(COPIA!$BU$1=1,COPIA!$BU$1=3),COPIA!CO14,IF(COPIA!$BU$1=2,COPIA!BZ14,IF(ROW()=COPIA!$BT$1,"TOTALE",""))) | D21: =IF(AND(OR(COPIA!$BU$1=1,COPIA!$BU$1=3),INDEX(COPIA!$BT$3:$BV$400,MATCH($C21,COPIA!$BT$3:$BT$400,0),2)<>0),INDEX(COPIA!$BT$3:$BV$400,MATCH($C21,COPIA!$BT$3:$BT$400,0),2),IF(AND(COPIA!$BU$1=2,INDEX(COPIA!$BZ$3:$CB$400,MATCH($C21,COPIA!$BZ$3:$BZ$400,0),2)<>0),INDEX(COPIA!$BZ$3:$CB$400,MATCH($C21,COPIA!$BZ$3:$BZ$400,0),2),"")) | E21: =IF(AND(OR(COPIA!$BU$1=1,COPIA!$BU$1=3),INDEX(COPIA!$BT$3:$BV$400,MATCH($C21,COPIA!$BT$3:$BT$400,0),3)<>0),INDEX(COPIA!$BT$3:$BV$400,MATCH($C21,COPIA!$BT$3:$BT$400,0),3),IF(AND(COPIA!$BU$1=2,INDEX(COPIA!$BZ$3:$CB$400,MATCH($C21,COPIA!$BZ$3:$BZ$400,0),3)<>0),INDEX(COPIA!$BZ$3:$CB$400,MATCH($C21,COPIA!$BZ$3:$BZ$400,0),3),"")) | F21: =IFERROR(IF(AND(COPIA!$BU$1=3,INDEX(COPIA!$BZ$3:$CB$400,MATCH($C21,COPIA!$BZ$3:$BZ$400,0),2)<>0),INDEX(COPIA!$BZ$3:$CB$400,MATCH($C21,COPIA!$BZ$3:$BZ$400,0),2),""),"") | G21: =IFERROR(IF(AND(COPIA!$BU$1=3,INDEX(COPIA!$BZ$3:$CB$400,MATCH($C21,COPIA!$BZ$3:$BZ$400,0),3)<>0),INDEX(COPIA!$BZ$3:$CB$400,MATCH($C21,COPIA!$BZ$3:$BZ$400,0),3),""),"") | H21: =IF(C21<>"",ROW(),"")
... B273: =IF(C273=" …………….","……",IFERROR(INDEX(PDC,MATCH(C273,DEN_PDC,0),1),0)) | C273: =IF(OR(COPIA!$BU$1=1,COPIA!$BU$1=3),COPIA!CO266,IF(COPIA!$BU$1=2,COPIA!BZ266,IF(ROW()=COPIA!$BT$1,"TOTALE",""))) | D273: =IF(AND(OR(COPIA!$BU$1=1,COPIA!$BU$1=3),INDEX(COPIA!$BT$3:$BV$400,MATCH($C273,COPIA!$BT$3:$BT$400,0),2)<>0),INDEX(COPIA!$BT$3:$BV$400,MATCH($C273,COPIA!$BT$3:$BT$400,0),2),IF(AND(COPIA!$BU$1=2,INDEX(COPIA!$BZ$3:$CB$400,MATCH($C273,COPIA!$BZ$3:$BZ$400,0),2)<>0),INDEX(COPIA!$BZ$3:$CB$400,MATCH($C273,COPIA!$BZ$3:$BZ$400,0),2),"")) | E273: =IF(AND(OR(COPIA!$BU$1=1,COPIA!$BU$1=3),INDEX(COPIA!$BT$3:$BV$400,MATCH($C273,COPIA!$BT$3:$BT$400,0),3)<>0),INDEX(COPIA!$BT$3:$BV$400,MATCH($C273,COPIA!$BT$3:$BT$400,0),3),IF(AND(COPIA!$BU$1=2,INDEX(COPIA!$BZ$3:$CB$400,MATCH($C273,COPIA!$BZ$3:$BZ$400,0),3)<>0),INDEX(COPIA!$BZ$3:$CB$400,MATCH($C273,COPIA!$BZ$3:$BZ$400,0),3),"")) | F273: =IFERROR(IF(AND(COPIA!$BU$1=3,INDEX(COPIA!$BZ$3:$CB$400,MATCH($C273,COPIA!$BZ$3:$BZ$400,0),2)<>0),INDEX(COPIA!$BZ$3:$CB$400,MATCH($C273,COPIA!$BZ$3:$BZ$400,0),2),""),"") | G273: =IFERROR(IF(AND(COPIA!$BU$1=3,INDEX(COPIA!$BZ$3:$CB$400,MATCH($C273,COPIA!$BZ$3:$BZ$400,0),3)<>0),INDEX(COPIA!$BZ$3:$CB$400,MATCH($C273,COPIA!$BZ$3:$BZ$400,0),3),""),"") | H273: =IF(C273<>"",ROW(),"")
B274: =IF(C274=" …………….","……",IFERROR(INDEX(PDC,MATCH(C274,DEN_PDC,0),1),0)) | C274: =IF(OR(COPIA!$BU$1=1,COPIA!$BU$1=3),COPIA!CO267,IF(COPIA!$BU$1=2,COPIA!BZ267,IF(ROW()=COPIA!$BT$1,"TOTALE",""))) | D274: =IF(AND(OR(COPIA!$BU$1=1,COPIA!$BU$1=3),INDEX(COPIA!$BT$3:$BV$400,MATCH($C274,COPIA!$BT$3:$BT$400,0),2)<>0),INDEX(COPIA!$BT$3:$BV$400,MATCH($C274,COPIA!$BT$3:$BT$400,0),2),IF(AND(COPIA!$BU$1=2,INDEX(COPIA!$BZ$3:$CB$400,MATCH($C274,COPIA!$BZ$3:$BZ$400,0),2)<>0),INDEX(COPIA!$BZ$3:$CB$400,MATCH($C274,COPIA!$BZ$3:$BZ$400,0),2),"")) | E274: =IF(AND(OR(COPIA!$BU$1=1,COPIA!$BU$1=3),INDEX(COPIA!$BT$3:$BV$400,MATCH($C274,COPIA!$BT$3:$BT$400,0),3)<>0),INDEX(COPIA!$BT$3:$BV$400,MATCH($C274,COPIA!$BT$3:$BT$400,0),3),IF(AND(COPIA!$BU$1=2,INDEX(COPIA!$BZ$3:$CB$400,MATCH($C274,COPIA!$BZ$3:$BZ$400,0),3)<>0),INDEX(COPIA!$BZ$3:$CB$400,MATCH($C274,COPIA!$BZ$3:$BZ$400,0),3),"")) | F274: =IFERROR(IF(AND(COPIA!$BU$1=3,INDEX(COPIA!$BZ$3:$CB$400,MATCH($C274,COPIA!$BZ$3:$BZ$400,0),2)<>0),INDEX(COPIA!$BZ$3:$CB$400,MATCH($C274,COPIA!$BZ$3:$BZ$400,0),2),""),"") | G274: =IFERROR(IF(AND(COPIA!$BU$1=3,INDEX(COPIA!$BZ$3:$CB$400,MATCH($C274,COPIA!$BZ$3:$BZ$400,0),3)<>0),INDEX(COPIA!$BZ$3:$CB$400,MATCH($C274,COPIA!$BZ$3:$BZ$400,0),3),""),"")
B275: =IF(C275=" …………….","……",IFERROR(INDEX(PDC,MATCH(C275,DEN_PDC,0),1),0)) | C275: =IF(OR(COPIA!$BU$1=1,COPIA!$BU$1=3),COPIA!CO268,IF(COPIA!$BU$1=2,COPIA!BZ268,IF(ROW()=COPIA!$BT$1,"TOTALE",""))) | D275: =IF(AND(OR(COPIA!$BU$1=1,COPIA!$BU$1=3),INDEX(COPIA!$BT$3:$BV$400,MATCH($C275,COPIA!$BT$3:$BT$400,0),2)<>0),INDEX(COPIA!$BT$3:$BV$400,MATCH($C275,COPIA!$BT$3:$BT$400,0),2),IF(AND(COPIA!$BU$1=2,INDEX(COPIA!$BZ$3:$CB$400,MATCH($C275,COPIA!$BZ$3:$BZ$400,0),2)<>0),INDEX(COPIA!$BZ$3:$CB$400,MATCH($C275,COPIA!$BZ$3:$BZ$400,0),2),"")) | E275: =IF(AND(OR(COPIA!$BU$1=1,COPIA!$BU$1=3),INDEX(COPIA!$BT$3:$BV$400,MATCH($C275,COPIA!$BT$3:$BT$400,0),3)<>0),INDEX(COPIA!$BT$3:$BV$400,MATCH($C275,COPIA!$BT$3:$BT$400,0),3),IF(AND(COPIA!$BU$1=2,INDEX(COPIA!$BZ$3:$CB$400,MATCH($C275,COPIA!$BZ$3:$BZ$400,0),3)<>0),INDEX(COPIA!$BZ$3:$CB$400,MATCH($C275,COPIA!$BZ$3:$BZ$400,0),3),"")) | F275: =IFERROR(IF(AND(COPIA!$BU$1=3,INDEX(COPIA!$BZ$3:$CB$400,MATCH($C275,COPIA!$BZ$3:$BZ$400,0),2)<>0),INDEX(COPIA!$BZ$3:$CB$400,MATCH($C275,COPIA!$BZ$3:$BZ$400,0),2),""),"") | G275: =IFERROR(IF(AND(COPIA!$BU$1=3,INDEX(COPIA!$BZ$3:$CB$400,MATCH($C275,COPIA!$BZ$3:$BZ$400,0),3)<>0),INDEX(COPIA!$BZ$3:$CB$400,MATCH($C275,COPIA!$BZ$3:$BZ$400,0),3),""),"")
B276: =IF(C276=" …………….","……",IFERROR(INDEX(PDC,MATCH(C276,DEN_PDC,0),1),0)) | C276: =IF(OR(COPIA!$BU$1=1,COPIA!$BU$1=3),COPIA!CO269,IF(COPIA!$BU$1=2,COPIA!BZ269,IF(ROW()=COPIA!$BT$1,"TOTALE",""))) | D276: =IF(AND(OR(COPIA!$BU$1=1,COPIA!$BU$1=3),INDEX(COPIA!$BT$3:$BV$400,MATCH($C276,COPIA!$BT$3:$BT$400,0),2)<>0),INDEX(COPIA!$BT$3:$BV$400,MATCH($C276,COPIA!$BT$3:$BT$400,0),2),IF(AND(COPIA!$BU$1=2,INDEX(COPIA!$BZ$3:$CB$400,MATCH($C276,COPIA!$BZ$3:$BZ$400,0),2)<>0),INDEX(COPIA!$BZ$3:$CB$400,MATCH($C276,COPIA!$BZ$3:$BZ$400,0),2),"")) | E276: =IF(AND(OR(COPIA!$BU$1=1,COPIA!$BU$1=3),INDEX(COPIA!$BT$3:$BV$400,MATCH($C276,COPIA!$BT$3:$BT$400,0),3)<>0),INDEX(COPIA!$BT$3:$BV$400,MATCH($C276,COPIA!$BT$3:$BT$400,0),3),IF(AND(COPIA!$BU$1=2,INDEX(COPIA!$BZ$3:$CB$400,MATCH($C276,COPIA!$BZ$3:$BZ$400,0),3)<>0),INDEX(COPIA!$BZ$3:$CB$400,MATCH($C276,COPIA!$BZ$3:$BZ$400,0),3),"")) | F276: =IFERROR(IF(AND(COPIA!$BU$1=3,INDEX(COPIA!$BZ$3:$CB$400,MATCH($C276,COPIA!$BZ$3:$BZ$400,0),2)<>0),INDEX(COPIA!$BZ$3:$CB$400,MATCH($C276,COPIA!$BZ$3:$BZ$400,0),2),""),"") | G276: =IFERROR(IF(AND(COPIA!$BU$1=3,INDEX(COPIA!$BZ$3:$CB$400,MATCH($C276,COPIA!$BZ$3:$BZ$400,0),3)<>0),INDEX(COPIA!$BZ$3:$CB$400,MATCH($C276,COPIA!$BZ$3:$BZ$400,0),3),""),"")
B277: =IF(C277=" …………….","……",IFERROR(INDEX(PDC,MATCH(C277,DEN_PDC,0),1),0)) | C277: =IF(OR(COPIA!$BU$1=1,COPIA!$BU$1=3),COPIA!CO270,IF(COPIA!$BU$1=2,COPIA!BZ270,IF(ROW()=COPIA!$BT$1,"TOTALE",""))) | D277: =IF(AND(OR(COPIA!$BU$1=1,COPIA!$BU$1=3),INDEX(COPIA!$BT$3:$BV$400,MATCH($C277,COPIA!$BT$3:$BT$400,0),2)<>0),INDEX(COPIA!$BT$3:$BV$400,MATCH($C277,COPIA!$BT$3:$BT$400,0),2),IF(AND(COPIA!$BU$1=2,INDEX(COPIA!$BZ$3:$CB$400,MATCH($C277,COPIA!$BZ$3:$BZ$400,0),2)<>0),INDEX(COPIA!$BZ$3:$CB$400,MATCH($C277,COPIA!$BZ$3:$BZ$400,0),2),"")) | E277: =IF(AND(OR(COPIA!$BU$1=1,COPIA!$BU$1=3),INDEX(COPIA!$BT$3:$BV$400,MATCH($C277,COPIA!$BT$3:$BT$400,0),3)<>0),INDEX(COPIA!$BT$3:$BV$400,MATCH($C277,COPIA!$BT$3:$BT$400,0),3),IF(AND(COPIA!$BU$1=2,INDEX(COPIA!$BZ$3:$CB$400,MATCH($C277,COPIA!$BZ$3:$BZ$400,0),3)<>0),INDEX(COPIA!$BZ$3:$CB$400,MATCH($C277,COPIA!$BZ$3:$BZ$400,0),3),"")) | F277: =IFERROR(IF(AND(COPIA!$BU$1=3,INDEX(COPIA!$BZ$3:$CB$400,MATCH($C277,COPIA!$BZ$3:$BZ$400,0),2)<>0),INDEX(COPIA!$BZ$3:$CB$400,MATCH($C277,COPIA!$BZ$3:$BZ$400,0),2),""),"") | G277: =IFERROR(IF(AND(COPIA!$BU$1=3,INDEX(COPIA!$BZ$3:$CB$400,MATCH($C277,COPIA!$BZ$3:$BZ$400,0),3)<>0),INDEX(COPIA!$BZ$3:$CB$400,MATCH($C277,COPIA!$BZ$3:$BZ$400,0),3),""),"")
B278: =IF(C278=" …………….","……",IFERROR(INDEX(PDC,MATCH(C278,DEN_PDC,0),1),0)) | C278: =IF(OR(COPIA!$BU$1=1,COPIA!$BU$1=3),COPIA!CO271,IF(COPIA!$BU$1=2,COPIA!BZ271,IF(ROW()=COPIA!$BT$1,"TOTALE",""))) | D278: =IF(AND(OR(COPIA!$BU$1=1,COPIA!$BU$1=3),INDEX(COPIA!$BT$3:$BV$400,MATCH($C278,COPIA!$BT$3:$BT$400,0),2)<>0),INDEX(COPIA!$BT$3:$BV$400,MATCH($C278,COPIA!$BT$3:$BT$400,0),2),IF(AND(COPIA!$BU$1=2,INDEX(COPIA!$BZ$3:$CB$400,MATCH($C278,COPIA!$BZ$3:$BZ$400,0),2)<>0),INDEX(COPIA!$BZ$3:$CB$400,MATCH($C278,COPIA!$BZ$3:$BZ$400,0),2),"")) | E278: =IF(AND(OR(COPIA!$BU$1=1,COPIA!$BU$1=3),INDEX(COPIA!$BT$3:$BV$400,MATCH($C278,COPIA!$BT$3:$BT$400,0),3)<>0),INDEX(COPIA!$BT$3:$BV$400,MATCH($C278,COPIA!$BT$3:$BT$400,0),3),IF(AND(COPIA!$BU$1=2,INDEX(COPIA!$BZ$3:$CB$400,MATCH($C278,COPIA!$BZ$3:$BZ$400,0),3)<>0),INDEX(COPIA!$BZ$3:$CB$400,MATCH($C278,COPIA!$BZ$3:$BZ$400,0),3),"")) | F278: =IFERROR(IF(AND(COPIA!$BU$1=3,INDEX(COPIA!$BZ$3:$CB$400,MATCH($C278,COPIA!$BZ$3:$BZ$400,0),2)<>0),INDEX(COPIA!$BZ$3:$CB$400,MATCH($C278,COPIA!$BZ$3:$BZ$400,0),2),""),"") | G278: =IFERROR(IF(AND(COPIA!$BU$1=3,INDEX(COPIA!$BZ$3:$CB$400,MATCH($C278,COPIA!$BZ$3:$BZ$400,0),3)<>0),INDEX(COPIA!$BZ$3:$CB$400,MATCH($C278,COPIA!$BZ$3:$BZ$400,0),3),""),"")
B279: =IF(C279=" …………….","……",IFERROR(INDEX(PDC,MATCH(C279,DEN_PDC,0),1),0)) | C279: =IF(OR(COPIA!$BU$1=1,COPIA!$BU$1=3),COPIA!CO272,IF(COPIA!$BU$1=2,COPIA!BZ272,IF(ROW()=COPIA!$BT$1,"TOTALE",""))) | D279: =IF(AND(OR(COPIA!$BU$1=1,COPIA!$BU$1=3),INDEX(COPIA!$BT$3:$BV$400,MATCH($C279,COPIA!$BT$3:$BT$400,0),2)<>0),INDEX(COPIA!$BT$3:$BV$400,MATCH($C279,COPIA!$BT$3:$BT$400,0),2),IF(AND(COPIA!$BU$1=2,INDEX(COPIA!$BZ$3:$CB$400,MATCH($C279,COPIA!$BZ$3:$BZ$400,0),2)<>0),INDEX(COPIA!$BZ$3:$CB$400,MATCH($C279,COPIA!$BZ$3:$BZ$400,0),2),"")) | E279: =IF(AND(OR(COPIA!$BU$1=1,COPIA!$BU$1=3),INDEX(COPIA!$BT$3:$BV$400,MATCH($C279,COPIA!$BT$3:$BT$400,0),3)<>0),INDEX(COPIA!$BT$3:$BV$400,MATCH($C279,COPIA!$BT$3:$BT$400,0),3),IF(AND(COPIA!$BU$1=2,INDEX(COPIA!$BZ$3:$CB$400,MATCH($C279,COPIA!$BZ$3:$BZ$400,0),3)<>0),INDEX(COPIA!$BZ$3:$CB$400,MATCH($C279,COPIA!$BZ$3:$BZ$400,0),3),"")) | F279: =IFERROR(IF(AND(COPIA!$BU$1=3,INDEX(COPIA!$BZ$3:$CB$400,MATCH($C279,COPIA!$BZ$3:$BZ$400,0),2)<>0),INDEX(COPIA!$BZ$3:$CB$400,MATCH($C279,COPIA!$BZ$3:$BZ$400,0),2),""),"") | G279: =IFERROR(IF(AND(COPIA!$BU$1=3,INDEX(COPIA!$BZ$3:$CB$400,MATCH($C279,COPIA!$BZ$3:$BZ$400,0),3)<>0),INDEX(COPIA!$BZ$3:$CB$400,MATCH($C279,COPIA!$BZ$3:$BZ$400,0),3),""),"")
B280: =IF(C280=" …………….","……",IFERROR(INDEX(PDC,MATCH(C280,DEN_PDC,0),1),0)) | C280: =IF(OR(COPIA!$BU$1=1,COPIA!$BU$1=3),COPIA!CO273,IF(COPIA!$BU$1=2,COPIA!BZ273,IF(ROW()=COPIA!$BT$1,"TOTALE",""))) | D280: =IF(AND(OR(COPIA!$BU$1=1,COPIA!$BU$1=3),INDEX(COPIA!$BT$3:$BV$400,MATCH($C280,COPIA!$BT$3:$BT$400,0),2)<>0),INDEX(COPIA!$BT$3:$BV$400,MATCH($C280,COPIA!$BT$3:$BT$400,0),2),IF(AND(COPIA!$BU$1=2,INDEX(COPIA!$BZ$3:$CB$400,MATCH($C280,COPIA!$BZ$3:$BZ$400,0),2)<>0),INDEX(COPIA!$BZ$3:$CB$400,MATCH($C280,COPIA!$BZ$3:$BZ$400,0),2),"")) | E280: =IF(AND(OR(COPIA!$BU$1=1,COPIA!$BU$1=3),INDEX(COPIA!$BT$3:$BV$400,MATCH($C280,COPIA!$BT$3:$BT$400,0),3)<>0),INDEX(COPIA!$BT$3:$BV$400,MATCH($C280,COPIA!$BT$3:$BT$400,0),3),IF(AND(COPIA!$BU$1=2,INDEX(COPIA!$BZ$3:$CB$400,MATCH($C280,COPIA!$BZ$3:$BZ$400,0),3)<>0),INDEX(COPIA!$BZ$3:$CB$400,MATCH($C280,COPIA!$BZ$3:$BZ$400,0),3),"")) | F280: =IFERROR(IF(AND(COPIA!$BU$1=3,INDEX(COPIA!$BZ$3:$CB$400,MATCH($C280,COPIA!$BZ$3:$BZ$400,0),2)<>0),INDEX(COPIA!$BZ$3:$CB$400,MATCH($C280,COPIA!$BZ$3:$BZ$400,0),2),""),"") | G280: =IFERROR(IF(AND(COPIA!$BU$1=3,INDEX(COPIA!$BZ$3:$CB$400,MATCH($C280,COPIA!$BZ$3:$BZ$400,0),3)<>0),INDEX(COPIA!$BZ$3:$CB$400,MATCH($C280,COPIA!$BZ$3:$BZ$400,0),3),""),"")

Sheet SIT.PATR._SIT.ECON.
B1: SITUAZIONE CONTABILE PER DESTINAZIONE
B3: VISUALIZZA IL SALDO ECONOMICO | C3: OPZIONI DI STAMPA | D3: =COPIA!CS3
B4: =COPIA!CQ58 | C4: RIGHE TRA I PROSPETTI
B6: =IF(INDIRECT(ADDRESS(8,6,,,"LIBRO_GIORNALE"))="","",INDIRECT(ADDRESS(8,6,,,"LIBRO_GIORNALE"))) | D6: =IF(INDIRECT(ADDRESS(8,7,,,"LIBRO_GIORNALE"))="","",INDIRECT(ADDRESS(8,7,,,"LIBRO_GIORNALE")))
B7: =IF(COPIA!CO1=0,"",IF(COPIA!$I$1=1,CONCATENATE("Situazione contabile per destinazione al ",COPIA!$AS$1,"/",COPIA!$AT$1,"/",COPIA!$AW$1),IF(COPIA!$I$1=2,CONCATENATE("Stralcio di Situazione contabile per destinazione al ",COPIA!$AS$1,"/",COPIA!AT1,"/",COPIA!AW1),"")))
A8: =IF(AND(OR(B8<>"",D8<>""),OR(C8>0,E8>0),B8<>"SITUAZIONE ECONOMICA"),ROW(),"") | B8: =IF(AND(COPIA!$CP$1=TRUE,IF((ROW())>=COPIA!$BL$1,INDIRECT(ADDRESS(ROW()-COPIA!$BM$1,10,4,,"COPIA")),COPIA!EF1)="SALDO ECONOMICO NEGATIVO"),REPLACE("SALDO ECONOMICO NEGATIVO",1,30,"PERDITA D'ESERCIZIO"),IF((ROW())>=COPIA!$BL$1,INDIRECT(ADDRESS(ROW()-COPIA!$BM$1,10,4,,"COPIA")),COPIA!EF1))
A9: =IF(AND(OR(B9<>"",D9<>""),OR(C9>0,E9>0),B9<>"SITUAZIONE ECONOMICA"),ROW(),IF(AND(OR(B9<>"",D9<>""),B9<>"SITUAZIONE ECONOMICA"),ROW(),"")) | B9: =IF(AND(COPIA!$CP$1=TRUE,IF((ROW())>=COPIA!$BL$1,INDIRECT(ADDRESS(ROW()-COPIA!$BM$1,10,4,,"COPIA")),COPIA!EF2)="SALDO ECONOMICO NEGATIVO"),REPLACE("SALDO ECONOMICO NEGATIVO",1,30,"PERDITA D'ESERCIZIO"),IF((ROW())>=COPIA!$BL$1,INDIRECT(ADDRESS(ROW()-COPIA!$BM$1,10,4,,"COPIA")),COPIA!EF2)) | C9: =IFERROR(IF(AND(COPIA!EG2<>0,ROW()<=COPIA!$BL$1),COPIA!EG2,IF(AND(ROW()>COPIA!$BL$1,INDEX(COPIA!$J$2:$L$200,MATCH('SIT.PATR._SIT.ECON.'!B9,COPIA!$J$2:$J$200,0),3)<>0),INDEX(COPIA!$J$2:$L$200,MATCH('SIT.PATR._SIT.ECON.'!B9,COPIA!$J$2:$J$200,0),3),"")),"") | D9: =IF(AND(COPIA!$CP$1=TRUE,IF((ROW())>=COPIA!$BL$1,CONCATENATE((INDIRECT(ADDRESS(ROW()-COPIA!$BM$1,131,4,,"COPIA")))),COPIA!EJ2)="SALDO ECONOMICO POSITIVO"),REPLACE(IF((ROW())>=COPIA!$BL$1,CONCATENATE((INDIRECT(ADDRESS(ROW()-COPIA!$BM$1,131,4,,"COPIA")))),COPIA!EJ2),1,30,"UTILE D'ESERCIZIO"),IF((ROW())>=COPIA!$BL$1,CONCATENATE((INDIRECT(ADDRESS(ROW()-COPIA!$BM$1,131,4,,"COPIA")))),COPIA!EJ2)) | E9: =IFERROR(IF(AND(ROW()<=COPIA!$BL$1,COPIA!EK2<>0),COPIA!EK2,IF(AND(ROW()>COPIA!$BL$1,INDEX(COPIA!$EA$2:$EC$200,MATCH('SIT.PATR._SIT.ECON.'!D9,COPIA!$EA$2:$EA$200,0),3)<>0),INDEX(COPIA!$EA$2:$EC$200,MATCH('SIT.PATR._SIT.ECON.'!D9,COPIA!$EA$2:$EA$200,0),3),"")),"")
A10: =IF(AND(OR(B10<>"",D10<>""),OR(C10>0,E10>0),B10<>"SITUAZIONE ECONOMICA"),ROW(),IF(AND(OR(B10<>"",D10<>""),B10<>"SITUAZIONE ECONOMICA"),ROW(),"")) | B10: =IF(AND(COPIA!$CP$1=TRUE,IF((ROW())+2>=COPIA!$BL$1,INDIRECT(ADDRESS(ROW()+2-COPIA!$BM$1,10,4,,"COPIA")),COPIA!EF3)="SALDO ECONOMICO NEGATIVO"),REPLACE("SALDO ECONOMICO NEGATIVO",1,30,"PERDITA D'ESERCIZIO"),IF((ROW())+2>=COPIA!$BL$1,INDIRECT(ADDRESS(ROW()+2-COPIA!$BM$1,10,4,,"COPIA")),COPIA!EF3)) | C10: =IFERROR(IF(AND(COPIA!EG3<>0,ROW()<=COPIA!$BL$1),COPIA!EG3,IF(AND(ROW()>COPIA!$BL$1,INDEX(COPIA!$J$2:$L$200,MATCH('SIT.PATR._SIT.ECON.'!B10,COPIA!$J$2:$J$200,0),3)<>0),INDEX(COPIA!$J$2:$L$200,MATCH('SIT.PATR._SIT.ECON.'!B10,COPIA!$J$2:$J$200,0),3),"")),"") | D10: =IF(AND(COPIA!$CP$1=TRUE,IF((ROW())>=COPIA!$BL$1,CONCATENATE((INDIRECT(ADDRESS(ROW()-COPIA!$BM$1,131,4,,"COPIA")))),COPIA!EJ3)="SALDO ECONOMICO POSITIVO"),REPLACE(IF((ROW())>=COPIA!$BL$1,CONCATENATE((INDIRECT(ADDRESS(ROW()-COPIA!$BM$1,131,4,,"COPIA")))),COPIA!EJ3),1,30,"UTILE D'ESERCIZIO"),IF((ROW())>=COPIA!$BL$1,CONCATENATE((INDIRECT(ADDRESS(ROW()-COPIA!$BM$1,131,4,,"COPIA")))),COPIA!EJ3)) | E10: =IFERROR(IF(AND(ROW()<=COPIA!$BL$1,COPIA!EK3<>0),COPIA!EK3,IF(AND(ROW()>COPIA!$BL$1,INDEX(COPIA!$EA$2:$EC$200,MATCH('SIT.PATR._SIT.ECON.'!D10,COPIA!$EA$2:$EA$200,0),3)<>0),INDEX(COPIA!$EA$2:$EC$200,MATCH('SIT.PATR._SIT.ECON.'!D10,COPIA!$EA$2:$EA$200,0),3),"")),"")
A11: =IF(AND(OR(B11<>"",D11<>""),OR(C11>0,E11>0),B11<>"SITUAZIONE ECONOMICA"),ROW(),IF(AND(OR(B11<>"",D11<>""),B11<>"SITUAZIONE ECONOMICA"),ROW(),"")) | B11: =IF(AND(COPIA!$CP$1=TRUE,IF((ROW())>=COPIA!$BL$1,INDIRECT(ADDRESS(ROW()-COPIA!$BM$1,10,4,,"COPIA")),COPIA!EF4)="SALDO ECONOMICO NEGATIVO"),REPLACE("SALDO ECONOMICO NEGATIVO",1,30,"PERDITA D'ESERCIZIO"),IF((ROW())>=COPIA!$BL$1,INDIRECT(ADDRESS(ROW()-COPIA!$BM$1,10,4,,"COPIA")),COPIA!EF4)) | C11: =IFERROR(IF(AND(COPIA!EG4<>0,ROW()<=COPIA!$BL$1),COPIA!EG4,IF(AND(ROW()>COPIA!$BL$1,INDEX(COPIA!$J$2:$L$200,MATCH('SIT.PATR._SIT.ECON.'!B11,COPIA!$J$2:$J$200,0),3)<>0),INDEX(COPIA!$J$2:$L$200,MATCH('SIT.PATR._SIT.ECON.'!B11,COPIA!$J$2:$J$200,0),3),"")),"") | D11: =IF(AND(COPIA!$CP$1=TRUE,IF((ROW())>=COPIA!$BL$1,CONCATENATE((INDIRECT(ADDRESS(ROW()-COPIA!$BM$1,131,4,,"COPIA")))),COPIA!EJ4)="SALDO ECONOMICO POSITIVO"),REPLACE(IF((ROW())>=COPIA!$BL$1,CONCATENATE((INDIRECT(ADDRESS(ROW()-COPIA!$BM$1,131,4,,"COPIA")))),COPIA!EJ4),1,30,"UTILE D'ESERCIZIO"),IF((ROW())>=COPIA!$BL$1,CONCATENATE((INDIRECT(ADDRESS(ROW()-COPIA!$BM$1,131,4,,"COPIA")))),COPIA!EJ4)) | E11: =IFERROR(IF(AND(ROW()<=COPIA!$BL$1,COPIA!EK4<>0),COPIA!EK4,IF(AND(ROW()>COPIA!$BL$1,INDEX(COPIA!$EA$2:$EC$200,MATCH('SIT.PATR._SIT.ECON.'!D11,COPIA!$EA$2:$EA$200,0),3)<>0),INDEX(COPIA!$EA$2:$EC$200,MATCH('SIT.PATR._SIT.ECON.'!D11,COPIA!$EA$2:$EA$200,0),3),"")),"")
A12: =IF(AND(OR(B12<>"",D12<>""),OR(C12>0,E12>0),B12<>"SITUAZIONE ECONOMICA"),ROW(),IF(AND(OR(B12<>"",D12<>""),B12<>"SITUAZIONE ECONOMICA"),ROW(),"")) | B12: =IF(AND(COPIA!$CP$1=TRUE,IF((ROW())>=COPIA!$BL$1,INDIRECT(ADDRESS(ROW()-COPIA!$BM$1,10,4,,"COPIA")),COPIA!EF5)="SALDO ECONOMICO NEGATIVO"),REPLACE("SALDO ECONOMICO NEGATIVO",1,30,"PERDITA D'ESERCIZIO"),IF((ROW())>=COPIA!$BL$1,INDIRECT(ADDRESS(ROW()-COPIA!$BM$1,10,4,,"COPIA")),COPIA!EF5)) | C12: =IFERROR(IF(AND(COPIA!EG5<>0,ROW()<=COPIA!$BL$1),COPIA!EG5,IF(AND(ROW()>COPIA!$BL$1,INDEX(COPIA!$J$2:$L$200,MATCH('SIT.PATR._SIT.ECON.'!B12,COPIA!$J$2:$J$200,0),3)<>0),INDEX(COPIA!$J$2:$L$200,MATCH('SIT.PATR._SIT.ECON.'!B12,COPIA!$J$2:$J$200,0),3),"")),"") | D12: =IF(AND(COPIA!$CP$1=TRUE,IF((ROW())>=COPIA!$BL$1,CONCATENATE((INDIRECT(ADDRESS(ROW()-COPIA!$BM$1,131,4,,"COPIA")))),COPIA!EJ5)="SALDO ECONOMICO POSITIVO"),REPLACE(IF((ROW())>=COPIA!$BL$1,CONCATENATE((INDIRECT(ADDRESS(ROW()-COPIA!$BM$1,131,4,,"COPIA")))),COPIA!EJ5),1,30,"UTILE D'ESERCIZIO"),IF((ROW())>=COPIA!$BL$1,CONCATENATE((INDIRECT(ADDRESS(ROW()-COPIA!$BM$1,131,4,,"COPIA")))),COPIA!EJ5)) | E12: =IFERROR(IF(AND(ROW()<=COPIA!$BL$1,COPIA!EK5<>0),COPIA!EK5,IF(AND(ROW()>COPIA!$BL$1,INDEX(COPIA!$EA$2:$EC$200,MATCH('SIT.PATR._SIT.ECON.'!D12,COPIA!$EA$2:$EA$200,0),3)<>0),INDEX(COPIA!$EA$2:$EC$200,MATCH('SIT.PATR._SIT.ECON.'!D12,COPIA!$EA$2:$EA$200,0),3),"")),"")
A13: =IF(AND(OR(B13<>"",D13<>""),OR(C13>0,E13>0),B13<>"SITUAZIONE ECONOMICA"),ROW(),IF(AND(OR(B13<>"",D13<>""),B13<>"SITUAZIONE ECONOMICA"),ROW(),"")) | B13: =IF(AND(COPIA!$CP$1=TRUE,IF((ROW())>=COPIA!$BL$1,INDIRECT(ADDRESS(ROW()-COPIA!$BM$1,10,4,,"COPIA")),COPIA!EF6)="SALDO ECONOMICO NEGATIVO"),REPLACE("SALDO ECONOMICO NEGATIVO",1,30,"PERDITA D'ESERCIZIO"),IF((ROW())>=COPIA!$BL$1,INDIRECT(ADDRESS(ROW()-COPIA!$BM$1,10,4,,"COPIA")),COPIA!EF6)) | C13: =IFERROR(IF(AND(COPIA!EG6<>0,ROW()<=COPIA!$BL$1),COPIA!EG6,IF(AND(ROW()>COPIA!$BL$1,INDEX(COPIA!$J$2:$L$200,MATCH('SIT.PATR._SIT.ECON.'!B13,COPIA!$J$2:$J$200,0),3)<>0),INDEX(COPIA!$J$2:$L$200,MATCH('SIT.PATR._SIT.ECON.'!B13,COPIA!$J$2:$J$200,0),3),"")),"") | D13: =IF(AND(COPIA!$CP$1=TRUE,IF((ROW())>=COPIA!$BL$1,CONCATENATE((INDIRECT(ADDRESS(ROW()-COPIA!$BM$1,131,4,,"COPIA")))),COPIA!EJ6)="SALDO ECONOMICO POSITIVO"),REPLACE(IF((ROW())>=COPIA!$BL$1,CONCATENATE((INDIRECT(ADDRESS(ROW()-COPIA!$BM$1,131,4,,"COPIA")))),COPIA!EJ6),1,30,"UTILE D'ESERCIZIO"),IF((ROW())>=COPIA!$BL$1,CONCATENATE((INDIRECT(ADDRESS(ROW()-COPIA!$BM$1,131,4,,"COPIA")))),COPIA!EJ6)) | E13: =IFERROR(IF(AND(ROW()<=COPIA!$BL$1,COPIA!EK6<>0),COPIA!EK6,IF(AND(ROW()>COPIA!$BL$1,INDEX(COPIA!$EA$2:$EC$200,MATCH('SIT.PATR._SIT.ECON.'!D13,COPIA!$EA$2:$EA$200,0),3)<>0),INDEX(COPIA!$EA$2:$EC$200,MATCH('SIT.PATR._SIT.ECON.'!D13,COPIA!$EA$2:$EA$200,0),3),"")),"")
A14: =IF(AND(OR(B14<>"",D14<>""),OR(C14>0,E14>0),B14<>"SITUAZIONE ECONOMICA"),ROW(),IF(AND(OR(B14<>"",D14<>""),B14<>"SITUAZIONE ECONOMICA"),ROW(),"")) | B14: =IF(AND(COPIA!$CP$1=TRUE,IF((ROW())>=COPIA!$BL$1,INDIRECT(ADDRESS(ROW()-COPIA!$BM$1,10,4,,"COPIA")),COPIA!EF7)="SALDO ECONOMICO NEGATIVO"),REPLACE("SALDO ECONOMICO NEGATIVO",1,30,"PERDITA D'ESERCIZIO"),IF((ROW())>=COPIA!$BL$1,INDIRECT(ADDRESS(ROW()-COPIA!$BM$1,10,4,,"COPIA")),COPIA!EF7)) | C14: =IFERROR(IF(AND(COPIA!EG7<>0,ROW()<=COPIA!$BL$1),COPIA!EG7,IF(AND(ROW()>COPIA!$BL$1,INDEX(COPIA!$J$2:$L$200,MATCH('SIT.PATR._SIT.ECON.'!B14,COPIA!$J$2:$J$200,0),3)<>0),INDEX(COPIA!$J$2:$L$200,MATCH('SIT.PATR._SIT.ECON.'!B14,COPIA!$J$2:$J$200,0),3),"")),"") | D14: =IF(AND(COPIA!$CP$1=TRUE,IF((ROW())>=COPIA!$BL$1,CONCATENATE((INDIRECT(ADDRESS(ROW()-COPIA!$BM$1,131,4,,"COPIA")))),COPIA!EJ7)="SALDO ECONOMICO POSITIVO"),REPLACE(IF((ROW())>=COPIA!$BL$1,CONCATENATE((INDIRECT(ADDRESS(ROW()-COPIA!$BM$1,131,4,,"COPIA")))),COPIA!EJ7),1,30,"UTILE D'ESERCIZIO"),IF((ROW())>=COPIA!$BL$1,CONCATENATE((INDIRECT(ADDRESS(ROW()-COPIA!$BM$1,131,4,,"COPIA")))),COPIA!EJ7)) | E14: =IFERROR(IF(AND(ROW()<=COPIA!$BL$1,COPIA!EK7<>0),COPIA!EK7,IF(AND(ROW()>COPIA!$BL$1,INDEX(COPIA!$EA$2:$EC$200,MATCH('SIT.PATR._SIT.ECON.'!D14,COPIA!$EA$2:$EA$200,0),3)<>0),INDEX(COPIA!$EA$2:$EC$200,MATCH('SIT.PATR._SIT.ECON.'!D14,COPIA!$EA$2:$EA$200,0),3),"")),"")
A15: =IF(AND(OR(B15<>"",D15<>""),OR(C15>0,E15>0),B15<>"SITUAZIONE ECONOMICA"),ROW(),IF(AND(OR(B15<>"",D15<>""),B15<>"SITUAZIONE ECONOMICA"),ROW(),"")) | B15: =IF(AND(COPIA!$CP$1=TRUE,IF((ROW())>=COPIA!$BL$1,INDIRECT(ADDRESS(ROW()-COPIA!$BM$1,10,4,,"COPIA")),COPIA!EF8)="SALDO ECONOMICO NEGATIVO"),REPLACE("SALDO ECONOMICO NEGATIVO",1,30,"PERDITA D'ESERCIZIO"),IF((ROW())>=COPIA!$BL$1,INDIRECT(ADDRESS(ROW()-COPIA!$BM$1,10,4,,"COPIA")),COPIA!EF8)) | C15: =IFERROR(IF(AND(COPIA!EG8<>0,ROW()<=COPIA!$BL$1),COPIA!EG8,IF(AND(ROW()>COPIA!$BL$1,INDEX(COPIA!$J$2:$L$200,MATCH('SIT.PATR._SIT.ECON.'!B15,COPIA!$J$2:$J$200,0),3)<>0),INDEX(COPIA!$J$2:$L$200,MATCH('SIT.PATR._SIT.ECON.'!B15,COPIA!$J$2:$J$200,0),3),"")),"") | D15: =IF(AND(COPIA!$CP$1=TRUE,IF((ROW())>=COPIA!$BL$1,CONCATENATE((INDIRECT(ADDRESS(ROW()-COPIA!$BM$1,131,4,,"COPIA")))),COPIA!EJ8)="SALDO ECONOMICO POSITIVO"),REPLACE(IF((ROW())>=COPIA!$BL$1,CONCATENATE((INDIRECT(ADDRESS(ROW()-COPIA!$BM$1,131,4,,"COPIA")))),COPIA!EJ8),1,30,"UTILE D'ESERCIZIO"),IF((ROW())>=COPIA!$BL$1,CONCATENATE((INDIRECT(ADDRESS(ROW()-COPIA!$BM$1,131,4,,"COPIA")))),COPIA!EJ8)) | E15: =IFERROR(IF(AND(ROW()<=COPIA!$BL$1,COPIA!EK8<>0),COPIA!EK8,IF(AND(ROW()>COPIA!$BL$1,INDEX(COPIA!$EA$2:$EC$200,MATCH('SIT.PATR._SIT.ECON.'!D15,COPIA!$EA$2:$EA$200,0),3)<>0),INDEX(COPIA!$EA$2:$EC$200,MATCH('SIT.PATR._SIT.ECON.'!D15,COPIA!$EA$2:$EA$200,0),3),"")),"")
A16: =IF(AND(OR(B16<>"",D16<>""),OR(C16>0,E16>0),B16<>"SITUAZIONE ECONOMICA"),ROW(),IF(AND(OR(B16<>"",D16<>""),B16<>"SITUAZIONE ECONOMICA"),ROW(),"")) | B16: =IF(AND(COPIA!$CP$1=TRUE,IF((ROW())>=COPIA!$BL$1,INDIRECT(ADDRESS(ROW()-COPIA!$BM$1,10,4,,"COPIA")),COPIA!EF9)="SALDO ECONOMICO NEGATIVO"),REPLACE("SALDO ECONOMICO NEGATIVO",1,30,"PERDITA D'ESERCIZIO"),IF((ROW())>=COPIA!$BL$1,INDIRECT(ADDRESS(ROW()-COPIA!$BM$1,10,4,,"COPIA")),COPIA!EF9)) | C16: =IFERROR(IF(AND(COPIA!EG9<>0,ROW()<=COPIA!$BL$1),COPIA!EG9,IF(AND(ROW()>COPIA!$BL$1,INDEX(COPIA!$J$2:$L$200,MATCH('SIT.PATR._SIT.ECON.'!B16,COPIA!$J$2:$J$200,0),3)<>0),INDEX(COPIA!$J$2:$L$200,MATCH('SIT.PATR._SIT.ECON.'!B16,COPIA!$J$2:$J$200,0),3),"")),"") | D16: =IF(AND(COPIA!$CP$1=TRUE,IF((ROW())>=COPIA!$BL$1,CONCATENATE((INDIRECT(ADDRESS(ROW()-COPIA!$BM$1,131,4,,"COPIA")))),COPIA!EJ9)="SALDO ECONOMICO POSITIVO"),REPLACE(IF((ROW())>=COPIA!$BL$1,CONCATENATE((INDIRECT(ADDRESS(ROW()-COPIA!$BM$1,131,4,,"COPIA")))),COPIA!EJ9),1,30,"UTILE D'ESERCIZIO"),IF((ROW())>=COPIA!$BL$1,CONCATENATE((INDIRECT(ADDRESS(ROW()-COPIA!$BM$1,131,4,,"COPIA")))),COPIA!EJ9)) | E16: =IFERROR(IF(AND(ROW()<=COPIA!$BL$1,COPIA!EK9<>0),COPIA!EK9,IF(AND(ROW()>COPIA!$BL$1,INDEX(COPIA!$EA$2:$EC$200,MATCH('SIT.PATR._SIT.ECON.'!D16,COPIA!$EA$2:$EA$200,0),3)<>0),INDEX(COPIA!$EA$2:$EC$200,MATCH('SIT.PATR._SIT.ECON.'!D16,COPIA!$EA$2:$EA$200,0),3),"")),"")
A17: =IF(AND(OR(B17<>"",D17<>""),OR(C17>0,E17>0),B17<>"SITUAZIONE ECONOMICA"),ROW(),IF(AND(OR(B17<>"",D17<>""),B17<>"SITUAZIONE ECONOMICA"),ROW(),"")) | B17: =IF(AND(COPIA!$CP$1=TRUE,IF((ROW())>=COPIA!$BL$1,INDIRECT(ADDRESS(ROW()-COPIA!$BM$1,10,4,,"COPIA")),COPIA!EF10)="SALDO ECONOMICO NEGATIVO"),REPLACE("SALDO ECONOMICO NEGATIVO",1,30,"PERDITA D'ESERCIZIO"),IF((ROW())>=COPIA!$BL$1,INDIRECT(ADDRESS(ROW()-COPIA!$BM$1,10,4,,"COPIA")),COPIA!EF10)) | C17: =IFERROR(IF(AND(COPIA!EG10<>0,ROW()<=COPIA!$BL$1),COPIA!EG10,IF(AND(ROW()>COPIA!$BL$1,INDEX(COPIA!$J$2:$L$200,MATCH('SIT.PATR._SIT.ECON.'!B17,COPIA!$J$2:$J$200,0),3)<>0),INDEX(COPIA!$J$2:$L$200,MATCH('SIT.PATR._SIT.ECON.'!B17,COPIA!$J$2:$J$200,0),3),"")),"") | D17: =IF(AND(COPIA!$CP$1=TRUE,IF((ROW())>=COPIA!$BL$1,CONCATENATE((INDIRECT(ADDRESS(ROW()-COPIA!$BM$1,131,4,,"COPIA")))),COPIA!EJ10)="SALDO ECONOMICO POSITIVO"),REPLACE(IF((ROW())>=COPIA!$BL$1,CONCATENATE((INDIRECT(ADDRESS(ROW()-COPIA!$BM$1,131,4,,"COPIA")))),COPIA!EJ10),1,30,"UTILE D'ESERCIZIO"),IF((ROW())>=COPIA!$BL$1,CONCATENATE((INDIRECT(ADDRESS(ROW()-COPIA!$BM$1,131,4,,"COPIA")))),COPIA!EJ10)) | E17: =IFERROR(IF(AND(ROW()<=COPIA!$BL$1,COPIA!EK10<>0),COPIA!EK10,IF(AND(ROW()>COPIA!$BL$1,INDEX(COPIA!$EA$2:$EC$200,MATCH('SIT.PATR._SIT.ECON.'!D17,COPIA!$EA$2:$EA$200,0),3)<>0),INDEX(COPIA!$EA$2:$EC$200,MATCH('SIT.PATR._SIT.ECON.'!D17,COPIA!$EA$2:$EA$200,0),3),"")),"")
A18: =IF(AND(OR(B18<>"",D18<>""),OR(C18>0,E18>0),B18<>"SITUAZIONE ECONOMICA"),ROW(),IF(AND(OR(B18<>"",D18<>""),B18<>"SITUAZIONE ECONOMICA"),ROW(),"")) | B18: =IF(AND(COPIA!$CP$1=TRUE,IF((ROW())>=COPIA!$BL$1,INDIRECT(ADDRESS(ROW()-COPIA!$BM$1,10,4,,"COPIA")),COPIA!EF11)="SALDO ECONOMICO NEGATIVO"),REPLACE("SALDO ECONOMICO NEGATIVO",1,30,"PERDITA D'ESERCIZIO"),IF((ROW())>=COPIA!$BL$1,INDIRECT(ADDRESS(ROW()-COPIA!$BM$1,10,4,,"COPIA")),COPIA!EF11)) | C18: =IFERROR(IF(AND(COPIA!EG11<>0,ROW()<=COPIA!$BL$1),COPIA!EG11,IF(AND(ROW()>COPIA!$BL$1,INDEX(COPIA!$J$2:$L$200,MATCH('SIT.PATR._SIT.ECON.'!B18,COPIA!$J$2:$J$200,0),3)<>0),INDEX(COPIA!$J$2:$L$200,MATCH('SIT.PATR._SIT.ECON.'!B18,COPIA!$J$2:$J$200,0),3),"")),"") | D18: =IF(AND(COPIA!$CP$1=TRUE,IF((ROW())>=COPIA!$BL$1,CONCATENATE((INDIRECT(ADDRESS(ROW()-COPIA!$BM$1,131,4,,"COPIA")))),COPIA!EJ11)="SALDO ECONOMICO POSITIVO"),REPLACE(IF((ROW())>=COPIA!$BL$1,CONCATENATE((INDIRECT(ADDRESS(ROW()-COPIA!$BM$1,131,4,,"COPIA")))),COPIA!EJ11),1,30,"UTILE D'ESERCIZIO"),IF((ROW())>=COPIA!$BL$1,CONCATENATE((INDIRECT(ADDRESS(ROW()-COPIA!$BM$1,131,4,,"COPIA")))),COPIA!EJ11)) | E18: =IFERROR(IF(AND(ROW()<=COPIA!$BL$1,COPIA!EK11<>0),COPIA!EK11,IF(AND(ROW()>COPIA!$BL$1,INDEX(COPIA!$EA$2:$EC$200,MATCH('SIT.PATR._SIT.ECON.'!D18,COPIA!$EA$2:$EA$200,0),3)<>0),INDEX(COPIA!$EA$2:$EC$200,MATCH('SIT.PATR._SIT.ECON.'!D18,COPIA!$EA$2:$EA$200,0),3),"")),"")
A19: =IF(AND(OR(B19<>"",D19<>""),OR(C19>0,E19>0),B19<>"SITUAZIONE ECONOMICA"),ROW(),IF(AND(OR(B19<>"",D19<>""),B19<>"SITUAZIONE ECONOMICA"),ROW(),"")) | B19: =IF(AND(COPIA!$CP$1=TRUE,IF((ROW())>=COPIA!$BL$1,INDIRECT(ADDRESS(ROW()-COPIA!$BM$1,10,4,,"COPIA")),COPIA!EF12)="SALDO ECONOMICO NEGATIVO"),REPLACE("SALDO ECONOMICO NEGATIVO",1,30,"PERDITA D'ESERCIZIO"),IF((ROW())>=COPIA!$BL$1,INDIRECT(ADDRESS(ROW()-COPIA!$BM$1,10,4,,"COPIA")),COPIA!EF12)) | C19: =IFERROR(IF(AND(COPIA!EG12<>0,ROW()<=COPIA!$BL$1),COPIA!EG12,IF(AND(ROW()>COPIA!$BL$1,INDEX(COPIA!$J$2:$L$200,MATCH('SIT.PATR._SIT.ECON.'!B19,COPIA!$J$2:$J$200,0),3)<>0),INDEX(COPIA!$J$2:$L$200,MATCH('SIT.PATR._SIT.ECON.'!B19,COPIA!$J$2:$J$200,0),3),"")),"") | D19: =IF(AND(COPIA!$CP$1=TRUE,IF((ROW())>=COPIA!$BL$1,CONCATENATE((INDIRECT(ADDRESS(ROW()-COPIA!$BM$1,131,4,,"COPIA")))),COPIA!EJ12)="SALDO ECONOMICO POSITIVO"),REPLACE(IF((ROW())>=COPIA!$BL$1,CONCATENATE((INDIRECT(ADDRESS(ROW()-COPIA!$BM$1,131,4,,"COPIA")))),COPIA!EJ12),1,30,"UTILE D'ESERCIZIO"),IF((ROW())>=COPIA!$BL$1,CONCATENATE((INDIRECT(ADDRESS(ROW()-COPIA!$BM$1,131,4,,"COPIA")))),COPIA!EJ12)) | E19: =IFERROR(IF(AND(ROW()<=COPIA!$BL$1,COPIA!EK12<>0),COPIA!EK12,IF(AND(ROW()>COPIA!$BL$1,INDEX(COPIA!$EA$2:$EC$200,MATCH('SIT.PATR._SIT.ECON.'!D19,COPIA!$EA$2:$EA$200,0),3)<>0),INDEX(COPIA!$EA$2:$EC$200,MATCH('SIT.PATR._SIT.ECON.'!D19,COPIA!$EA$2:$EA$200,0),3),"")),"")
A20: =IF(AND(OR(B20<>"",D20<>""),OR(C20>0,E20>0),B20<>"SITUAZIONE ECONOMICA"),ROW(),IF(AND(OR(B20<>"",D20<>""),B20<>"SITUAZIONE ECONOMICA"),ROW(),"")) | B20: =IF(AND(COPIA!$CP$1=TRUE,IF((ROW())>=COPIA!$BL$1,INDIRECT(ADDRESS(ROW()-COPIA!$BM$1,10,4,,"COPIA")),COPIA!EF13)="SALDO ECONOMICO NEGATIVO"),REPLACE("SALDO ECONOMICO NEGATIVO",1,30,"PERDITA D'ESERCIZIO"),IF((ROW())>=COPIA!$BL$1,INDIRECT(ADDRESS(ROW()-COPIA!$BM$1,10,4,,"COPIA")),COPIA!EF13)) | C20: =IFERROR(IF(AND(COPIA!EG13<>0,ROW()<=COPIA!$BL$1),COPIA!EG13,IF(AND(ROW()>COPIA!$BL$1,INDEX(COPIA!$J$2:$L$200,MATCH('SIT.PATR._SIT.ECON.'!B20,COPIA!$J$2:$J$200,0),3)<>0),INDEX(COPIA!$J$2:$L$200,MATCH('SIT.PATR._SIT.ECON.'!B20,COPIA!$J$2:$J$200,0),3),"")),"") | D20: =IF(AND(COPIA!$CP$1=TRUE,IF((ROW())>=COPIA!$BL$1,CONCATENATE((INDIRECT(ADDRESS(ROW()-COPIA!$BM$1,131,4,,"COPIA")))),COPIA!EJ13)="SALDO ECONOMICO POSITIVO"),REPLACE(IF((ROW())>=COPIA!$BL$1,CONCATENATE((INDIRECT(ADDRESS(ROW()-COPIA!$BM$1,131,4,,"COPIA")))),COPIA!EJ13),1,30,"UTILE D'ESERCIZIO"),IF((ROW())>=COPIA!$BL$1,CONCATENATE((INDIRECT(ADDRESS(ROW()-COPIA!$BM$1,131,4,,"COPIA")))),COPIA!EJ13)) | E20: =IFERROR(IF(AND(ROW()<=COPIA!$BL$1,COPIA!EK13<>0),COPIA!EK13,IF(AND(ROW()>COPIA!$BL$1,INDEX(COPIA!$EA$2:$EC$200,MATCH('SIT.PATR._SIT.ECON.'!D20,COPIA!$EA$2:$EA$200,0),3)<>0),INDEX(COPIA!$EA$2:$EC$200,MATCH('SIT.PATR._SIT.ECON.'!D20,COPIA!$EA$2:$EA$200,0),3),"")),"")
A21: =IF(AND(OR(B21<>"",D21<>""),OR(C21>0,E21>0),B21<>"SITUAZIONE ECONOMICA"),ROW(),IF(AND(OR(B21<>"",D21<>""),B21<>"SITUAZIONE ECONOMICA"),ROW(),"")) | B21: =IF(AND(COPIA!$CP$1=TRUE,IF((ROW())>=COPIA!$BL$1,INDIRECT(ADDRESS(ROW()-COPIA!$BM$1,10,4,,"COPIA")),COPIA!EF14)="SALDO ECONOMICO NEGATIVO"),REPLACE("SALDO ECONOMICO NEGATIVO",1,30,"PERDITA D'ESERCIZIO"),IF((ROW())>=COPIA!$BL$1,INDIRECT(ADDRESS(ROW()-COPIA!$BM$1,10,4,,"COPIA")),COPIA!EF14)) | C21: =IFERROR(IF(AND(COPIA!EG14<>0,ROW()<=COPIA!$BL$1),COPIA!EG14,IF(AND(ROW()>COPIA!$BL$1,INDEX(COPIA!$J$2:$L$200,MATCH('SIT.PATR._SIT.ECON.'!B21,COPIA!$J$2:$J$200,0),3)<>0),INDEX(COPIA!$J$2:$L$200,MATCH('SIT.PATR._SIT.ECON.'!B21,COPIA!$J$2:$J$200,0),3),"")),"") | D21: =IF(AND(COPIA!$CP$1=TRUE,IF((ROW())>=COPIA!$BL$1,CONCATENATE((INDIRECT(ADDRESS(ROW()-COPIA!$BM$1,131,4,,"COPIA")))),COPIA!EJ14)="SALDO ECONOMICO POSITIVO"),REPLACE(IF((ROW())>=COPIA!$BL$1,CONCATENATE((INDIRECT(ADDRESS(ROW()-COPIA!$BM$1,131,4,,"COPIA")))),COPIA!EJ14),1,30,"UTILE D'ESERCIZIO"),IF((ROW())>=COPIA!$BL$1,CONCATENATE((INDIRECT(ADDRESS(ROW()-COPIA!$BM$1,131,4,,"COPIA")))),COPIA!EJ14)) | E21: =IFERROR(IF(AND(ROW()<=COPIA!$BL$1,COPIA!EK14<>0),COPIA!EK14,IF(AND(ROW()>COPIA!$BL$1,INDEX(COPIA!$EA$2:$EC$200,MATCH('SIT.PATR._SIT.ECON.'!D21,COPIA!$EA$2:$EA$200,0),3)<>0),INDEX(COPIA!$EA$2:$EC$200,MATCH('SIT.PATR._SIT.ECON.'!D21,COPIA!$EA$2:$EA$200,0),3),"")),"")
A22: =IF(AND(OR(B22<>"",D22<>""),OR(C22>0,E22>0),B22<>"SITUAZIONE ECONOMICA"),ROW(),IF(AND(OR(B22<>"",D22<>""),B22<>"SITUAZIONE ECONOMICA"),ROW(),"")) | B22: =IF(AND(COPIA!$CP$1=TRUE,IF((ROW())>=COPIA!$BL$1,INDIRECT(ADDRESS(ROW()-COPIA!$BM$1,10,4,,"COPIA")),COPIA!EF15)="SALDO ECONOMICO NEGATIVO"),REPLACE("SALDO ECONOMICO NEGATIVO",1,30,"PERDITA D'ESERCIZIO"),IF((ROW())>=COPIA!$BL$1,INDIRECT(ADDRESS(ROW()-COPIA!$BM$1,10,4,,"COPIA")),COPIA!EF15)) | C22: =IFERROR(IF(AND(COPIA!EG15<>0,ROW()<=COPIA!$BL$1),COPIA!EG15,IF(AND(ROW()>COPIA!$BL$1,INDEX(COPIA!$J$2:$L$200,MATCH('SIT.PATR._SIT.ECON.'!B22,COPIA!$J$2:$J$200,0),3)<>0),INDEX(COPIA!$J$2:$L$200,MATCH('SIT.PATR._SIT.ECON.'!B22,COPIA!$J$2:$J$200,0),3),"")),"") | D22: =IF(AND(COPIA!$CP$1=TRUE,IF((ROW())>=COPIA!$BL$1,CONCATENATE((INDIRECT(ADDRESS(ROW()-COPIA!$BM$1,131,4,,"COPIA")))),COPIA!EJ15)="SALDO ECONOMICO POSITIVO"),REPLACE(IF((ROW())>=COPIA!$BL$1,CONCATENATE((INDIRECT(ADDRESS(ROW()-COPIA!$BM$1,131,4,,"COPIA")))),COPIA!EJ15),1,30,"UTILE D'ESERCIZIO"),IF((ROW())>=COPIA!$BL$1,CONCATENATE((INDIRECT(ADDRESS(ROW()-COPIA!$BM$1,131,4,,"COPIA")))),COPIA!EJ15)) | E22: =IFERROR(IF(AND(ROW()<=COPIA!$BL$1,COPIA!EK15<>0),COPIA!EK15,IF(AND(ROW()>COPIA!$BL$1,INDEX(COPIA!$EA$2:$EC$200,MATCH('SIT.PATR._SIT.ECON.'!D22,COPIA!$EA$2:$EA$200,0),3)<>0),INDEX(COPIA!$EA$2:$EC$200,MATCH('SIT.PATR._SIT.ECON.'!D22,COPIA!$EA$2:$EA$200,0),3),"")),"")
... A145: =IF(AND(OR(B145<>"",D145<>""),OR(C145>0,E145>0),B145<>"SITUAZIONE ECONOMICA"),ROW(),IF(AND(OR(B145<>"",D145<>""),B145<>"SITUAZIONE ECONOMICA"),ROW(),"")) | B145: =IF(AND(COPIA!$CP$1=TRUE,IF((ROW())>=COPIA!$BL$1,INDIRECT(ADDRESS(ROW()-COPIA!$BM$1,10,4,,"COPIA")),COPIA!EF138)="SALDO ECONOMICO NEGATIVO"),REPLACE("SALDO ECONOMICO NEGATIVO",1,30,"PERDITA D'ESERCIZIO"),IF((ROW())>=COPIA!$BL$1,INDIRECT(ADDRESS(ROW()-COPIA!$BM$1,10,4,,"COPIA")),COPIA!EF138)) | C145: =IFERROR(IF(AND(COPIA!EG138<>0,ROW()<=COPIA!$BL$1),COPIA!EG138,IF(AND(ROW()>COPIA!$BL$1,INDEX(COPIA!$J$2:$L$200,MATCH('SIT.PATR._SIT.ECON.'!B145,COPIA!$J$2:$J$200,0),3)<>0),INDEX(COPIA!$J$2:$L$200,MATCH('SIT.PATR._SIT.ECON.'!B145,COPIA!$J$2:$J$200,0),3),"")),"") | D145: =IF(AND(COPIA!$CP$1=TRUE,IF((ROW())>=COPIA!$BL$1,CONCATENATE((INDIRECT(ADDRESS(ROW()-COPIA!$BM$1,131,4,,"COPIA")))),COPIA!EJ138)="SALDO ECONOMICO POSITIVO"),REPLACE(IF((ROW())>=COPIA!$BL$1,CONCATENATE((INDIRECT(ADDRESS(ROW()-COPIA!$BM$1,131,4,,"COPIA")))),COPIA!EJ138),1,30,"UTILE D'ESERCIZIO"),IF((ROW())>=COPIA!$BL$1,CONCATENATE((INDIRECT(ADDRESS(ROW()-COPIA!$BM$1,131,4,,"COPIA")))),COPIA!EJ138)) | E145: =IFERROR(IF(AND(ROW()<=COPIA!$BL$1,COPIA!EK138<>0),COPIA!EK138,IF(AND(ROW()>COPIA!$BL$1,INDEX(COPIA!$EA$2:$EC$200,MATCH('SIT.PATR._SIT.ECON.'!D145,COPIA!$EA$2:$EA$200,0),3)<>0),INDEX(COPIA!$EA$2:$EC$200,MATCH('SIT.PATR._SIT.ECON.'!D145,COPIA!$EA$2:$EA$200,0),3),"")),"")

Sheet BILANCIO
B1: BILANCIO DI ESERCIZIO
B3: OPZIONI DI VISUALIZZAZIONE: | D3: VISUALIZZA I TOTALI: | E3: OPZIONI DI STAMPA
B4: IN FORMA ABBREVIATA | D4: DELLE CLASSI
B6: SEMPLIFICAZIONI PER LO STATO PATRIMONIALE IN FORMA ABBREVIATA | D6: Destinazione degli interessi attivi verso controllate, collegate, controllanti: | E6: RIGHE TRA I PROSPETTI
B7: NON ATTIVATE | D7: C 16 b)
B9: =CONCATENATE('SIT.PATR._SIT.ECON.'!D3," - ",COPIA!FL1) -> - - | H9: =IF(COPIA!CO1=0,"","Riporta le informazioni di carattere finanziario nelle celle in grigio.") | K9: =COPIA!E1 -> 0 | L9: =COPIA!F1 -> 0
B10: =IF(INDIRECT(ADDRESS(8,6,,,"LIBRO_GIORNALE"))="","",INDIRECT(ADDRESS(8,6,,,"LIBRO_GIORNALE"))) | D10: =IF(INDIRECT(ADDRESS(8,7,,,"LIBRO_GIORNALE"))="","",INDIRECT(ADDRESS(8,7,,,"LIBRO_GIORNALE")))
A11: =COPIA!CD1-1 -> 3 | B11: =IF(COPIA!CO1=0,"",IF(AND(COPIA!$I$1=1,COPIA!$BF$9=1),CONCATENATE("STATO PATRIMONIALE in forma ordinaria al ",COPIA!$AS$1,"/",COPIA!$AT$1,"/",COPIA!$AW$1),IF(AND(COPIA!$I$1=1,COPIA!$BF$9=2),CONCATENATE("STATO PATRIMONIALE in forma abbreviata al ",COPIA!$AS$1,"/",COPIA!$AT$1,"/",COPIA!$AW$1),IF(AND(COPIA!$I$1=2,COPIA!$BF$9=1),CONCATENATE("Stralcio di STATO PATRIMONIALE in forma ordinaria al ",COPIA!$AS$1,"/",COPIA!$AT$1,"/",COPIA!$AW$1),IF(AND(COPIA!$I$1=2,COPIA!$BF$9=2),CONCATENATE("Stralcio di STATO PATRIMONIALE in forma abbreviata al ",COPIA!$AS$1,"/",COPIA!$AT$1,"/",COPIA!$AW$1)))))) | F11: =COPIA!CI1 -> 11 | K11: =COPIA!I1 -> 1 | L11: =COPIA!I1 -> 1
A12: =MAX(COPIA!CD1,COPIA!CE1)-3 -> 1 | B12: =IF(COPIA!CO1=0,"","ATTIVO") | C12: =IF(B12<>"","importi","") | D12: =IF(COPIA!CO1=0,"","PASSIVO") | E12: =IF(D12<>"","importi","")
A13: =IF(ROW()<=$A$11,ROW(),0)-4 -> -4 | B13: =IF(ROW()-9>COPIA!$CI$1,SUBSTITUTE(IFERROR(INDEX(ECONOMICO,MATCH((ROWS($B$12:B13)-COPIA!$CI$2),COPIA!$CD$191:$CD$247,0),4),""),"_"," "),IF(ROW()-9<=COPIA!$CI$1,CONCATENATE(IFERROR(IF(MID(CONCATENATE(SUBSTITUTE(IFERROR(INDEX(ATTIVO,MATCH(ROWS(B$13:$B13),COPIA!$CD$3:$CD$250,0),4),""),"_"," ")," ",),8,6)="di cui",CONCATENATE(SUBSTITUTE(IFERROR(INDEX(ATTIVO,MATCH(ROWS(B$13:$B13),COPIA!$CD$3:$CD$250,0),4),""),"_"," ")," ",FIXED(IFERROR(INDEX(ATTIVO,MATCH(ROW()-12,COPIA!$CD$3:$CD$250,0),2),""),,FALSE)," euro"),SUBSTITUTE(IFERROR(INDEX(ATTIVO,MATCH(ROWS(B$13:$B13),COPIA!$CD$3:$CD$250,0),4),""),"_"," ")),"")),"")) | C13: =IF(IFERROR(IF(ROW()-9>COPIA!$CI$1,INDEX(ECONOMICO,MATCH((ROWS($B$12:B13)-COPIA!$CI$2),COPIA!$CD$191:$CD$247,0),5),INDEX(ATTIVO,MATCH(ROWS($C$13:C13),COPIA!$CD$3:$CD$250,0),5)),0)=0,"",IFERROR(IF(ROW()-9>COPIA!$CI$1,INDEX(ECONOMICO,MATCH((ROWS($B$12:B13)-COPIA!$CI$2),COPIA!$CD$191:$CD$247,0),5),INDEX(ATTIVO,MATCH(ROWS($C$13:C13),COPIA!$CD$3:$CD$250,0),5)),0)) | D13: =CONCATENATE(IFERROR(IF(MID(CONCATENATE(SUBSTITUTE(IFERROR(INDEX(PASSIVO,MATCH(ROWS(D$13:$D13),COPIA!$CD$105:$CD$189,0),4),""),"_"," ")," ",),8,6)="di cui",CONCATENATE(SUBSTITUTE(IFERROR(INDEX(PASSIVO,MATCH(ROWS(D$13:$D13),COPIA!$CD$105:$CD$189,0),4),""),"_"," ")," ",FIXED(IFERROR(INDEX(PASSIVO,MATCH(ROW()-12,COPIA!$CD$105:$CD$189,0),2),""),,FALSE)," euro"),SUBSTITUTE(IFERROR(INDEX(PASSIVO,MATCH(ROWS($D$13:$D13),COPIA!$CD$105:$CD$189,0),4),""),"_"," ")),"")) | E13: =IF(IFERROR(INDEX(PASSIVO,MATCH(ROWS($E$13:E13),COPIA!$CD$105:$CD$189,0),5),0)=0,"",IFERROR(INDEX(PASSIVO,MATCH(ROWS($E$13:E13),COPIA!$CD$105:$CD$189,0),5),0)) | H13: =SUBSTITUTE(IFERROR(INDEX(COPIA!$CG$22:$CK$187,MATCH(ROWS($H$13:H13),COPIA!$CK$22:$CK$187,0),1),""),"_"," ") | J13: =IFERROR(INDEX(COPIA!$CK$22:$CL$187,MATCH(ROWS(BILANCIO!$J$13:J13),COPIA!$CK$22:$CK$187,0),2),"")
A14: =IF(ROW()<=$A$11,ROW(),0) -> 0 | B14: =IF(ROW()-9>COPIA!$CI$1,SUBSTITUTE(IFERROR(INDEX(ECONOMICO,MATCH((ROWS($B$12:B14)-COPIA!$CI$2),COPIA!$CD$191:$CD$247,0),4),""),"_"," "),IF(ROW()-9<=COPIA!$CI$1,CONCATENATE(IFERROR(IF(MID(CONCATENATE(SUBSTITUTE(IFERROR(INDEX(ATTIVO,MATCH(ROWS(B$13:$B14),COPIA!$CD$3:$CD$250,0),4),""),"_"," ")," ",),8,6)="di cui",CONCATENATE(SUBSTITUTE(IFERROR(INDEX(ATTIVO,MATCH(ROWS(B$13:$B14),COPIA!$CD$3:$CD$250,0),4),""),"_"," ")," ",FIXED(IFERROR(INDEX(ATTIVO,MATCH(ROW()-12,COPIA!$CD$3:$CD$250,0),2),""),,FALSE)," euro"),SUBSTITUTE(IFERROR(INDEX(ATTIVO,MATCH(ROWS(B$13:$B14),COPIA!$CD$3:$CD$250,0),4),""),"_"," ")),"")),"")) | C14: =IF(IFERROR(IF(ROW()-9>COPIA!$CI$1,INDEX(ECONOMICO,MATCH((ROWS($B$12:B14)-COPIA!$CI$2),COPIA!$CD$191:$CD$247,0),5),INDEX(ATTIVO,MATCH(ROWS($C$13:C14),COPIA!$CD$3:$CD$250,0),5)),0)=0,"",IFERROR(IF(ROW()-9>COPIA!$CI$1,INDEX(ECONOMICO,MATCH((ROWS($B$12:B14)-COPIA!$CI$2),COPIA!$CD$191:$CD$247,0),5),INDEX(ATTIVO,MATCH(ROWS($C$13:C14),COPIA!$CD$3:$CD$250,0),5)),0)) | D14: =CONCATENATE(IFERROR(IF(MID(CONCATENATE(SUBSTITUTE(IFERROR(INDEX(PASSIVO,MATCH(ROWS(D$13:$D14),COPIA!$CD$105:$CD$189,0),4),""),"_"," ")," ",),8,6)="di cui",CONCATENATE(SUBSTITUTE(IFERROR(INDEX(PASSIVO,MATCH(ROWS(D$13:$D14),COPIA!$CD$105:$CD$189,0),4),""),"_"," ")," ",FIXED(IFERROR(INDEX(PASSIVO,MATCH(ROW()-12,COPIA!$CD$105:$CD$189,0),2),""),,FALSE)," euro"),SUBSTITUTE(IFERROR(INDEX(PASSIVO,MATCH(ROWS($D$13:$D14),COPIA!$CD$105:$CD$189,0),4),""),"_"," ")),"")) | E14: =IF(IFERROR(INDEX(PASSIVO,MATCH(ROWS($E$13:E14),COPIA!$CD$105:$CD$189,0),5),0)=0,"",IFERROR(INDEX(PASSIVO,MATCH(ROWS($E$13:E14),COPIA!$CD$105:$CD$189,0),5),0)) | H14: =SUBSTITUTE(IFERROR(INDEX(COPIA!$CG$22:$CK$187,MATCH(ROWS($H$13:H14),COPIA!$CK$22:$CK$187,0),1),""),"_"," ") | J14: =IFERROR(INDEX(COPIA!$CK$22:$CL$187,MATCH(ROWS(BILANCIO!$J$13:J14),COPIA!$CK$22:$CK$187,0),2),"")
A15: =IF(ROW()<=$A$11,ROW(),0) -> 0 | B15: =IF(ROW()-9>COPIA!$CI$1,SUBSTITUTE(IFERROR(INDEX(ECONOMICO,MATCH((ROWS($B$12:B15)-COPIA!$CI$2),COPIA!$CD$191:$CD$247,0),4),""),"_"," "),IF(ROW()-9<=COPIA!$CI$1,CONCATENATE(IFERROR(IF(MID(CONCATENATE(SUBSTITUTE(IFERROR(INDEX(ATTIVO,MATCH(ROWS(B$13:$B15),COPIA!$CD$3:$CD$250,0),4),""),"_"," ")," ",),8,6)="di cui",CONCATENATE(SUBSTITUTE(IFERROR(INDEX(ATTIVO,MATCH(ROWS(B$13:$B15),COPIA!$CD$3:$CD$250,0),4),""),"_"," ")," ",FIXED(IFERROR(INDEX(ATTIVO,MATCH(ROW()-12,COPIA!$CD$3:$CD$250,0),2),""),,FALSE)," euro"),SUBSTITUTE(IFERROR(INDEX(ATTIVO,MATCH(ROWS(B$13:$B15),COPIA!$CD$3:$CD$250,0),4),""),"_"," ")),"")),"")) | C15: =IF(IFERROR(IF(ROW()-9>COPIA!$CI$1,INDEX(ECONOMICO,MATCH((ROWS($B$12:B15)-COPIA!$CI$2),COPIA!$CD$191:$CD$247,0),5),INDEX(ATTIVO,MATCH(ROWS($C$13:C15),COPIA!$CD$3:$CD$250,0),5)),0)=0,"",IFERROR(IF(ROW()-9>COPIA!$CI$1,INDEX(ECONOMICO,MATCH((ROWS($B$12:B15)-COPIA!$CI$2),COPIA!$CD$191:$CD$247,0),5),INDEX(ATTIVO,MATCH(ROWS($C$13:C15),COPIA!$CD$3:$CD$250,0),5)),0)) | D15: =CONCATENATE(IFERROR(IF(MID(CONCATENATE(SUBSTITUTE(IFERROR(INDEX(PASSIVO,MATCH(ROWS(D$13:$D15),COPIA!$CD$105:$CD$189,0),4),""),"_"," ")," ",),8,6)="di cui",CONCATENATE(SUBSTITUTE(IFERROR(INDEX(PASSIVO,MATCH(ROWS(D$13:$D15),COPIA!$CD$105:$CD$189,0),4),""),"_"," ")," ",FIXED(IFERROR(INDEX(PASSIVO,MATCH(ROW()-12,COPIA!$CD$105:$CD$189,0),2),""),,FALSE)," euro"),SUBSTITUTE(IFERROR(INDEX(PASSIVO,MATCH(ROWS($D$13:$D15),COPIA!$CD$105:$CD$189,0),4),""),"_"," ")),"")) | E15: =IF(IFERROR(INDEX(PASSIVO,MATCH(ROWS($E$13:E15),COPIA!$CD$105:$CD$189,0),5),0)=0,"",IFERROR(INDEX(PASSIVO,MATCH(ROWS($E$13:E15),COPIA!$CD$105:$CD$189,0),5),0)) | H15: =SUBSTITUTE(IFERROR(INDEX(COPIA!$CG$22:$CK$187,MATCH(ROWS($H$13:H15),COPIA!$CK$22:$CK$187,0),1),""),"_"," ") | J15: =IFERROR(INDEX(COPIA!$CK$22:$CL$187,MATCH(ROWS(BILANCIO!$J$13:J15),COPIA!$CK$22:$CK$187,0),2),"")
A16: =IF(ROW()<=$A$11,ROW(),0) -> 0 | B16: =IF(ROW()-9>COPIA!$CI$1,SUBSTITUTE(IFERROR(INDEX(ECONOMICO,MATCH((ROWS($B$12:B16)-COPIA!$CI$2),COPIA!$CD$191:$CD$247,0),4),""),"_"," "),IF(ROW()-9<=COPIA!$CI$1,CONCATENATE(IFERROR(IF(MID(CONCATENATE(SUBSTITUTE(IFERROR(INDEX(ATTIVO,MATCH(ROWS(B$13:$B16),COPIA!$CD$3:$CD$250,0),4),""),"_"," ")," ",),8,6)="di cui",CONCATENATE(SUBSTITUTE(IFERROR(INDEX(ATTIVO,MATCH(ROWS(B$13:$B16),COPIA!$CD$3:$CD$250,0),4),""),"_"," ")," ",FIXED(IFERROR(INDEX(ATTIVO,MATCH(ROW()-12,COPIA!$CD$3:$CD$250,0),2),""),,FALSE)," euro"),SUBSTITUTE(IFERROR(INDEX(ATTIVO,MATCH(ROWS(B$13:$B16),COPIA!$CD$3:$CD$250,0),4),""),"_"," ")),"")),"")) | C16: =IF(IFERROR(IF(ROW()-9>COPIA!$CI$1,INDEX(ECONOMICO,MATCH((ROWS($B$12:B16)-COPIA!$CI$2),COPIA!$CD$191:$CD$247,0),5),INDEX(ATTIVO,MATCH(ROWS($C$13:C16),COPIA!$CD$3:$CD$250,0),5)),0)=0,"",IFERROR(IF(ROW()-9>COPIA!$CI$1,INDEX(ECONOMICO,MATCH((ROWS($B$12:B16)-COPIA!$CI$2),COPIA!$CD$191:$CD$247,0),5),INDEX(ATTIVO,MATCH(ROWS($C$13:C16),COPIA!$CD$3:$CD$250,0),5)),0)) | D16: =CONCATENATE(IFERROR(IF(MID(CONCATENATE(SUBSTITUTE(IFERROR(INDEX(PASSIVO,MATCH(ROWS(D$13:$D16),COPIA!$CD$105:$CD$189,0),4),""),"_"," ")," ",),8,6)="di cui",CONCATENATE(SUBSTITUTE(IFERROR(INDEX(PASSIVO,MATCH(ROWS(D$13:$D16),COPIA!$CD$105:$CD$189,0),4),""),"_"," ")," ",FIXED(IFERROR(INDEX(PASSIVO,MATCH(ROW()-12,COPIA!$CD$105:$CD$189,0),2),""),,FALSE)," euro"),SUBSTITUTE(IFERROR(INDEX(PASSIVO,MATCH(ROWS($D$13:$D16),COPIA!$CD$105:$CD$189,0),4),""),"_"," ")),"")) | E16: =IF(IFERROR(INDEX(PASSIVO,MATCH(ROWS($E$13:E16),COPIA!$CD$105:$CD$189,0),5),0)=0,"",IFERROR(INDEX(PASSIVO,MATCH(ROWS($E$13:E16),COPIA!$CD$105:$CD$189,0),5),0)) | H16: =SUBSTITUTE(IFERROR(INDEX(COPIA!$CG$22:$CK$187,MATCH(ROWS($H$13:H16),COPIA!$CK$22:$CK$187,0),1),""),"_"," ") | J16: =IFERROR(INDEX(COPIA!$CK$22:$CL$187,MATCH(ROWS(BILANCIO!$J$13:J16),COPIA!$CK$22:$CK$187,0),2),"")
A17: =IF(ROW()<=$A$11,ROW(),0) -> 0 | B17: =IF(ROW()-9>COPIA!$CI$1,SUBSTITUTE(IFERROR(INDEX(ECONOMICO,MATCH((ROWS($B$12:B17)-COPIA!$CI$2),COPIA!$CD$191:$CD$247,0),4),""),"_"," "),IF(ROW()-9<=COPIA!$CI$1,CONCATENATE(IFERROR(IF(MID(CONCATENATE(SUBSTITUTE(IFERROR(INDEX(ATTIVO,MATCH(ROWS(B$13:$B17),COPIA!$CD$3:$CD$250,0),4),""),"_"," ")," ",),8,6)="di cui",CONCATENATE(SUBSTITUTE(IFERROR(INDEX(ATTIVO,MATCH(ROWS(B$13:$B17),COPIA!$CD$3:$CD$250,0),4),""),"_"," ")," ",FIXED(IFERROR(INDEX(ATTIVO,MATCH(ROW()-12,COPIA!$CD$3:$CD$250,0),2),""),,FALSE)," euro"),SUBSTITUTE(IFERROR(INDEX(ATTIVO,MATCH(ROWS(B$13:$B17),COPIA!$CD$3:$CD$250,0),4),""),"_"," ")),"")),"")) | C17: =IF(IFERROR(IF(ROW()-9>COPIA!$CI$1,INDEX(ECONOMICO,MATCH((ROWS($B$12:B17)-COPIA!$CI$2),COPIA!$CD$191:$CD$247,0),5),INDEX(ATTIVO,MATCH(ROWS($C$13:C17),COPIA!$CD$3:$CD$250,0),5)),0)=0,"",IFERROR(IF(ROW()-9>COPIA!$CI$1,INDEX(ECONOMICO,MATCH((ROWS($B$12:B17)-COPIA!$CI$2),COPIA!$CD$191:$CD$247,0),5),INDEX(ATTIVO,MATCH(ROWS($C$13:C17),COPIA!$CD$3:$CD$250,0),5)),0)) | D17: =CONCATENATE(IFERROR(IF(MID(CONCATENATE(SUBSTITUTE(IFERROR(INDEX(PASSIVO,MATCH(ROWS(D$13:$D17),COPIA!$CD$105:$CD$189,0),4),""),"_"," ")," ",),8,6)="di cui",CONCATENATE(SUBSTITUTE(IFERROR(INDEX(PASSIVO,MATCH(ROWS(D$13:$D17),COPIA!$CD$105:$CD$189,0),4),""),"_"," ")," ",FIXED(IFERROR(INDEX(PASSIVO,MATCH(ROW()-12,COPIA!$CD$105:$CD$189,0),2),""),,FALSE)," euro"),SUBSTITUTE(IFERROR(INDEX(PASSIVO,MATCH(ROWS($D$13:$D17),COPIA!$CD$105:$CD$189,0),4),""),"_"," ")),"")) | E17: =IF(IFERROR(INDEX(PASSIVO,MATCH(ROWS($E$13:E17),COPIA!$CD$105:$CD$189,0),5),0)=0,"",IFERROR(INDEX(PASSIVO,MATCH(ROWS($E$13:E17),COPIA!$CD$105:$CD$189,0),5),0)) | H17: =SUBSTITUTE(IFERROR(INDEX(COPIA!$CG$22:$CK$187,MATCH(ROWS($H$13:H17),COPIA!$CK$22:$CK$187,0),1),""),"_"," ") | J17: =IFERROR(INDEX(COPIA!$CK$22:$CL$187,MATCH(ROWS(BILANCIO!$J$13:J17),COPIA!$CK$22:$CK$187,0),2),"")
A18: =IF(ROW()<=$A$11,ROW(),0) -> 0 | B18: =IF(ROW()-9>COPIA!$CI$1,SUBSTITUTE(IFERROR(INDEX(ECONOMICO,MATCH((ROWS($B$12:B18)-COPIA!$CI$2),COPIA!$CD$191:$CD$247,0),4),""),"_"," "),IF(ROW()-9<=COPIA!$CI$1,CONCATENATE(IFERROR(IF(MID(CONCATENATE(SUBSTITUTE(IFERROR(INDEX(ATTIVO,MATCH(ROWS(B$13:$B18),COPIA!$CD$3:$CD$250,0),4),""),"_"," ")," ",),8,6)="di cui",CONCATENATE(SUBSTITUTE(IFERROR(INDEX(ATTIVO,MATCH(ROWS(B$13:$B18),COPIA!$CD$3:$CD$250,0),4),""),"_"," ")," ",FIXED(IFERROR(INDEX(ATTIVO,MATCH(ROW()-12,COPIA!$CD$3:$CD$250,0),2),""),,FALSE)," euro"),SUBSTITUTE(IFERROR(INDEX(ATTIVO,MATCH(ROWS(B$13:$B18),COPIA!$CD$3:$CD$250,0),4),""),"_"," ")),"")),"")) | C18: =IF(IFERROR(IF(ROW()-9>COPIA!$CI$1,INDEX(ECONOMICO,MATCH((ROWS($B$12:B18)-COPIA!$CI$2),COPIA!$CD$191:$CD$247,0),5),INDEX(ATTIVO,MATCH(ROWS($C$13:C18),COPIA!$CD$3:$CD$250,0),5)),0)=0,"",IFERROR(IF(ROW()-9>COPIA!$CI$1,INDEX(ECONOMICO,MATCH((ROWS($B$12:B18)-COPIA!$CI$2),COPIA!$CD$191:$CD$247,0),5),INDEX(ATTIVO,MATCH(ROWS($C$13:C18),COPIA!$CD$3:$CD$250,0),5)),0)) | D18: =CONCATENATE(IFERROR(IF(MID(CONCATENATE(SUBSTITUTE(IFERROR(INDEX(PASSIVO,MATCH(ROWS(D$13:$D18),COPIA!$CD$105:$CD$189,0),4),""),"_"," ")," ",),8,6)="di cui",CONCATENATE(SUBSTITUTE(IFERROR(INDEX(PASSIVO,MATCH(ROWS(D$13:$D18),COPIA!$CD$105:$CD$189,0),4),""),"_"," ")," ",FIXED(IFERROR(INDEX(PASSIVO,MATCH(ROW()-12,COPIA!$CD$105:$CD$189,0),2),""),,FALSE)," euro"),SUBSTITUTE(IFERROR(INDEX(PASSIVO,MATCH(ROWS($D$13:$D18),COPIA!$CD$105:$CD$189,0),4),""),"_"," ")),"")) | E18: =IF(IFERROR(INDEX(PASSIVO,MATCH(ROWS($E$13:E18),COPIA!$CD$105:$CD$189,0),5),0)=0,"",IFERROR(INDEX(PASSIVO,MATCH(ROWS($E$13:E18),COPIA!$CD$105:$CD$189,0),5),0)) | H18: =SUBSTITUTE(IFERROR(INDEX(COPIA!$CG$22:$CK$187,MATCH(ROWS($H$13:H18),COPIA!$CK$22:$CK$187,0),1),""),"_"," ") | J18: =IFERROR(INDEX(COPIA!$CK$22:$CL$187,MATCH(ROWS(BILANCIO!$J$13:J18),COPIA!$CK$22:$CK$187,0),2),"")
A19: =IF(ROW()<=$A$11,ROW(),0) -> 0 | B19: =IF(ROW()-9>COPIA!$CI$1,SUBSTITUTE(IFERROR(INDEX(ECONOMICO,MATCH((ROWS($B$12:B19)-COPIA!$CI$2),COPIA!$CD$191:$CD$247,0),4),""),"_"," "),IF(ROW()-9<=COPIA!$CI$1,CONCATENATE(IFERROR(IF(MID(CONCATENATE(SUBSTITUTE(IFERROR(INDEX(ATTIVO,MATCH(ROWS(B$13:$B19),COPIA!$CD$3:$CD$250,0),4),""),"_"," ")," ",),8,6)="di cui",CONCATENATE(SUBSTITUTE(IFERROR(INDEX(ATTIVO,MATCH(ROWS(B$13:$B19),COPIA!$CD$3:$CD$250,0),4),""),"_"," ")," ",FIXED(IFERROR(INDEX(ATTIVO,MATCH(ROW()-12,COPIA!$CD$3:$CD$250,0),2),""),,FALSE)," euro"),SUBSTITUTE(IFERROR(INDEX(ATTIVO,MATCH(ROWS(B$13:$B19),COPIA!$CD$3:$CD$250,0),4),""),"_"," ")),"")),"")) | C19: =IF(IFERROR(IF(ROW()-9>COPIA!$CI$1,INDEX(ECONOMICO,MATCH((ROWS($B$12:B19)-COPIA!$CI$2),COPIA!$CD$191:$CD$247,0),5),INDEX(ATTIVO,MATCH(ROWS($C$13:C19),COPIA!$CD$3:$CD$250,0),5)),0)=0,"",IFERROR(IF(ROW()-9>COPIA!$CI$1,INDEX(ECONOMICO,MATCH((ROWS($B$12:B19)-COPIA!$CI$2),COPIA!$CD$191:$CD$247,0),5),INDEX(ATTIVO,MATCH(ROWS($C$13:C19),COPIA!$CD$3:$CD$250,0),5)),0)) | D19: =CONCATENATE(IFERROR(IF(MID(CONCATENATE(SUBSTITUTE(IFERROR(INDEX(PASSIVO,MATCH(ROWS(D$13:$D19),COPIA!$CD$105:$CD$189,0),4),""),"_"," ")," ",),8,6)="di cui",CONCATENATE(SUBSTITUTE(IFERROR(INDEX(PASSIVO,MATCH(ROWS(D$13:$D19),COPIA!$CD$105:$CD$189,0),4),""),"_"," ")," ",FIXED(IFERROR(INDEX(PASSIVO,MATCH(ROW()-12,COPIA!$CD$105:$CD$189,0),2),""),,FALSE)," euro"),SUBSTITUTE(IFERROR(INDEX(PASSIVO,MATCH(ROWS($D$13:$D19),COPIA!$CD$105:$CD$189,0),4),""),"_"," ")),"")) | E19: =IF(IFERROR(INDEX(PASSIVO,MATCH(ROWS($E$13:E19),COPIA!$CD$105:$CD$189,0),5),0)=0,"",IFERROR(INDEX(PASSIVO,MATCH(ROWS($E$13:E19),COPIA!$CD$105:$CD$189,0),5),0)) | H19: =SUBSTITUTE(IFERROR(INDEX(COPIA!$CG$22:$CK$187,MATCH(ROWS($H$13:H19),COPIA!$CK$22:$CK$187,0),1),""),"_"," ") | J19: =IFERROR(INDEX(COPIA!$CK$22:$CL$187,MATCH(ROWS(BILANCIO!$J$13:J19),COPIA!$CK$22:$CK$187,0),2),"")
A20: =IF(ROW()<=$A$11,ROW(),0) -> 0 | B20: =IF(ROW()-9>COPIA!$CI$1,SUBSTITUTE(IFERROR(INDEX(ECONOMICO,MATCH((ROWS($B$12:B20)-COPIA!$CI$2),COPIA!$CD$191:$CD$247,0),4),""),"_"," "),IF(ROW()-9<=COPIA!$CI$1,CONCATENATE(IFERROR(IF(MID(CONCATENATE(SUBSTITUTE(IFERROR(INDEX(ATTIVO,MATCH(ROWS(B$13:$B20),COPIA!$CD$3:$CD$250,0),4),""),"_"," ")," ",),8,6)="di cui",CONCATENATE(SUBSTITUTE(IFERROR(INDEX(ATTIVO,MATCH(ROWS(B$13:$B20),COPIA!$CD$3:$CD$250,0),4),""),"_"," ")," ",FIXED(IFERROR(INDEX(ATTIVO,MATCH(ROW()-12,COPIA!$CD$3:$CD$250,0),2),""),,FALSE)," euro"),SUBSTITUTE(IFERROR(INDEX(ATTIVO,MATCH(ROWS(B$13:$B20),COPIA!$CD$3:$CD$250,0),4),""),"_"," ")),"")),"")) | C20: =IF(IFERROR(IF(ROW()-9>COPIA!$CI$1,INDEX(ECONOMICO,MATCH((ROWS($B$12:B20)-COPIA!$CI$2),COPIA!$CD$191:$CD$247,0),5),INDEX(ATTIVO,MATCH(ROWS($C$13:C20),COPIA!$CD$3:$CD$250,0),5)),0)=0,"",IFERROR(IF(ROW()-9>COPIA!$CI$1,INDEX(ECONOMICO,MATCH((ROWS($B$12:B20)-COPIA!$CI$2),COPIA!$CD$191:$CD$247,0),5),INDEX(ATTIVO,MATCH(ROWS($C$13:C20),COPIA!$CD$3:$CD$250,0),5)),0)) | D20: =CONCATENATE(IFERROR(IF(MID(CONCATENATE(SUBSTITUTE(IFERROR(INDEX(PASSIVO,MATCH(ROWS(D$13:$D20),COPIA!$CD$105:$CD$189,0),4),""),"_"," ")," ",),8,6)="di cui",CONCATENATE(SUBSTITUTE(IFERROR(INDEX(PASSIVO,MATCH(ROWS(D$13:$D20),COPIA!$CD$105:$CD$189,0),4),""),"_"," ")," ",FIXED(IFERROR(INDEX(PASSIVO,MATCH(ROW()-12,COPIA!$CD$105:$CD$189,0),2),""),,FALSE)," euro"),SUBSTITUTE(IFERROR(INDEX(PASSIVO,MATCH(ROWS($D$13:$D20),COPIA!$CD$105:$CD$189,0),4),""),"_"," ")),"")) | E20: =IF(IFERROR(INDEX(PASSIVO,MATCH(ROWS($E$13:E20),COPIA!$CD$105:$CD$189,0),5),0)=0,"",IFERROR(INDEX(PASSIVO,MATCH(ROWS($E$13:E20),COPIA!$CD$105:$CD$189,0),5),0)) | H20: =SUBSTITUTE(IFERROR(INDEX(COPIA!$CG$22:$CK$187,MATCH(ROWS($H$13:H20),COPIA!$CK$22:$CK$187,0),1),""),"_"," ") | J20: =IFERROR(INDEX(COPIA!$CK$22:$CL$187,MATCH(ROWS(BILANCIO!$J$13:J20),COPIA!$CK$22:$CK$187,0),2),"")
A21: =IF(ROW()<=$A$11,ROW(),0) -> 0 | B21: =IF(ROW()-9>COPIA!$CI$1,SUBSTITUTE(IFERROR(INDEX(ECONOMICO,MATCH((ROWS($B$12:B21)-COPIA!$CI$2),COPIA!$CD$191:$CD$247,0),4),""),"_"," "),IF(ROW()-9<=COPIA!$CI$1,CONCATENATE(IFERROR(IF(MID(CONCATENATE(SUBSTITUTE(IFERROR(INDEX(ATTIVO,MATCH(ROWS(B$13:$B21),COPIA!$CD$3:$CD$250,0),4),""),"_"," ")," ",),8,6)="di cui",CONCATENATE(SUBSTITUTE(IFERROR(INDEX(ATTIVO,MATCH(ROWS(B$13:$B21),COPIA!$CD$3:$CD$250,0),4),""),"_"," ")," ",FIXED(IFERROR(INDEX(ATTIVO,MATCH(ROW()-12,COPIA!$CD$3:$CD$250,0),2),""),,FALSE)," euro"),SUBSTITUTE(IFERROR(INDEX(ATTIVO,MATCH(ROWS(B$13:$B21),COPIA!$CD$3:$CD$250,0),4),""),"_"," ")),"")),"")) | C21: =IF(IFERROR(IF(ROW()-9>COPIA!$CI$1,INDEX(ECONOMICO,MATCH((ROWS($B$12:B21)-COPIA!$CI$2),COPIA!$CD$191:$CD$247,0),5),INDEX(ATTIVO,MATCH(ROWS($C$13:C21),COPIA!$CD$3:$CD$250,0),5)),0)=0,"",IFERROR(IF(ROW()-9>COPIA!$CI$1,INDEX(ECONOMICO,MATCH((ROWS($B$12:B21)-COPIA!$CI$2),COPIA!$CD$191:$CD$247,0),5),INDEX(ATTIVO,MATCH(ROWS($C$13:C21),COPIA!$CD$3:$CD$250,0),5)),0)) | D21: =CONCATENATE(IFERROR(IF(MID(CONCATENATE(SUBSTITUTE(IFERROR(INDEX(PASSIVO,MATCH(ROWS(D$13:$D21),COPIA!$CD$105:$CD$189,0),4),""),"_"," ")," ",),8,6)="di cui",CONCATENATE(SUBSTITUTE(IFERROR(INDEX(PASSIVO,MATCH(ROWS(D$13:$D21),COPIA!$CD$105:$CD$189,0),4),""),"_"," ")," ",FIXED(IFERROR(INDEX(PASSIVO,MATCH(ROW()-12,COPIA!$CD$105:$CD$189,0),2),""),,FALSE)," euro"),SUBSTITUTE(IFERROR(INDEX(PASSIVO,MATCH(ROWS($D$13:$D21),COPIA!$CD$105:$CD$189,0),4),""),"_"," ")),"")) | E21: =IF(IFERROR(INDEX(PASSIVO,MATCH(ROWS($E$13:E21),COPIA!$CD$105:$CD$189,0),5),0)=0,"",IFERROR(INDEX(PASSIVO,MATCH(ROWS($E$13:E21),COPIA!$CD$105:$CD$189,0),5),0)) | H21: =SUBSTITUTE(IFERROR(INDEX(COPIA!$CG$22:$CK$187,MATCH(ROWS($H$13:H21),COPIA!$CK$22:$CK$187,0),1),""),"_"," ") | J21: =IFERROR(INDEX(COPIA!$CK$22:$CL$187,MATCH(ROWS(BILANCIO!$J$13:J21),COPIA!$CK$22:$CK$187,0),2),"")
A22: =IF(ROW()<=$A$11,ROW(),0) -> 0 | B22: =IF(ROW()-9>COPIA!$CI$1,SUBSTITUTE(IFERROR(INDEX(ECONOMICO,MATCH((ROWS($B$12:B22)-COPIA!$CI$2),COPIA!$CD$191:$CD$247,0),4),""),"_"," "),IF(ROW()-9<=COPIA!$CI$1,CONCATENATE(IFERROR(IF(MID(CONCATENATE(SUBSTITUTE(IFERROR(INDEX(ATTIVO,MATCH(ROWS(B$13:$B22),COPIA!$CD$3:$CD$250,0),4),""),"_"," ")," ",),8,6)="di cui",CONCATENATE(SUBSTITUTE(IFERROR(INDEX(ATTIVO,MATCH(ROWS(B$13:$B22),COPIA!$CD$3:$CD$250,0),4),""),"_"," ")," ",FIXED(IFERROR(INDEX(ATTIVO,MATCH(ROW()-12,COPIA!$CD$3:$CD$250,0),2),""),,FALSE)," euro"),SUBSTITUTE(IFERROR(INDEX(ATTIVO,MATCH(ROWS(B$13:$B22),COPIA!$CD$3:$CD$250,0),4),""),"_"," ")),"")),"")) | C22: =IF(IFERROR(IF(ROW()-9>COPIA!$CI$1,INDEX(ECONOMICO,MATCH((ROWS($B$12:B22)-COPIA!$CI$2),COPIA!$CD$191:$CD$247,0),5),INDEX(ATTIVO,MATCH(ROWS($C$13:C22),COPIA!$CD$3:$CD$250,0),5)),0)=0,"",IFERROR(IF(ROW()-9>COPIA!$CI$1,INDEX(ECONOMICO,MATCH((ROWS($B$12:B22)-COPIA!$CI$2),COPIA!$CD$191:$CD$247,0),5),INDEX(ATTIVO,MATCH(ROWS($C$13:C22),COPIA!$CD$3:$CD$250,0),5)),0)) | D22: =CONCATENATE(IFERROR(IF(MID(CONCATENATE(SUBSTITUTE(IFERROR(INDEX(PASSIVO,MATCH(ROWS(D$13:$D22),COPIA!$CD$105:$CD$189,0),4),""),"_"," ")," ",),8,6)="di cui",CONCATENATE(SUBSTITUTE(IFERROR(INDEX(PASSIVO,MATCH(ROWS(D$13:$D22),COPIA!$CD$105:$CD$189,0),4),""),"_"," ")," ",FIXED(IFERROR(INDEX(PASSIVO,MATCH(ROW()-12,COPIA!$CD$105:$CD$189,0),2),""),,FALSE)," euro"),SUBSTITUTE(IFERROR(INDEX(PASSIVO,MATCH(ROWS($D$13:$D22),COPIA!$CD$105:$CD$189,0),4),""),"_"," ")),"")) | E22: =IF(IFERROR(INDEX(PASSIVO,MATCH(ROWS($E$13:E22),COPIA!$CD$105:$CD$189,0),5),0)=0,"",IFERROR(INDEX(PASSIVO,MATCH(ROWS($E$13:E22),COPIA!$CD$105:$CD$189,0),5),0)) | H22: =SUBSTITUTE(IFERROR(INDEX(COPIA!$CG$22:$CK$187,MATCH(ROWS($H$13:H22),COPIA!$CK$22:$CK$187,0),1),""),"_"," ") | J22: =IFERROR(INDEX(COPIA!$CK$22:$CL$187,MATCH(ROWS(BILANCIO!$J$13:J22),COPIA!$CK$22:$CK$187,0),2),"")
A23: =IF(ROW()<=$A$11,ROW(),0) -> 0 | B23: =IF(ROW()-9>COPIA!$CI$1,SUBSTITUTE(IFERROR(INDEX(ECONOMICO,MATCH((ROWS($B$12:B23)-COPIA!$CI$2),COPIA!$CD$191:$CD$247,0),4),""),"_"," "),IF(ROW()-9<=COPIA!$CI$1,CONCATENATE(IFERROR(IF(MID(CONCATENATE(SUBSTITUTE(IFERROR(INDEX(ATTIVO,MATCH(ROWS(B$13:$B23),COPIA!$CD$3:$CD$250,0),4),""),"_"," ")," ",),8,6)="di cui",CONCATENATE(SUBSTITUTE(IFERROR(INDEX(ATTIVO,MATCH(ROWS(B$13:$B23),COPIA!$CD$3:$CD$250,0),4),""),"_"," ")," ",FIXED(IFERROR(INDEX(ATTIVO,MATCH(ROW()-12,COPIA!$CD$3:$CD$250,0),2),""),,FALSE)," euro"),SUBSTITUTE(IFERROR(INDEX(ATTIVO,MATCH(ROWS(B$13:$B23),COPIA!$CD$3:$CD$250,0),4),""),"_"," ")),"")),"")) | C23: =IF(IFERROR(IF(ROW()-9>COPIA!$CI$1,INDEX(ECONOMICO,MATCH((ROWS($B$12:B23)-COPIA!$CI$2),COPIA!$CD$191:$CD$247,0),5),INDEX(ATTIVO,MATCH(ROWS($C$13:C23),COPIA!$CD$3:$CD$250,0),5)),0)=0,"",IFERROR(IF(ROW()-9>COPIA!$CI$1,INDEX(ECONOMICO,MATCH((ROWS($B$12:B23)-COPIA!$CI$2),COPIA!$CD$191:$CD$247,0),5),INDEX(ATTIVO,MATCH(ROWS($C$13:C23),COPIA!$CD$3:$CD$250,0),5)),0)) | D23: =CONCATENATE(IFERROR(IF(MID(CONCATENATE(SUBSTITUTE(IFERROR(INDEX(PASSIVO,MATCH(ROWS(D$13:$D23),COPIA!$CD$105:$CD$189,0),4),""),"_"," ")," ",),8,6)="di cui",CONCATENATE(SUBSTITUTE(IFERROR(INDEX(PASSIVO,MATCH(ROWS(D$13:$D23),COPIA!$CD$105:$CD$189,0),4),""),"_"," ")," ",FIXED(IFERROR(INDEX(PASSIVO,MATCH(ROW()-12,COPIA!$CD$105:$CD$189,0),2),""),,FALSE)," euro"),SUBSTITUTE(IFERROR(INDEX(PASSIVO,MATCH(ROWS($D$13:$D23),COPIA!$CD$105:$CD$189,0),4),""),"_"," ")),"")) | E23: =IF(IFERROR(INDEX(PASSIVO,MATCH(ROWS($E$13:E23),COPIA!$CD$105:$CD$189,0),5),0)=0,"",IFERROR(INDEX(PASSIVO,MATCH(ROWS($E$13:E23),COPIA!$CD$105:$CD$189,0),5),0)) | H23: =SUBSTITUTE(IFERROR(INDEX(COPIA!$CG$22:$CK$187,MATCH(ROWS($H$13:H23),COPIA!$CK$22:$CK$187,0),1),""),"_"," ") | J23: =IFERROR(INDEX(COPIA!$CK$22:$CL$187,MATCH(ROWS(BILANCIO!$J$13:J23),COPIA!$CK$22:$CK$187,0),2),"")
A24: =IF(ROW()<=$A$11,ROW(),0) -> 0 | B24: =IF(ROW()-9>COPIA!$CI$1,SUBSTITUTE(IFERROR(INDEX(ECONOMICO,MATCH((ROWS($B$12:B24)-COPIA!$CI$2),COPIA!$CD$191:$CD$247,0),4),""),"_"," "),IF(ROW()-9<=COPIA!$CI$1,CONCATENATE(IFERROR(IF(MID(CONCATENATE(SUBSTITUTE(IFERROR(INDEX(ATTIVO,MATCH(ROWS(B$13:$B24),COPIA!$CD$3:$CD$250,0),4),""),"_"," ")," ",),8,6)="di cui",CONCATENATE(SUBSTITUTE(IFERROR(INDEX(ATTIVO,MATCH(ROWS(B$13:$B24),COPIA!$CD$3:$CD$250,0),4),""),"_"," ")," ",FIXED(IFERROR(INDEX(ATTIVO,MATCH(ROW()-12,COPIA!$CD$3:$CD$250,0),2),""),,FALSE)," euro"),SUBSTITUTE(IFERROR(INDEX(ATTIVO,MATCH(ROWS(B$13:$B24),COPIA!$CD$3:$CD$250,0),4),""),"_"," ")),"")),"")) | C24: =IF(IFERROR(IF(ROW()-9>COPIA!$CI$1,INDEX(ECONOMICO,MATCH((ROWS($B$12:B24)-COPIA!$CI$2),COPIA!$CD$191:$CD$247,0),5),INDEX(ATTIVO,MATCH(ROWS($C$13:C24),COPIA!$CD$3:$CD$250,0),5)),0)=0,"",IFERROR(IF(ROW()-9>COPIA!$CI$1,INDEX(ECONOMICO,MATCH((ROWS($B$12:B24)-COPIA!$CI$2),COPIA!$CD$191:$CD$247,0),5),INDEX(ATTIVO,MATCH(ROWS($C$13:C24),COPIA!$CD$3:$CD$250,0),5)),0)) | D24: =CONCATENATE(IFERROR(IF(MID(CONCATENATE(SUBSTITUTE(IFERROR(INDEX(PASSIVO,MATCH(ROWS(D$13:$D24),COPIA!$CD$105:$CD$189,0),4),""),"_"," ")," ",),8,6)="di cui",CONCATENATE(SUBSTITUTE(IFERROR(INDEX(PASSIVO,MATCH(ROWS(D$13:$D24),COPIA!$CD$105:$CD$189,0),4),""),"_"," ")," ",FIXED(IFERROR(INDEX(PASSIVO,MATCH(ROW()-12,COPIA!$CD$105:$CD$189,0),2),""),,FALSE)," euro"),SUBSTITUTE(IFERROR(INDEX(PASSIVO,MATCH(ROWS($D$13:$D24),COPIA!$CD$105:$CD$189,0),4),""),"_"," ")),"")) | E24: =IF(IFERROR(INDEX(PASSIVO,MATCH(ROWS($E$13:E24),COPIA!$CD$105:$CD$189,0),5),0)=0,"",IFERROR(INDEX(PASSIVO,MATCH(ROWS($E$13:E24),COPIA!$CD$105:$CD$189,0),5),0)) | H24: =SUBSTITUTE(IFERROR(INDEX(COPIA!$CG$22:$CK$187,MATCH(ROWS($H$13:H24),COPIA!$CK$22:$CK$187,0),1),""),"_"," ") | J24: =IFERROR(INDEX(COPIA!$CK$22:$CL$187,MATCH(ROWS(BILANCIO!$J$13:J24),COPIA!$CK$22:$CK$187,0),2),"")
A25: =IF(ROW()<=$A$11,ROW(),0) -> 0 | B25: =IF(ROW()-9>COPIA!$CI$1,SUBSTITUTE(IFERROR(INDEX(ECONOMICO,MATCH((ROWS($B$12:B25)-COPIA!$CI$2),COPIA!$CD$191:$CD$247,0),4),""),"_"," "),IF(ROW()-9<=COPIA!$CI$1,CONCATENATE(IFERROR(IF(MID(CONCATENATE(SUBSTITUTE(IFERROR(INDEX(ATTIVO,MATCH(ROWS(B$13:$B25),COPIA!$CD$3:$CD$250,0),4),""),"_"," ")," ",),8,6)="di cui",CONCATENATE(SUBSTITUTE(IFERROR(INDEX(ATTIVO,MATCH(ROWS(B$13:$B25),COPIA!$CD$3:$CD$250,0),4),""),"_"," ")," ",FIXED(IFERROR(INDEX(ATTIVO,MATCH(ROW()-12,COPIA!$CD$3:$CD$250,0),2),""),,FALSE)," euro"),SUBSTITUTE(IFERROR(INDEX(ATTIVO,MATCH(ROWS(B$13:$B25),COPIA!$CD$3:$CD$250,0),4),""),"_"," ")),"")),"")) | C25: =IF(IFERROR(IF(ROW()-9>COPIA!$CI$1,INDEX(ECONOMICO,MATCH((ROWS($B$12:B25)-COPIA!$CI$2),COPIA!$CD$191:$CD$247,0),5),INDEX(ATTIVO,MATCH(ROWS($C$13:C25),COPIA!$CD$3:$CD$250,0),5)),0)=0,"",IFERROR(IF(ROW()-9>COPIA!$CI$1,INDEX(ECONOMICO,MATCH((ROWS($B$12:B25)-COPIA!$CI$2),COPIA!$CD$191:$CD$247,0),5),INDEX(ATTIVO,MATCH(ROWS($C$13:C25),COPIA!$CD$3:$CD$250,0),5)),0)) | D25: =CONCATENATE(IFERROR(IF(MID(CONCATENATE(SUBSTITUTE(IFERROR(INDEX(PASSIVO,MATCH(ROWS(D$13:$D25),COPIA!$CD$105:$CD$189,0),4),""),"_"," ")," ",),8,6)="di cui",CONCATENATE(SUBSTITUTE(IFERROR(INDEX(PASSIVO,MATCH(ROWS(D$13:$D25),COPIA!$CD$105:$CD$189,0),4),""),"_"," ")," ",FIXED(IFERROR(INDEX(PASSIVO,MATCH(ROW()-12,COPIA!$CD$105:$CD$189,0),2),""),,FALSE)," euro"),SUBSTITUTE(IFERROR(INDEX(PASSIVO,MATCH(ROWS($D$13:$D25),COPIA!$CD$105:$CD$189,0),4),""),"_"," ")),"")) | E25: =IF(IFERROR(INDEX(PASSIVO,MATCH(ROWS($E$13:E25),COPIA!$CD$105:$CD$189,0),5),0)=0,"",IFERROR(INDEX(PASSIVO,MATCH(ROWS($E$13:E25),COPIA!$CD$105:$CD$189,0),5),0)) | H25: =SUBSTITUTE(IFERROR(INDEX(COPIA!$CG$22:$CK$187,MATCH(ROWS($H$13:H25),COPIA!$CK$22:$CK$187,0),1),""),"_"," ") | J25: =IFERROR(INDEX(COPIA!$CK$22:$CL$187,MATCH(ROWS(BILANCIO!$J$13:J25),COPIA!$CK$22:$CK$187,0),2),"")
... A59: =IF(ROW()<=$A$11,ROW(),0) -> 0 | B59: =IF(ROW()-9>COPIA!$CI$1,SUBSTITUTE(IFERROR(INDEX(ECONOMICO,MATCH((ROWS($B$12:B59)-COPIA!$CI$2),COPIA!$CD$191:$CD$247,0),4),""),"_"," "),IF(ROW()-9<=COPIA!$CI$1,CONCATENATE(IFERROR(IF(MID(CONCATENATE(SUBSTITUTE(IFERROR(INDEX(ATTIVO,MATCH(ROWS(B$13:$B59),COPIA!$CD$3:$CD$250,0),4),""),"_"," ")," ",),8,6)="di cui",CONCATENATE(SUBSTITUTE(IFERROR(INDEX(ATTIVO,MATCH(ROWS(B$13:$B59),COPIA!$CD$3:$CD$250,0),4),""),"_"," ")," ",FIXED(IFERROR(INDEX(ATTIVO,MATCH(ROW()-12,COPIA!$CD$3:$CD$250,0),2),""),,FALSE)," euro"),SUBSTITUTE(IFERROR(INDEX(ATTIVO,MATCH(ROWS(B$13:$B59),COPIA!$CD$3:$CD$250,0),4),""),"_"," ")),"")),"")) | C59: =IF(IFERROR(IF(ROW()-9>COPIA!$CI$1,INDEX(ECONOMICO,MATCH((ROWS($B$12:B59)-COPIA!$CI$2),COPIA!$CD$191:$CD$247,0),5),INDEX(ATTIVO,MATCH(ROWS($C$13:C59),COPIA!$CD$3:$CD$250,0),5)),0)=0,"",IFERROR(IF(ROW()-9>COPIA!$CI$1,INDEX(ECONOMICO,MATCH((ROWS($B$12:B59)-COPIA!$CI$2),COPIA!$CD$191:$CD$247,0),5),INDEX(ATTIVO,MATCH(ROWS($C$13:C59),COPIA!$CD$3:$CD$250,0),5)),0)) | D59: =CONCATENATE(IFERROR(IF(MID(CONCATENATE(SUBSTITUTE(IFERROR(INDEX(PASSIVO,MATCH(ROWS(D$13:$D59),COPIA!$CD$105:$CD$189,0),4),""),"_"," ")," ",),8,6)="di cui",CONCATENATE(SUBSTITUTE(IFERROR(INDEX(PASSIVO,MATCH(ROWS(D$13:$D59),COPIA!$CD$105:$CD$189,0),4),""),"_"," ")," ",FIXED(IFERROR(INDEX(PASSIVO,MATCH(ROW()-12,COPIA!$CD$105:$CD$189,0),2),""),,FALSE)," euro"),SUBSTITUTE(IFERROR(INDEX(PASSIVO,MATCH(ROWS($D$13:$D59),COPIA!$CD$105:$CD$189,0),4),""),"_"," ")),"")) | E59: =IF(IFERROR(INDEX(PASSIVO,MATCH(ROWS($E$13:E59),COPIA!$CD$105:$CD$189,0),5),0)=0,"",IFERROR(INDEX(PASSIVO,MATCH(ROWS($E$13:E59),COPIA!$CD$105:$CD$189,0),5),0)) | H59: =SUBSTITUTE(IFERROR(INDEX(COPIA!$CG$22:$CK$187,MATCH(ROWS($H$13:H59),COPIA!$CK$22:$CK$187,0),1),""),"_"," ") | J59: =IFERROR(INDEX(COPIA!$CK$22:$CL$187,MATCH(ROWS(BILANCIO!$J$13:J59),COPIA!$CK$22:$CK$187,0),2),"")
A60: =IF(ROW()<=$A$11,ROW(),0) -> 0 | B60: =IF(ROW()-9>COPIA!$CI$1,SUBSTITUTE(IFERROR(INDEX(ECONOMICO,MATCH((ROWS($B$12:B60)-COPIA!$CI$2),COPIA!$CD$191:$CD$247,0),4),""),"_"," "),IF(ROW()-9<=COPIA!$CI$1,CONCATENATE(IFERROR(IF(MID(CONCATENATE(SUBSTITUTE(IFERROR(INDEX(ATTIVO,MATCH(ROWS(B$13:$B60),COPIA!$CD$3:$CD$250,0),4),""),"_"," ")," ",),8,6)="di cui",CONCATENATE(SUBSTITUTE(IFERROR(INDEX(ATTIVO,MATCH(ROWS(B$13:$B60),COPIA!$CD$3:$CD$250,0),4),""),"_"," ")," ",FIXED(IFERROR(INDEX(ATTIVO,MATCH(ROW()-12,COPIA!$CD$3:$CD$250,0),2),""),,FALSE)," euro"),SUBSTITUTE(IFERROR(INDEX(ATTIVO,MATCH(ROWS(B$13:$B60),COPIA!$CD$3:$CD$250,0),4),""),"_"," ")),"")),"")) | C60: =IF(IFERROR(IF(ROW()-9>COPIA!$CI$1,INDEX(ECONOMICO,MATCH((ROWS($B$12:B60)-COPIA!$CI$2),COPIA!$CD$191:$CD$247,0),5),INDEX(ATTIVO,MATCH(ROWS($C$13:C60),COPIA!$CD$3:$CD$250,0),5)),0)=0,"",IFERROR(IF(ROW()-9>COPIA!$CI$1,INDEX(ECONOMICO,MATCH((ROWS($B$12:B60)-COPIA!$CI$2),COPIA!$CD$191:$CD$247,0),5),INDEX(ATTIVO,MATCH(ROWS($C$13:C60),COPIA!$CD$3:$CD$250,0),5)),0)) | D60: =CONCATENATE(IFERROR(IF(MID(CONCATENATE(SUBSTITUTE(IFERROR(INDEX(PASSIVO,MATCH(ROWS(D$13:$D60),COPIA!$CD$105:$CD$189,0),4),""),"_"," ")," ",),8,6)="di cui",CONCATENATE(SUBSTITUTE(IFERROR(INDEX(PASSIVO,MATCH(ROWS(D$13:$D60),COPIA!$CD$105:$CD$189,0),4),""),"_"," ")," ",FIXED(IFERROR(INDEX(PASSIVO,MATCH(ROW()-12,COPIA!$CD$105:$CD$189,0),2),""),,FALSE)," euro"),SUBSTITUTE(IFERROR(INDEX(PASSIVO,MATCH(ROWS($D$13:$D60),COPIA!$CD$105:$CD$189,0),4),""),"_"," ")),"")) | E60: =IF(IFERROR(INDEX(PASSIVO,MATCH(ROWS($E$13:E60),COPIA!$CD$105:$CD$189,0),5),0)=0,"",IFERROR(INDEX(PASSIVO,MATCH(ROWS($E$13:E60),COPIA!$CD$105:$CD$189,0),5),0))
A61: =IF(ROW()<=$A$11,ROW(),0) -> 0 | B61: =IF(ROW()-9>COPIA!$CI$1,SUBSTITUTE(IFERROR(INDEX(ECONOMICO,MATCH((ROWS($B$12:B61)-COPIA!$CI$2),COPIA!$CD$191:$CD$247,0),4),""),"_"," "),IF(ROW()-9<=COPIA!$CI$1,CONCATENATE(IFERROR(IF(MID(CONCATENATE(SUBSTITUTE(IFERROR(INDEX(ATTIVO,MATCH(ROWS(B$13:$B61),COPIA!$CD$3:$CD$250,0),4),""),"_"," ")," ",),8,6)="di cui",CONCATENATE(SUBSTITUTE(IFERROR(INDEX(ATTIVO,MATCH(ROWS(B$13:$B61),COPIA!$CD$3:$CD$250,0),4),""),"_"," ")," ",FIXED(IFERROR(INDEX(ATTIVO,MATCH(ROW()-12,COPIA!$CD$3:$CD$250,0),2),""),,FALSE)," euro"),SUBSTITUTE(IFERROR(INDEX(ATTIVO,MATCH(ROWS(B$13:$B61),COPIA!$CD$3:$CD$250,0),4),""),"_"," ")),"")),"")) | C61: =IF(IFERROR(IF(ROW()-9>COPIA!$CI$1,INDEX(ECONOMICO,MATCH((ROWS($B$12:B61)-COPIA!$CI$2),COPIA!$CD$191:$CD$247,0),5),INDEX(ATTIVO,MATCH(ROWS($C$13:C61),COPIA!$CD$3:$CD$250,0),5)),0)=0,"",IFERROR(IF(ROW()-9>COPIA!$CI$1,INDEX(ECONOMICO,MATCH((ROWS($B$12:B61)-COPIA!$CI$2),COPIA!$CD$191:$CD$247,0),5),INDEX(ATTIVO,MATCH(ROWS($C$13:C61),COPIA!$CD$3:$CD$250,0),5)),0)) | D61: =CONCATENATE(IFERROR(IF(MID(CONCATENATE(SUBSTITUTE(IFERROR(INDEX(PASSIVO,MATCH(ROWS(D$13:$D61),COPIA!$CD$105:$CD$189,0),4),""),"_"," ")," ",),8,6)="di cui",CONCATENATE(SUBSTITUTE(IFERROR(INDEX(PASSIVO,MATCH(ROWS(D$13:$D61),COPIA!$CD$105:$CD$189,0),4),""),"_"," ")," ",FIXED(IFERROR(INDEX(PASSIVO,MATCH(ROW()-12,COPIA!$CD$105:$CD$189,0),2),""),,FALSE)," euro"),SUBSTITUTE(IFERROR(INDEX(PASSIVO,MATCH(ROWS($D$13:$D61),COPIA!$CD$105:$CD$189,0),4),""),"_"," ")),"")) | E61: =IF(IFERROR(INDEX(PASSIVO,MATCH(ROWS($E$13:E61),COPIA!$CD$105:$CD$189,0),5),0)=0,"",IFERROR(INDEX(PASSIVO,MATCH(ROWS($E$13:E61),COPIA!$CD$105:$CD$189,0),5),0))
A62: =IF(ROW()<=$A$11,ROW(),0) -> 0 | B62: =IF(ROW()-9>COPIA!$CI$1,SUBSTITUTE(IFERROR(INDEX(ECONOMICO,MATCH((ROWS($B$12:B62)-COPIA!$CI$2),COPIA!$CD$191:$CD$247,0),4),""),"_"," "),IF(ROW()-9<=COPIA!$CI$1,CONCATENATE(IFERROR(IF(MID(CONCATENATE(SUBSTITUTE(IFERROR(INDEX(ATTIVO,MATCH(ROWS(B$13:$B62),COPIA!$CD$3:$CD$250,0),4),""),"_"," ")," ",),8,6)="di cui",CONCATENATE(SUBSTITUTE(IFERROR(INDEX(ATTIVO,MATCH(ROWS(B$13:$B62),COPIA!$CD$3:$CD$250,0),4),""),"_"," ")," ",FIXED(IFERROR(INDEX(ATTIVO,MATCH(ROW()-12,COPIA!$CD$3:$CD$250,0),2),""),,FALSE)," euro"),SUBSTITUTE(IFERROR(INDEX(ATTIVO,MATCH(ROWS(B$13:$B62),COPIA!$CD$3:$CD$250,0),4),""),"_"," ")),"")),"")) | C62: =IF(IFERROR(IF(ROW()-9>COPIA!$CI$1,INDEX(ECONOMICO,MATCH((ROWS($B$12:B62)-COPIA!$CI$2),COPIA!$CD$191:$CD$247,0),5),INDEX(ATTIVO,MATCH(ROWS($C$13:C62),COPIA!$CD$3:$CD$250,0),5)),0)=0,"",IFERROR(IF(ROW()-9>COPIA!$CI$1,INDEX(ECONOMICO,MATCH((ROWS($B$12:B62)-COPIA!$CI$2),COPIA!$CD$191:$CD$247,0),5),INDEX(ATTIVO,MATCH(ROWS($C$13:C62),COPIA!$CD$3:$CD$250,0),5)),0)) | D62: =CONCATENATE(IFERROR(IF(MID(CONCATENATE(SUBSTITUTE(IFERROR(INDEX(PASSIVO,MATCH(ROWS(D$13:$D62),COPIA!$CD$105:$CD$189,0),4),""),"_"," ")," ",),8,6)="di cui",CONCATENATE(SUBSTITUTE(IFERROR(INDEX(PASSIVO,MATCH(ROWS(D$13:$D62),COPIA!$CD$105:$CD$189,0),4),""),"_"," ")," ",FIXED(IFERROR(INDEX(PASSIVO,MATCH(ROW()-12,COPIA!$CD$105:$CD$189,0),2),""),,FALSE)," euro"),SUBSTITUTE(IFERROR(INDEX(PASSIVO,MATCH(ROWS($D$13:$D62),COPIA!$CD$105:$CD$189,0),4),""),"_"," ")),"")) | E62: =IF(IFERROR(INDEX(PASSIVO,MATCH(ROWS($E$13:E62),COPIA!$CD$105:$CD$189,0),5),0)=0,"",IFERROR(INDEX(PASSIVO,MATCH(ROWS($E$13:E62),COPIA!$CD$105:$CD$189,0),5),0))
A63: =IF(ROW()<=$A$11,ROW(),0) -> 0 | B63: =IF(ROW()-9>COPIA!$CI$1,SUBSTITUTE(IFERROR(INDEX(ECONOMICO,MATCH((ROWS($B$12:B63)-COPIA!$CI$2),COPIA!$CD$191:$CD$247,0),4),""),"_"," "),IF(ROW()-9<=COPIA!$CI$1,CONCATENATE(IFERROR(IF(MID(CONCATENATE(SUBSTITUTE(IFERROR(INDEX(ATTIVO,MATCH(ROWS(B$13:$B63),COPIA!$CD$3:$CD$250,0),4),""),"_"," ")," ",),8,6)="di cui",CONCATENATE(SUBSTITUTE(IFERROR(INDEX(ATTIVO,MATCH(ROWS(B$13:$B63),COPIA!$CD$3:$CD$250,0),4),""),"_"," ")," ",FIXED(IFERROR(INDEX(ATTIVO,MATCH(ROW()-12,COPIA!$CD$3:$CD$250,0),2),""),,FALSE)," euro"),SUBSTITUTE(IFERROR(INDEX(ATTIVO,MATCH(ROWS(B$13:$B63),COPIA!$CD$3:$CD$250,0),4),""),"_"," ")),"")),"")) | C63: =IF(IFERROR(IF(ROW()-9>COPIA!$CI$1,INDEX(ECONOMICO,MATCH((ROWS($B$12:B63)-COPIA!$CI$2),COPIA!$CD$191:$CD$247,0),5),INDEX(ATTIVO,MATCH(ROWS($C$13:C63),COPIA!$CD$3:$CD$250,0),5)),0)=0,"",IFERROR(IF(ROW()-9>COPIA!$CI$1,INDEX(ECONOMICO,MATCH((ROWS($B$12:B63)-COPIA!$CI$2),COPIA!$CD$191:$CD$247,0),5),INDEX(ATTIVO,MATCH(ROWS($C$13:C63),COPIA!$CD$3:$CD$250,0),5)),0)) | D63: =CONCATENATE(IFERROR(IF(MID(CONCATENATE(SUBSTITUTE(IFERROR(INDEX(PASSIVO,MATCH(ROWS(D$13:$D63),COPIA!$CD$105:$CD$189,0),4),""),"_"," ")," ",),8,6)="di cui",CONCATENATE(SUBSTITUTE(IFERROR(INDEX(PASSIVO,MATCH(ROWS(D$13:$D63),COPIA!$CD$105:$CD$189,0),4),""),"_"," ")," ",FIXED(IFERROR(INDEX(PASSIVO,MATCH(ROW()-12,COPIA!$CD$105:$CD$189,0),2),""),,FALSE)," euro"),SUBSTITUTE(IFERROR(INDEX(PASSIVO,MATCH(ROWS($D$13:$D63),COPIA!$CD$105:$CD$189,0),4),""),"_"," ")),"")) | E63: =IF(IFERROR(INDEX(PASSIVO,MATCH(ROWS($E$13:E63),COPIA!$CD$105:$CD$189,0),5),0)=0,"",IFERROR(INDEX(PASSIVO,MATCH(ROWS($E$13:E63),COPIA!$CD$105:$CD$189,0),5),0))
A64: =IF(ROW()<=$A$11,ROW(),0) -> 0 | B64: =IF(ROW()-9>COPIA!$CI$1,SUBSTITUTE(IFERROR(INDEX(ECONOMICO,MATCH((ROWS($B$12:B64)-COPIA!$CI$2),COPIA!$CD$191:$CD$247,0),4),""),"_"," "),IF(ROW()-9<=COPIA!$CI$1,CONCATENATE(IFERROR(IF(MID(CONCATENATE(SUBSTITUTE(IFERROR(INDEX(ATTIVO,MATCH(ROWS(B$13:$B64),COPIA!$CD$3:$CD$250,0),4),""),"_"," ")," ",),8,6)="di cui",CONCATENATE(SUBSTITUTE(IFERROR(INDEX(ATTIVO,MATCH(ROWS(B$13:$B64),COPIA!$CD$3:$CD$250,0),4),""),"_"," ")," ",FIXED(IFERROR(INDEX(ATTIVO,MATCH(ROW()-12,COPIA!$CD$3:$CD$250,0),2),""),,FALSE)," euro"),SUBSTITUTE(IFERROR(INDEX(ATTIVO,MATCH(ROWS(B$13:$B64),COPIA!$CD$3:$CD$250,0),4),""),"_"," ")),"")),"")) | C64: =IF(IFERROR(IF(ROW()-9>COPIA!$CI$1,INDEX(ECONOMICO,MATCH((ROWS($B$12:B64)-COPIA!$CI$2),COPIA!$CD$191:$CD$247,0),5),INDEX(ATTIVO,MATCH(ROWS($C$13:C64),COPIA!$CD$3:$CD$250,0),5)),0)=0,"",IFERROR(IF(ROW()-9>COPIA!$CI$1,INDEX(ECONOMICO,MATCH((ROWS($B$12:B64)-COPIA!$CI$2),COPIA!$CD$191:$CD$247,0),5),INDEX(ATTIVO,MATCH(ROWS($C$13:C64),COPIA!$CD$3:$CD$250,0),5)),0)) | D64: =CONCATENATE(IFERROR(IF(MID(CONCATENATE(SUBSTITUTE(IFERROR(INDEX(PASSIVO,MATCH(ROWS(D$13:$D64),COPIA!$CD$105:$CD$189,0),4),""),"_"," ")," ",),8,6)="di cui",CONCATENATE(SUBSTITUTE(IFERROR(INDEX(PASSIVO,MATCH(ROWS(D$13:$D64),COPIA!$CD$105:$CD$189,0),4),""),"_"," ")," ",FIXED(IFERROR(INDEX(PASSIVO,MATCH(ROW()-12,COPIA!$CD$105:$CD$189,0),2),""),,FALSE)," euro"),SUBSTITUTE(IFERROR(INDEX(PASSIVO,MATCH(ROWS($D$13:$D64),COPIA!$CD$105:$CD$189,0),4),""),"_"," ")),"")) | E64: =IF(IFERROR(INDEX(PASSIVO,MATCH(ROWS($E$13:E64),COPIA!$CD$105:$CD$189,0),5),0)=0,"",IFERROR(INDEX(PASSIVO,MATCH(ROWS($E$13:E64),COPIA!$CD$105:$CD$189,0),5),0))
A65: =IF(ROW()<=$A$11,ROW(),0) -> 0 | B65: =IF(ROW()-9>COPIA!$CI$1,SUBSTITUTE(IFERROR(INDEX(ECONOMICO,MATCH((ROWS($B$12:B65)-COPIA!$CI$2),COPIA!$CD$191:$CD$247,0),4),""),"_"," "),IF(ROW()-9<=COPIA!$CI$1,CONCATENATE(IFERROR(IF(MID(CONCATENATE(SUBSTITUTE(IFERROR(INDEX(ATTIVO,MATCH(ROWS(B$13:$B65),COPIA!$CD$3:$CD$250,0),4),""),"_"," ")," ",),8,6)="di cui",CONCATENATE(SUBSTITUTE(IFERROR(INDEX(ATTIVO,MATCH(ROWS(B$13:$B65),COPIA!$CD$3:$CD$250,0),4),""),"_"," ")," ",FIXED(IFERROR(INDEX(ATTIVO,MATCH(ROW()-12,COPIA!$CD$3:$CD$250,0),2),""),,FALSE)," euro"),SUBSTITUTE(IFERROR(INDEX(ATTIVO,MATCH(ROWS(B$13:$B65),COPIA!$CD$3:$CD$250,0),4),""),"_"," ")),"")),"")) | C65: =IF(IFERROR(IF(ROW()-9>COPIA!$CI$1,INDEX(ECONOMICO,MATCH((ROWS($B$12:B65)-COPIA!$CI$2),COPIA!$CD$191:$CD$247,0),5),INDEX(ATTIVO,MATCH(ROWS($C$13:C65),COPIA!$CD$3:$CD$250,0),5)),0)=0,"",IFERROR(IF(ROW()-9>COPIA!$CI$1,INDEX(ECONOMICO,MATCH((ROWS($B$12:B65)-COPIA!$CI$2),COPIA!$CD$191:$CD$247,0),5),INDEX(ATTIVO,MATCH(ROWS($C$13:C65),COPIA!$CD$3:$CD$250,0),5)),0)) | D65: =CONCATENATE(IFERROR(IF(MID(CONCATENATE(SUBSTITUTE(IFERROR(INDEX(PASSIVO,MATCH(ROWS(D$13:$D65),COPIA!$CD$105:$CD$189,0),4),""),"_"," ")," ",),8,6)="di cui",CONCATENATE(SUBSTITUTE(IFERROR(INDEX(PASSIVO,MATCH(ROWS(D$13:$D65),COPIA!$CD$105:$CD$189,0),4),""),"_"," ")," ",FIXED(IFERROR(INDEX(PASSIVO,MATCH(ROW()-12,COPIA!$CD$105:$CD$189,0),2),""),,FALSE)," euro"),SUBSTITUTE(IFERROR(INDEX(PASSIVO,MATCH(ROWS($D$13:$D65),COPIA!$CD$105:$CD$189,0),4),""),"_"," ")),"")) | E65: =IF(IFERROR(INDEX(PASSIVO,MATCH(ROWS($E$13:E65),COPIA!$CD$105:$CD$189,0),5),0)=0,"",IFERROR(INDEX(PASSIVO,MATCH(ROWS($E$13:E65),COPIA!$CD$105:$CD$189,0),5),0))
A66: =IF(ROW()<=$A$11,ROW(),0) -> 0 | B66: =IF(ROW()-9>COPIA!$CI$1,SUBSTITUTE(IFERROR(INDEX(ECONOMICO,MATCH((ROWS($B$12:B66)-COPIA!$CI$2),COPIA!$CD$191:$CD$247,0),4),""),"_"," "),IF(ROW()-9<=COPIA!$CI$1,CONCATENATE(IFERROR(IF(MID(CONCATENATE(SUBSTITUTE(IFERROR(INDEX(ATTIVO,MATCH(ROWS(B$13:$B66),COPIA!$CD$3:$CD$250,0),4),""),"_"," ")," ",),8,6)="di cui",CONCATENATE(SUBSTITUTE(IFERROR(INDEX(ATTIVO,MATCH(ROWS(B$13:$B66),COPIA!$CD$3:$CD$250,0),4),""),"_"," ")," ",FIXED(IFERROR(INDEX(ATTIVO,MATCH(ROW()-12,COPIA!$CD$3:$CD$250,0),2),""),,FALSE)," euro"),SUBSTITUTE(IFERROR(INDEX(ATTIVO,MATCH(ROWS(B$13:$B66),COPIA!$CD$3:$CD$250,0),4),""),"_"," ")),"")),"")) | C66: =IF(IFERROR(IF(ROW()-9>COPIA!$CI$1,INDEX(ECONOMICO,MATCH((ROWS($B$12:B66)-COPIA!$CI$2),COPIA!$CD$191:$CD$247,0),5),INDEX(ATTIVO,MATCH(ROWS($C$13:C66),COPIA!$CD$3:$CD$250,0),5)),0)=0,"",IFERROR(IF(ROW()-9>COPIA!$CI$1,INDEX(ECONOMICO,MATCH((ROWS($B$12:B66)-COPIA!$CI$2),COPIA!$CD$191:$CD$247,0),5),INDEX(ATTIVO,MATCH(ROWS($C$13:C66),COPIA!$CD$3:$CD$250,0),5)),0)) | D66: =CONCATENATE(IFERROR(IF(MID(CONCATENATE(SUBSTITUTE(IFERROR(INDEX(PASSIVO,MATCH(ROWS(D$13:$D66),COPIA!$CD$105:$CD$189,0),4),""),"_"," ")," ",),8,6)="di cui",CONCATENATE(SUBSTITUTE(IFERROR(INDEX(PASSIVO,MATCH(ROWS(D$13:$D66),COPIA!$CD$105:$CD$189,0),4),""),"_"," ")," ",FIXED(IFERROR(INDEX(PASSIVO,MATCH(ROW()-12,COPIA!$CD$105:$CD$189,0),2),""),,FALSE)," euro"),SUBSTITUTE(IFERROR(INDEX(PASSIVO,MATCH(ROWS($D$13:$D66),COPIA!$CD$105:$CD$189,0),4),""),"_"," ")),"")) | E66: =IF(IFERROR(INDEX(PASSIVO,MATCH(ROWS($E$13:E66),COPIA!$CD$105:$CD$189,0),5),0)=0,"",IFERROR(INDEX(PASSIVO,MATCH(ROWS($E$13:E66),COPIA!$CD$105:$CD$189,0),5),0))
A67: =IF(ROW()<=$A$11,ROW(),0) -> 0 | B67: =IF(ROW()-9>COPIA!$CI$1,SUBSTITUTE(IFERROR(INDEX(ECONOMICO,MATCH((ROWS($B$12:B67)-COPIA!$CI$2),COPIA!$CD$191:$CD$247,0),4),""),"_"," "),IF(ROW()-9<=COPIA!$CI$1,CONCATENATE(IFERROR(IF(MID(CONCATENATE(SUBSTITUTE(IFERROR(INDEX(ATTIVO,MATCH(ROWS(B$13:$B67),COPIA!$CD$3:$CD$250,0),4),""),"_"," ")," ",),8,6)="di cui",CONCATENATE(SUBSTITUTE(IFERROR(INDEX(ATTIVO,MATCH(ROWS(B$13:$B67),COPIA!$CD$3:$CD$250,0),4),""),"_"," ")," ",FIXED(IFERROR(INDEX(ATTIVO,MATCH(ROW()-12,COPIA!$CD$3:$CD$250,0),2),""),,FALSE)," euro"),SUBSTITUTE(IFERROR(INDEX(ATTIVO,MATCH(ROWS(B$13:$B67),COPIA!$CD$3:$CD$250,0),4),""),"_"," ")),"")),"")) | C67: =IF(IFERROR(IF(ROW()-9>COPIA!$CI$1,INDEX(ECONOMICO,MATCH((ROWS($B$12:B67)-COPIA!$CI$2),COPIA!$CD$191:$CD$247,0),5),INDEX(ATTIVO,MATCH(ROWS($C$13:C67),COPIA!$CD$3:$CD$250,0),5)),0)=0,"",IFERROR(IF(ROW()-9>COPIA!$CI$1,INDEX(ECONOMICO,MATCH((ROWS($B$12:B67)-COPIA!$CI$2),COPIA!$CD$191:$CD$247,0),5),INDEX(ATTIVO,MATCH(ROWS($C$13:C67),COPIA!$CD$3:$CD$250,0),5)),0)) | D67: =CONCATENATE(IFERROR(IF(MID(CONCATENATE(SUBSTITUTE(IFERROR(INDEX(PASSIVO,MATCH(ROWS(D$13:$D67),COPIA!$CD$105:$CD$189,0),4),""),"_"," ")," ",),8,6)="di cui",CONCATENATE(SUBSTITUTE(IFERROR(INDEX(PASSIVO,MATCH(ROWS(D$13:$D67),COPIA!$CD$105:$CD$189,0),4),""),"_"," ")," ",FIXED(IFERROR(INDEX(PASSIVO,MATCH(ROW()-12,COPIA!$CD$105:$CD$189,0),2),""),,FALSE)," euro"),SUBSTITUTE(IFERROR(INDEX(PASSIVO,MATCH(ROWS($D$13:$D67),COPIA!$CD$105:$CD$189,0),4),""),"_"," ")),"")) | E67: =IF(IFERROR(INDEX(PASSIVO,MATCH(ROWS($E$13:E67),COPIA!$CD$105:$CD$189,0),5),0)=0,"",IFERROR(INDEX(PASSIVO,MATCH(ROWS($E$13:E67),COPIA!$CD$105:$CD$189,0),5),0))
A68: =IF(ROW()<=$A$11,ROW(),0) -> 0 | B68: =IF(ROW()-9>COPIA!$CI$1,SUBSTITUTE(IFERROR(INDEX(ECONOMICO,MATCH((ROWS($B$12:B68)-COPIA!$CI$2),COPIA!$CD$191:$CD$247,0),4),""),"_"," "),IF(ROW()-9<=COPIA!$CI$1,CONCATENATE(IFERROR(IF(MID(CONCATENATE(SUBSTITUTE(IFERROR(INDEX(ATTIVO,MATCH(ROWS(B$13:$B68),COPIA!$CD$3:$CD$250,0),4),""),"_"," ")," ",),8,6)="di cui",CONCATENATE(SUBSTITUTE(IFERROR(INDEX(ATTIVO,MATCH(ROWS(B$13:$B68),COPIA!$CD$3:$CD$250,0),4),""),"_"," ")," ",FIXED(IFERROR(INDEX(ATTIVO,MATCH(ROW()-12,COPIA!$CD$3:$CD$250,0),2),""),,FALSE)," euro"),SUBSTITUTE(IFERROR(INDEX(ATTIVO,MATCH(ROWS(B$13:$B68),COPIA!$CD$3:$CD$250,0),4),""),"_"," ")),"")),"")) | C68: =IF(IFERROR(IF(ROW()-9>COPIA!$CI$1,INDEX(ECONOMICO,MATCH((ROWS($B$12:B68)-COPIA!$CI$2),COPIA!$CD$191:$CD$247,0),5),INDEX(ATTIVO,MATCH(ROWS($C$13:C68),COPIA!$CD$3:$CD$250,0),5)),0)=0,"",IFERROR(IF(ROW()-9>COPIA!$CI$1,INDEX(ECONOMICO,MATCH((ROWS($B$12:B68)-COPIA!$CI$2),COPIA!$CD$191:$CD$247,0),5),INDEX(ATTIVO,MATCH(ROWS($C$13:C68),COPIA!$CD$3:$CD$250,0),5)),0)) | D68: =CONCATENATE(IFERROR(IF(MID(CONCATENATE(SUBSTITUTE(IFERROR(INDEX(PASSIVO,MATCH(ROWS(D$13:$D68),COPIA!$CD$105:$CD$189,0),4),""),"_"," ")," ",),8,6)="di cui",CONCATENATE(SUBSTITUTE(IFERROR(INDEX(PASSIVO,MATCH(ROWS(D$13:$D68),COPIA!$CD$105:$CD$189,0),4),""),"_"," ")," ",FIXED(IFERROR(INDEX(PASSIVO,MATCH(ROW()-12,COPIA!$CD$105:$CD$189,0),2),""),,FALSE)," euro"),SUBSTITUTE(IFERROR(INDEX(PASSIVO,MATCH(ROWS($D$13:$D68),COPIA!$CD$105:$CD$189,0),4),""),"_"," ")),"")) | E68: =IF(IFERROR(INDEX(PASSIVO,MATCH(ROWS($E$13:E68),COPIA!$CD$105:$CD$189,0),5),0)=0,"",IFERROR(INDEX(PASSIVO,MATCH(ROWS($E$13:E68),COPIA!$CD$105:$CD$189,0),5),0))
A69: =IF(ROW()<=$A$11,ROW(),0) -> 0 | B69: =IF(ROW()-9>COPIA!$CI$1,SUBSTITUTE(IFERROR(INDEX(ECONOMICO,MATCH((ROWS($B$12:B69)-COPIA!$CI$2),COPIA!$CD$191:$CD$247,0),4),""),"_"," "),IF(ROW()-9<=COPIA!$CI$1,CONCATENATE(IFERROR(IF(MID(CONCATENATE(SUBSTITUTE(IFERROR(INDEX(ATTIVO,MATCH(ROWS(B$13:$B69),COPIA!$CD$3:$CD$250,0),4),""),"_"," ")," ",),8,6)="di cui",CONCATENATE(SUBSTITUTE(IFERROR(INDEX(ATTIVO,MATCH(ROWS(B$13:$B69),COPIA!$CD$3:$CD$250,0),4),""),"_"," ")," ",FIXED(IFERROR(INDEX(ATTIVO,MATCH(ROW()-12,COPIA!$CD$3:$CD$250,0),2),""),,FALSE)," euro"),SUBSTITUTE(IFERROR(INDEX(ATTIVO,MATCH(ROWS(B$13:$B69),COPIA!$CD$3:$CD$250,0),4),""),"_"," ")),"")),"")) | C69: =IF(IFERROR(IF(ROW()-9>COPIA!$CI$1,INDEX(ECONOMICO,MATCH((ROWS($B$12:B69)-COPIA!$CI$2),COPIA!$CD$191:$CD$247,0),5),INDEX(ATTIVO,MATCH(ROWS($C$13:C69),COPIA!$CD$3:$CD$250,0),5)),0)=0,"",IFERROR(IF(ROW()-9>COPIA!$CI$1,INDEX(ECONOMICO,MATCH((ROWS($B$12:B69)-COPIA!$CI$2),COPIA!$CD$191:$CD$247,0),5),INDEX(ATTIVO,MATCH(ROWS($C$13:C69),COPIA!$CD$3:$CD$250,0),5)),0)) | D69: =CONCATENATE(IFERROR(IF(MID(CONCATENATE(SUBSTITUTE(IFERROR(INDEX(PASSIVO,MATCH(ROWS(D$13:$D69),COPIA!$CD$105:$CD$189,0),4),""),"_"," ")," ",),8,6)="di cui",CONCATENATE(SUBSTITUTE(IFERROR(INDEX(PASSIVO,MATCH(ROWS(D$13:$D69),COPIA!$CD$105:$CD$189,0),4),""),"_"," ")," ",FIXED(IFERROR(INDEX(PASSIVO,MATCH(ROW()-12,COPIA!$CD$105:$CD$189,0),2),""),,FALSE)," euro"),SUBSTITUTE(IFERROR(INDEX(PASSIVO,MATCH(ROWS($D$13:$D69),COPIA!$CD$105:$CD$189,0),4),""),"_"," ")),"")) | E69: =IF(IFERROR(INDEX(PASSIVO,MATCH(ROWS($E$13:E69),COPIA!$CD$105:$CD$189,0),5),0)=0,"",IFERROR(INDEX(PASSIVO,MATCH(ROWS($E$13:E69),COPIA!$CD$105:$CD$189,0),5),0))
A70: =IF(ROW()<=$A$11,ROW(),0) -> 0 | B70: =IF(ROW()-9>COPIA!$CI$1,SUBSTITUTE(IFERROR(INDEX(ECONOMICO,MATCH((ROWS($B$12:B70)-COPIA!$CI$2),COPIA!$CD$191:$CD$247,0),4),""),"_"," "),IF(ROW()-9<=COPIA!$CI$1,CONCATENATE(IFERROR(IF(MID(CONCATENATE(SUBSTITUTE(IFERROR(INDEX(ATTIVO,MATCH(ROWS(B$13:$B70),COPIA!$CD$3:$CD$250,0),4),""),"_"," ")," ",),8,6)="di cui",CONCATENATE(SUBSTITUTE(IFERROR(INDEX(ATTIVO,MATCH(ROWS(B$13:$B70),COPIA!$CD$3:$CD$250,0),4),""),"_"," ")," ",FIXED(IFERROR(INDEX(ATTIVO,MATCH(ROW()-12,COPIA!$CD$3:$CD$250,0),2),""),,FALSE)," euro"),SUBSTITUTE(IFERROR(INDEX(ATTIVO,MATCH(ROWS(B$13:$B70),COPIA!$CD$3:$CD$250,0),4),""),"_"," ")),"")),"")) | C70: =IF(IFERROR(IF(ROW()-9>COPIA!$CI$1,INDEX(ECONOMICO,MATCH((ROWS($B$12:B70)-COPIA!$CI$2),COPIA!$CD$191:$CD$247,0),5),INDEX(ATTIVO,MATCH(ROWS($C$13:C70),COPIA!$CD$3:$CD$250,0),5)),0)=0,"",IFERROR(IF(ROW()-9>COPIA!$CI$1,INDEX(ECONOMICO,MATCH((ROWS($B$12:B70)-COPIA!$CI$2),COPIA!$CD$191:$CD$247,0),5),INDEX(ATTIVO,MATCH(ROWS($C$13:C70),COPIA!$CD$3:$CD$250,0),5)),0)) | D70: =CONCATENATE(IFERROR(IF(MID(CONCATENATE(SUBSTITUTE(IFERROR(INDEX(PASSIVO,MATCH(ROWS(D$13:$D70),COPIA!$CD$105:$CD$189,0),4),""),"_"," ")," ",),8,6)="di cui",CONCATENATE(SUBSTITUTE(IFERROR(INDEX(PASSIVO,MATCH(ROWS(D$13:$D70),COPIA!$CD$105:$CD$189,0),4),""),"_"," ")," ",FIXED(IFERROR(INDEX(PASSIVO,MATCH(ROW()-12,COPIA!$CD$105:$CD$189,0),2),""),,FALSE)," euro"),SUBSTITUTE(IFERROR(INDEX(PASSIVO,MATCH(ROWS($D$13:$D70),COPIA!$CD$105:$CD$189,0),4),""),"_"," ")),"")) | E70: =IF(IFERROR(INDEX(PASSIVO,MATCH(ROWS($E$13:E70),COPIA!$CD$105:$CD$189,0),5),0)=0,"",IFERROR(INDEX(PASSIVO,MATCH(ROWS($E$13:E70),COPIA!$CD$105:$CD$189,0),5),0))
A71: =IF(ROW()<=$A$11,ROW(),0) -> 0 | B71: =IF(ROW()-9>COPIA!$CI$1,SUBSTITUTE(IFERROR(INDEX(ECONOMICO,MATCH((ROWS($B$12:B71)-COPIA!$CI$2),COPIA!$CD$191:$CD$247,0),4),""),"_"," "),IF(ROW()-9<=COPIA!$CI$1,CONCATENATE(IFERROR(IF(MID(CONCATENATE(SUBSTITUTE(IFERROR(INDEX(ATTIVO,MATCH(ROWS(B$13:$B71),COPIA!$CD$3:$CD$250,0),4),""),"_"," ")," ",),8,6)="di cui",CONCATENATE(SUBSTITUTE(IFERROR(INDEX(ATTIVO,MATCH(ROWS(B$13:$B71),COPIA!$CD$3:$CD$250,0),4),""),"_"," ")," ",FIXED(IFERROR(INDEX(ATTIVO,MATCH(ROW()-12,COPIA!$CD$3:$CD$250,0),2),""),,FALSE)," euro"),SUBSTITUTE(IFERROR(INDEX(ATTIVO,MATCH(ROWS(B$13:$B71),COPIA!$CD$3:$CD$250,0),4),""),"_"," ")),"")),"")) | C71: =IF(IFERROR(IF(ROW()-9>COPIA!$CI$1,INDEX(ECONOMICO,MATCH((ROWS($B$12:B71)-COPIA!$CI$2),COPIA!$CD$191:$CD$247,0),5),INDEX(ATTIVO,MATCH(ROWS($C$13:C71),COPIA!$CD$3:$CD$250,0),5)),0)=0,"",IFERROR(IF(ROW()-9>COPIA!$CI$1,INDEX(ECONOMICO,MATCH((ROWS($B$12:B71)-COPIA!$CI$2),COPIA!$CD$191:$CD$247,0),5),INDEX(ATTIVO,MATCH(ROWS($C$13:C71),COPIA!$CD$3:$CD$250,0),5)),0)) | D71: =CONCATENATE(IFERROR(IF(MID(CONCATENATE(SUBSTITUTE(IFERROR(INDEX(PASSIVO,MATCH(ROWS(D$13:$D71),COPIA!$CD$105:$CD$189,0),4),""),"_"," ")," ",),8,6)="di cui",CONCATENATE(SUBSTITUTE(IFERROR(INDEX(PASSIVO,MATCH(ROWS(D$13:$D71),COPIA!$CD$105:$CD$189,0),4),""),"_"," ")," ",FIXED(IFERROR(INDEX(PASSIVO,MATCH(ROW()-12,COPIA!$CD$105:$CD$189,0),2),""),,FALSE)," euro"),SUBSTITUTE(IFERROR(INDEX(PASSIVO,MATCH(ROWS($D$13:$D71),COPIA!$CD$105:$CD$189,0),4),""),"_"," ")),"")) | E71: =IF(IFERROR(INDEX(PASSIVO,MATCH(ROWS($E$13:E71),COPIA!$CD$105:$CD$189,0),5),0)=0,"",IFERROR(INDEX(PASSIVO,MATCH(ROWS($E$13:E71),COPIA!$CD$105:$CD$189,0),5),0))
... A139: =IF(ROW()<=$A$11,ROW(),0) -> 0 | B139: =IF(ROW()-9>COPIA!$CI$1,SUBSTITUTE(IFERROR(INDEX(ECONOMICO,MATCH((ROWS($B$12:B139)-COPIA!$CI$2),COPIA!$CD$191:$CD$247,0),4),""),"_"," "),IF(ROW()-9<=COPIA!$CI$1,CONCATENATE(IFERROR(IF(MID(CONCATENATE(SUBSTITUTE(IFERROR(INDEX(ATTIVO,MATCH(ROWS(B$13:$B139),COPIA!$CD$3:$CD$250,0),4),""),"_"," ")," ",),8,6)="di cui",CONCATENATE(SUBSTITUTE(IFERROR(INDEX(ATTIVO,MATCH(ROWS(B$13:$B139),COPIA!$CD$3:$CD$250,0),4),""),"_"," ")," ",FIXED(IFERROR(INDEX(ATTIVO,MATCH(ROW()-12,COPIA!$CD$3:$CD$250,0),2),""),,FALSE)," euro"),SUBSTITUTE(IFERROR(INDEX(ATTIVO,MATCH(ROWS(B$13:$B139),COPIA!$CD$3:$CD$250,0),4),""),"_"," ")),"")),"")) | C139: =IF(IFERROR(IF(ROW()-9>COPIA!$CI$1,INDEX(ECONOMICO,MATCH((ROWS($B$12:B139)-COPIA!$CI$2),COPIA!$CD$191:$CD$247,0),5),INDEX(ATTIVO,MATCH(ROWS($C$13:C139),COPIA!$CD$3:$CD$250,0),5)),0)=0,"",IFERROR(IF(ROW()-9>COPIA!$CI$1,INDEX(ECONOMICO,MATCH((ROWS($B$12:B139)-COPIA!$CI$2),COPIA!$CD$191:$CD$247,0),5),INDEX(ATTIVO,MATCH(ROWS($C$13:C139),COPIA!$CD$3:$CD$250,0),5)),0)) | D139: =CONCATENATE(IFERROR(IF(MID(CONCATENATE(SUBSTITUTE(IFERROR(INDEX(PASSIVO,MATCH(ROWS(D$13:$D139),COPIA!$CD$105:$CD$189,0),4),""),"_"," ")," ",),8,6)="di cui",CONCATENATE(SUBSTITUTE(IFERROR(INDEX(PASSIVO,MATCH(ROWS(D$13:$D139),COPIA!$CD$105:$CD$189,0),4),""),"_"," ")," ",FIXED(IFERROR(INDEX(PASSIVO,MATCH(ROW()-12,COPIA!$CD$105:$CD$189,0),2),""),,FALSE)," euro"),SUBSTITUTE(IFERROR(INDEX(PASSIVO,MATCH(ROWS($D$13:$D139),COPIA!$CD$105:$CD$189,0),4),""),"_"," ")),"")) | E139: =IF(IFERROR(INDEX(PASSIVO,MATCH(ROWS($E$13:E139),COPIA!$CD$105:$CD$189,0),5),0)=0,"",IFERROR(INDEX(PASSIVO,MATCH(ROWS($E$13:E139),COPIA!$CD$105:$CD$189,0),5),0))

Sheet VALORI_INIZIALI
B1: VALORI INIZIALI
B2: È possibile riportare la Situazione contabile pregressa o singoli valori, per totali o per eccedenze. | E2: =LIBRO_GIORNALE!E3 | G2: La suddivisione dei conti è quella impostata nel Foglio Libro Giornale | H2: I valori devono riferirsi all'anno corrente
H3: TOT. DARE | I3: TOT. AVERE
H4: =ROUND(SUMIFS(INDIRECT(CONCATENATE(ADDRESS(9,8,,,),":",ADDRESS(108,8,,,))),INDIRECT(CONCATENATE(ADDRESS(9,4,,,),":",ADDRESS(108,4,,,))),"<="&FINE_PERIODO,INDIRECT(CONCATENATE(ADDRESS(9,4,,,),":",ADDRESS(108,4,,,))),">="&INIZIO_A_PC,$B$9:$B$108,"<>"&0),2) -> 0 | I4: =ROUND(SUMIFS(INDIRECT(CONCATENATE(ADDRESS(9,9,,,),":",ADDRESS(108,9,,,))),INDIRECT(CONCATENATE(ADDRESS(9,4,,,),":",ADDRESS(108,4,,,))),"<="&FINE_PERIODO,INDIRECT(CONCATENATE(ADDRESS(9,4,,,),":",ADDRESS(108,4,,,))),">="&INIZIO_A_PC,$B$9:$B$108,"<>"&0),2) -> 0
H5: =K7 -> Bilanciamento richiesto.
E6: =LIBRO_GIORNALE!E5 -> ATTIVA LA VERSIONE ONLINE | G6: RIPORTA LA DESCRIZIONE VALORE INIZIALE | H6: La descrizione Valore iniziale può essere modificata sovrascrivendone il testo
G7: =IF(INDIRECT(ADDRESS(8,6,,,"LIBRO_GIORNALE"))="","",INDIRECT(ADDRESS(8,6,,,"LIBRO_GIORNALE"))) | H7: =IF(INDIRECT(ADDRESS(8,7,,,"LIBRO_GIORNALE"))="","",INDIRECT(ADDRESS(8,7,,,"LIBRO_GIORNALE"))) | K7: =IF(COPIA!$I$1=2,"Bilanciamento non richiesto.","Bilanciamento richiesto.") -> Bilanciamento richiesto.
B8: Codice | C8: Nr. riga | D8: DATA | E8: DENOMINAZIONE DEI CONTI | G8: DESCRIZIONE | H8: DARE | I8: AVERE | K8: =COPIA!$AP$1 -> 2026
B9: =IF(INDIRECT(ADDRESS(ROW(),4,,,))="",0,IFERROR(INDEX(PDC,MATCH(INDIRECT(ADDRESS(ROW(),5,,,)),DEN_PDC,0),1),0)) -> 0 | C9: =IF(INDIRECT(ADDRESS(ROW(),5,4,,"VALORI_INIZIALI"))<>"",CONCATENATE(ROW()-8," V.I."),"") | F9: =IF(AND(COPIA!$AK$2=TRUE,INDIRECT(ADDRESS(ROW(),4,,,))<>"",INDIRECT(ADDRESS(ROW(),5,,,))<>"",INDIRECT(ADDRESS(ROW(),7,,,))=""),"valore iniziale","") | K9: =IF(INDIRECT(ADDRESS(ROW(),4,4,,))<>"",YEAR(INDIRECT(ADDRESS(ROW(),4,4,,))),0) -> 0
B10: =IF(INDIRECT(ADDRESS(ROW(),4,,,))="",0,IFERROR(INDEX(PDC,MATCH(INDIRECT(ADDRESS(ROW(),5,,,)),DEN_PDC,0),1),0)) -> 0 | C10: =IF(INDIRECT(ADDRESS(ROW(),5,4,,"VALORI_INIZIALI"))<>"",CONCATENATE(ROW()-8," V.I."),"") | F10: =IF(AND(COPIA!$AK$2=TRUE,INDIRECT(ADDRESS(ROW(),4,,,))<>"",INDIRECT(ADDRESS(ROW(),5,,,))<>"",INDIRECT(ADDRESS(ROW(),7,,,))=""),"valore iniziale","") | K10: =IF(INDIRECT(ADDRESS(ROW(),4,4,,))<>"",YEAR(INDIRECT(ADDRESS(ROW(),4,4,,))),0) -> 0
B11: =IF(INDIRECT(ADDRESS(ROW(),4,,,))="",0,IFERROR(INDEX(PDC,MATCH(INDIRECT(ADDRESS(ROW(),5,,,)),DEN_PDC,0),1),0)) -> 0 | C11: =IF(INDIRECT(ADDRESS(ROW(),5,4,,"VALORI_INIZIALI"))<>"",CONCATENATE(ROW()-8," V.I."),"") | F11: =IF(AND(COPIA!$AK$2=TRUE,INDIRECT(ADDRESS(ROW(),4,,,))<>"",INDIRECT(ADDRESS(ROW(),5,,,))<>"",INDIRECT(ADDRESS(ROW(),7,,,))=""),"valore iniziale","") | K11: =IF(INDIRECT(ADDRESS(ROW(),4,4,,))<>"",YEAR(INDIRECT(ADDRESS(ROW(),4,4,,))),0) -> 0
B12: =IF(INDIRECT(ADDRESS(ROW(),4,,,))="",0,IFERROR(INDEX(PDC,MATCH(INDIRECT(ADDRESS(ROW(),5,,,)),DEN_PDC,0),1),0)) -> 0 | C12: =IF(INDIRECT(ADDRESS(ROW(),5,4,,"VALORI_INIZIALI"))<>"",CONCATENATE(ROW()-8," V.I."),"") | F12: =IF(AND(COPIA!$AK$2=TRUE,INDIRECT(ADDRESS(ROW(),4,,,))<>"",INDIRECT(ADDRESS(ROW(),5,,,))<>"",INDIRECT(ADDRESS(ROW(),7,,,))=""),"valore iniziale","") | K12: =IF(INDIRECT(ADDRESS(ROW(),4,4,,))<>"",YEAR(INDIRECT(ADDRESS(ROW(),4,4,,))),0) -> 0
B13: =IF(INDIRECT(ADDRESS(ROW(),4,,,))="",0,IFERROR(INDEX(PDC,MATCH(INDIRECT(ADDRESS(ROW(),5,,,)),DEN_PDC,0),1),0)) -> 0 | C13: =IF(INDIRECT(ADDRESS(ROW(),5,4,,"VALORI_INIZIALI"))<>"",CONCATENATE(ROW()-8," V.I."),"") | F13: =IF(AND(COPIA!$AK$2=TRUE,INDIRECT(ADDRESS(ROW(),4,,,))<>"",INDIRECT(ADDRESS(ROW(),5,,,))<>"",INDIRECT(ADDRESS(ROW(),7,,,))=""),"valore iniziale","") | K13: =IF(INDIRECT(ADDRESS(ROW(),4,4,,))<>"",YEAR(INDIRECT(ADDRESS(ROW(),4,4,,))),0) -> 0
B14: =IF(INDIRECT(ADDRESS(ROW(),4,,,))="",0,IFERROR(INDEX(PDC,MATCH(INDIRECT(ADDRESS(ROW(),5,,,)),DEN_PDC,0),1),0)) -> 0 | C14: =IF(INDIRECT(ADDRESS(ROW(),5,4,,"VALORI_INIZIALI"))<>"",CONCATENATE(ROW()-8," V.I."),"") | F14: =IF(AND(COPIA!$AK$2=TRUE,INDIRECT(ADDRESS(ROW(),4,,,))<>"",INDIRECT(ADDRESS(ROW(),5,,,))<>"",INDIRECT(ADDRESS(ROW(),7,,,))=""),"valore iniziale","") | K14: =IF(INDIRECT(ADDRESS(ROW(),4,4,,))<>"",YEAR(INDIRECT(ADDRESS(ROW(),4,4,,))),0) -> 0
B15: =IF(INDIRECT(ADDRESS(ROW(),4,,,))="",0,IFERROR(INDEX(PDC,MATCH(INDIRECT(ADDRESS(ROW(),5,,,)),DEN_PDC,0),1),0)) -> 0 | C15: =IF(INDIRECT(ADDRESS(ROW(),5,4,,"VALORI_INIZIALI"))<>"",CONCATENATE(ROW()-8," V.I."),"") | F15: =IF(AND(COPIA!$AK$2=TRUE,INDIRECT(ADDRESS(ROW(),4,,,))<>"",INDIRECT(ADDRESS(ROW(),5,,,))<>"",INDIRECT(ADDRESS(ROW(),7,,,))=""),"valore iniziale","") | K15: =IF(INDIRECT(ADDRESS(ROW(),4,4,,))<>"",YEAR(INDIRECT(ADDRESS(ROW(),4,4,,))),0) -> 0
B16: =IF(INDIRECT(ADDRESS(ROW(),4,,,))="",0,IFERROR(INDEX(PDC,MATCH(INDIRECT(ADDRESS(ROW(),5,,,)),DEN_PDC,0),1),0)) -> 0 | C16: =IF(INDIRECT(ADDRESS(ROW(),5,4,,"VALORI_INIZIALI"))<>"",CONCATENATE(ROW()-8," V.I."),"") | F16: =IF(AND(COPIA!$AK$2=TRUE,INDIRECT(ADDRESS(ROW(),4,,,))<>"",INDIRECT(ADDRESS(ROW(),5,,,))<>"",INDIRECT(ADDRESS(ROW(),7,,,))=""),"valore iniziale","") | K16: =IF(INDIRECT(ADDRESS(ROW(),4,4,,))<>"",YEAR(INDIRECT(ADDRESS(ROW(),4,4,,))),0) -> 0
B17: =IF(INDIRECT(ADDRESS(ROW(),4,,,))="",0,IFERROR(INDEX(PDC,MATCH(INDIRECT(ADDRESS(ROW(),5,,,)),DEN_PDC,0),1),0)) -> 0 | C17: =IF(INDIRECT(ADDRESS(ROW(),5,4,,"VALORI_INIZIALI"))<>"",CONCATENATE(ROW()-8," V.I."),"") | F17: =IF(AND(COPIA!$AK$2=TRUE,INDIRECT(ADDRESS(ROW(),4,,,))<>"",INDIRECT(ADDRESS(ROW(),5,,,))<>"",INDIRECT(ADDRESS(ROW(),7,,,))=""),"valore iniziale","") | K17: =IF(INDIRECT(ADDRESS(ROW(),4,4,,))<>"",YEAR(INDIRECT(ADDRESS(ROW(),4,4,,))),0) -> 0
B18: =IF(INDIRECT(ADDRESS(ROW(),4,,,))="",0,IFERROR(INDEX(PDC,MATCH(INDIRECT(ADDRESS(ROW(),5,,,)),DEN_PDC,0),1),0)) -> 0 | C18: =IF(INDIRECT(ADDRESS(ROW(),5,4,,"VALORI_INIZIALI"))<>"",CONCATENATE(ROW()-8," V.I."),"") | F18: =IF(AND(COPIA!$AK$2=TRUE,INDIRECT(ADDRESS(ROW(),4,,,))<>"",INDIRECT(ADDRESS(ROW(),5,,,))<>"",INDIRECT(ADDRESS(ROW(),7,,,))=""),"valore iniziale","") | K18: =IF(INDIRECT(ADDRESS(ROW(),4,4,,))<>"",YEAR(INDIRECT(ADDRESS(ROW(),4,4,,))),0) -> 0
B19: =IF(INDIRECT(ADDRESS(ROW(),4,,,))="",0,IFERROR(INDEX(PDC,MATCH(INDIRECT(ADDRESS(ROW(),5,,,)),DEN_PDC,0),1),0)) -> 0 | C19: =IF(INDIRECT(ADDRESS(ROW(),5,4,,"VALORI_INIZIALI"))<>"",CONCATENATE(ROW()-8," V.I."),"") | F19: =IF(AND(COPIA!$AK$2=TRUE,INDIRECT(ADDRESS(ROW(),4,,,))<>"",INDIRECT(ADDRESS(ROW(),5,,,))<>"",INDIRECT(ADDRESS(ROW(),7,,,))=""),"valore iniziale","") | K19: =IF(INDIRECT(ADDRESS(ROW(),4,4,,))<>"",YEAR(INDIRECT(ADDRESS(ROW(),4,4,,))),0) -> 0
B20: =IF(INDIRECT(ADDRESS(ROW(),4,,,))="",0,IFERROR(INDEX(PDC,MATCH(INDIRECT(ADDRESS(ROW(),5,,,)),DEN_PDC,0),1),0)) -> 0 | C20: =IF(INDIRECT(ADDRESS(ROW(),5,4,,"VALORI_INIZIALI"))<>"",CONCATENATE(ROW()-8," V.I."),"") | F20: =IF(AND(COPIA!$AK$2=TRUE,INDIRECT(ADDRESS(ROW(),4,,,))<>"",INDIRECT(ADDRESS(ROW(),5,,,))<>"",INDIRECT(ADDRESS(ROW(),7,,,))=""),"valore iniziale","") | K20: =IF(INDIRECT(ADDRESS(ROW(),4,4,,))<>"",YEAR(INDIRECT(ADDRESS(ROW(),4,4,,))),0) -> 0
... B108: =IF(INDIRECT(ADDRESS(ROW(),4,,,))="",0,IFERROR(INDEX(PDC,MATCH(INDIRECT(ADDRESS(ROW(),5,,,)),DEN_PDC,0),1),0)) -> 0 | C108: =IF(INDIRECT(ADDRESS(ROW(),5,4,,"VALORI_INIZIALI"))<>"",CONCATENATE(ROW()-8," V.I."),"") | F108: =IF(AND(COPIA!$AK$2=TRUE,INDIRECT(ADDRESS(ROW(),4,,,))<>"",INDIRECT(ADDRESS(ROW(),5,,,))<>"",INDIRECT(ADDRESS(ROW(),7,,,))=""),"valore iniziale","") | K108: =IF(INDIRECT(ADDRESS(ROW(),4,4,,))<>"",YEAR(INDIRECT(ADDRESS(ROW(),4,4,,))),0) -> 0

Sheet COPIA
A1: =IF(INDIRECT(ADDRESS(4,4,,,"PIANO_DEI_CONTI"))="SOCIETÀ IN NOME COLLETTIVO",1,2) -> 2 | D1: =IF(AND(W18=0,$AI$1=0,$AF$1=0,$ES$1=0,$CL$2=$CM$2,$CN$2=$CO$2,LIBRO_GIORNALE!$G$4=LIBRO_GIORNALE!$H$4,VALORI_INIZIALI!$H$4=VALORI_INIZIALI!$I$4),1,0) -> 1 | E1: =IF(AND(W2=0,W5=0,W6=0,$CT$107=0,$CT$84=0,$AF$1=0,$AI$1=0,$CO$1=1,$EL$2=0,$ES$1=0,$BD$1=1,$I$1=2,LIBRO_GIORNALE!$H$4=LIBRO_GIORNALE!$G$4),1,0) -> 0 | F1: =IF(AND($D$1=1,$I$1=1,$BA$1>0,$BD$1=1),1,0) -> 0 | I1: =IF(INDIRECT(ADDRESS(4,6,,,"PIANO_DEI_CONTI"))="CALCOLO AUTOMATICO",1,2) -> 1 | J1: =IF($CO$1=0,"",IF(AND($I$1=1,OR($BI$1>0,$BJ$1>0)),"SITUAZIONE ECONOMICA",IF($I$1=2,"SITUAZIONE ECONOMICA",""))) | M1: PER TOTALI | N1: PER ECCEDENZE | O1: PER TOTALI ED ECCEDENZE | R1: =IF(INDIRECT(ADDRESS(6,6,,,"LIBRO_GIORNALE"))="DELIMITAZIONE ARTICOLO ATTIVATA",TRUE,FALSE) -> TRUE | T1: =IF(INDIRECT(ADDRESS(3,2,,,"LIBRO_GIORNALE"))="DESKTOP: Office",IF(ISNUMBER(U1),INDEX($R$3:$S$60,MATCH($U$1,$R$3:$R$60,0),2),U1),S2) -> VISUALIZZA TUTTI I CONTI | U1: 1 | V1: =MAX($V$3:$V$400) -> 291 | W1: =COUNTIFS(INDIRECT(CONCATENATE(ADDRESS(3,5,,,"LIBRO_GIORNALE"),":",ADDRESS(200,5,,,))),"="&"CONTO DI RISULTATO ECONOMICO",INDIRECT(CONCATENATE(ADDRESS(3,4,,,"LIBRO_GIORNALE"),":",ADDRESS(200,4,,,))),">="&INIZIO_A_PC,INDIRECT(CONCATENATE(ADDRESS(3,4,,,"LIBRO_GIORNALE"),":",ADDRESS(200,4,,,))),"<="&FINE_AC) -> 0 | X1: =SUMIFS(INDIRECT(CONCATENATE(ADDRESS(3,8,,,"LIBRO_GIORNALE"),":",ADDRESS(200,8,,,))),INDIRECT(CONCATENATE(ADDRESS(3,5,,,"LIBRO_GIORNALE"),":",ADDRESS(200,5,,,))),"="&"CONTO DI RISULTATO ECONOMICO",INDIRECT(CONCATENATE(ADDRESS(3,4,,,"LIBRO_GIORNALE"),":",ADDRESS(200,4,,,))),">="&INIZIO_A_PC,INDIRECT(CONCATENATE(ADDRESS(3,4,,,"LIBRO_GIORNALE"),":",ADDRESS(200,4,,,))),"<="&FINE_AC) -> 0 | Y1: =SUMIFS(INDIRECT(CONCATENATE(ADDRESS(3,7,,,"LIBRO_GIORNALE"),":",ADDRESS(200,7,,,))),INDIRECT(CONCATENATE(ADDRESS(3,5,,,"LIBRO_GIORNALE"),":",ADDRESS(200,5,,,))),"="&"CONTO DI RISULTATO ECONOMICO",INDIRECT(CONCATENATE(ADDRESS(3,4,,,"LIBRO_GIORNALE"),":",ADDRESS(200,4,,,))),">="&INIZIO_A_PC,INDIRECT(CONCATENATE(ADDRESS(3,4,,,"LIBRO_GIORNALE"),":",ADDRESS(200,4,,,))),"<="&FINE_AC) -> 0 | AD1: =SUMIFS(dare_grezzo,den_grezzo,"="&"BILANCIO DI APERTURA",data_grezzo,">="&INIZIO_A_PC,data_grezzo,"<="&FINE_AC) -> 0 | AE1: =SUMIFS(avere_grezzo,den_grezzo,"="&"BILANCIO DI APERTURA",data_grezzo,">="&INIZIO_A_PC,data_grezzo,"<="&FINE_AC) -> 0 | AF1: =IF(AD1=AE1,0,1) -> 0 | AG1: =SUMIFS(dare_grezzo,den_grezzo,"="&"BILANCIO DI CHIUSURA",data_grezzo,">="&INIZIO_A_PC,data_grezzo,"<="&FINE_AC) -> 0 | AH1: =SUMIFS(avere_grezzo,den_grezzo,"="&"BILANCIO DI CHIUSURA",data_grezzo,">="&INIZIO_A_PC,data_grezzo,"<="&FINE_AC) -> 0 | AI1: =IF(AG1=AH1,0,1) -> 0 | AK1: =AL1 -> 1 | AL1: =IF(INDIRECT(ADDRESS(5,4,,,"LIBRO_GIORNALE"))="N+1",2,IF(INDIRECT(ADDRESS(5,4,,,"LIBRO_GIORNALE"))="N+2",3,IF(INDIRECT(ADDRESS(5,4,,,"LIBRO_GIORNALE"))="N+3",4,IF(INDIRECT(ADDRESS(5,4,,,"LIBRO_GIORNALE"))="N+4",5,IF(INDIRECT(ADDRESS(5,4,,,"LIBRO_GIORNALE"))="N+5",6,1))))) -> 1 | AN1: =AL1-1 -> 0 | AP1: =CW1 -> 2026 | AR1: =AP1+AN1 -> 2026 | AS1: =IF(INDIRECT(ADDRESS(5,2,,,"LIBRO_GIORNALE"))="",31,INDIRECT(ADDRESS(5,2,,,"LIBRO_GIORNALE"))) -> 31 | AT1: =IF(INDIRECT(ADDRESS(5,3,,,"LIBRO_GIORNALE"))="",12,INDIRECT(ADDRESS(5,3,,,"LIBRO_GIORNALE"))) -> 12 | AW1: =UPPER(IF($AL$1=1,"n",IF($AL$1=2,"n+1",IF($AL$1=3,"n+2",IF($AL$1=4,"n+3",IF($AL$1=5,"n+4",IF($AL$1=6,"n+5",""))))))) -> N | AY1: =SUMIFS(avere_grezzo,den_grezzo,"="&"GESTIONE TITOLI",data_grezzo,">="&INIZIO_A_PC,data_grezzo,"<="&FINE_AC)-SUMIFS(dare_grezzo,den_grezzo,"="&"GESTIONE TITOLI",data_grezzo,">="&INIZIO_A_PC,data_grezzo,"<="&FINE_AC) -> 0 | AZ1: =94-COUNTBLANK(AZ3:AZ96)+1 -> 1 | BA1: =ABS(SUMIFS(avere_grezzo,den_grezzo,"="&"CAPITALE SOCIALE",data_grezzo,">="&INIZIO_A_PC,data_grezzo,"<="&FINE_AC)-SUMIFS(dare_grezzo,den_grezzo,"="&"CAPITALE SOCIALE",data_grezzo,">="&INIZIO_A_PC,data_grezzo,"<="&FINE_AC)) -> 0 | BB1: =SUMIFS(dare_grezzo,dest_grezzo,"="&"sp",data_grezzo,">="&INIZIO_A_PC,data_grezzo,"<="&FINE_AC) -> 0 | BC1: =SUMIFS(avere_grezzo,dest_grezzo,"="&"sp",data_grezzo,">="&INIZIO_A_PC,data_grezzo,"<="&FINE_AC) -> 0 | BD1: =IF(BB1=BC1,1,0) -> 1 | BF1: =IF(INDIRECT(ADDRESS(6,8,,,"LIBRO_GIORNALE"))="ATTIVA",1,INDIRECT(ADDRESS(6,8,,,"LIBRO_GIORNALE"))+1) -> 1 | BG1: =MAX(BG3:BG388) -> 0 | BH1: =MAX(BH3:BH400) -> 0 | BI1: =MAX(BI3:BI400) -> 0 | BJ1: =MAX(BJ3:BJ400) -> 0 | BK1: =MAX(BG1,BH1)+5 -> 5 | BL1: =BK1+10+BN1 -> 19 | BM1: =BL1-1 -> 18 | BN1: =IFERROR(IF(INDIRECT(ADDRESS(4,3,,,"SIT.PATR._SIT.ECON."))="RIGHE TRA I PROSPETTI",4,INDIRECT(ADDRESS(4,3,,,"SIT.PATR._SIT.ECON."))+4),4) -> 4 | BO1: =IF(AND(BP2=0,BR2=0),"","SITUAZIONE ECONOMICA") | BQ1: =BS1+1 -> 5 | BR1: =BT1+2 -> 2 | BS1: =BR1+2 -> 4 | BT1: =MAX(BS3:BS399) -> 0 | BU1: =IF(INDIRECT(ADDRESS(4,3,,,"SIT._CONTABILE"))="PER TOTALI",1,IF(INDIRECT(ADDRESS(4,3,,,"SIT._CONTABILE"))="PER ECCEDENZE",2,3)) -> 3 | BV1: =IF(BU1=1,"TOTALI",IF(BU1=2,"ECCEDENZE",IF(BU1=3,"TOTALI ED ECCEDENZE",""))) -> TOTALI ED ECCEDENZE | BW1: =IF(AND(BU401=BV401,BW401=BX401,BD1=1,$EL$2=0),1,0) -> 1 | BX1: =IF(AND($I$1=1,LIBRO_GIORNALE!H4=LIBRO_GIORNALE!G4,VALORI_INIZIALI!H4=VALORI_INIZIALI!I4),1,IF(AND($I$1=2,LIBRO_GIORNALE!H4=LIBRO_GIORNALE!G4),1,0)) -> 1 | BY1: =MAX(BY3:BY400) -> 0 | CC1: =ROUND(SUMIFS(avere_grezzo,dest_grezzo,"="&"SE AVERE",data_grezzo,"<"&INIZIO_AC,data_grezzo,">="&INIZIO_A_PC)-SUMIFS(dare_grezzo,dest_grezzo,"="&"SE DARE",data_grezzo,"<"&INIZIO_AC,data_grezzo,">="&INIZIO_A_PC),0) -> 0 | CD1: =MAX(CD3:CD103)+4 -> 4 | CE1: =MAX(CD105:CD189)+4 -> 4 | CF1: =IF(OR(INDIRECT(ADDRESS(4,4,,,"BILANCIO"))="DELLE CLASSI",INDIRECT(ADDRESS(4,4,,,"BILANCIO"))="DELLE CLASSI E DELLE SOTTOCLASSI"),TRUE,FALSE) -> TRUE | CG1: =IF(OR(INDIRECT(ADDRESS(4,4,,,"BILANCIO"))="DELLE SOTTOCLASSI",INDIRECT(ADDRESS(4,4,,,"BILANCIO"))="DELLE CLASSI E DELLE SOTTOCLASSI"),TRUE,FALSE) -> FALSE | CI1: =SUM(MAX(CD3:CD189),10,CE2) -> 11 | CJ1: PER TOTALI | CL1: =IF(AND(CL2=CM2,CN2=CO2),1,0) -> 1 | CO1: =IF(AND(SUM(dare_grezzo)=0,SUM(avere_grezzo)=0),0,1) -> 0 | CP1: =IF(INDIRECT(ADDRESS(3,2,,,"SIT.PATR._SIT.ECON."))="VISUALIZZA IL RISULTATO ECONOMICO",TRUE,FALSE) -> FALSE | CQ1: TRUE | CR1: =MAX(CR3:CR10) -> 0 | CU1: =TODAY() -> 46107 | CV1: 1 | CW1: =YEAR(CU1) -> 2026 | CX1: =DATE(CW1,CV1,CV1) -> 46023 | CY1: =AS1 -> 31 | CZ1: =AT1 -> 12 | DA1: =FINE_AC -> 46387 | DB1: =MAX(CW3:CW220) -> 0 | DC1: =IF(INDIRECT(ADDRESS(2,COLUMN()-102,,,"Conti_di_mastro"))>31,"",INDIRECT(ADDRESS(2,COLUMN()-102,,,"Conti_di_mastro"))) | DD1: =IF(INDIRECT(ADDRESS(2,COLUMN()-102,,,"Conti_di_mastro"))>12,"",INDIRECT(ADDRESS(2,COLUMN()-102,,,"Conti_di_mastro"))) -> 0 | DE1: =IF(DB1>100,100,DB1) -> 0 | DF1: =IF($DG$1>$DB$1+1,0,DG1-1) -> 0 | DG1: =DD2 -> 1 | DH1: =IF(INDIRECT(ADDRESS(7,4,,,"BILANCIO"))="C 16 d) INTERESSI ATTIVI V/CONTROLLATE",TRUE,FALSE) -> FALSE | DJ1: =IF(INDIRECT(ADDRESS(7,2,,,"BILANCIO"))="ATTIVATE",TRUE,FALSE) -> FALSE | DK1: =IF(INDIRECT(ADDRESS(7,4,,,"BILANCIO"))="C 16 d) INTERESSI ATTIVI V/COLLEGATE",TRUE,FALSE) -> FALSE | DL1: =IF(INDIRECT(ADDRESS(4,4,,,"PIANO_DEI_CONTI"))="Adatta ad una S.r.l. solo alcuni dei conti della S.p.A.",TRUE,FALSE) -> FALSE | DM1: =IF(INDIRECT(ADDRESS(7,4,,,"BILANCIO"))="C 16 d) INTERESSI ATTIVI V/CONTROLLANTI",TRUE,FALSE) -> FALSE | DN1: =IF(A1=2,MAX($DN$3:$DN$401),0) -> 328 | DO1: =IF($A$1=1,MAX(DW3:DW400),0) -> 0 | DP1: =MAX(DN1,DO1) -> 328 | DR1: =SUM(DS1:DV1) -> 0 | DS1: =IFERROR(FIND("SOCIO",$DR5),0) -> 0 | DT1: =IFERROR(FIND("SOCIO",$DR6),0) -> 0 | DU1: =IFERROR(FIND("SOCIO",$DR7),0) -> 0 | DV1: =IFERROR(FIND("SOCIO",$DR8),0) -> 0 | DW1: =IF(AND(DY1>0,DY2>0),0,1) -> 1 | DX1: =IF(DY1>0,"perdita d'esercizio","") | DY1: =SUMIFS($AO$103:$AO$302,$AM$103:$AM$302,"="&"perdita d'esercizio",$AL$103:$AL$302,">="&INIZIO_A_PC,$AL$103:$AL$302,">="&INIZIO_AC,$AL$103:$AL$302,"<="&FINE_AC) -> 0 | EF1: =IF($CO$1=1,"SITUAZIONE PATRIMONIALE","") | EK1: =IF(EL1<0,"UTILE D'ESERCIZIO","") | EL1: =IF(I1=2,0,SUMIFS(INDIRECT(CONCATENATE(ADDRESS(3,8,1,,"libro_giornale"),":",ADDRESS(200,8,1,,))),INDIRECT(CONCATENATE(ADDRESS(3,5,1,,"libro_giornale"),":",ADDRESS(200,5,1,,))),"="&"UTILE D'ESERCIZIO",INDIRECT(CONCATENATE(ADDRESS(3,4,1,,"libro_giornale"),":",ADDRESS(200,4,1,,))),">="&INIZIO_A_PC,INDIRECT(CONCATENATE(ADDRESS(3,4,1,,"libro_giornale"),":",ADDRESS(200,4,1,,))),"<="&FINE_AC)-SUMIFS(INDIRECT(CONCATENATE(ADDRESS(3,7,1,,"libro_giornale"),":",ADDRESS(200,7,1,,))),INDIRECT(CONCATENATE(ADDRESS(3,5,1,,"libro_giornale"),":",ADDRESS(200,5,1,,))),"="&"UTILE D'ESERCIZIO",INDIRECT(CONCATENATE(ADDRESS(3,4,1,,"libro_giornale"),":",ADDRESS(200,4,1,,))),">="&INIZIO_A_PC,INDIRECT(CONCATENATE(ADDRESS(3,4,1,,"libro_giornale"),":",ADDRESS(200,4,1,,))),"<="&FINE_AC)) -> 0 | EM1: =IF(I1=2,0,SUMIFS(INDIRECT(CONCATENATE(ADDRESS(3,7,1,,"libro_giornale"),":",ADDRESS(200,7,1,,))),INDIRECT(CONCATENATE(ADDRESS(3,5,1,,"libro_giornale"),":",ADDRESS(200,5,1,,))),"="&"PERDITA D'ESERCIZIO",INDIRECT(CONCATENATE(ADDRESS(3,4,1,,"libro_giornale"),":",ADDRESS(200,4,1,,))),">="&INIZIO_A_PC,INDIRECT(CONCATENATE(ADDRESS(3,4,1,,"libro_giornale"),":",ADDRESS(200,4,1,,))),"<="&FINE_AC)-SUMIFS(INDIRECT(CONCATENATE(ADDRESS(3,8,1,,"libro_giornale"),":",ADDRESS(200,8,1,,))),INDIRECT(CONCATENATE(ADDRESS(3,5,1,,"libro_giornale"),":",ADDRESS(200,5,1,,))),"="&"PERDITA D'ESERCIZIO",INDIRECT(CONCATENATE(ADDRESS(3,4,1,,"libro_giornale"),":",ADDRESS(200,4,1,,))),">="&INIZIO_A_PC,INDIRECT(CONCATENATE(ADDRESS(3,4,1,,"libro_giornale"),":",ADDRESS(200,4,1,,))),"<="&FINE_AC)) -> 0 | EN1: =IF(EM1<0,"PERDITA D'ESERCIZIO","") | EO1: =IF($EL$2=0,SUMIFS(avere_grezzo,dest_grezzo,"="&"SE AVERE",data_grezzo,"<="&FINE_AC,data_grezzo,">="&INIZIO_AC,progressivo,"<="&$EP$1)+SUMIFS(avere_grezzo,dest_grezzo,"="&"SE DARE",data_grezzo,"<="&FINE_AC,data_grezzo,">="&INIZIO_AC,progressivo,"<="&$EP1)-SUMIFS(dare_grezzo,dest_grezzo,"="&"SE AVERE",data_grezzo,"<="&FINE_AC,data_grezzo,">="&INIZIO_AC,progressivo,"<="&EP1)-SUMIFS(dare_grezzo,dest_grezzo,"="&"SE DARE",data_grezzo,"<="&FINE_AC,data_grezzo,">="&INIZIO_AC,progressivo,"<="&EP1),0) -> 0 | EP1: =IF(BF1=1,400,68+BF1) -> 400 | ES1: =MAX($ER$3:$ER$400) -> 0 | EV1: =IF(INDIRECT(ADDRESS(6,5,,,"CONTI_DI_MASTRO"))="VISUALIZZA PRIMA I CONTI DELL'ULTIMO ARTICOLO",1,0) -> 1 | FG1: =IF(FG2>0,"I movimenti non sono in ordine cronologico","") | FJ1: =IF(AND(FK1=0,FP1=0),"","Non sono stati girati i seguenti conti: ") | FK1: =MAX(FK3:FK400) -> 0 | FL1: =CONCATENATE(FJ1,FL3,FL4,FL5,FL6,FL7,FL8,FL9,FL10,FL11," - ",FQ3,FQ4,FQ5,FQ6,FQ7,FQ8,FQ9,FQ10,FQ11) -> - | FP1: =MAX(FP3:FP400) -> 0 | FQ1: =IF(FP1=0,"",CONCATENATE("Non sono stati girati i seguenti conti: ",FQ3,FQ4,FQ5,FQ6,FQ7,FQ8,FQ9,FQ10,FQ11))
J2: =IF($CO$1=0,"",IF(AND($I$1=1,OR($BI$1>0,$BJ$1>0)),"COSTI",IF($I$1=2,"COSTI",""))) | L2: =IF($CO$1=0,"",IF(AND($I$1=1,OR($BI$1>0,$BJ$1>0)),"importi ",IF($I$1=2,"importi ",""))) | S2: =IF(INDIRECT(ADDRESS(3,2,,,"LIBRO_GIORNALE"))="Cloud: Office 365","VISUALIZZA TUTTI I CONTI","VISUALIZZA TUTTI I CONTI") -> VISUALIZZA TUTTI I CONTI | U2: =IF(INDIRECT(ADDRESS(2,5,,,"LIBRO_GIORNALE"))="CONTI SUDDIVISI PER CLASSIFICAZIONE",1,2) -> 2 | W2: =COUNTIFS(INDIRECT(CONCATENATE(ADDRESS(3,5,,,"VALORI_INIZIALI"),":",ADDRESS(70,5,,,))),"="&"CONTO DI RISULTATO ECONOMICO",INDIRECT(CONCATENATE(ADDRESS(3,4,,,"VALORI_INIZIALI"),":",ADDRESS(70,4,,,))),">="&INIZIO_A_PC,INDIRECT(CONCATENATE(ADDRESS(3,4,,,"valori_iniziali"),":",ADDRESS(70,4,,,))),"<="&FINE_A_PC) -> 0 | X2: =SUMIFS(INDIRECT(CONCATENATE(ADDRESS(3,7,,,"LIBRO_GIORNALE"),":",ADDRESS(200,7,,,))),INDIRECT(CONCATENATE(ADDRESS(3,5,,,"LIBRO_GIORNALE"),":",ADDRESS(200,5,,,))),"="&"PERDITA D'ESERCIZIO",INDIRECT(CONCATENATE(ADDRESS(3,4,,,"LIBRO_GIORNALE"),":",ADDRESS(200,4,,,))),">="&INIZIO_A_PC,INDIRECT(CONCATENATE(ADDRESS(3,4,,,"LIBRO_GIORNALE"),":",ADDRESS(200,4,,,))),"<="&FINE_AC) -> 0 | Y2: =SUMIFS(INDIRECT(CONCATENATE(ADDRESS(3,8,,,"LIBRO_GIORNALE"),":",ADDRESS(200,8,,,))),INDIRECT(CONCATENATE(ADDRESS(3,5,,,"LIBRO_GIORNALE"),":",ADDRESS(200,5,,,))),"="&"UTILE D'ESERCIZIO",INDIRECT(CONCATENATE(ADDRESS(3,4,,,"LIBRO_GIORNALE"),":",ADDRESS(200,4,,,))),">="&INIZIO_A_PC,INDIRECT(CONCATENATE(ADDRESS(3,4,,,"LIBRO_GIORNALE"),":",ADDRESS(200,4,,,))),"<="&FINE_AC) -> 0 | AI2: =DATE(ANNO_SELEZIONATO-1,1,1) -> 45658 | AJ2: =DATE(ANNO_SELEZIONATO-1,12,31) -> 46022 | AK2: =IF(INDIRECT(ADDRESS(6,7,,,"VALORI_INIZIALI"))="RIPORTA LA DESCRIZIONE VALORE INIZIALE",TRUE,FALSE) -> TRUE | AL2: =COUNTIFS($AL$71:$AL$400,">"&0) -> 0 | AM2: =DATE(anno_CORRENTE,12,31) -> 46387 | AO2: =DATE(AP1,1,1) -> 46023 | AP2: =DATE(AP1+5,12,31) -> 48213 | AQ2: =DATE(AR1,1,1) -> 46023 | AR2: =DATE(AR1,AT1,AS1) -> 46387 | BF2: =IF($BF$1=1,400,BF1-1) -> 400 | BL2: =SUM(BL3:BL398) -> 0 | BN2: =SUM(BN3:BN398) -> 0 | BO2: =IF(AND(I1=1,BP2=0,BR2=0),"","COSTI") | BP2: =SUM(BP3:BP398) -> 0 | BQ2: =IF(AND(I1=1,BP2=0,BR2=0),"","RICAVI") | BR2: =SUM(BR3:BR398) -> 0 | CE2: =IFERROR(IF(INDIRECT(ADDRESS(6,5,,,"BILANCIO"))="RIGHE TRA I PROSPETTI",1,INDIRECT(ADDRESS(6,5,,,"BILANCIO"))+1),1) -> 1 | CF2: TRUE | CG2: TRUE | CH2: =SUMIFS(dare_grezzo,dest_grezzo,"="&"sp dare")+SUMIFS(avere_grezzo,dest_grezzo,"="&"SP AVERE") -> 0 | CI2: =CI1-2 -> 9 | CJ2: PER ECCEDENZE | CL2: =SUM($BU$3:$BU$398) -> 0 | CM2: =SUM($BV$3:$BV$398) -> 0 | CN2: =SUM($BW$3:$BW$398) -> 0 | CO2: =SUM($BX$3:$BX$398) -> 0 | CV2: MOSTRA UN CONTO IN EVIDENZA | CY2: mastro | DA2: =IF(INDIRECT(ADDRESS(6,8,,,"CONTI_DI_MASTRO"))="VISUALIZZA I MOVIMENTI E IL SALDO",TRUE,FALSE) -> TRUE | DB2: =IF(OR($DC$1=0,$DD$1=0),$CW$1-1,$AR$1) -> 2025 | DC2: =IF(INDIRECT(ADDRESS(6,4,,,"CONTI_DI_MASTRO"))="",1,INDIRECT(ADDRESS(6,4,,,"CONTI_DI_MASTRO"))) -> MOSTRA UN CONTO IN EVIDENZA | DD2: =IFERROR(MATCH(DC2,$CV$2:$CV$400,0),1) -> 1 | DF2: =DG2 -> 0 | DG2: =MAX(DF1304:DF1339) -> 0 | DX2: =IF(DY2>0,"utile d'esercizio","") | DY2: =SUMIFS($AP$103:$AP$302,$AM$103:$AM$302,"="&"utile d'esercizio",$AL$103:$AL$302,">="&INIZIO_A_PC,$AL$103:$AL$302,">="&INIZIO_AC,$AL$103:$AL$302,"<="&FINE_AC) -> 0 | EA2: =IF($CO$1=0,"",IF(AND($I$1=1,OR($BI$1>0,$BJ$1>0)),"RICAVI",IF($I$1=2,"RICAVI",""))) | EC2: =IF($CO$1=0,"",IF(AND($I$1=1,OR($BI$1>0,$BJ$1>0)),"importi ",IF($I$1=2,"importi ",""))) | EF2: =IF($CO$1=1,"ATTIVITÀ","") | EG2: =IF($CO$1=1,"importi ","") | EJ2: =IF($CO$1=1,"PASSIVITÀ E NETTO","") | EK2: =IF($CO$1=1,"importi ","") | EL2: =COUNTIFS(EL3:EL400,"<"&0) -> 0 | EN2: =MAX(EM3:EM400) -> 0 | FF2: ordine mastri | FG2: =SUM(FG103:FG400) -> 0
