Workbook
Name ANNI: COPIA!$AN$1:$AN$2
Name AVERE: COPIA!$BE$3:$BE$500
Name avere_grezzo: COPIA!$FC$3:$FC$400
Name CLASSIFICAZIONE: COPIA!$AD$3:$AD$230
Name CODICE: COPIA!$Z$3:$Z$230
Name conti_aperti: OFFSET(COPIA!$CV$2,,,COPIA!$CX$2+1,)
Name DARE: COPIA!$BD$3:$BD$500
Name dare_grezzo: COPIA!$FB$3:$FB$400
Name DATA: COPIA!$BA$3:$BA$500
Name data_grezzo: COPIA!$EY$3:$EY$400
Name den_grezzo: COPIA!$EZ$3:$EZ$400
Name DENOMINAZIONE: COPIA!$AA$3:$AA$230
Name DENOMINAZIONE_GIORNALE: COPIA!$BB$3:$BB$500
Name DESCRIZIONE: COPIA!$BC$3:$BC$500
Name DESTINAZIONE: COPIA!$AE$3:$AE$230
Name ECCEDENZA: COPIA!$AC$3:$AC$230
Name elenco_aperti: OFFSET(COPIA!$CV$2,,,COPIA!$CX$2+1,)
Name FILTRO_CELLA: COPIA!$EP$1:$EP$2
Name FINE_A_PC: COPIA!$EX$2
Name FINE_AC: COPIA!$FC$1
Name GIORNALE: COPIA!$AZ$3:$BE$500
Name giornale_grezzo: COPIA!$EY$3:$FC$400
Name GIORNI: COPIA!$J$4:$J$34
Name INIZIO_A_PC: COPIA!$EY$2
Name INIZIO_AC: COPIA!$FC$2
Name LIBRO_GIORNALE: COPIA!$AZ$3:$BF$500
Name MENU__TENDINA: OFFSET(COPIA!$DI$3,,,COPIA!$DH$1)
Name MENU_TENDINA: OFFSET(COPIA!$M$3,,,COPIA!$P$1)
Name MESI: COPIA!$J$4:$J$15
Name nascondi_righe: COPIA!$EX$102:$EX$400
Name NATURA: COPIA!$AB$3:$AB$230
Name Num._riga: COPIA!$AZ$3:$AZ$500
Name office365: COPIA!$K$3:$K$250
Name PIANO_DEI_CONTI: COPIA!$Z$3:$AI$230
Name PROGRESSIVO: COPIA!$EL$3:$EL$500
Name RAGRUPPAMENTO: COPIA!$AF$3:$AF$230
Name rettifiche: OFFSET(COPIA!$IR$3,,,COPIA!$IQ$1,1)
Name RIGHE_PROSPETTI: COPIA!$JM$3:$JM$33
Name saldi: OFFSET(COPIA!$GW$3,,,COPIA!$GW$1,1)
Name VALORI_INIZIALI: VALORI_INIZIALI!$B$8:$I$75

Sheet PIANO_DEI_CONTI
A1: PIANO DEI CONTI
A2: Inserire una X per filtrare i conti in relazione al livello di svolgimento del programma | F2: LIVELLO DI PROGRESSIONE DEL PROGRAMMA | I2: RINOMINARE I CONTI
F3: C - SCRITTURE DI ASSESTAMENTO | I3: 1.BANCA X C/C - 2.BANCA Y C/C - 3. CEDENTE C/CESSIONE
A5: QUADRO DEI CONTI DI UN'IMPRESA INDIVIDUALE - DAL FASCICOLO ALLEGATO AL LIBRO DI TESTO FUTURO IMPRESA SMART 3 - TE213FA - TRAMONTANA
A6: Assegnazione dei conti alle macroaree | D6: Codice | E6: DENOMINAZIONE DEL CONTO | F6: NATURA | G6: ECCEDENZA | H6: CLASSIFICAZIONE | I6: DESTINAZIONE
A7: A | B7: B | C7: C | D7: =IF(COPIA!A3=0,"",COPIA!A3) -> 01.00 | E7: =IF(COPIA!B3=0,"",COPIA!B3) -> IMMOBILIZZAZIONI IMMATERIALI | F7: =IF(COPIA!C3=0,"",COPIA!C3) | G7: =IF(COPIA!D3=0,"",COPIA!D3) | H7: =IF(COPIA!E3=0,"",IF(COPIA!B3="FONDO SVALUTAZIONE CREDITI","RETTIFICA CREDITI",COPIA!E3)) | I7: =IF(COPIA!F3=0,"",COPIA!F3) | M7: 1
A8: x | B8: x | C8: x | D8: =IF(COPIA!A4=0,"",COPIA!A4) -> 01.01 | E8: =IF(COPIA!B4=0,"",COPIA!B4) -> COSTI DI IMPIANTO | F8: =IF(COPIA!C4=0,"",COPIA!C4) -> E | G8: =IF(COPIA!D4=0,"",COPIA!D4) -> D | H8: =IF(COPIA!E4=0,"",IF(COPIA!B4="FONDO SVALUTAZIONE CREDITI","RETTIFICA CREDITI",COPIA!E4)) -> COSTI PLURIENNALI | I8: =IF(COPIA!F4=0,"",COPIA!F4) -> SP DARE | M8: 2
A9: x | B9: x | C9: x | D9: =IF(COPIA!A5=0,"",COPIA!A5) -> 01.03 | E9: =IF(COPIA!B5=0,"",COPIA!B5) -> BREVETTI | F9: =IF(COPIA!C5=0,"",COPIA!C5) -> E | G9: =IF(COPIA!D5=0,"",COPIA!D5) -> D | H9: =IF(COPIA!E5=0,"",IF(COPIA!B5="FONDO SVALUTAZIONE CREDITI","RETTIFICA CREDITI",COPIA!E5)) -> COSTI PLURIENNALI | I9: =IF(COPIA!F5=0,"",COPIA!F5) -> SP DARE | M9: 3
A10: x | B10: x | C10: x | D10: =IF(COPIA!A6=0,"",COPIA!A6) -> 01.04 | E10: =IF(COPIA!B6=0,"",COPIA!B6) -> SOFTWARE | F10: =IF(COPIA!C6=0,"",COPIA!C6) -> E | G10: =IF(COPIA!D6=0,"",COPIA!D6) -> D | H10: =IF(COPIA!E6=0,"",IF(COPIA!B6="FONDO SVALUTAZIONE CREDITI","RETTIFICA CREDITI",COPIA!E6)) -> COSTI PLURIENNALI | I10: =IF(COPIA!F6=0,"",COPIA!F6) -> SP DARE
C11: x | D11: =IF(COPIA!A7=0,"",COPIA!A7) -> 01.05 | E11: =IF(COPIA!B7=0,"",COPIA!B7) -> AVVIAMENTO | F11: =IF(COPIA!C7=0,"",COPIA!C7) -> E | G11: =IF(COPIA!D7=0,"",COPIA!D7) -> D | H11: =IF(COPIA!E7=0,"",IF(COPIA!B7="FONDO SVALUTAZIONE CREDITI","RETTIFICA CREDITI",COPIA!E7)) -> COSTI PLURIENNALI | I11: =IF(COPIA!F7=0,"",COPIA!F7) -> SP DARE
C12: x | D12: =IF(COPIA!A8=0,"",COPIA!A8) -> 01.11 | E12: =IF(COPIA!B8=0,"",COPIA!B8) -> FONDO AMMORTAMENTO COSTI DI IMPIANTO | F12: =IF(COPIA!C8=0,"",COPIA!C8) -> E | G12: =IF(COPIA!D8=0,"",COPIA!D8) -> A | H12: =IF(COPIA!E8=0,"",IF(COPIA!B8="FONDO SVALUTAZIONE CREDITI","RETTIFICA CREDITI",COPIA!E8)) -> RETTIFICHE COSTI PLURIENNALI | I12: =IF(COPIA!F8=0,"",COPIA!F8) -> SP AVERE
B13: x | C13: x | D13: =IF(COPIA!A9=0,"",COPIA!A9) -> 01.13 | E13: =IF(COPIA!B9=0,"",COPIA!B9) -> FONDO AMMORTAMENTO BREVETTI | F13: =IF(COPIA!C9=0,"",COPIA!C9) -> E | G13: =IF(COPIA!D9=0,"",COPIA!D9) -> A | H13: =IF(COPIA!E9=0,"",IF(COPIA!B9="FONDO SVALUTAZIONE CREDITI","RETTIFICA CREDITI",COPIA!E9)) -> RETTIFICHE COSTI PLURIENNALI | I13: =IF(COPIA!F9=0,"",COPIA!F9) -> SP AVERE
B14: x | C14: x | D14: =IF(COPIA!A10=0,"",COPIA!A10) -> 01.14 | E14: =IF(COPIA!B10=0,"",COPIA!B10) -> FONDO AMMORTAMENTO SOFTWARE | F14: =IF(COPIA!C10=0,"",COPIA!C10) -> E | G14: =IF(COPIA!D10=0,"",COPIA!D10) -> A | H14: =IF(COPIA!E10=0,"",IF(COPIA!B10="FONDO SVALUTAZIONE CREDITI","RETTIFICA CREDITI",COPIA!E10)) -> RETTIFICHE COSTI PLURIENNALI | I14: =IF(COPIA!F10=0,"",COPIA!F10) -> SP AVERE
C15: x | D15: =IF(COPIA!A11=0,"",COPIA!A11) -> 01.15 | E15: =IF(COPIA!B11=0,"",COPIA!B11) -> FONDO AMMORTAMENTO AVVIAMENTO | F15: =IF(COPIA!C11=0,"",COPIA!C11) -> E | G15: =IF(COPIA!D11=0,"",COPIA!D11) -> A | H15: =IF(COPIA!E11=0,"",IF(COPIA!B11="FONDO SVALUTAZIONE CREDITI","RETTIFICA CREDITI",COPIA!E11)) -> RETTIFICHE COSTI PLURIENNALI | I15: =IF(COPIA!F11=0,"",COPIA!F11) -> SP AVERE
A16: x | B16: x | C16: x | D16: =IF(COPIA!A12=0,"",COPIA!A12) -> 01.20 | E16: =IF(COPIA!B12=0,"",COPIA!B12) -> FORNITORI IMMOBILIZZ. IMMATERIALI C/ACCONTI | F16: =IF(COPIA!C12=0,"",COPIA!C12) -> F | G16: =IF(COPIA!D12=0,"",COPIA!D12) -> D | H16: =IF(COPIA!E12=0,"",IF(COPIA!B12="FONDO SVALUTAZIONE CREDITI","RETTIFICA CREDITI",COPIA!E12)) -> CREDITI | I16: =IF(COPIA!F12=0,"",COPIA!F12) -> SP DARE
D17: =IF(COPIA!A13=0,"",COPIA!A13) -> 02.00 | E17: =IF(COPIA!B13=0,"",COPIA!B13) -> IMMOBILIZZAZIONI MATERIALI | F17: =IF(COPIA!C13=0,"",COPIA!C13) | G17: =IF(COPIA!D13=0,"",COPIA!D13) | H17: =IF(COPIA!E13=0,"",IF(COPIA!B13="FONDO SVALUTAZIONE CREDITI","RETTIFICA CREDITI",COPIA!E13)) | I17: =IF(COPIA!F13=0,"",COPIA!F13)
A18: x | B18: x | C18: x | D18: =IF(COPIA!A14=0,"",COPIA!A14) -> 02.01 | E18: =IF(COPIA!B14=0,"",COPIA!B14) -> FABBRICATI | F18: =IF(COPIA!C14=0,"",COPIA!C14) -> E | G18: =IF(COPIA!D14=0,"",COPIA!D14) -> D | H18: =IF(COPIA!E14=0,"",IF(COPIA!B14="FONDO SVALUTAZIONE CREDITI","RETTIFICA CREDITI",COPIA!E14)) -> COSTI PLURIENNALI | I18: =IF(COPIA!F14=0,"",COPIA!F14) -> SP DARE
A19: x | B19: x | C19: x | D19: =IF(COPIA!A15=0,"",COPIA!A15) -> 02.02 | E19: =IF(COPIA!B15=0,"",COPIA!B15) -> IMPIANTI E MACCHINARI | F19: =IF(COPIA!C15=0,"",COPIA!C15) -> E | G19: =IF(COPIA!D15=0,"",COPIA!D15) -> D | H19: =IF(COPIA!E15=0,"",IF(COPIA!B15="FONDO SVALUTAZIONE CREDITI","RETTIFICA CREDITI",COPIA!E15)) -> COSTI PLURIENNALI | I19: =IF(COPIA!F15=0,"",COPIA!F15) -> SP DARE
A20: x | B20: x | C20: x | D20: =IF(COPIA!A16=0,"",COPIA!A16) -> 02.04 | E20: =IF(COPIA!B16=0,"",COPIA!B16) -> ATTREZZATURE COMMERCIALI | F20: =IF(COPIA!C16=0,"",COPIA!C16) -> E | G20: =IF(COPIA!D16=0,"",COPIA!D16) -> D | H20: =IF(COPIA!E16=0,"",IF(COPIA!B16="FONDO SVALUTAZIONE CREDITI","RETTIFICA CREDITI",COPIA!E16)) -> COSTI PLURIENNALI | I20: =IF(COPIA!F16=0,"",COPIA!F16) -> SP DARE
A21: x | B21: x | C21: x | D21: =IF(COPIA!A17=0,"",COPIA!A17) -> 02.05 | E21: =IF(COPIA!B17=0,"",COPIA!B17) -> MACCHINE D'UFFICIO | F21: =IF(COPIA!C17=0,"",COPIA!C17) -> E | G21: =IF(COPIA!D17=0,"",COPIA!D17) -> D | H21: =IF(COPIA!E17=0,"",IF(COPIA!B17="FONDO SVALUTAZIONE CREDITI","RETTIFICA CREDITI",COPIA!E17)) -> COSTI PLURIENNALI | I21: =IF(COPIA!F17=0,"",COPIA!F17) -> SP DARE
A22: x | B22: x | C22: x | D22: =IF(COPIA!A18=0,"",COPIA!A18) -> 02.06 | E22: =IF(COPIA!B18=0,"",COPIA!B18) -> ARREDAMENTO | F22: =IF(COPIA!C18=0,"",COPIA!C18) -> E | G22: =IF(COPIA!D18=0,"",COPIA!D18) -> D | H22: =IF(COPIA!E18=0,"",IF(COPIA!B18="FONDO SVALUTAZIONE CREDITI","RETTIFICA CREDITI",COPIA!E18)) -> COSTI PLURIENNALI | I22: =IF(COPIA!F18=0,"",COPIA!F18) -> SP DARE
A23: x | B23: x | C23: x | D23: =IF(COPIA!A19=0,"",COPIA!A19) -> 02.07 | E23: =IF(COPIA!B19=0,"",COPIA!B19) -> AUTOMEZZI | F23: =IF(COPIA!C19=0,"",COPIA!C19) -> E | G23: =IF(COPIA!D19=0,"",COPIA!D19) -> D | H23: =IF(COPIA!E19=0,"",IF(COPIA!B19="FONDO SVALUTAZIONE CREDITI","RETTIFICA CREDITI",COPIA!E19)) -> COSTI PLURIENNALI | I23: =IF(COPIA!F19=0,"",COPIA!F19) -> SP DARE
A24: x | B24: x | C24: x | D24: =IF(COPIA!A20=0,"",COPIA!A20) -> 02.08 | E24: =IF(COPIA!B20=0,"",COPIA!B20) -> IMBALLAGGI DUREVOLI | F24: =IF(COPIA!C20=0,"",COPIA!C20) -> E | G24: =IF(COPIA!D20=0,"",COPIA!D20) -> D | H24: =IF(COPIA!E20=0,"",IF(COPIA!B20="FONDO SVALUTAZIONE CREDITI","RETTIFICA CREDITI",COPIA!E20)) -> COSTI PLURIENNALI | I24: =IF(COPIA!F20=0,"",COPIA!F20) -> SP DARE
B25: x | C25: x | D25: =IF(COPIA!A21=0,"",COPIA!A21) -> 02.11 | E25: =IF(COPIA!B21=0,"",COPIA!B21) -> FONDO AMMORTAMENTO FABBRICATI | F25: =IF(COPIA!C21=0,"",COPIA!C21) -> E | G25: =IF(COPIA!D21=0,"",COPIA!D21) -> A | H25: =IF(COPIA!E21=0,"",IF(COPIA!B21="FONDO SVALUTAZIONE CREDITI","RETTIFICA CREDITI",COPIA!E21)) -> RETTIFICHE COSTI PLURIENNALI | I25: =IF(COPIA!F21=0,"",COPIA!F21) -> SP AVERE
B26: x | C26: x | D26: =IF(COPIA!A22=0,"",COPIA!A22) -> 02.12 | E26: =IF(COPIA!B22=0,"",COPIA!B22) -> FONDO AMMORT. IMPIANTI E MACCHINARI | F26: =IF(COPIA!C22=0,"",COPIA!C22) -> E | G26: =IF(COPIA!D22=0,"",COPIA!D22) -> A | H26: =IF(COPIA!E22=0,"",IF(COPIA!B22="FONDO SVALUTAZIONE CREDITI","RETTIFICA CREDITI",COPIA!E22)) -> RETTIFICHE COSTI PLURIENNALI | I26: =IF(COPIA!F22=0,"",COPIA!F22) -> SP AVERE
B27: x | C27: x | D27: =IF(COPIA!A23=0,"",COPIA!A23) -> 02.14 | E27: =IF(COPIA!B23=0,"",COPIA!B23) -> FONDO AMMORT. ATTREZZATURE COMMERCIALI | F27: =IF(COPIA!C23=0,"",COPIA!C23) -> E | G27: =IF(COPIA!D23=0,"",COPIA!D23) -> A | H27: =IF(COPIA!E23=0,"",IF(COPIA!B23="FONDO SVALUTAZIONE CREDITI","RETTIFICA CREDITI",COPIA!E23)) -> RETTIFICHE COSTI PLURIENNALI | I27: =IF(COPIA!F23=0,"",COPIA!F23) -> SP AVERE
B28: x | C28: x | D28: =IF(COPIA!A24=0,"",COPIA!A24) -> 02.15 | E28: =IF(COPIA!B24=0,"",COPIA!B24) -> FONDO AMMORT. MACCHINE D'UFFICIO | F28: =IF(COPIA!C24=0,"",COPIA!C24) -> E | G28: =IF(COPIA!D24=0,"",COPIA!D24) -> A | H28: =IF(COPIA!E24=0,"",IF(COPIA!B24="FONDO SVALUTAZIONE CREDITI","RETTIFICA CREDITI",COPIA!E24)) -> RETTIFICHE COSTI PLURIENNALI | I28: =IF(COPIA!F24=0,"",COPIA!F24) -> SP AVERE
B29: x | C29: x | D29: =IF(COPIA!A25=0,"",COPIA!A25) -> 02.16 | E29: =IF(COPIA!B25=0,"",COPIA!B25) -> FONDO AMMORT. ARREDAMENTO | F29: =IF(COPIA!C25=0,"",COPIA!C25) -> E | G29: =IF(COPIA!D25=0,"",COPIA!D25) -> A | H29: =IF(COPIA!E25=0,"",IF(COPIA!B25="FONDO SVALUTAZIONE CREDITI","RETTIFICA CREDITI",COPIA!E25)) -> RETTIFICHE COSTI PLURIENNALI | I29: =IF(COPIA!F25=0,"",COPIA!F25) -> SP AVERE
B30: x | C30: x | D30: =IF(COPIA!A26=0,"",COPIA!A26) -> 02.17 | E30: =IF(COPIA!B26=0,"",COPIA!B26) -> FONDO AMMORT. AUTOMEZZI | F30: =IF(COPIA!C26=0,"",COPIA!C26) -> E | G30: =IF(COPIA!D26=0,"",COPIA!D26) -> A | H30: =IF(COPIA!E26=0,"",IF(COPIA!B26="FONDO SVALUTAZIONE CREDITI","RETTIFICA CREDITI",COPIA!E26)) -> RETTIFICHE COSTI PLURIENNALI | I30: =IF(COPIA!F26=0,"",COPIA!F26) -> SP AVERE
B31: x | C31: x | D31: =IF(COPIA!A27=0,"",COPIA!A27) -> 02.18 | E31: =IF(COPIA!B27=0,"",COPIA!B27) -> FONDO AMMORT. IMBALLAGGI DUREVOLI | F31: =IF(COPIA!C27=0,"",COPIA!C27) -> E | G31: =IF(COPIA!D27=0,"",COPIA!D27) -> A | H31: =IF(COPIA!E27=0,"",IF(COPIA!B27="FONDO SVALUTAZIONE CREDITI","RETTIFICA CREDITI",COPIA!E27)) -> RETTIFICHE COSTI PLURIENNALI | I31: =IF(COPIA!F27=0,"",COPIA!F27) -> SP AVERE
A32: x | B32: x | C32: x | D32: =IF(COPIA!A28=0,"",COPIA!A28) -> 02.30 | E32: =IF(COPIA!B28=0,"",COPIA!B28) -> FORNITORI IMMOBILIZZ. MATERIALI C/ACCONTI | F32: =IF(COPIA!C28=0,"",COPIA!C28) -> F | G32: =IF(COPIA!D28=0,"",COPIA!D28) -> D | H32: =IF(COPIA!E28=0,"",IF(COPIA!B28="FONDO SVALUTAZIONE CREDITI","RETTIFICA CREDITI",COPIA!E28)) -> CREDITI | I32: =IF(COPIA!F28=0,"",COPIA!F28) -> SP DARE
D33: =IF(COPIA!A29=0,"",COPIA!A29) -> 03.00 | E33: =IF(COPIA!B29=0,"",COPIA!B29) -> IMMOBILIZZAZIONI FINANZIARIE | F33: =IF(COPIA!C29=0,"",COPIA!C29) | G33: =IF(COPIA!D29=0,"",COPIA!D29) | H33: =IF(COPIA!E29=0,"",IF(COPIA!B29="FONDO SVALUTAZIONE CREDITI","RETTIFICA CREDITI",COPIA!E29)) | I33: =IF(COPIA!F29=0,"",COPIA!F29)
A34: x | B34: x | C34: x | D34: =IF(COPIA!A30=0,"",COPIA!A30) -> 03.01 | E34: =IF(COPIA!B30=0,"",COPIA!B30) -> MUTUI ATTIVI | F34: =IF(COPIA!C30=0,"",COPIA!C30) -> F | G34: =IF(COPIA!D30=0,"",COPIA!D30) -> D | H34: =IF(COPIA!E30=0,"",IF(COPIA!B30="FONDO SVALUTAZIONE CREDITI","RETTIFICA CREDITI",COPIA!E30)) -> CREDITI | I34: =IF(COPIA!F30=0,"",COPIA!F30) -> SP DARE
D35: =IF(COPIA!A31=0,"",COPIA!A31) -> 04.00 | E35: =IF(COPIA!B31=0,"",COPIA!B31) -> RIMANENZE | F35: =IF(COPIA!C31=0,"",COPIA!C31) | G35: =IF(COPIA!D31=0,"",COPIA!D31) | H35: =IF(COPIA!E31=0,"",IF(COPIA!B31="FONDO SVALUTAZIONE CREDITI","RETTIFICA CREDITI",COPIA!E31)) | I35: =IF(COPIA!F31=0,"",COPIA!F31)
A36: x | B36: x | C36: x | D36: =IF(COPIA!A32=0,"",COPIA!A32) -> 04.01 | E36: =IF(COPIA!B32=0,"",COPIA!B32) -> MATERIE DI CONSUMO | F36: =IF(COPIA!C32=0,"",COPIA!C32) -> E | G36: =IF(COPIA!D32=0,"",COPIA!D32) -> D | H36: =IF(COPIA!E32=0,"",IF(COPIA!B32="FONDO SVALUTAZIONE CREDITI","RETTIFICA CREDITI",COPIA!E32)) -> COSTI SOSPESI | I36: =IF(COPIA!F32=0,"",COPIA!F32) -> SP DARE
A37: x | B37: x | C37: x | D37: =IF(COPIA!A33=0,"",COPIA!A33) -> 04.04 | E37: =IF(COPIA!B33=0,"",COPIA!B33) -> MERCI | F37: =IF(COPIA!C33=0,"",COPIA!C33) -> E | G37: =IF(COPIA!D33=0,"",COPIA!D33) -> D | H37: =IF(COPIA!E33=0,"",IF(COPIA!B33="FONDO SVALUTAZIONE CREDITI","RETTIFICA CREDITI",COPIA!E33)) -> COSTI SOSPESI | I37: =IF(COPIA!F33=0,"",COPIA!F33) -> SP DARE
A38: x | B38: x | C38: x | D38: =IF(COPIA!A34=0,"",COPIA!A34) -> 04.10 | E38: =IF(COPIA!B34=0,"",COPIA!B34) -> FORNITORI C/ACCONTI | F38: =IF(COPIA!C34=0,"",COPIA!C34) -> F | G38: =IF(COPIA!D34=0,"",COPIA!D34) -> D | H38: =IF(COPIA!E34=0,"",IF(COPIA!B34="FONDO SVALUTAZIONE CREDITI","RETTIFICA CREDITI",COPIA!E34)) -> CREDITI | I38: =IF(COPIA!F34=0,"",COPIA!F34) -> SP DARE
D39: =IF(COPIA!A35=0,"",COPIA!A35) -> 05.00 | E39: =IF(COPIA!B35=0,"",COPIA!B35) -> CREDITI COMMERCIALI | F39: =IF(COPIA!C35=0,"",COPIA!C35) | G39: =IF(COPIA!D35=0,"",COPIA!D35) | H39: =IF(COPIA!E35=0,"",IF(COPIA!B35="FONDO SVALUTAZIONE CREDITI","RETTIFICA CREDITI",COPIA!E35)) | I39: =IF(COPIA!F35=0,"",COPIA!F35)
A40: x | B40: x | C40: x | D40: =IF(COPIA!A36=0,"",COPIA!A36) -> 05.01 | E40: =IF(COPIA!B36=0,"",COPIA!B36) -> CREDITI V/CLIENTI | F40: =IF(COPIA!C36=0,"",COPIA!C36) -> F | G40: =IF(COPIA!D36=0,"",COPIA!D36) -> D | H40: =IF(COPIA!E36=0,"",IF(COPIA!B36="FONDO SVALUTAZIONE CREDITI","RETTIFICA CREDITI",COPIA!E36)) -> CREDITI | I40: =IF(COPIA!F36=0,"",COPIA!F36) -> SP DARE
C41: x | D41: =IF(COPIA!A37=0,"",COPIA!A37) -> 05.02 | E41: =IF(COPIA!B37=0,"",COPIA!B37) -> FATTURE DA EMETTERE | F41: =IF(COPIA!C37=0,"",COPIA!C37) -> F | G41: =IF(COPIA!D37=0,"",COPIA!D37) -> D | H41: =IF(COPIA!E37=0,"",IF(COPIA!B37="FONDO SVALUTAZIONE CREDITI","RETTIFICA CREDITI",COPIA!E37)) -> CREDITI | I41: =IF(COPIA!F37=0,"",COPIA!F37) -> SP DARE
B42: x | C42: x | D42: =IF(COPIA!A38=0,"",COPIA!A38) -> 05.03 | E42: =IF(COPIA!B38=0,"",COPIA!B38) -> CREDITI COMMERCIALI DIVERSI | F42: =IF(COPIA!C38=0,"",COPIA!C38) -> F | G42: =IF(COPIA!D38=0,"",COPIA!D38) -> D | H42: =IF(COPIA!E38=0,"",IF(COPIA!B38="FONDO SVALUTAZIONE CREDITI","RETTIFICA CREDITI",COPIA!E38)) -> CREDITI | I42: =IF(COPIA!F38=0,"",COPIA!F38) -> SP DARE
A43: x | B43: x | C43: x | D43: =IF(COPIA!A39=0,"",COPIA!A39) -> 05.05 | E43: =IF(COPIA!B39=0,"",COPIA!B39) -> CLIENTI C/COSTI ANTICIPATI | F43: =IF(COPIA!C39=0,"",COPIA!C39) -> F | G43: =IF(COPIA!D39=0,"",COPIA!D39) -> D | H43: =IF(COPIA!E39=0,"",IF(COPIA!B39="FONDO SVALUTAZIONE CREDITI","RETTIFICA CREDITI",COPIA!E39)) -> CREDITI | I43: =IF(COPIA!F39=0,"",COPIA!F39) -> SP DARE
A44: x | B44: x | C44: x | D44: =IF(COPIA!A40=0,"",COPIA!A40) -> 05.06 | E44: =IF(COPIA!B40=0,"",COPIA!B40) -> CAMBIALI ATTIVE | F44: =IF(COPIA!C40=0,"",COPIA!C40) -> F | G44: =IF(COPIA!D40=0,"",COPIA!D40) -> D | H44: =IF(COPIA!E40=0,"",IF(COPIA!B40="FONDO SVALUTAZIONE CREDITI","RETTIFICA CREDITI",COPIA!E40)) -> CREDITI | I44: =IF(COPIA!F40=0,"",COPIA!F40) -> SP DARE
B45: x | C45: x | D45: =IF(COPIA!A41=0,"",COPIA!A41) -> 05.07 | E45: =IF(COPIA!B41=0,"",COPIA!B41) -> CAMBIALI ALLO SCONTO | F45: =IF(COPIA!C41=0,"",COPIA!C41) -> F | G45: =IF(COPIA!D41=0,"",COPIA!D41) -> D | H45: =IF(COPIA!E41=0,"",IF(COPIA!B41="FONDO SVALUTAZIONE CREDITI","RETTIFICA CREDITI",COPIA!E41)) -> CREDITI | I45: =IF(COPIA!F41=0,"",COPIA!F41) -> SP DARE
A46: x | B46: x | C46: x | D46: =IF(COPIA!A42=0,"",COPIA!A42) -> 05.08 | E46: =IF(COPIA!B42=0,"",COPIA!B42) -> CAMBIALI ALL'INCASSO | F46: =IF(COPIA!C42=0,"",COPIA!C42) -> F | G46: =IF(COPIA!D42=0,"",COPIA!D42) -> D | H46: =IF(COPIA!E42=0,"",IF(COPIA!B42="FONDO SVALUTAZIONE CREDITI","RETTIFICA CREDITI",COPIA!E42)) -> CREDITI | I46: =IF(COPIA!F42=0,"",COPIA!F42) -> SP DARE
C47: x | D47: =IF(COPIA!A43=0,"",COPIA!A43) -> 05.09 | E47: =IF(COPIA!B43=0,"",COPIA!B43) -> CREDITI DA LIQUIDARE | F47: =IF(COPIA!C43=0,"",COPIA!C43) -> F | G47: =IF(COPIA!D43=0,"",COPIA!D43) -> D | H47: =IF(COPIA!E43=0,"",IF(COPIA!B43="FONDO SVALUTAZIONE CREDITI","RETTIFICA CREDITI",COPIA!E43)) -> CREDITI | I47: =IF(COPIA!F43=0,"",COPIA!F43) -> SP DARE
A48: x | B48: x | C48: x | D48: =IF(COPIA!A44=0,"",COPIA!A44) -> 05.10 | E48: =IF(COPIA!B44=0,"",COPIA!B44) -> CREDITI INSOLUTI | F48: =IF(COPIA!C44=0,"",COPIA!C44) -> F | G48: =IF(COPIA!D44=0,"",COPIA!D44) -> D | H48: =IF(COPIA!E44=0,"",IF(COPIA!B44="FONDO SVALUTAZIONE CREDITI","RETTIFICA CREDITI",COPIA!E44)) -> CREDITI | I48: =IF(COPIA!F44=0,"",COPIA!F44) -> SP DARE
A49: x | B49: x | C49: x | D49: =IF(COPIA!A45=0,"",COPIA!A45) -> 05.11 | E49: =IF(COPIA!B45=0,"",COPIA!B45) -> CAMBIALI INSOLUTE | F49: =IF(COPIA!C45=0,"",COPIA!C45) -> F | G49: =IF(COPIA!D45=0,"",COPIA!D45) -> D | H49: =IF(COPIA!E45=0,"",IF(COPIA!B45="FONDO SVALUTAZIONE CREDITI","RETTIFICA CREDITI",COPIA!E45)) -> CREDITI | I49: =IF(COPIA!F45=0,"",COPIA!F45) -> SP DARE
A50: x | B50: x | C50: x | D50: =IF(COPIA!A46=0,"",COPIA!A46) -> 05.15 | E50: =IF(COPIA!B46=0,"",COPIA!B46) -> CREDITI PER ACCONTI DA CLIENTI | F50: =IF(COPIA!C46=0,"",COPIA!C46) -> F | G50: =IF(COPIA!D46=0,"",COPIA!D46) -> D | H50: =IF(COPIA!E46=0,"",IF(COPIA!B46="FONDO SVALUTAZIONE CREDITI","RETTIFICA CREDITI",COPIA!E46)) -> CREDITI | I50: =IF(COPIA!F46=0,"",COPIA!F46) -> SP DARE
C51: x | D51: =IF(COPIA!A47=0,"",COPIA!A47) -> 05.20 | E51: =IF(COPIA!B47=0,"",COPIA!B47) -> FONDO SVALUTAZIONE CREDITI | F51: =IF(COPIA!C47=0,"",COPIA!C47) -> F | G51: =IF(COPIA!D47=0,"",COPIA!D47) -> A | H51: =IF(COPIA!E47=0,"",IF(COPIA!B47="FONDO SVALUTAZIONE CREDITI","RETTIFICA CREDITI",COPIA!E47)) -> RETTIFICA CREDITI | I51: =IF(COPIA!F47=0,"",COPIA!F47) -> SP AVERE
D52: =IF(COPIA!A48=0,"",COPIA!A48) -> 06.00 | E52: =IF(COPIA!B48=0,"",COPIA!B48) -> CREDITI DIVERSI | F52: =IF(COPIA!C48=0,"",COPIA!C48) | G52: =IF(COPIA!D48=0,"",COPIA!D48) | H52: =IF(COPIA!E48=0,"",IF(COPIA!B48="FONDO SVALUTAZIONE CREDITI","RETTIFICA CREDITI",COPIA!E48)) | I52: =IF(COPIA!F48=0,"",COPIA!F48)
A53: x | B53: x | C53: x | D53: =IF(COPIA!A49=0,"",COPIA!A49) -> 06.01 | E53: =IF(COPIA!B49=0,"",COPIA!B49) -> IVA NS/CREDITO | F53: =IF(COPIA!C49=0,"",COPIA!C49) -> F | G53: =IF(COPIA!D49=0,"",COPIA!D49) -> D | H53: =IF(COPIA!E49=0,"",IF(COPIA!B49="FONDO SVALUTAZIONE CREDITI","RETTIFICA CREDITI",COPIA!E49)) -> CREDITI | I53: =IF(COPIA!F49=0,"",COPIA!F49) -> SP DARE
B54: x | C54: x | D54: =IF(COPIA!A50=0,"",COPIA!A50) -> 06.02 | E54: =IF(COPIA!B50=0,"",COPIA!B50) -> IVA C/ACCONTO | F54: =IF(COPIA!C50=0,"",COPIA!C50) -> F | G54: =IF(COPIA!D50=0,"",COPIA!D50) -> D | H54: =IF(COPIA!E50=0,"",IF(COPIA!B50="FONDO SVALUTAZIONE CREDITI","RETTIFICA CREDITI",COPIA!E50)) -> CREDITI | I54: =IF(COPIA!F50=0,"",COPIA!F50) -> SP DARE
C55: x | D55: =IF(COPIA!A51=0,"",COPIA!A51) -> 06.03 | E55: =IF(COPIA!B51=0,"",COPIA!B51) -> CREDITI PER IVA | F55: =IF(COPIA!C51=0,"",COPIA!C51) -> F | G55: =IF(COPIA!D51=0,"",COPIA!D51) -> D | H55: =IF(COPIA!E51=0,"",IF(COPIA!B51="FONDO SVALUTAZIONE CREDITI","RETTIFICA CREDITI",COPIA!E51)) -> CREDITI | I55: =IF(COPIA!F51=0,"",COPIA!F51) -> SP DARE
C56: x | D56: =IF(COPIA!A52=0,"",COPIA!A52) -> 06.04 | E56: =IF(COPIA!B52=0,"",COPIA!B52) -> CREDITI V/ISTITUTI PREVIDENZIALI | F56: =IF(COPIA!C52=0,"",COPIA!C52) -> F | G56: =IF(COPIA!D52=0,"",COPIA!D52) -> D | H56: =IF(COPIA!E52=0,"",IF(COPIA!B52="FONDO SVALUTAZIONE CREDITI","RETTIFICA CREDITI",COPIA!E52)) -> CREDITI | I56: =IF(COPIA!F52=0,"",COPIA!F52) -> SP DARE
A57: x | B57: x | C57: x | D57: =IF(COPIA!A53=0,"",COPIA!A53) -> 06.05 | E57: =IF(COPIA!B53=0,"",COPIA!B53) -> CREDITI PER CAUZIONI | F57: =IF(COPIA!C53=0,"",COPIA!C53) -> F | G57: =IF(COPIA!D53=0,"",COPIA!D53) -> D | H57: =IF(COPIA!E53=0,"",IF(COPIA!B53="FONDO SVALUTAZIONE CREDITI","RETTIFICA CREDITI",COPIA!E53)) -> CREDITI | I57: =IF(COPIA!F53=0,"",COPIA!F53) -> SP DARE
A58: x | B58: x | C58: x | D58: =IF(COPIA!A54=0,"",COPIA!A54) -> 06.10 | E58: =IF(COPIA!B54=0,"",COPIA!B54) -> CREDITI DIVERSI | F58: =IF(COPIA!C54=0,"",COPIA!C54) -> F | G58: =IF(COPIA!D54=0,"",COPIA!D54) -> D | H58: =IF(COPIA!E54=0,"",IF(COPIA!B54="FONDO SVALUTAZIONE CREDITI","RETTIFICA CREDITI",COPIA!E54)) -> CREDITI | I58: =IF(COPIA!F54=0,"",COPIA!F54) -> SP DARE
B59: x | C59: x | D59: =IF(COPIA!A55=0,"",COPIA!A55) -> 06.20 | E59: =IF(COPIA!B55=0,"",COPIA!B55) -> PERSONALE C/ACCONTI | F59: =IF(COPIA!C55=0,"",COPIA!C55) -> F | G59: =IF(COPIA!D55=0,"",COPIA!D55) -> D | H59: =IF(COPIA!E55=0,"",IF(COPIA!B55="FONDO SVALUTAZIONE CREDITI","RETTIFICA CREDITI",COPIA!E55)) -> CREDITI | I59: =IF(COPIA!F55=0,"",COPIA!F55) -> SP DARE
D60: =IF(COPIA!A56=0,"",COPIA!A56) -> 08.00 | E60: =IF(COPIA!B56=0,"",COPIA!B56) -> DISPONIBILITÀ LIQUIDE | F60: =IF(COPIA!C56=0,"",COPIA!C56) | G60: =IF(COPIA!D56=0,"",COPIA!D56) | H60: =IF(COPIA!E56=0,"",IF(COPIA!B56="FONDO SVALUTAZIONE CREDITI","RETTIFICA CREDITI",COPIA!E56)) | I60: =IF(COPIA!F56=0,"",COPIA!F56)
C61: x | D61: =IF(COPIA!A57=0,"",COPIA!A57) -> 08.01 | E61: =IF(COPIA!B57=0,"",COPIA!B57) -> BANCHE C/C ATTIVI | F61: =IF(COPIA!C57=0,"",COPIA!C57) -> F | G61: =IF(COPIA!D57=0,"",COPIA!D57) -> D | H61: =IF(COPIA!E57=0,"",IF(COPIA!B57="FONDO SVALUTAZIONE CREDITI","RETTIFICA CREDITI",COPIA!E57)) -> DISPONIBILITÀ LIQUIDE | I61: =IF(COPIA!F57=0,"",COPIA!F57) -> SP DARE
A62: x | B62: x | C62: x | D62: =IF(COPIA!A58=0,"",COPIA!A58) -> 08.02 | E62: =IF(COPIA!B58=0,"",COPIA!B58) -> C/C POSTALI | F62: =IF(COPIA!C58=0,"",COPIA!C58) -> F | G62: =IF(COPIA!D58=0,"",COPIA!D58) -> D | H62: =IF(COPIA!E58=0,"",IF(COPIA!B58="FONDO SVALUTAZIONE CREDITI","RETTIFICA CREDITI",COPIA!E58)) -> DISPONIBILITÀ LIQUIDE | I62: =IF(COPIA!F58=0,"",COPIA!F58) -> SP DARE
A63: x | B63: x | C63: x | D63: =IF(COPIA!A59=0,"",COPIA!A59) -> 08.10 | E63: =IF(COPIA!B59=0,"",COPIA!B59) -> ASSEGNI | F63: =IF(COPIA!C59=0,"",COPIA!C59) -> F | G63: =IF(COPIA!D59=0,"",COPIA!D59) -> D | H63: =IF(COPIA!E59=0,"",IF(COPIA!B59="FONDO SVALUTAZIONE CREDITI","RETTIFICA CREDITI",COPIA!E59)) -> DISPONIBILITÀ LIQUIDE | I63: =IF(COPIA!F59=0,"",COPIA!F59) -> SP DARE
A64: x | B64: x | C64: x | D64: =IF(COPIA!A60=0,"",COPIA!A60) -> 08.20 | E64: =IF(COPIA!B60=0,"",COPIA!B60) -> DENARO IN CASSA | F64: =IF(COPIA!C60=0,"",COPIA!C60) -> F | G64: =IF(COPIA!D60=0,"",COPIA!D60) -> D | H64: =IF(COPIA!E60=0,"",IF(COPIA!B60="FONDO SVALUTAZIONE CREDITI","RETTIFICA CREDITI",COPIA!E60)) -> DISPONIBILITÀ LIQUIDE | I64: =IF(COPIA!F60=0,"",COPIA!F60) -> SP DARE
B65: x | C65: x | D65: =IF(COPIA!A61=0,"",COPIA!A61) -> 08.21 | E65: =IF(COPIA!B61=0,"",COPIA!B61) -> VALORI BOLLATI | F65: =IF(COPIA!C61=0,"",COPIA!C61) -> F | G65: =IF(COPIA!D61=0,"",COPIA!D61) -> D | H65: =IF(COPIA!E61=0,"",IF(COPIA!B61="FONDO SVALUTAZIONE CREDITI","RETTIFICA CREDITI",COPIA!E61)) -> DISPONIBILITÀ LIQUIDE | I65: =IF(COPIA!F61=0,"",COPIA!F61) -> SP DARE
D66: =IF(COPIA!A62=0,"",COPIA!A62) -> 09.00 | E66: =IF(COPIA!B62=0,"",COPIA!B62) -> RATEI E RISCONTI ATTIVI | F66: =IF(COPIA!C62=0,"",COPIA!C62) | G66: =IF(COPIA!D62=0,"",COPIA!D62) | H66: =IF(COPIA!E62=0,"",IF(COPIA!B62="FONDO SVALUTAZIONE CREDITI","RETTIFICA CREDITI",COPIA!E62)) | I66: =IF(COPIA!F62=0,"",COPIA!F62)
C67: x | D67: =IF(COPIA!A63=0,"",COPIA!A63) -> 09.01 | E67: =IF(COPIA!B63=0,"",COPIA!B63) -> RATEI ATTIVI | F67: =IF(COPIA!C63=0,"",COPIA!C63) -> F | G67: =IF(COPIA!D63=0,"",COPIA!D63) -> D | H67: =IF(COPIA!E63=0,"",IF(COPIA!B63="FONDO SVALUTAZIONE CREDITI","RETTIFICA CREDITI",COPIA!E63)) -> RATEI, FONDI RISCHI E ONERI | I67: =IF(COPIA!F63=0,"",COPIA!F63) -> SP DARE
C68: x | D68: =IF(COPIA!A64=0,"",COPIA!A64) -> 09.02 | E68: =IF(COPIA!B64=0,"",COPIA!B64) -> RISCONTI ATTIVI | F68: =IF(COPIA!C64=0,"",COPIA!C64) -> E | G68: =IF(COPIA!D64=0,"",COPIA!D64) -> D | H68: =IF(COPIA!E64=0,"",IF(COPIA!B64="FONDO SVALUTAZIONE CREDITI","RETTIFICA CREDITI",COPIA!E64)) -> COSTI SOSPESI | I68: =IF(COPIA!F64=0,"",COPIA!F64) -> SP DARE
D69: =IF(COPIA!A65=0,"",COPIA!A65) -> 10.00 | E69: =IF(COPIA!B65=0,"",COPIA!B65) -> PATRIMONIO NETTO | F69: =IF(COPIA!C65=0,"",COPIA!C65) | G69: =IF(COPIA!D65=0,"",COPIA!D65) | H69: =IF(COPIA!E65=0,"",IF(COPIA!B65="FONDO SVALUTAZIONE CREDITI","RETTIFICA CREDITI",COPIA!E65)) | I69: =IF(COPIA!F65=0,"",COPIA!F65)
A70: x | B70: x | C70: x | D70: =IF(COPIA!A66=0,"",COPIA!A66) -> 10.01 | E70: =IF(COPIA!B66=0,"",COPIA!B66) -> PATRIMONIO NETTO | F70: =IF(COPIA!C66=0,"",COPIA!C66) -> E | G70: =IF(COPIA!D66=0,"",COPIA!D66) -> A | H70: =IF(COPIA!E66=0,"",IF(COPIA!B66="FONDO SVALUTAZIONE CREDITI","RETTIFICA CREDITI",COPIA!E66)) -> PATRIMONIO NETTO | I70: =IF(COPIA!F66=0,"",COPIA!F66) -> SP AVERE
A71: x | B71: x | C71: x | D71: =IF(COPIA!A67=0,"",COPIA!A67) -> 10.02 | E71: =IF(COPIA!B67=0,"",COPIA!B67) -> PRELEVAMENTI EXTRAGESTIONE | F71: =IF(COPIA!C67=0,"",COPIA!C67) -> E | G71: =IF(COPIA!D67=0,"",COPIA!D67) -> D | H71: =IF(COPIA!E67=0,"",IF(COPIA!B67="FONDO SVALUTAZIONE CREDITI","RETTIFICA CREDITI",COPIA!E67)) -> PATRIMONIO NETTO | I71: =IF(COPIA!F67=0,"",COPIA!F67) -> SP DARE
B72: x | C72: x | D72: =IF(COPIA!A68=0,"",COPIA!A68) -> 10.03 | E72: =IF(COPIA!B68=0,"",COPIA!B68) -> TITOLARE C/RITENUTE SUBITE | F72: =IF(COPIA!C68=0,"",COPIA!C68) -> E | G72: =IF(COPIA!D68=0,"",COPIA!D68) -> D | H72: =IF(COPIA!E68=0,"",IF(COPIA!B68="FONDO SVALUTAZIONE CREDITI","RETTIFICA CREDITI",COPIA!E68)) -> PATRIMONIO NETTO | I72: =IF(COPIA!F68=0,"",COPIA!F68) -> SP DARE
D73: =IF(COPIA!A69=0,"",COPIA!A69) -> 10.04 | E73: =IF(COPIA!B69=0,"",COPIA!B69) -> UTILE D'ESERCIZIO | F73: =IF(COPIA!C69=0,"",COPIA!C69) -> E | G73: =IF(COPIA!D69=0,"",COPIA!D69) -> A | H73: =IF(COPIA!E69=0,"",IF(COPIA!B69="FONDO SVALUTAZIONE CREDITI","RETTIFICA CREDITI",COPIA!E69)) -> PATRIMONIO NETTO | I73: =IF(COPIA!F69=0,"",COPIA!F69) -> SP AVERE - SE DARE
D74: =IF(COPIA!A70=0,"",COPIA!A70) -> 10.05 | E74: =IF(COPIA!B70=0,"",COPIA!B70) -> PERDITA D'ESERCIZIO | F74: =IF(COPIA!C70=0,"",COPIA!C70) -> E | G74: =IF(COPIA!D70=0,"",COPIA!D70) -> D | H74: =IF(COPIA!E70=0,"",IF(COPIA!B70="FONDO SVALUTAZIONE CREDITI","RETTIFICA CREDITI",COPIA!E70)) -> PATRIMONIO NETTO | I74: =IF(COPIA!F70=0,"",COPIA!F70) -> SP DARE - SE AVERE
D75: =IF(COPIA!A71=0,"",COPIA!A71) -> 11.00 | E75: =IF(COPIA!B71=0,"",COPIA!B71) -> FONDI PER RISCHI E ONERI | F75: =IF(COPIA!C71=0,"",COPIA!C71) | G75: =IF(COPIA!D71=0,"",COPIA!D71) | H75: =IF(COPIA!E71=0,"",IF(COPIA!B71="FONDO SVALUTAZIONE CREDITI","RETTIFICA CREDITI",COPIA!E71)) | I75: =IF(COPIA!F71=0,"",COPIA!F71)
C76: x | D76: =IF(COPIA!A72=0,"",COPIA!A72) -> 11.01 | E76: =IF(COPIA!B72=0,"",COPIA!B72) -> FONDO RESPONSABILITÀ CIVILE | F76: =IF(COPIA!C72=0,"",COPIA!C72) -> F | G76: =IF(COPIA!D72=0,"",COPIA!D72) -> A | H76: =IF(COPIA!E72=0,"",IF(COPIA!B72="FONDO SVALUTAZIONE CREDITI","RETTIFICA CREDITI",COPIA!E72)) -> RATEI, FONDI RISCHI E ONERI | I76: =IF(COPIA!F72=0,"",COPIA!F72) -> SP AVERE
C77: x | D77: =IF(COPIA!A73=0,"",COPIA!A73) -> 11.10 | E77: =IF(COPIA!B73=0,"",COPIA!B73) -> FONDO MANUTENZIONI PROGRAMMATE | F77: =IF(COPIA!C73=0,"",COPIA!C73) -> F | G77: =IF(COPIA!D73=0,"",COPIA!D73) -> A | H77: =IF(COPIA!E73=0,"",IF(COPIA!B73="FONDO SVALUTAZIONE CREDITI","RETTIFICA CREDITI",COPIA!E73)) -> RATEI, FONDI RISCHI E ONERI | I77: =IF(COPIA!F73=0,"",COPIA!F73) -> SP AVERE
D78: =IF(COPIA!A74=0,"",COPIA!A74) -> 12.00 | E78: =IF(COPIA!B74=0,"",COPIA!B74) -> TRATTAMENTO FINE RAPPORTO | F78: =IF(COPIA!C74=0,"",COPIA!C74) | G78: =IF(COPIA!D74=0,"",COPIA!D74) | H78: =IF(COPIA!E74=0,"",IF(COPIA!B74="FONDO SVALUTAZIONE CREDITI","RETTIFICA CREDITI",COPIA!E74)) | I78: =IF(COPIA!F74=0,"",COPIA!F74)
C79: x | D79: =IF(COPIA!A75=0,"",COPIA!A75) -> 12.01 | E79: =IF(COPIA!B75=0,"",COPIA!B75) -> DEBITI PER TFR | F79: =IF(COPIA!C75=0,"",COPIA!C75) -> F | G79: =IF(COPIA!D75=0,"",COPIA!D75) -> A | H79: =IF(COPIA!E75=0,"",IF(COPIA!B75="FONDO SVALUTAZIONE CREDITI","RETTIFICA CREDITI",COPIA!E75)) -> DEBITI | I79: =IF(COPIA!F75=0,"",COPIA!F75) -> SP AVERE
D80: =IF(COPIA!A76=0,"",COPIA!A76) -> 13.00 | E80: =IF(COPIA!B76=0,"",COPIA!B76) -> DEBITI FINANZIARI | F80: =IF(COPIA!C76=0,"",COPIA!C76) | G80: =IF(COPIA!D76=0,"",COPIA!D76) | H80: =IF(COPIA!E76=0,"",IF(COPIA!B76="FONDO SVALUTAZIONE CREDITI","RETTIFICA CREDITI",COPIA!E76)) | I80: =IF(COPIA!F76=0,"",COPIA!F76)
A81: x | B81: x | C81: x | D81: =IF(COPIA!A77=0,"",COPIA!A77) -> 13.01 | E81: =IF(COPIA!B77=0,"",COPIA!B77) -> MUTUI PASSIVI | F81: =IF(COPIA!C77=0,"",COPIA!C77) -> F | G81: =IF(COPIA!D77=0,"",COPIA!D77) -> A | H81: =IF(COPIA!E77=0,"",IF(COPIA!B77="FONDO SVALUTAZIONE CREDITI","RETTIFICA CREDITI",COPIA!E77)) -> DEBITI | I81: =IF(COPIA!F77=0,"",COPIA!F77) -> SP AVERE
B82: x | C82: x | D82: =IF(COPIA!A78=0,"",COPIA!A78) -> 13.10 | E82: =IF(COPIA!B78=0,"",COPIA!B78) -> BANCHE C/RI.BA. SBF | F82: =IF(COPIA!C78=0,"",COPIA!C78) -> F | G82: =IF(COPIA!D78=0,"",COPIA!D78) -> A | H82: =IF(COPIA!E78=0,"",IF(COPIA!B78="FONDO SVALUTAZIONE CREDITI","RETTIFICA CREDITI",COPIA!E78)) -> DEBITI | I82: =IF(COPIA!F78=0,"",COPIA!F78) -> SP AVERE
B83: x | C83: x | D83: =IF(COPIA!A79=0,"",COPIA!A79) -> 13.11 | E83: =IF(COPIA!B79=0,"",COPIA!B79) -> BANCHE C/ANTICIPI SU FATTURE | F83: =IF(COPIA!C79=0,"",COPIA!C79) -> F | G83: =IF(COPIA!D79=0,"",COPIA!D79) -> A | H83: =IF(COPIA!E79=0,"",IF(COPIA!B79="FONDO SVALUTAZIONE CREDITI","RETTIFICA CREDITI",COPIA!E79)) -> DEBITI | I83: =IF(COPIA!F79=0,"",COPIA!F79) -> SP AVERE
B84: x | C84: x | D84: =IF(COPIA!A80=0,"",COPIA!A80) -> 13.15 | E84: =IF(COPIA!B80=0,"",COPIA!B80) -> SOVVENZIONI BANCARIE | F84: =IF(COPIA!C80=0,"",COPIA!C80) -> F | G84: =IF(COPIA!D80=0,"",COPIA!D80) -> A | H84: =IF(COPIA!E80=0,"",IF(COPIA!B80="FONDO SVALUTAZIONE CREDITI","RETTIFICA CREDITI",COPIA!E80)) -> DEBITI | I84: =IF(COPIA!F80=0,"",COPIA!F80) -> SP AVERE
C85: x | D85: =IF(COPIA!A81=0,"",COPIA!A81) -> 13.20 | E85: =IF(COPIA!B81=0,"",COPIA!B81) -> BANCHE C/C PASSIVI | F85: =IF(COPIA!C81=0,"",COPIA!C81) -> F | G85: =IF(COPIA!D81=0,"",COPIA!D81) -> A | H85: =IF(COPIA!E81=0,"",IF(COPIA!B81="FONDO SVALUTAZIONE CREDITI","RETTIFICA CREDITI",COPIA!E81)) -> DEBITI | I85: =IF(COPIA!F81=0,"",COPIA!F81) -> SP AVERE
C86: x | D86: =IF(COPIA!A82=0,"",COPIA!A82) -> 13.21 | E86: =IF(COPIA!B82=0,"",COPIA!B82) -> BANCHE C/INTERESSI MATURATI | F86: =IF(COPIA!C82=0,"",COPIA!C82) -> F | G86: =IF(COPIA!D82=0,"",COPIA!D82) -> A | H86: =IF(COPIA!E82=0,"",IF(COPIA!B82="FONDO SVALUTAZIONE CREDITI","RETTIFICA CREDITI",COPIA!E82)) -> DEBITI | I86: =IF(COPIA!F82=0,"",COPIA!F82) -> SP AVERE
C87: x | D87: =IF(COPIA!A83=0,"",COPIA!A83) -> 13.30 | E87: =IF(COPIA!B83=0,"",COPIA!B83) -> DEBITI V/ALTRI FINANZIATORI | F87: =IF(COPIA!C83=0,"",COPIA!C83) -> F | G87: =IF(COPIA!D83=0,"",COPIA!D83) -> A | H87: =IF(COPIA!E83=0,"",IF(COPIA!B83="FONDO SVALUTAZIONE CREDITI","RETTIFICA CREDITI",COPIA!E83)) -> DEBITI | I87: =IF(COPIA!F83=0,"",COPIA!F83) -> SP AVERE
D88: =IF(COPIA!A84=0,"",COPIA!A84) -> 14.00 | E88: =IF(COPIA!B84=0,"",COPIA!B84) -> DEBITI COMMERCIALI | F88: =IF(COPIA!C84=0,"",COPIA!C84) | G88: =IF(COPIA!D84=0,"",COPIA!D84) | H88: =IF(COPIA!E84=0,"",IF(COPIA!B84="FONDO SVALUTAZIONE CREDITI","RETTIFICA CREDITI",COPIA!E84)) | I88: =IF(COPIA!F84=0,"",COPIA!F84)
A89: x | B89: x | C89: x | D89: =IF(COPIA!A85=0,"",COPIA!A85) -> 14.01 | E89: =IF(COPIA!B85=0,"",COPIA!B85) -> DEBITI V/FORNITORI | F89: =IF(COPIA!C85=0,"",COPIA!C85) -> F | G89: =IF(COPIA!D85=0,"",COPIA!D85) -> A | H89: =IF(COPIA!E85=0,"",IF(COPIA!B85="FONDO SVALUTAZIONE CREDITI","RETTIFICA CREDITI",COPIA!E85)) -> DEBITI | I89: =IF(COPIA!F85=0,"",COPIA!F85) -> SP AVERE
C90: x | D90: =IF(COPIA!A86=0,"",COPIA!A86) -> 14.02 | E90: =IF(COPIA!B86=0,"",COPIA!B86) -> FATTURE DA RICEVERE | F90: =IF(COPIA!C86=0,"",COPIA!C86) -> F | G90: =IF(COPIA!D86=0,"",COPIA!D86) -> A | H90: =IF(COPIA!E86=0,"",IF(COPIA!B86="FONDO SVALUTAZIONE CREDITI","RETTIFICA CREDITI",COPIA!E86)) -> DEBITI | I90: =IF(COPIA!F86=0,"",COPIA!F86) -> SP AVERE
A91: x | B91: x | C91: x | D91: =IF(COPIA!A87=0,"",COPIA!A87) -> 14.03 | E91: =IF(COPIA!B87=0,"",COPIA!B87) -> DEBITI COMMERCIALI DIVERSI | F91: =IF(COPIA!C87=0,"",COPIA!C87) -> F | G91: =IF(COPIA!D87=0,"",COPIA!D87) -> A | H91: =IF(COPIA!E87=0,"",IF(COPIA!B87="FONDO SVALUTAZIONE CREDITI","RETTIFICA CREDITI",COPIA!E87)) -> DEBITI | I91: =IF(COPIA!F87=0,"",COPIA!F87) -> SP AVERE
A92: x | B92: x | C92: x | D92: =IF(COPIA!A88=0,"",COPIA!A88) -> 14.06 | E92: =IF(COPIA!B88=0,"",COPIA!B88) -> CAMBIALI PASSIVE | F92: =IF(COPIA!C88=0,"",COPIA!C88) -> F | G92: =IF(COPIA!D88=0,"",COPIA!D88) -> A | H92: =IF(COPIA!E88=0,"",IF(COPIA!B88="FONDO SVALUTAZIONE CREDITI","RETTIFICA CREDITI",COPIA!E88)) -> DEBITI | I92: =IF(COPIA!F88=0,"",COPIA!F88) -> SP AVERE
C93: x | D93: =IF(COPIA!A89=0,"",COPIA!A89) -> 14.09 | E93: =IF(COPIA!B89=0,"",COPIA!B89) -> DEBITI DA LIQUIDARE | F93: =IF(COPIA!C89=0,"",COPIA!C89) -> F | G93: =IF(COPIA!D89=0,"",COPIA!D89) -> A | H93: =IF(COPIA!E89=0,"",IF(COPIA!B89="FONDO SVALUTAZIONE CREDITI","RETTIFICA CREDITI",COPIA!E89)) -> DEBITI | I93: =IF(COPIA!F89=0,"",COPIA!F89) -> SP AVERE
A94: x | B94: x | C94: x | D94: =IF(COPIA!A90=0,"",COPIA!A90) -> 14.15 | E94: =IF(COPIA!B90=0,"",COPIA!B90) -> DEBITI PER ACCONTI A FORNITORI | F94: =IF(COPIA!C90=0,"",COPIA!C90) -> F | G94: =IF(COPIA!D90=0,"",COPIA!D90) -> A | H94: =IF(COPIA!E90=0,"",IF(COPIA!B90="FONDO SVALUTAZIONE CREDITI","RETTIFICA CREDITI",COPIA!E90)) -> DEBITI | I94: =IF(COPIA!F90=0,"",COPIA!F90) -> SP AVERE
A95: x | B95: x | C95: x | D95: =IF(COPIA!A91=0,"",COPIA!A91) -> 14.20 | E95: =IF(COPIA!B91=0,"",COPIA!B91) -> CLIENTI C/ACCONTI | F95: =IF(COPIA!C91=0,"",COPIA!C91) -> F | G95: =IF(COPIA!D91=0,"",COPIA!D91) -> A | H95: =IF(COPIA!E91=0,"",IF(COPIA!B91="FONDO SVALUTAZIONE CREDITI","RETTIFICA CREDITI",COPIA!E91)) -> DEBITI | I95: =IF(COPIA!F91=0,"",COPIA!F91) -> SP AVERE
D96: =IF(COPIA!A92=0,"",COPIA!A92) -> 15.00 | E96: =IF(COPIA!B92=0,"",COPIA!B92) -> DEBITI DIVERSI | F96: =IF(COPIA!C92=0,"",COPIA!C92) | G96: =IF(COPIA!D92=0,"",COPIA!D92) | H96: =IF(COPIA!E92=0,"",IF(COPIA!B92="FONDO SVALUTAZIONE CREDITI","RETTIFICA CREDITI",COPIA!E92)) | I96: =IF(COPIA!F92=0,"",COPIA!F92)
A97: x | B97: x | C97: x | D97: =IF(COPIA!A93=0,"",COPIA!A93) -> 15.01 | E97: =IF(COPIA!B93=0,"",COPIA!B93) -> IVA NS/DEBITO | F97: =IF(COPIA!C93=0,"",COPIA!C93) -> F | G97: =IF(COPIA!D93=0,"",COPIA!D93) -> A | H97: =IF(COPIA!E93=0,"",IF(COPIA!B93="FONDO SVALUTAZIONE CREDITI","RETTIFICA CREDITI",COPIA!E93)) -> DEBITI | I97: =IF(COPIA!F93=0,"",COPIA!F93) -> SP AVERE
A98: x | B98: x | C98: x | D98: =IF(COPIA!A94=0,"",COPIA!A94) -> 15.02 | E98: =IF(COPIA!B94=0,"",COPIA!B94) -> DEBITI PER RITENUTE DA VERSARE | F98: =IF(COPIA!C94=0,"",COPIA!C94) -> F | G98: =IF(COPIA!D94=0,"",COPIA!D94) -> A | H98: =IF(COPIA!E94=0,"",IF(COPIA!B94="FONDO SVALUTAZIONE CREDITI","RETTIFICA CREDITI",COPIA!E94)) -> DEBITI | I98: =IF(COPIA!F94=0,"",COPIA!F94) -> SP AVERE
C99: x | D99: =IF(COPIA!A95=0,"",COPIA!A95) -> 15.03 | E99: =IF(COPIA!B95=0,"",COPIA!B95) -> DEBITI PER IVA | F99: =IF(COPIA!C95=0,"",COPIA!C95) -> F | G99: =IF(COPIA!D95=0,"",COPIA!D95) -> A | H99: =IF(COPIA!E95=0,"",IF(COPIA!B95="FONDO SVALUTAZIONE CREDITI","RETTIFICA CREDITI",COPIA!E95)) -> DEBITI | I99: =IF(COPIA!F95=0,"",COPIA!F95) -> SP AVERE
A100: x | B100: x | C100: x | D100: =IF(COPIA!A96=0,"",COPIA!A96) -> 15.04 | E100: =IF(COPIA!B96=0,"",COPIA!B96) -> DEBITI FISCALI DIVERSI | F100: =IF(COPIA!C96=0,"",COPIA!C96) -> F | G100: =IF(COPIA!D96=0,"",COPIA!D96) -> A | H100: =IF(COPIA!E96=0,"",IF(COPIA!B96="FONDO SVALUTAZIONE CREDITI","RETTIFICA CREDITI",COPIA!E96)) -> DEBITI | I100: =IF(COPIA!F96=0,"",COPIA!F96) -> SP AVERE
C101: x | D101: =IF(COPIA!A97=0,"",COPIA!A97) -> 15.06 | E101: =IF(COPIA!B97=0,"",COPIA!B97) -> DEBITI V/ISTITUTI PREVIDENZIALI | F101: =IF(COPIA!C97=0,"",COPIA!C97) -> F | G101: =IF(COPIA!D97=0,"",COPIA!D97) -> A | H101: =IF(COPIA!E97=0,"",IF(COPIA!B97="FONDO SVALUTAZIONE CREDITI","RETTIFICA CREDITI",COPIA!E97)) -> DEBITI | I101: =IF(COPIA!F97=0,"",COPIA!F97) -> SP AVERE
...

Sheet LIBRO_GIORNALE
B1: LIBRO GIORNALE
B2: SCEGLI VERSIONE | E2: CONTI SUDDIVISI PER RAGGRUPPAMENTO | F2: =IF(COPIA!CH1=0,"",CONCATENATE("Articoli registrati: ",COUNTIFS(K11:K308,"="&0))) | G2: TOT. DARE | H2: TOT. AVERE
A3: =IF(INDIRECT(ADDRESS(3,2,,,))="Cloud: Office 365",2,1) -> 1 | B3: Desktop: Office | E3: =IF(A3=2,"VERSIONE OFFICE 365","") | F3: =COPIA!JM1 | G3: =$L$4 -> esercizio n
B4: Periodo di riferimento dei prospetti | F4: =I4 | G4: =IFERROR(ROUND(SUMIFS(COPIA!$FB$103:$FB$400,COPIA!$EW$103:$EW$400,1,COPIA!$EY$103:$EY$400,">="&INIZIO_AC,COPIA!$EY$103:$EY$400,"<="&FINE_AC),2),0) -> 0 | H4: =IFERROR(ROUND(SUMIFS(COPIA!$FC$103:$FC$400,COPIA!$EW$103:$EW$400,1,COPIA!$EY$103:$EY$400,">="&INIZIO_AC,COPIA!$EY$103:$EY$400,"<="&FINE_AC),2),0) -> 0 | I4: =IF(VALORI_INIZIALI!H3<>VALORI_INIZIALI!I3,"I valori iniziali non bilanciano.",IF(AND(VALORI_INIZIALI!H3=VALORI_INIZIALI!I3,VALORI_INIZIALI!H3>0,VALORI_INIZIALI!I3>0),"Sono presenti valori iniziali.","")) | J4: =COPIA!CW1 -> 2026 | K4: =J4+1 -> 2027 | L4: =CONCATENATE("esercizio ",COPIA!EW1) -> esercizio n | P4: =INDEX($L$11:$M$308,MATCH(MAX($L$11:$L$308),$L$11:$L$308,0),2) -> 0
B6: 31 | C6: 12 | D6: N | E6: =IF(B3="desktop: Office - Libre office","ATTIVA LA VERSIONE ONLINE","") | F6: DELIMITAZIONE ARTICOLO ATTIVATA | G6: Nascondi righe dalla n. | H6: ATTIVA
B7: GG | C7: MM | D7: AA | F7: STUDENTE | G7: ESERCIZIO
E9: .
A10: =COPIA!EX3 -> 0 | B10: Codice | C10: Nr. riga | D10: DATA | E10: DENOMINAZIONE DEI CONTI | F10: DESCRIZIONE | G10: DARE | H10: AVERE | P10: =IFERROR(INDEX($L$11:$M$308,MATCH(MAX($L$11:$L$308)-1,$L$11:$L$308,0),2),0) -> 0
B11: =IF(D11<>"",IFERROR(IF(C11<>"",INDEX(PIANO_DEI_CONTI,MATCH(INDIRECT(ADDRESS(ROW(),5,,,)),DENOMINAZIONE,0),1),""),""),"") | C11: =IF(D11<>"",IF(INDIRECT(ADDRESS(ROW(),5,,,))<>"",ROW()-10,""),"") | K11: =IF(IF(COPIA!$J$3=TRUE,IF(OR(G11<>0,H11<>0),ROUND(SUM(COPIA!$FB$103:FB103),2)-ROUND(SUM(COPIA!$FC$103:FC103),2),""),"")<>0,"",0) | L11: =IFERROR(IF(AND(INDIRECT(ADDRESS(ROW(),4,,,))<=COPIA!$DA$1,K11=0,COPIA!$EX$1>1,ROW()<=COPIA!$EX$1),MAX($L$10:L10)+1,IF(AND(INDIRECT(ADDRESS(ROW(),4,,,))<=COPIA!$DA$1,K11=0,COPIA!$EX$1=1),MAX($L$10:L10)+1,0)),0) -> 0 | M11: =IF(AND(COPIA!$EX$1=1,L11<>0),ROW()-10,IF(AND(COPIA!$EX$1>1,ROW()>COPIA!$EX$1,L11<>0),0,IF(AND(COPIA!$EX$1>1,ROW()<=COPIA!$EX$1,L11<>0),ROW()-10,0))) -> 0 | N11: =IF(AND($P$4=0,ROW()-10<=$P$10),MAX($N$10:N10)+1,IF(AND(ROW()-10>$P$10,ROW()-10<=$P$4),ROW()-10,0)) -> 0 | O11: =IF(N11>0,MAX($O$10:O10)+1,0) -> 0
B12: =IF(D12<>"",IFERROR(IF(C12<>"",INDEX(PIANO_DEI_CONTI,MATCH(INDIRECT(ADDRESS(ROW(),5,,,)),DENOMINAZIONE,0),1),""),""),"") | C12: =IF(D12<>"",IF(INDIRECT(ADDRESS(ROW(),5,,,))<>"",ROW()-10,""),"") | K12: =IF(IF(COPIA!$J$3=TRUE,IF(OR(G12<>0,H12<>0),ROUND(SUM(COPIA!$FB$103:FB104),2)-ROUND(SUM(COPIA!$FC$103:FC104),2),""),"")<>0,"",0) | L12: =IFERROR(IF(AND(INDIRECT(ADDRESS(ROW(),4,,,))<=COPIA!$DA$1,K12=0,COPIA!$EX$1>1,ROW()<=COPIA!$EX$1),MAX($L$10:L11)+1,IF(AND(INDIRECT(ADDRESS(ROW(),4,,,))<=COPIA!$DA$1,K12=0,COPIA!$EX$1=1),MAX($L$10:L11)+1,0)),0) -> 0 | M12: =IF(AND(COPIA!$EX$1=1,L12<>0),ROW()-10,IF(AND(COPIA!$EX$1>1,ROW()>COPIA!$EX$1,L12<>0),0,IF(AND(COPIA!$EX$1>1,ROW()<=COPIA!$EX$1,L12<>0),ROW()-10,0))) -> 0 | N12: =IF(AND($P$4=0,ROW()-10<=$P$10),MAX($N$10:N11)+1,IF(AND(ROW()-10>$P$10,ROW()-10<=$P$4),ROW()-10,0)) -> 0 | O12: =IF(N12>0,MAX($O$10:O11)+1,0) -> 0
B13: =IF(D13<>"",IFERROR(IF(C13<>"",INDEX(PIANO_DEI_CONTI,MATCH(INDIRECT(ADDRESS(ROW(),5,,,)),DENOMINAZIONE,0),1),""),""),"") | C13: =IF(D13<>"",IF(INDIRECT(ADDRESS(ROW(),5,,,))<>"",ROW()-10,""),"") | K13: =IF(IF(COPIA!$J$3=TRUE,IF(OR(G13<>0,H13<>0),ROUND(SUM(COPIA!$FB$103:FB105),2)-ROUND(SUM(COPIA!$FC$103:FC105),2),""),"")<>0,"",0) | L13: =IFERROR(IF(AND(INDIRECT(ADDRESS(ROW(),4,,,))<=COPIA!$DA$1,K13=0,COPIA!$EX$1>1,ROW()<=COPIA!$EX$1),MAX($L$10:L12)+1,IF(AND(INDIRECT(ADDRESS(ROW(),4,,,))<=COPIA!$DA$1,K13=0,COPIA!$EX$1=1),MAX($L$10:L12)+1,0)),0) -> 0 | M13: =IF(AND(COPIA!$EX$1=1,L13<>0),ROW()-10,IF(AND(COPIA!$EX$1>1,ROW()>COPIA!$EX$1,L13<>0),0,IF(AND(COPIA!$EX$1>1,ROW()<=COPIA!$EX$1,L13<>0),ROW()-10,0))) -> 0 | N13: =IF(AND($P$4=0,ROW()-10<=$P$10),MAX($N$10:N12)+1,IF(AND(ROW()-10>$P$10,ROW()-10<=$P$4),ROW()-10,0)) -> 0 | O13: =IF(N13>0,MAX($O$10:O12)+1,0) -> 0
B14: =IF(D14<>"",IFERROR(IF(C14<>"",INDEX(PIANO_DEI_CONTI,MATCH(INDIRECT(ADDRESS(ROW(),5,,,)),DENOMINAZIONE,0),1),""),""),"") | C14: =IF(D14<>"",IF(INDIRECT(ADDRESS(ROW(),5,,,))<>"",ROW()-10,""),"") | K14: =IF(IF(COPIA!$J$3=TRUE,IF(OR(G14<>0,H14<>0),ROUND(SUM(COPIA!$FB$103:FB106),2)-ROUND(SUM(COPIA!$FC$103:FC106),2),""),"")<>0,"",0) | L14: =IFERROR(IF(AND(INDIRECT(ADDRESS(ROW(),4,,,))<=COPIA!$DA$1,K14=0,COPIA!$EX$1>1,ROW()<=COPIA!$EX$1),MAX($L$10:L13)+1,IF(AND(INDIRECT(ADDRESS(ROW(),4,,,))<=COPIA!$DA$1,K14=0,COPIA!$EX$1=1),MAX($L$10:L13)+1,0)),0) -> 0 | M14: =IF(AND(COPIA!$EX$1=1,L14<>0),ROW()-10,IF(AND(COPIA!$EX$1>1,ROW()>COPIA!$EX$1,L14<>0),0,IF(AND(COPIA!$EX$1>1,ROW()<=COPIA!$EX$1,L14<>0),ROW()-10,0))) -> 0 | N14: =IF(AND($P$4=0,ROW()-10<=$P$10),MAX($N$10:N13)+1,IF(AND(ROW()-10>$P$10,ROW()-10<=$P$4),ROW()-10,0)) -> 0 | O14: =IF(N14>0,MAX($O$10:O13)+1,0) -> 0
B15: =IF(D15<>"",IFERROR(IF(C15<>"",INDEX(PIANO_DEI_CONTI,MATCH(INDIRECT(ADDRESS(ROW(),5,,,)),DENOMINAZIONE,0),1),""),""),"") | C15: =IF(D15<>"",IF(INDIRECT(ADDRESS(ROW(),5,,,))<>"",ROW()-10,""),"") | K15: =IF(IF(COPIA!$J$3=TRUE,IF(OR(G15<>0,H15<>0),ROUND(SUM(COPIA!$FB$103:FB107),2)-ROUND(SUM(COPIA!$FC$103:FC107),2),""),"")<>0,"",0) | L15: =IFERROR(IF(AND(INDIRECT(ADDRESS(ROW(),4,,,))<=COPIA!$DA$1,K15=0,COPIA!$EX$1>1,ROW()<=COPIA!$EX$1),MAX($L$10:L14)+1,IF(AND(INDIRECT(ADDRESS(ROW(),4,,,))<=COPIA!$DA$1,K15=0,COPIA!$EX$1=1),MAX($L$10:L14)+1,0)),0) -> 0 | M15: =IF(AND(COPIA!$EX$1=1,L15<>0),ROW()-10,IF(AND(COPIA!$EX$1>1,ROW()>COPIA!$EX$1,L15<>0),0,IF(AND(COPIA!$EX$1>1,ROW()<=COPIA!$EX$1,L15<>0),ROW()-10,0))) -> 0 | N15: =IF(AND($P$4=0,ROW()-10<=$P$10),MAX($N$10:N14)+1,IF(AND(ROW()-10>$P$10,ROW()-10<=$P$4),ROW()-10,0)) -> 0 | O15: =IF(N15>0,MAX($O$10:O14)+1,0) -> 0
B16: =IF(D16<>"",IFERROR(IF(C16<>"",INDEX(PIANO_DEI_CONTI,MATCH(INDIRECT(ADDRESS(ROW(),5,,,)),DENOMINAZIONE,0),1),""),""),"") | C16: =IF(D16<>"",IF(INDIRECT(ADDRESS(ROW(),5,,,))<>"",ROW()-10,""),"") | K16: =IF(IF(COPIA!$J$3=TRUE,IF(OR(G16<>0,H16<>0),ROUND(SUM(COPIA!$FB$103:FB108),2)-ROUND(SUM(COPIA!$FC$103:FC108),2),""),"")<>0,"",0) | L16: =IFERROR(IF(AND(INDIRECT(ADDRESS(ROW(),4,,,))<=COPIA!$DA$1,K16=0,COPIA!$EX$1>1,ROW()<=COPIA!$EX$1),MAX($L$10:L15)+1,IF(AND(INDIRECT(ADDRESS(ROW(),4,,,))<=COPIA!$DA$1,K16=0,COPIA!$EX$1=1),MAX($L$10:L15)+1,0)),0) -> 0 | M16: =IF(AND(COPIA!$EX$1=1,L16<>0),ROW()-10,IF(AND(COPIA!$EX$1>1,ROW()>COPIA!$EX$1,L16<>0),0,IF(AND(COPIA!$EX$1>1,ROW()<=COPIA!$EX$1,L16<>0),ROW()-10,0))) -> 0 | N16: =IF(AND($P$4=0,ROW()-10<=$P$10),MAX($N$10:N15)+1,IF(AND(ROW()-10>$P$10,ROW()-10<=$P$4),ROW()-10,0)) -> 0 | O16: =IF(N16>0,MAX($O$10:O15)+1,0) -> 0
B17: =IF(D17<>"",IFERROR(IF(C17<>"",INDEX(PIANO_DEI_CONTI,MATCH(INDIRECT(ADDRESS(ROW(),5,,,)),DENOMINAZIONE,0),1),""),""),"") | C17: =IF(D17<>"",IF(INDIRECT(ADDRESS(ROW(),5,,,))<>"",ROW()-10,""),"") | K17: =IF(IF(COPIA!$J$3=TRUE,IF(OR(G17<>0,H17<>0),ROUND(SUM(COPIA!$FB$103:FB109),2)-ROUND(SUM(COPIA!$FC$103:FC109),2),""),"")<>0,"",0) | L17: =IFERROR(IF(AND(INDIRECT(ADDRESS(ROW(),4,,,))<=COPIA!$DA$1,K17=0,COPIA!$EX$1>1,ROW()<=COPIA!$EX$1),MAX($L$10:L16)+1,IF(AND(INDIRECT(ADDRESS(ROW(),4,,,))<=COPIA!$DA$1,K17=0,COPIA!$EX$1=1),MAX($L$10:L16)+1,0)),0) -> 0 | M17: =IF(AND(COPIA!$EX$1=1,L17<>0),ROW()-10,IF(AND(COPIA!$EX$1>1,ROW()>COPIA!$EX$1,L17<>0),0,IF(AND(COPIA!$EX$1>1,ROW()<=COPIA!$EX$1,L17<>0),ROW()-10,0))) -> 0 | N17: =IF(AND($P$4=0,ROW()-10<=$P$10),MAX($N$10:N16)+1,IF(AND(ROW()-10>$P$10,ROW()-10<=$P$4),ROW()-10,0)) -> 0 | O17: =IF(N17>0,MAX($O$10:O16)+1,0) -> 0
B18: =IF(D18<>"",IFERROR(IF(C18<>"",INDEX(PIANO_DEI_CONTI,MATCH(INDIRECT(ADDRESS(ROW(),5,,,)),DENOMINAZIONE,0),1),""),""),"") | C18: =IF(D18<>"",IF(INDIRECT(ADDRESS(ROW(),5,,,))<>"",ROW()-10,""),"") | K18: =IF(IF(COPIA!$J$3=TRUE,IF(OR(G18<>0,H18<>0),ROUND(SUM(COPIA!$FB$103:FB110),2)-ROUND(SUM(COPIA!$FC$103:FC110),2),""),"")<>0,"",0) | L18: =IFERROR(IF(AND(INDIRECT(ADDRESS(ROW(),4,,,))<=COPIA!$DA$1,K18=0,COPIA!$EX$1>1,ROW()<=COPIA!$EX$1),MAX($L$10:L17)+1,IF(AND(INDIRECT(ADDRESS(ROW(),4,,,))<=COPIA!$DA$1,K18=0,COPIA!$EX$1=1),MAX($L$10:L17)+1,0)),0) -> 0 | M18: =IF(AND(COPIA!$EX$1=1,L18<>0),ROW()-10,IF(AND(COPIA!$EX$1>1,ROW()>COPIA!$EX$1,L18<>0),0,IF(AND(COPIA!$EX$1>1,ROW()<=COPIA!$EX$1,L18<>0),ROW()-10,0))) -> 0 | N18: =IF(AND($P$4=0,ROW()-10<=$P$10),MAX($N$10:N17)+1,IF(AND(ROW()-10>$P$10,ROW()-10<=$P$4),ROW()-10,0)) -> 0 | O18: =IF(N18>0,MAX($O$10:O17)+1,0) -> 0
B19: =IF(D19<>"",IFERROR(IF(C19<>"",INDEX(PIANO_DEI_CONTI,MATCH(INDIRECT(ADDRESS(ROW(),5,,,)),DENOMINAZIONE,0),1),""),""),"") | C19: =IF(D19<>"",IF(INDIRECT(ADDRESS(ROW(),5,,,))<>"",ROW()-10,""),"") | K19: =IF(IF(COPIA!$J$3=TRUE,IF(OR(G19<>0,H19<>0),ROUND(SUM(COPIA!$FB$103:FB111),2)-ROUND(SUM(COPIA!$FC$103:FC111),2),""),"")<>0,"",0) | L19: =IFERROR(IF(AND(INDIRECT(ADDRESS(ROW(),4,,,))<=COPIA!$DA$1,K19=0,COPIA!$EX$1>1,ROW()<=COPIA!$EX$1),MAX($L$10:L18)+1,IF(AND(INDIRECT(ADDRESS(ROW(),4,,,))<=COPIA!$DA$1,K19=0,COPIA!$EX$1=1),MAX($L$10:L18)+1,0)),0) -> 0 | M19: =IF(AND(COPIA!$EX$1=1,L19<>0),ROW()-10,IF(AND(COPIA!$EX$1>1,ROW()>COPIA!$EX$1,L19<>0),0,IF(AND(COPIA!$EX$1>1,ROW()<=COPIA!$EX$1,L19<>0),ROW()-10,0))) -> 0 | N19: =IF(AND($P$4=0,ROW()-10<=$P$10),MAX($N$10:N18)+1,IF(AND(ROW()-10>$P$10,ROW()-10<=$P$4),ROW()-10,0)) -> 0 | O19: =IF(N19>0,MAX($O$10:O18)+1,0) -> 0
B20: =IF(D20<>"",IFERROR(IF(C20<>"",INDEX(PIANO_DEI_CONTI,MATCH(INDIRECT(ADDRESS(ROW(),5,,,)),DENOMINAZIONE,0),1),""),""),"") | C20: =IF(D20<>"",IF(INDIRECT(ADDRESS(ROW(),5,,,))<>"",ROW()-10,""),"") | K20: =IF(IF(COPIA!$J$3=TRUE,IF(OR(G20<>0,H20<>0),ROUND(SUM(COPIA!$FB$103:FB112),2)-ROUND(SUM(COPIA!$FC$103:FC112),2),""),"")<>0,"",0) | L20: =IFERROR(IF(AND(INDIRECT(ADDRESS(ROW(),4,,,))<=COPIA!$DA$1,K20=0,COPIA!$EX$1>1,ROW()<=COPIA!$EX$1),MAX($L$10:L19)+1,IF(AND(INDIRECT(ADDRESS(ROW(),4,,,))<=COPIA!$DA$1,K20=0,COPIA!$EX$1=1),MAX($L$10:L19)+1,0)),0) -> 0 | M20: =IF(AND(COPIA!$EX$1=1,L20<>0),ROW()-10,IF(AND(COPIA!$EX$1>1,ROW()>COPIA!$EX$1,L20<>0),0,IF(AND(COPIA!$EX$1>1,ROW()<=COPIA!$EX$1,L20<>0),ROW()-10,0))) -> 0 | N20: =IF(AND($P$4=0,ROW()-10<=$P$10),MAX($N$10:N19)+1,IF(AND(ROW()-10>$P$10,ROW()-10<=$P$4),ROW()-10,0)) -> 0 | O20: =IF(N20>0,MAX($O$10:O19)+1,0) -> 0
B21: =IF(D21<>"",IFERROR(IF(C21<>"",INDEX(PIANO_DEI_CONTI,MATCH(INDIRECT(ADDRESS(ROW(),5,,,)),DENOMINAZIONE,0),1),""),""),"") | C21: =IF(D21<>"",IF(INDIRECT(ADDRESS(ROW(),5,,,))<>"",ROW()-10,""),"") | K21: =IF(IF(COPIA!$J$3=TRUE,IF(OR(G21<>0,H21<>0),ROUND(SUM(COPIA!$FB$103:FB113),2)-ROUND(SUM(COPIA!$FC$103:FC113),2),""),"")<>0,"",0) | L21: =IFERROR(IF(AND(INDIRECT(ADDRESS(ROW(),4,,,))<=COPIA!$DA$1,K21=0,COPIA!$EX$1>1,ROW()<=COPIA!$EX$1),MAX($L$10:L20)+1,IF(AND(INDIRECT(ADDRESS(ROW(),4,,,))<=COPIA!$DA$1,K21=0,COPIA!$EX$1=1),MAX($L$10:L20)+1,0)),0) -> 0 | M21: =IF(AND(COPIA!$EX$1=1,L21<>0),ROW()-10,IF(AND(COPIA!$EX$1>1,ROW()>COPIA!$EX$1,L21<>0),0,IF(AND(COPIA!$EX$1>1,ROW()<=COPIA!$EX$1,L21<>0),ROW()-10,0))) -> 0 | N21: =IF(AND($P$4=0,ROW()-10<=$P$10),MAX($N$10:N20)+1,IF(AND(ROW()-10>$P$10,ROW()-10<=$P$4),ROW()-10,0)) -> 0 | O21: =IF(N21>0,MAX($O$10:O20)+1,0) -> 0
B22: =IF(D22<>"",IFERROR(IF(C22<>"",INDEX(PIANO_DEI_CONTI,MATCH(INDIRECT(ADDRESS(ROW(),5,,,)),DENOMINAZIONE,0),1),""),""),"") | C22: =IF(D22<>"",IF(INDIRECT(ADDRESS(ROW(),5,,,))<>"",ROW()-10,""),"") | K22: =IF(IF(COPIA!$J$3=TRUE,IF(OR(G22<>0,H22<>0),ROUND(SUM(COPIA!$FB$103:FB114),2)-ROUND(SUM(COPIA!$FC$103:FC114),2),""),"")<>0,"",0) | L22: =IFERROR(IF(AND(INDIRECT(ADDRESS(ROW(),4,,,))<=COPIA!$DA$1,K22=0,COPIA!$EX$1>1,ROW()<=COPIA!$EX$1),MAX($L$10:L21)+1,IF(AND(INDIRECT(ADDRESS(ROW(),4,,,))<=COPIA!$DA$1,K22=0,COPIA!$EX$1=1),MAX($L$10:L21)+1,0)),0) -> 0 | M22: =IF(AND(COPIA!$EX$1=1,L22<>0),ROW()-10,IF(AND(COPIA!$EX$1>1,ROW()>COPIA!$EX$1,L22<>0),0,IF(AND(COPIA!$EX$1>1,ROW()<=COPIA!$EX$1,L22<>0),ROW()-10,0))) -> 0 | N22: =IF(AND($P$4=0,ROW()-10<=$P$10),MAX($N$10:N21)+1,IF(AND(ROW()-10>$P$10,ROW()-10<=$P$4),ROW()-10,0)) -> 0 | O22: =IF(N22>0,MAX($O$10:O21)+1,0) -> 0
... B308: =IF(D308<>"",IFERROR(IF(C308<>"",INDEX(PIANO_DEI_CONTI,MATCH(INDIRECT(ADDRESS(ROW(),5,,,)),DENOMINAZIONE,0),1),""),""),"") | C308: =IF(D308<>"",IF(INDIRECT(ADDRESS(ROW(),5,,,))<>"",ROW()-10,""),"") | K308: =IF(IF(COPIA!$J$3=TRUE,IF(OR(G308<>0,H308<>0),ROUND(SUM(COPIA!$FB$103:FB400),2)-ROUND(SUM(COPIA!$FC$103:FC400),2),""),"")<>0,"",0) | L308: =IFERROR(IF(AND(INDIRECT(ADDRESS(ROW(),4,,,))<=COPIA!$DA$1,K308=0,COPIA!$EX$1>1,ROW()<=COPIA!$EX$1),MAX($L$10:L307)+1,IF(AND(INDIRECT(ADDRESS(ROW(),4,,,))<=COPIA!$DA$1,K308=0,COPIA!$EX$1=1),MAX($L$10:L307)+1,0)),0) -> 0 | M308: =IF(AND(COPIA!$EX$1=1,L308<>0),ROW()-10,IF(AND(COPIA!$EX$1>1,ROW()>COPIA!$EX$1,L308<>0),0,IF(AND(COPIA!$EX$1>1,ROW()<=COPIA!$EX$1,L308<>0),ROW()-10,0))) -> 0 | N308: =IF(AND($P$4=0,ROW()-10<=$P$10),MAX($N$10:N307)+1,IF(AND(ROW()-10>$P$10,ROW()-10<=$P$4),ROW()-10,0)) -> 0 | O308: =IF(N308>0,MAX($O$10:O307)+1,0) -> 0

Sheet CONTI_DI_MASTRO
B1: CONTI DI MASTRO
B2: =COPIA!JL1 -> Nessun conto visualizzato | E2: Riquadro dI controllo: DENOMINAZIONE dei conti | I2: Riquadro di controllo: ECCEDENZA dei conti
D3: =IF(COPIA!CH1=0,"",CONCATENATE("Numero dei conti con eccedenza errata: ",COPIA!FM1," Numero dei conti con denominazione errata: ",COPIA!EQ2)) | E3: =COPIA!ET3 | I3: =COPIA!FP3
B5: Opzioni di visualizzazione | D5: VISUALIZZA UN CONTO IN EVIDENZA | E5: VISUALIZZA I CONTI SECONDO L'ORDINE DEL PIANO DEI CONTI | I5: VISUALIZZA I MOVIMENTI DEI CONTI E IL SALDO
B7: =IF(INDIRECT(ADDRESS(8,7,,,"LIBRO_GIORNALE"))="","",INDIRECT(ADDRESS(8,7,,,"LIBRO_GIORNALE"))) | D7: =IF(COPIA!CH1=0,"",CONCATENATE("CONTI DI MASTRO al ",COPIA!DS2,"/",COPIA!DT2,"/",COPIA!DU2)) | E7: =IF(INDIRECT(ADDRESS(8,6,,,"LIBRO_GIORNALE"))="","",INDIRECT(ADDRESS(8,6,,,"LIBRO_GIORNALE")))
B8: =IF(IFERROR(INDEX((COPIA!$DA$3:$DE$2300),MATCH(ROWS(B$8:B8),COPIA!$DF$3:$DF$2300,0),COLUMN()-1),"")>=1,IFERROR(INDEX((COPIA!$DA$3:$DE$2300),MATCH(ROWS(B$8:B8),COPIA!$DF$3:$DF$2300,0),COLUMN()-1),""),"") | C8: =SUBSTITUTE(IFERROR(INDEX((COPIA!$DA$3:$DE$2300),MATCH(ROWS(C$8:C8),COPIA!$DF$3:$DF$2300,0),COLUMN()-1),""),"MASTRO","") | D8: =IF(IFERROR(INDEX((COPIA!$DA$3:$DE$2300),MATCH(ROWS(D$8:D8),COPIA!$DF$3:$DF$2300,0),COLUMN()-1),"")=0,"",IFERROR(INDEX((COPIA!$DA$3:$DE$2300),MATCH(ROWS(D$8:D8),COPIA!$DF$3:$DF$2300,0),COLUMN()-1),"")) | E8: =IF(IFERROR(INDEX((COPIA!$DA$3:$DE$2300),MATCH(ROWS(E$8:E8),COPIA!$DF$3:$DF$2300,0),COLUMN()-1),"")=0,"",IFERROR(INDEX((COPIA!$DA$3:$DE$2300),MATCH(ROWS(E$8:E8),COPIA!$DF$3:$DF$2300,0),COLUMN()-1),"")) | F8: =IF(IFERROR(INDEX((COPIA!$DA$3:$DE$2300),MATCH(ROWS(F$8:F8),COPIA!$DF$3:$DF$2300,0),COLUMN()-1),"")=0,"",IFERROR(INDEX((COPIA!$DA$3:$DE$2300),MATCH(ROWS(F$8:F8),COPIA!$DF$3:$DF$2300,0),COLUMN()-1),""))
B9: =IF(IFERROR(INDEX((COPIA!$DA$3:$DE$2300),MATCH(ROWS(B$8:B9),COPIA!$DF$3:$DF$2300,0),COLUMN()-1),"")>=1,IFERROR(INDEX((COPIA!$DA$3:$DE$2300),MATCH(ROWS(B$8:B9),COPIA!$DF$3:$DF$2300,0),COLUMN()-1),""),"") | C9: =SUBSTITUTE(IFERROR(INDEX((COPIA!$DA$3:$DE$2300),MATCH(ROWS(C$8:C9),COPIA!$DF$3:$DF$2300,0),COLUMN()-1),""),"MASTRO","") | D9: =IF(IFERROR(INDEX((COPIA!$DA$3:$DE$2300),MATCH(ROWS(D$8:D9),COPIA!$DF$3:$DF$2300,0),COLUMN()-1),"")=0,"",IFERROR(INDEX((COPIA!$DA$3:$DE$2300),MATCH(ROWS(D$8:D9),COPIA!$DF$3:$DF$2300,0),COLUMN()-1),"")) | E9: =IF(IFERROR(INDEX((COPIA!$DA$3:$DE$2300),MATCH(ROWS(E$8:E9),COPIA!$DF$3:$DF$2300,0),COLUMN()-1),"")=0,"",IFERROR(INDEX((COPIA!$DA$3:$DE$2300),MATCH(ROWS(E$8:E9),COPIA!$DF$3:$DF$2300,0),COLUMN()-1),"")) | F9: =IF(IFERROR(INDEX((COPIA!$DA$3:$DE$2300),MATCH(ROWS(F$8:F9),COPIA!$DF$3:$DF$2300,0),COLUMN()-1),"")=0,"",IFERROR(INDEX((COPIA!$DA$3:$DE$2300),MATCH(ROWS(F$8:F9),COPIA!$DF$3:$DF$2300,0),COLUMN()-1),""))
B10: =IF(IFERROR(INDEX((COPIA!$DA$3:$DE$2300),MATCH(ROWS(B$8:B10),COPIA!$DF$3:$DF$2300,0),COLUMN()-1),"")>=1,IFERROR(INDEX((COPIA!$DA$3:$DE$2300),MATCH(ROWS(B$8:B10),COPIA!$DF$3:$DF$2300,0),COLUMN()-1),""),"") | C10: =SUBSTITUTE(IFERROR(INDEX((COPIA!$DA$3:$DE$2300),MATCH(ROWS(C$8:C10),COPIA!$DF$3:$DF$2300,0),COLUMN()-1),""),"MASTRO","") | D10: =IF(IFERROR(INDEX((COPIA!$DA$3:$DE$2300),MATCH(ROWS(D$8:D10),COPIA!$DF$3:$DF$2300,0),COLUMN()-1),"")=0,"",IFERROR(INDEX((COPIA!$DA$3:$DE$2300),MATCH(ROWS(D$8:D10),COPIA!$DF$3:$DF$2300,0),COLUMN()-1),"")) | E10: =IF(IFERROR(INDEX((COPIA!$DA$3:$DE$2300),MATCH(ROWS(E$8:E10),COPIA!$DF$3:$DF$2300,0),COLUMN()-1),"")=0,"",IFERROR(INDEX((COPIA!$DA$3:$DE$2300),MATCH(ROWS(E$8:E10),COPIA!$DF$3:$DF$2300,0),COLUMN()-1),"")) | F10: =IF(IFERROR(INDEX((COPIA!$DA$3:$DE$2300),MATCH(ROWS(F$8:F10),COPIA!$DF$3:$DF$2300,0),COLUMN()-1),"")=0,"",IFERROR(INDEX((COPIA!$DA$3:$DE$2300),MATCH(ROWS(F$8:F10),COPIA!$DF$3:$DF$2300,0),COLUMN()-1),""))
B11: =IF(IFERROR(INDEX((COPIA!$DA$3:$DE$2300),MATCH(ROWS(B$8:B11),COPIA!$DF$3:$DF$2300,0),COLUMN()-1),"")>=1,IFERROR(INDEX((COPIA!$DA$3:$DE$2300),MATCH(ROWS(B$8:B11),COPIA!$DF$3:$DF$2300,0),COLUMN()-1),""),"") | C11: =SUBSTITUTE(IFERROR(INDEX((COPIA!$DA$3:$DE$2300),MATCH(ROWS(C$8:C11),COPIA!$DF$3:$DF$2300,0),COLUMN()-1),""),"MASTRO","") | D11: =IF(IFERROR(INDEX((COPIA!$DA$3:$DE$2300),MATCH(ROWS(D$8:D11),COPIA!$DF$3:$DF$2300,0),COLUMN()-1),"")=0,"",IFERROR(INDEX((COPIA!$DA$3:$DE$2300),MATCH(ROWS(D$8:D11),COPIA!$DF$3:$DF$2300,0),COLUMN()-1),"")) | E11: =IF(IFERROR(INDEX((COPIA!$DA$3:$DE$2300),MATCH(ROWS(E$8:E11),COPIA!$DF$3:$DF$2300,0),COLUMN()-1),"")=0,"",IFERROR(INDEX((COPIA!$DA$3:$DE$2300),MATCH(ROWS(E$8:E11),COPIA!$DF$3:$DF$2300,0),COLUMN()-1),"")) | F11: =IF(IFERROR(INDEX((COPIA!$DA$3:$DE$2300),MATCH(ROWS(F$8:F11),COPIA!$DF$3:$DF$2300,0),COLUMN()-1),"")=0,"",IFERROR(INDEX((COPIA!$DA$3:$DE$2300),MATCH(ROWS(F$8:F11),COPIA!$DF$3:$DF$2300,0),COLUMN()-1),""))
B12: =IF(IFERROR(INDEX((COPIA!$DA$3:$DE$2300),MATCH(ROWS(B$8:B12),COPIA!$DF$3:$DF$2300,0),COLUMN()-1),"")>=1,IFERROR(INDEX((COPIA!$DA$3:$DE$2300),MATCH(ROWS(B$8:B12),COPIA!$DF$3:$DF$2300,0),COLUMN()-1),""),"") | C12: =SUBSTITUTE(IFERROR(INDEX((COPIA!$DA$3:$DE$2300),MATCH(ROWS(C$8:C12),COPIA!$DF$3:$DF$2300,0),COLUMN()-1),""),"MASTRO","") | D12: =IF(IFERROR(INDEX((COPIA!$DA$3:$DE$2300),MATCH(ROWS(D$8:D12),COPIA!$DF$3:$DF$2300,0),COLUMN()-1),"")=0,"",IFERROR(INDEX((COPIA!$DA$3:$DE$2300),MATCH(ROWS(D$8:D12),COPIA!$DF$3:$DF$2300,0),COLUMN()-1),"")) | E12: =IF(IFERROR(INDEX((COPIA!$DA$3:$DE$2300),MATCH(ROWS(E$8:E12),COPIA!$DF$3:$DF$2300,0),COLUMN()-1),"")=0,"",IFERROR(INDEX((COPIA!$DA$3:$DE$2300),MATCH(ROWS(E$8:E12),COPIA!$DF$3:$DF$2300,0),COLUMN()-1),"")) | F12: =IF(IFERROR(INDEX((COPIA!$DA$3:$DE$2300),MATCH(ROWS(F$8:F12),COPIA!$DF$3:$DF$2300,0),COLUMN()-1),"")=0,"",IFERROR(INDEX((COPIA!$DA$3:$DE$2300),MATCH(ROWS(F$8:F12),COPIA!$DF$3:$DF$2300,0),COLUMN()-1),""))
B13: =IF(IFERROR(INDEX((COPIA!$DA$3:$DE$2300),MATCH(ROWS(B$8:B13),COPIA!$DF$3:$DF$2300,0),COLUMN()-1),"")>=1,IFERROR(INDEX((COPIA!$DA$3:$DE$2300),MATCH(ROWS(B$8:B13),COPIA!$DF$3:$DF$2300,0),COLUMN()-1),""),"") | C13: =SUBSTITUTE(IFERROR(INDEX((COPIA!$DA$3:$DE$2300),MATCH(ROWS(C$8:C13),COPIA!$DF$3:$DF$2300,0),COLUMN()-1),""),"MASTRO","") | D13: =IF(IFERROR(INDEX((COPIA!$DA$3:$DE$2300),MATCH(ROWS(D$8:D13),COPIA!$DF$3:$DF$2300,0),COLUMN()-1),"")=0,"",IFERROR(INDEX((COPIA!$DA$3:$DE$2300),MATCH(ROWS(D$8:D13),COPIA!$DF$3:$DF$2300,0),COLUMN()-1),"")) | E13: =IF(IFERROR(INDEX((COPIA!$DA$3:$DE$2300),MATCH(ROWS(E$8:E13),COPIA!$DF$3:$DF$2300,0),COLUMN()-1),"")=0,"",IFERROR(INDEX((COPIA!$DA$3:$DE$2300),MATCH(ROWS(E$8:E13),COPIA!$DF$3:$DF$2300,0),COLUMN()-1),"")) | F13: =IF(IFERROR(INDEX((COPIA!$DA$3:$DE$2300),MATCH(ROWS(F$8:F13),COPIA!$DF$3:$DF$2300,0),COLUMN()-1),"")=0,"",IFERROR(INDEX((COPIA!$DA$3:$DE$2300),MATCH(ROWS(F$8:F13),COPIA!$DF$3:$DF$2300,0),COLUMN()-1),""))
B14: =IF(IFERROR(INDEX((COPIA!$DA$3:$DE$2300),MATCH(ROWS(B$8:B14),COPIA!$DF$3:$DF$2300,0),COLUMN()-1),"")>=1,IFERROR(INDEX((COPIA!$DA$3:$DE$2300),MATCH(ROWS(B$8:B14),COPIA!$DF$3:$DF$2300,0),COLUMN()-1),""),"") | C14: =SUBSTITUTE(IFERROR(INDEX((COPIA!$DA$3:$DE$2300),MATCH(ROWS(C$8:C14),COPIA!$DF$3:$DF$2300,0),COLUMN()-1),""),"MASTRO","") | D14: =IF(IFERROR(INDEX((COPIA!$DA$3:$DE$2300),MATCH(ROWS(D$8:D14),COPIA!$DF$3:$DF$2300,0),COLUMN()-1),"")=0,"",IFERROR(INDEX((COPIA!$DA$3:$DE$2300),MATCH(ROWS(D$8:D14),COPIA!$DF$3:$DF$2300,0),COLUMN()-1),"")) | E14: =IF(IFERROR(INDEX((COPIA!$DA$3:$DE$2300),MATCH(ROWS(E$8:E14),COPIA!$DF$3:$DF$2300,0),COLUMN()-1),"")=0,"",IFERROR(INDEX((COPIA!$DA$3:$DE$2300),MATCH(ROWS(E$8:E14),COPIA!$DF$3:$DF$2300,0),COLUMN()-1),"")) | F14: =IF(IFERROR(INDEX((COPIA!$DA$3:$DE$2300),MATCH(ROWS(F$8:F14),COPIA!$DF$3:$DF$2300,0),COLUMN()-1),"")=0,"",IFERROR(INDEX((COPIA!$DA$3:$DE$2300),MATCH(ROWS(F$8:F14),COPIA!$DF$3:$DF$2300,0),COLUMN()-1),""))
B15: =IF(IFERROR(INDEX((COPIA!$DA$3:$DE$2300),MATCH(ROWS(B$8:B15),COPIA!$DF$3:$DF$2300,0),COLUMN()-1),"")>=1,IFERROR(INDEX((COPIA!$DA$3:$DE$2300),MATCH(ROWS(B$8:B15),COPIA!$DF$3:$DF$2300,0),COLUMN()-1),""),"") | C15: =SUBSTITUTE(IFERROR(INDEX((COPIA!$DA$3:$DE$2300),MATCH(ROWS(C$8:C15),COPIA!$DF$3:$DF$2300,0),COLUMN()-1),""),"MASTRO","") | D15: =IF(IFERROR(INDEX((COPIA!$DA$3:$DE$2300),MATCH(ROWS(D$8:D15),COPIA!$DF$3:$DF$2300,0),COLUMN()-1),"")=0,"",IFERROR(INDEX((COPIA!$DA$3:$DE$2300),MATCH(ROWS(D$8:D15),COPIA!$DF$3:$DF$2300,0),COLUMN()-1),"")) | E15: =IF(IFERROR(INDEX((COPIA!$DA$3:$DE$2300),MATCH(ROWS(E$8:E15),COPIA!$DF$3:$DF$2300,0),COLUMN()-1),"")=0,"",IFERROR(INDEX((COPIA!$DA$3:$DE$2300),MATCH(ROWS(E$8:E15),COPIA!$DF$3:$DF$2300,0),COLUMN()-1),"")) | F15: =IF(IFERROR(INDEX((COPIA!$DA$3:$DE$2300),MATCH(ROWS(F$8:F15),COPIA!$DF$3:$DF$2300,0),COLUMN()-1),"")=0,"",IFERROR(INDEX((COPIA!$DA$3:$DE$2300),MATCH(ROWS(F$8:F15),COPIA!$DF$3:$DF$2300,0),COLUMN()-1),""))
B16: =IF(IFERROR(INDEX((COPIA!$DA$3:$DE$2300),MATCH(ROWS(B$8:B16),COPIA!$DF$3:$DF$2300,0),COLUMN()-1),"")>=1,IFERROR(INDEX((COPIA!$DA$3:$DE$2300),MATCH(ROWS(B$8:B16),COPIA!$DF$3:$DF$2300,0),COLUMN()-1),""),"") | C16: =SUBSTITUTE(IFERROR(INDEX((COPIA!$DA$3:$DE$2300),MATCH(ROWS(C$8:C16),COPIA!$DF$3:$DF$2300,0),COLUMN()-1),""),"MASTRO","") | D16: =IF(IFERROR(INDEX((COPIA!$DA$3:$DE$2300),MATCH(ROWS(D$8:D16),COPIA!$DF$3:$DF$2300,0),COLUMN()-1),"")=0,"",IFERROR(INDEX((COPIA!$DA$3:$DE$2300),MATCH(ROWS(D$8:D16),COPIA!$DF$3:$DF$2300,0),COLUMN()-1),"")) | E16: =IF(IFERROR(INDEX((COPIA!$DA$3:$DE$2300),MATCH(ROWS(E$8:E16),COPIA!$DF$3:$DF$2300,0),COLUMN()-1),"")=0,"",IFERROR(INDEX((COPIA!$DA$3:$DE$2300),MATCH(ROWS(E$8:E16),COPIA!$DF$3:$DF$2300,0),COLUMN()-1),"")) | F16: =IF(IFERROR(INDEX((COPIA!$DA$3:$DE$2300),MATCH(ROWS(F$8:F16),COPIA!$DF$3:$DF$2300,0),COLUMN()-1),"")=0,"",IFERROR(INDEX((COPIA!$DA$3:$DE$2300),MATCH(ROWS(F$8:F16),COPIA!$DF$3:$DF$2300,0),COLUMN()-1),""))
B17: =IF(IFERROR(INDEX((COPIA!$DA$3:$DE$2300),MATCH(ROWS(B$8:B17),COPIA!$DF$3:$DF$2300,0),COLUMN()-1),"")>=1,IFERROR(INDEX((COPIA!$DA$3:$DE$2300),MATCH(ROWS(B$8:B17),COPIA!$DF$3:$DF$2300,0),COLUMN()-1),""),"") | C17: =SUBSTITUTE(IFERROR(INDEX((COPIA!$DA$3:$DE$2300),MATCH(ROWS(C$8:C17),COPIA!$DF$3:$DF$2300,0),COLUMN()-1),""),"MASTRO","") | D17: =IF(IFERROR(INDEX((COPIA!$DA$3:$DE$2300),MATCH(ROWS(D$8:D17),COPIA!$DF$3:$DF$2300,0),COLUMN()-1),"")=0,"",IFERROR(INDEX((COPIA!$DA$3:$DE$2300),MATCH(ROWS(D$8:D17),COPIA!$DF$3:$DF$2300,0),COLUMN()-1),"")) | E17: =IF(IFERROR(INDEX((COPIA!$DA$3:$DE$2300),MATCH(ROWS(E$8:E17),COPIA!$DF$3:$DF$2300,0),COLUMN()-1),"")=0,"",IFERROR(INDEX((COPIA!$DA$3:$DE$2300),MATCH(ROWS(E$8:E17),COPIA!$DF$3:$DF$2300,0),COLUMN()-1),"")) | F17: =IF(IFERROR(INDEX((COPIA!$DA$3:$DE$2300),MATCH(ROWS(F$8:F17),COPIA!$DF$3:$DF$2300,0),COLUMN()-1),"")=0,"",IFERROR(INDEX((COPIA!$DA$3:$DE$2300),MATCH(ROWS(F$8:F17),COPIA!$DF$3:$DF$2300,0),COLUMN()-1),""))
B18: =IF(IFERROR(INDEX((COPIA!$DA$3:$DE$2300),MATCH(ROWS(B$8:B18),COPIA!$DF$3:$DF$2300,0),COLUMN()-1),"")>=1,IFERROR(INDEX((COPIA!$DA$3:$DE$2300),MATCH(ROWS(B$8:B18),COPIA!$DF$3:$DF$2300,0),COLUMN()-1),""),"") | C18: =SUBSTITUTE(IFERROR(INDEX((COPIA!$DA$3:$DE$2300),MATCH(ROWS(C$8:C18),COPIA!$DF$3:$DF$2300,0),COLUMN()-1),""),"MASTRO","") | D18: =IF(IFERROR(INDEX((COPIA!$DA$3:$DE$2300),MATCH(ROWS(D$8:D18),COPIA!$DF$3:$DF$2300,0),COLUMN()-1),"")=0,"",IFERROR(INDEX((COPIA!$DA$3:$DE$2300),MATCH(ROWS(D$8:D18),COPIA!$DF$3:$DF$2300,0),COLUMN()-1),"")) | E18: =IF(IFERROR(INDEX((COPIA!$DA$3:$DE$2300),MATCH(ROWS(E$8:E18),COPIA!$DF$3:$DF$2300,0),COLUMN()-1),"")=0,"",IFERROR(INDEX((COPIA!$DA$3:$DE$2300),MATCH(ROWS(E$8:E18),COPIA!$DF$3:$DF$2300,0),COLUMN()-1),"")) | F18: =IF(IFERROR(INDEX((COPIA!$DA$3:$DE$2300),MATCH(ROWS(F$8:F18),COPIA!$DF$3:$DF$2300,0),COLUMN()-1),"")=0,"",IFERROR(INDEX((COPIA!$DA$3:$DE$2300),MATCH(ROWS(F$8:F18),COPIA!$DF$3:$DF$2300,0),COLUMN()-1),""))
B19: =IF(IFERROR(INDEX((COPIA!$DA$3:$DE$2300),MATCH(ROWS(B$8:B19),COPIA!$DF$3:$DF$2300,0),COLUMN()-1),"")>=1,IFERROR(INDEX((COPIA!$DA$3:$DE$2300),MATCH(ROWS(B$8:B19),COPIA!$DF$3:$DF$2300,0),COLUMN()-1),""),"") | C19: =SUBSTITUTE(IFERROR(INDEX((COPIA!$DA$3:$DE$2300),MATCH(ROWS(C$8:C19),COPIA!$DF$3:$DF$2300,0),COLUMN()-1),""),"MASTRO","") | D19: =IF(IFERROR(INDEX((COPIA!$DA$3:$DE$2300),MATCH(ROWS(D$8:D19),COPIA!$DF$3:$DF$2300,0),COLUMN()-1),"")=0,"",IFERROR(INDEX((COPIA!$DA$3:$DE$2300),MATCH(ROWS(D$8:D19),COPIA!$DF$3:$DF$2300,0),COLUMN()-1),"")) | E19: =IF(IFERROR(INDEX((COPIA!$DA$3:$DE$2300),MATCH(ROWS(E$8:E19),COPIA!$DF$3:$DF$2300,0),COLUMN()-1),"")=0,"",IFERROR(INDEX((COPIA!$DA$3:$DE$2300),MATCH(ROWS(E$8:E19),COPIA!$DF$3:$DF$2300,0),COLUMN()-1),"")) | F19: =IF(IFERROR(INDEX((COPIA!$DA$3:$DE$2300),MATCH(ROWS(F$8:F19),COPIA!$DF$3:$DF$2300,0),COLUMN()-1),"")=0,"",IFERROR(INDEX((COPIA!$DA$3:$DE$2300),MATCH(ROWS(F$8:F19),COPIA!$DF$3:$DF$2300,0),COLUMN()-1),""))
... B604: =IF(IFERROR(INDEX((COPIA!$DA$3:$DE$2300),MATCH(ROWS(B$8:B604),COPIA!$DF$3:$DF$2300,0),COLUMN()-1),"")>=1,IFERROR(INDEX((COPIA!$DA$3:$DE$2300),MATCH(ROWS(B$8:B604),COPIA!$DF$3:$DF$2300,0),COLUMN()-1),""),"") | C604: =SUBSTITUTE(IFERROR(INDEX((COPIA!$DA$3:$DE$2300),MATCH(ROWS(C$8:C604),COPIA!$DF$3:$DF$2300,0),COLUMN()-1),""),"MASTRO","") | D604: =IF(IFERROR(INDEX((COPIA!$DA$3:$DE$2300),MATCH(ROWS(D$8:D604),COPIA!$DF$3:$DF$2300,0),COLUMN()-1),"")=0,"",IFERROR(INDEX((COPIA!$DA$3:$DE$2300),MATCH(ROWS(D$8:D604),COPIA!$DF$3:$DF$2300,0),COLUMN()-1),"")) | E604: =IF(IFERROR(INDEX((COPIA!$DA$3:$DE$2300),MATCH(ROWS(E$8:E604),COPIA!$DF$3:$DF$2300,0),COLUMN()-1),"")=0,"",IFERROR(INDEX((COPIA!$DA$3:$DE$2300),MATCH(ROWS(E$8:E604),COPIA!$DF$3:$DF$2300,0),COLUMN()-1),"")) | F604: =IF(IFERROR(INDEX((COPIA!$DA$3:$DE$2300),MATCH(ROWS(F$8:F604),COPIA!$DF$3:$DF$2300,0),COLUMN()-1),"")=0,"",IFERROR(INDEX((COPIA!$DA$3:$DE$2300),MATCH(ROWS(F$8:F604),COPIA!$DF$3:$DF$2300,0),COLUMN()-1),""))

Sheet SIT._CONTABILE
B1: SITUAZIONE CONTABILE
B2: OPZIONI DI VISUALIZZAZIONE | D2: =IF(COPIA!CH1=0,"",IF(COPIA!EV1=0,"I TOTALI SONO CORRETTAMENTE VISUALIZZATI",COPIA!ES1))
B3: PER TOTALI ED ECCEDENZE
A6: =COPIA!DU1 -> 3 | C6: =IF(INDIRECT(ADDRESS(8,6,,,"LIBRO_GIORNALE"))="","",INDIRECT(ADDRESS(8,6,,,"LIBRO_GIORNALE"))) | D6: =IF(INDIRECT(ADDRESS(8,7,,,"LIBRO_GIORNALE"))="","",INDIRECT(ADDRESS(8,7,,,"LIBRO_GIORNALE")))
A7: =MAX(COPIA!DQ3:DQ220)+5 -> 5 | C7: =IF(COPIA!CH1=0,"",IFERROR(CONCATENATE("Situazione contabile per ",LOWER(COPIA!$DQ$1)," al ",COPIA!DS2,"/",COPIA!DT2,"/",COPIA!DU2),""))
A8: =IF(A6=3,6,4) -> 6 | B8: =IF(COPIA!CH1=0,"","CODICI") | C8: =IF(COPIA!CH1=0,"","DENOMINAZIONE DEI CONTI") | D8: =IF(COPIA!CH1=0,"",IF(COPIA!$DU$1=3,MID(COPIA!$DQ$1,1,6),COPIA!$DQ$1)) | F8: =IF(COPIA!CH1=0,"",MID(COPIA!DQ1,11,10))
D9: =IF(COPIA!CH1=0,"","DARE") | E9: =IF(COPIA!CH1=0,"","AVERE") | F9: =IF(COPIA!CH1=0,"",IF(COPIA!$DQ$1="Totali ed eccedenze","DARE","")) | G9: =IF(COPIA!CH1=0,"",IF(COPIA!$DQ$1="Totali ed eccedenze","AVERE",""))
B10: =IFERROR(INDEX(PIANO_DEI_CONTI,MATCH(C10,DENOMINAZIONE,0),1),"") | C10: =IFERROR(CONCATENATE(COPIA!DR3,COPIA!DX3),"") | D10: =IF(IFERROR(IF(COPIA!DS3=0,"",VALUE(CONCATENATE(COPIA!DS3,COPIA!$DY3))),"")=0,"",IFERROR(IF(COPIA!DS3=0,"",VALUE(CONCATENATE(COPIA!DS3,COPIA!$DY3))),"")) | E10: =IF(IFERROR(IF(COPIA!DT3=0,"",VALUE(CONCATENATE(COPIA!DT3,COPIA!$DY3))),"")=0,"",IFERROR(IF(COPIA!DT3=0,"",VALUE(CONCATENATE(COPIA!DT3,COPIA!$DY3))),"")) | F10: =IF(IFERROR(IF(COPIA!DU3=0,"",VALUE(CONCATENATE(COPIA!DU3,COPIA!$DZ3))),"")=0,"",IFERROR(IF(COPIA!DU3=0,"",VALUE(CONCATENATE(COPIA!DU3,COPIA!$DZ3))),"")) | G10: =IF(IFERROR(IF(COPIA!DV3=0,"",VALUE(CONCATENATE(COPIA!DV3,COPIA!$DZ3))),"")=0,"",IFERROR(IF(COPIA!DV3=0,"",VALUE(CONCATENATE(COPIA!DV3,COPIA!$DZ3))),"")) | H10: =IFERROR(COPIA!DW3,"") -> 0
B11: =IFERROR(INDEX(PIANO_DEI_CONTI,MATCH(C11,DENOMINAZIONE,0),1),"") | C11: =IFERROR(CONCATENATE(COPIA!DR4,COPIA!DX4),"") | D11: =IF(IFERROR(IF(COPIA!DS4=0,"",VALUE(CONCATENATE(COPIA!DS4,COPIA!$DY4))),"")=0,"",IFERROR(IF(COPIA!DS4=0,"",VALUE(CONCATENATE(COPIA!DS4,COPIA!$DY4))),"")) | E11: =IF(IFERROR(IF(COPIA!DT4=0,"",VALUE(CONCATENATE(COPIA!DT4,COPIA!$DY4))),"")=0,"",IFERROR(IF(COPIA!DT4=0,"",VALUE(CONCATENATE(COPIA!DT4,COPIA!$DY4))),"")) | F11: =IF(IFERROR(IF(COPIA!DU4=0,"",VALUE(CONCATENATE(COPIA!DU4,COPIA!$DZ4))),"")=0,"",IFERROR(IF(COPIA!DU4=0,"",VALUE(CONCATENATE(COPIA!DU4,COPIA!$DZ4))),"")) | G11: =IF(IFERROR(IF(COPIA!DV4=0,"",VALUE(CONCATENATE(COPIA!DV4,COPIA!$DZ4))),"")=0,"",IFERROR(IF(COPIA!DV4=0,"",VALUE(CONCATENATE(COPIA!DV4,COPIA!$DZ4))),"")) | H11: =IFERROR(COPIA!DW4,"") -> 0
B12: =IFERROR(INDEX(PIANO_DEI_CONTI,MATCH(C12,DENOMINAZIONE,0),1),"") | C12: =IFERROR(CONCATENATE(COPIA!DR5,COPIA!DX5),"") | D12: =IF(IFERROR(IF(COPIA!DS5=0,"",VALUE(CONCATENATE(COPIA!DS5,COPIA!$DY5))),"")=0,"",IFERROR(IF(COPIA!DS5=0,"",VALUE(CONCATENATE(COPIA!DS5,COPIA!$DY5))),"")) | E12: =IF(IFERROR(IF(COPIA!DT5=0,"",VALUE(CONCATENATE(COPIA!DT5,COPIA!$DY5))),"")=0,"",IFERROR(IF(COPIA!DT5=0,"",VALUE(CONCATENATE(COPIA!DT5,COPIA!$DY5))),"")) | F12: =IF(IFERROR(IF(COPIA!DU5=0,"",VALUE(CONCATENATE(COPIA!DU5,COPIA!$DZ5))),"")=0,"",IFERROR(IF(COPIA!DU5=0,"",VALUE(CONCATENATE(COPIA!DU5,COPIA!$DZ5))),"")) | G12: =IF(IFERROR(IF(COPIA!DV5=0,"",VALUE(CONCATENATE(COPIA!DV5,COPIA!$DZ5))),"")=0,"",IFERROR(IF(COPIA!DV5=0,"",VALUE(CONCATENATE(COPIA!DV5,COPIA!$DZ5))),"")) | H12: =IFERROR(COPIA!DW5,"") -> 0
B13: =IFERROR(INDEX(PIANO_DEI_CONTI,MATCH(C13,DENOMINAZIONE,0),1),"") | C13: =IFERROR(CONCATENATE(COPIA!DR6,COPIA!DX6),"") | D13: =IF(IFERROR(IF(COPIA!DS6=0,"",VALUE(CONCATENATE(COPIA!DS6,COPIA!$DY6))),"")=0,"",IFERROR(IF(COPIA!DS6=0,"",VALUE(CONCATENATE(COPIA!DS6,COPIA!$DY6))),"")) | E13: =IF(IFERROR(IF(COPIA!DT6=0,"",VALUE(CONCATENATE(COPIA!DT6,COPIA!$DY6))),"")=0,"",IFERROR(IF(COPIA!DT6=0,"",VALUE(CONCATENATE(COPIA!DT6,COPIA!$DY6))),"")) | F13: =IF(IFERROR(IF(COPIA!DU6=0,"",VALUE(CONCATENATE(COPIA!DU6,COPIA!$DZ6))),"")=0,"",IFERROR(IF(COPIA!DU6=0,"",VALUE(CONCATENATE(COPIA!DU6,COPIA!$DZ6))),"")) | G13: =IF(IFERROR(IF(COPIA!DV6=0,"",VALUE(CONCATENATE(COPIA!DV6,COPIA!$DZ6))),"")=0,"",IFERROR(IF(COPIA!DV6=0,"",VALUE(CONCATENATE(COPIA!DV6,COPIA!$DZ6))),"")) | H13: =IFERROR(COPIA!DW6,"") -> 0
B14: =IFERROR(INDEX(PIANO_DEI_CONTI,MATCH(C14,DENOMINAZIONE,0),1),"") | C14: =IFERROR(CONCATENATE(COPIA!DR7,COPIA!DX7),"") | D14: =IF(IFERROR(IF(COPIA!DS7=0,"",VALUE(CONCATENATE(COPIA!DS7,COPIA!$DY7))),"")=0,"",IFERROR(IF(COPIA!DS7=0,"",VALUE(CONCATENATE(COPIA!DS7,COPIA!$DY7))),"")) | E14: =IF(IFERROR(IF(COPIA!DT7=0,"",VALUE(CONCATENATE(COPIA!DT7,COPIA!$DY7))),"")=0,"",IFERROR(IF(COPIA!DT7=0,"",VALUE(CONCATENATE(COPIA!DT7,COPIA!$DY7))),"")) | F14: =IF(IFERROR(IF(COPIA!DU7=0,"",VALUE(CONCATENATE(COPIA!DU7,COPIA!$DZ7))),"")=0,"",IFERROR(IF(COPIA!DU7=0,"",VALUE(CONCATENATE(COPIA!DU7,COPIA!$DZ7))),"")) | G14: =IF(IFERROR(IF(COPIA!DV7=0,"",VALUE(CONCATENATE(COPIA!DV7,COPIA!$DZ7))),"")=0,"",IFERROR(IF(COPIA!DV7=0,"",VALUE(CONCATENATE(COPIA!DV7,COPIA!$DZ7))),"")) | H14: =IFERROR(COPIA!DW7,"") -> 0
B15: =IFERROR(INDEX(PIANO_DEI_CONTI,MATCH(C15,DENOMINAZIONE,0),1),"") | C15: =IFERROR(CONCATENATE(COPIA!DR8,COPIA!DX8),"") | D15: =IF(IFERROR(IF(COPIA!DS8=0,"",VALUE(CONCATENATE(COPIA!DS8,COPIA!$DY8))),"")=0,"",IFERROR(IF(COPIA!DS8=0,"",VALUE(CONCATENATE(COPIA!DS8,COPIA!$DY8))),"")) | E15: =IF(IFERROR(IF(COPIA!DT8=0,"",VALUE(CONCATENATE(COPIA!DT8,COPIA!$DY8))),"")=0,"",IFERROR(IF(COPIA!DT8=0,"",VALUE(CONCATENATE(COPIA!DT8,COPIA!$DY8))),"")) | F15: =IF(IFERROR(IF(COPIA!DU8=0,"",VALUE(CONCATENATE(COPIA!DU8,COPIA!$DZ8))),"")=0,"",IFERROR(IF(COPIA!DU8=0,"",VALUE(CONCATENATE(COPIA!DU8,COPIA!$DZ8))),"")) | G15: =IF(IFERROR(IF(COPIA!DV8=0,"",VALUE(CONCATENATE(COPIA!DV8,COPIA!$DZ8))),"")=0,"",IFERROR(IF(COPIA!DV8=0,"",VALUE(CONCATENATE(COPIA!DV8,COPIA!$DZ8))),"")) | H15: =IFERROR(COPIA!DW8,"") -> 0
B16: =IFERROR(INDEX(PIANO_DEI_CONTI,MATCH(C16,DENOMINAZIONE,0),1),"") | C16: =IFERROR(CONCATENATE(COPIA!DR9,COPIA!DX9),"") | D16: =IF(IFERROR(IF(COPIA!DS9=0,"",VALUE(CONCATENATE(COPIA!DS9,COPIA!$DY9))),"")=0,"",IFERROR(IF(COPIA!DS9=0,"",VALUE(CONCATENATE(COPIA!DS9,COPIA!$DY9))),"")) | E16: =IF(IFERROR(IF(COPIA!DT9=0,"",VALUE(CONCATENATE(COPIA!DT9,COPIA!$DY9))),"")=0,"",IFERROR(IF(COPIA!DT9=0,"",VALUE(CONCATENATE(COPIA!DT9,COPIA!$DY9))),"")) | F16: =IF(IFERROR(IF(COPIA!DU9=0,"",VALUE(CONCATENATE(COPIA!DU9,COPIA!$DZ9))),"")=0,"",IFERROR(IF(COPIA!DU9=0,"",VALUE(CONCATENATE(COPIA!DU9,COPIA!$DZ9))),"")) | G16: =IF(IFERROR(IF(COPIA!DV9=0,"",VALUE(CONCATENATE(COPIA!DV9,COPIA!$DZ9))),"")=0,"",IFERROR(IF(COPIA!DV9=0,"",VALUE(CONCATENATE(COPIA!DV9,COPIA!$DZ9))),"")) | H16: =IFERROR(COPIA!DW9,"") -> 0
B17: =IFERROR(INDEX(PIANO_DEI_CONTI,MATCH(C17,DENOMINAZIONE,0),1),"") | C17: =IFERROR(CONCATENATE(COPIA!DR10,COPIA!DX10),"") | D17: =IF(IFERROR(IF(COPIA!DS10=0,"",VALUE(CONCATENATE(COPIA!DS10,COPIA!$DY10))),"")=0,"",IFERROR(IF(COPIA!DS10=0,"",VALUE(CONCATENATE(COPIA!DS10,COPIA!$DY10))),"")) | E17: =IF(IFERROR(IF(COPIA!DT10=0,"",VALUE(CONCATENATE(COPIA!DT10,COPIA!$DY10))),"")=0,"",IFERROR(IF(COPIA!DT10=0,"",VALUE(CONCATENATE(COPIA!DT10,COPIA!$DY10))),"")) | F17: =IF(IFERROR(IF(COPIA!DU10=0,"",VALUE(CONCATENATE(COPIA!DU10,COPIA!$DZ10))),"")=0,"",IFERROR(IF(COPIA!DU10=0,"",VALUE(CONCATENATE(COPIA!DU10,COPIA!$DZ10))),"")) | G17: =IF(IFERROR(IF(COPIA!DV10=0,"",VALUE(CONCATENATE(COPIA!DV10,COPIA!$DZ10))),"")=0,"",IFERROR(IF(COPIA!DV10=0,"",VALUE(CONCATENATE(COPIA!DV10,COPIA!$DZ10))),"")) | H17: =IFERROR(COPIA!DW10,"") -> 0
B18: =IFERROR(INDEX(PIANO_DEI_CONTI,MATCH(C18,DENOMINAZIONE,0),1),"") | C18: =IFERROR(CONCATENATE(COPIA!DR11,COPIA!DX11),"") | D18: =IF(IFERROR(IF(COPIA!DS11=0,"",VALUE(CONCATENATE(COPIA!DS11,COPIA!$DY11))),"")=0,"",IFERROR(IF(COPIA!DS11=0,"",VALUE(CONCATENATE(COPIA!DS11,COPIA!$DY11))),"")) | E18: =IF(IFERROR(IF(COPIA!DT11=0,"",VALUE(CONCATENATE(COPIA!DT11,COPIA!$DY11))),"")=0,"",IFERROR(IF(COPIA!DT11=0,"",VALUE(CONCATENATE(COPIA!DT11,COPIA!$DY11))),"")) | F18: =IF(IFERROR(IF(COPIA!DU11=0,"",VALUE(CONCATENATE(COPIA!DU11,COPIA!$DZ11))),"")=0,"",IFERROR(IF(COPIA!DU11=0,"",VALUE(CONCATENATE(COPIA!DU11,COPIA!$DZ11))),"")) | G18: =IF(IFERROR(IF(COPIA!DV11=0,"",VALUE(CONCATENATE(COPIA!DV11,COPIA!$DZ11))),"")=0,"",IFERROR(IF(COPIA!DV11=0,"",VALUE(CONCATENATE(COPIA!DV11,COPIA!$DZ11))),"")) | H18: =IFERROR(COPIA!DW11,"") -> 0
B19: =IFERROR(INDEX(PIANO_DEI_CONTI,MATCH(C19,DENOMINAZIONE,0),1),"") | C19: =IFERROR(CONCATENATE(COPIA!DR12,COPIA!DX12),"") | D19: =IF(IFERROR(IF(COPIA!DS12=0,"",VALUE(CONCATENATE(COPIA!DS12,COPIA!$DY12))),"")=0,"",IFERROR(IF(COPIA!DS12=0,"",VALUE(CONCATENATE(COPIA!DS12,COPIA!$DY12))),"")) | E19: =IF(IFERROR(IF(COPIA!DT12=0,"",VALUE(CONCATENATE(COPIA!DT12,COPIA!$DY12))),"")=0,"",IFERROR(IF(COPIA!DT12=0,"",VALUE(CONCATENATE(COPIA!DT12,COPIA!$DY12))),"")) | F19: =IF(IFERROR(IF(COPIA!DU12=0,"",VALUE(CONCATENATE(COPIA!DU12,COPIA!$DZ12))),"")=0,"",IFERROR(IF(COPIA!DU12=0,"",VALUE(CONCATENATE(COPIA!DU12,COPIA!$DZ12))),"")) | G19: =IF(IFERROR(IF(COPIA!DV12=0,"",VALUE(CONCATENATE(COPIA!DV12,COPIA!$DZ12))),"")=0,"",IFERROR(IF(COPIA!DV12=0,"",VALUE(CONCATENATE(COPIA!DV12,COPIA!$DZ12))),"")) | H19: =IFERROR(COPIA!DW12,"") -> 0
B20: =IFERROR(INDEX(PIANO_DEI_CONTI,MATCH(C20,DENOMINAZIONE,0),1),"") | C20: =IFERROR(CONCATENATE(COPIA!DR13,COPIA!DX13),"") | D20: =IF(IFERROR(IF(COPIA!DS13=0,"",VALUE(CONCATENATE(COPIA!DS13,COPIA!$DY13))),"")=0,"",IFERROR(IF(COPIA!DS13=0,"",VALUE(CONCATENATE(COPIA!DS13,COPIA!$DY13))),"")) | E20: =IF(IFERROR(IF(COPIA!DT13=0,"",VALUE(CONCATENATE(COPIA!DT13,COPIA!$DY13))),"")=0,"",IFERROR(IF(COPIA!DT13=0,"",VALUE(CONCATENATE(COPIA!DT13,COPIA!$DY13))),"")) | F20: =IF(IFERROR(IF(COPIA!DU13=0,"",VALUE(CONCATENATE(COPIA!DU13,COPIA!$DZ13))),"")=0,"",IFERROR(IF(COPIA!DU13=0,"",VALUE(CONCATENATE(COPIA!DU13,COPIA!$DZ13))),"")) | G20: =IF(IFERROR(IF(COPIA!DV13=0,"",VALUE(CONCATENATE(COPIA!DV13,COPIA!$DZ13))),"")=0,"",IFERROR(IF(COPIA!DV13=0,"",VALUE(CONCATENATE(COPIA!DV13,COPIA!$DZ13))),"")) | H20: =IFERROR(COPIA!DW13,"") -> 0
B21: =IFERROR(INDEX(PIANO_DEI_CONTI,MATCH(C21,DENOMINAZIONE,0),1),"") | C21: =IFERROR(CONCATENATE(COPIA!DR14,COPIA!DX14),"") | D21: =IF(IFERROR(IF(COPIA!DS14=0,"",VALUE(CONCATENATE(COPIA!DS14,COPIA!$DY14))),"")=0,"",IFERROR(IF(COPIA!DS14=0,"",VALUE(CONCATENATE(COPIA!DS14,COPIA!$DY14))),"")) | E21: =IF(IFERROR(IF(COPIA!DT14=0,"",VALUE(CONCATENATE(COPIA!DT14,COPIA!$DY14))),"")=0,"",IFERROR(IF(COPIA!DT14=0,"",VALUE(CONCATENATE(COPIA!DT14,COPIA!$DY14))),"")) | F21: =IF(IFERROR(IF(COPIA!DU14=0,"",VALUE(CONCATENATE(COPIA!DU14,COPIA!$DZ14))),"")=0,"",IFERROR(IF(COPIA!DU14=0,"",VALUE(CONCATENATE(COPIA!DU14,COPIA!$DZ14))),"")) | G21: =IF(IFERROR(IF(COPIA!DV14=0,"",VALUE(CONCATENATE(COPIA!DV14,COPIA!$DZ14))),"")=0,"",IFERROR(IF(COPIA!DV14=0,"",VALUE(CONCATENATE(COPIA!DV14,COPIA!$DZ14))),"")) | H21: =IFERROR(COPIA!DW14,"") -> 0
... B227: =IFERROR(INDEX(PIANO_DEI_CONTI,MATCH(C227,DENOMINAZIONE,0),1),"") | C227: =IFERROR(CONCATENATE(COPIA!DR220,COPIA!DX220),"") | D227: =IF(IFERROR(IF(COPIA!DS220=0,"",VALUE(CONCATENATE(COPIA!DS220,COPIA!$DY220))),"")=0,"",IFERROR(IF(COPIA!DS220=0,"",VALUE(CONCATENATE(COPIA!DS220,COPIA!$DY220))),"")) | E227: =IF(IFERROR(IF(COPIA!DT220=0,"",VALUE(CONCATENATE(COPIA!DT220,COPIA!$DY220))),"")=0,"",IFERROR(IF(COPIA!DT220=0,"",VALUE(CONCATENATE(COPIA!DT220,COPIA!$DY220))),"")) | F227: =IF(IFERROR(IF(COPIA!DU220=0,"",VALUE(CONCATENATE(COPIA!DU220,COPIA!$DZ220))),"")=0,"",IFERROR(IF(COPIA!DU220=0,"",VALUE(CONCATENATE(COPIA!DU220,COPIA!$DZ220))),"")) | G227: =IF(IFERROR(IF(COPIA!DV220=0,"",VALUE(CONCATENATE(COPIA!DV220,COPIA!$DZ220))),"")=0,"",IFERROR(IF(COPIA!DV220=0,"",VALUE(CONCATENATE(COPIA!DV220,COPIA!$DZ220))),"")) | H227: =IFERROR(COPIA!DW220,"") -> 0

Sheet SIT.PATR._SIT.ECON.
B1: SITUAZIONE CONTABILE PER DESTINAZIONE
B2: VISUALIZZA IL RISULTATO ECONOMICO | D2: =IF(COPIA!CH1=0,"",COPIA!ES1) | H2: OPZIONI DI STAMPA
B3: =IF(COPIA!CH1=0,"",COPIA!EU37) | H3: RIGHE TRA I PROSPETTI
B4: =IF(INDIRECT(ADDRESS(8,6,,,"LIBRO_GIORNALE"))="","",INDIRECT(ADDRESS(8,6,,,"LIBRO_GIORNALE"))) | D4: =IF(INDIRECT(ADDRESS(8,7,,,"LIBRO_GIORNALE"))="","",INDIRECT(ADDRESS(8,7,,,"LIBRO_GIORNALE")))
B5: =IF(COPIA!CH1=0,"",CONCATENATE("Situazione contabile per destinazione ","al", " ",COPIA!DS2,"/",COPIA!DT2,"/",COPIA!DU2))
B6: =IF(COPIA!CH1=0,"","SITUAZIONE PATRIMONIALE")
B7: =IF(COPIA!CH1=0,"","ATTIVITÀ") | D7: =IF(COPIA!CH1=0,"","PASSIVITÀ E NETTO")
B8: =IF((ROW())>=MAX(COPIA!$BV$2,COPIA!$BW$2)+COPIA!$CB$2,CONCATENATE((INDIRECT(ADDRESS(ROW()-MAX(COPIA!$BV$2,COPIA!$BW$2)-COPIA!$CC$2,87,4,,"COPIA"))),INDIRECT(ADDRESS(ROW()-MAX(COPIA!$BV$2,COPIA!$BW$2)-COPIA!$CC$2,96,4,,"COPIA"))),IF(AND(COPIA!$EO$1=TRUE,UPPER(COPIA!BZ3)="SALDO ECONOMICO NEGATIVO"),SUBSTITUTE(COPIA!BZ3,"SALDO ECONOMICO NEGATIVO","PERDITA D'ESERCIZIO"),UPPER(COPIA!BZ3))) | C8: =IFERROR(VALUE(IF((ROW())>=MAX(COPIA!$BV$2,COPIA!$BW$2)+COPIA!$CB$2,CONCATENATE((INDIRECT(ADDRESS(ROW()-MAX(COPIA!$BV$2,COPIA!$BW$2)-COPIA!$CC$2,88,4,,"COPIA"))),INDIRECT(ADDRESS(ROW()-MAX(COPIA!$BV$2,COPIA!$BW$2)-COPIA!$CC$2,137,4,,"COPIA"))),UPPER(COPIA!CA3))),"") -> 0 | D8: =IF((ROW())>=MAX(COPIA!$BV$2,COPIA!$BW$2)+COPIA!$CB$2,CONCATENATE((INDIRECT(ADDRESS(ROW()-MAX(COPIA!$BV$2,COPIA!$BW$2)-COPIA!$CC$2,138,4,,"COPIA"))),INDIRECT(ADDRESS(ROW()-MAX(COPIA!$BV$2,COPIA!$BW$2)-COPIA!$CC$2,135,4,,"COPIA"))),IF(AND($EO$4=TRUE,UPPER(COPIA!CB3)="SALDO ECONOMICO POSITIVO"),SUBSTITUTE(COPIA!CB3,"SALDO ECONOMICO POSITIVO","UTILE D'ESERCIZIO"),UPPER(COPIA!CB3))) | E8: =IFERROR(VALUE(IF((ROW())>=MAX(COPIA!$BV$2,COPIA!$BW$2)+COPIA!$CB$2,CONCATENATE((INDIRECT(ADDRESS(ROW()-MAX(COPIA!$BV$2,COPIA!$BW$2)-COPIA!$CC$2,136,4,,"COPIA"))),INDIRECT(ADDRESS(ROW()-MAX(COPIA!$BV$2,COPIA!$BW$2)-COPIA!$CC$2,95,4,,"COPIA"))),UPPER(COPIA!CC3))),"")
B9: =IF((ROW())>=MAX(COPIA!$BV$2,COPIA!$BW$2)+COPIA!$CB$2,CONCATENATE((INDIRECT(ADDRESS(ROW()-MAX(COPIA!$BV$2,COPIA!$BW$2)-COPIA!$CC$2,87,4,,"COPIA"))),INDIRECT(ADDRESS(ROW()-MAX(COPIA!$BV$2,COPIA!$BW$2)-COPIA!$CC$2,96,4,,"COPIA"))),IF(AND(COPIA!$EO$1=TRUE,UPPER(COPIA!BZ4)="SALDO ECONOMICO NEGATIVO"),SUBSTITUTE(COPIA!BZ4,"SALDO ECONOMICO NEGATIVO","PERDITA D'ESERCIZIO"),UPPER(COPIA!BZ4))) | C9: =IFERROR(VALUE(IF((ROW())>=MAX(COPIA!$BV$2,COPIA!$BW$2)+COPIA!$CB$2,CONCATENATE((INDIRECT(ADDRESS(ROW()-MAX(COPIA!$BV$2,COPIA!$BW$2)-COPIA!$CC$2,88,4,,"COPIA"))),INDIRECT(ADDRESS(ROW()-MAX(COPIA!$BV$2,COPIA!$BW$2)-COPIA!$CC$2,137,4,,"COPIA"))),UPPER(COPIA!CA4))),"") -> 0 | D9: =IF((ROW())>=MAX(COPIA!$BV$2,COPIA!$BW$2)+COPIA!$CB$2,CONCATENATE((INDIRECT(ADDRESS(ROW()-MAX(COPIA!$BV$2,COPIA!$BW$2)-COPIA!$CC$2,138,4,,"COPIA"))),INDIRECT(ADDRESS(ROW()-MAX(COPIA!$BV$2,COPIA!$BW$2)-COPIA!$CC$2,135,4,,"COPIA"))),IF(AND($EO$4=TRUE,UPPER(COPIA!CB4)="SALDO ECONOMICO POSITIVO"),SUBSTITUTE(COPIA!CB4,"SALDO ECONOMICO POSITIVO","UTILE D'ESERCIZIO"),UPPER(COPIA!CB4))) | E9: =IFERROR(VALUE(IF((ROW())>=MAX(COPIA!$BV$2,COPIA!$BW$2)+COPIA!$CB$2,CONCATENATE((INDIRECT(ADDRESS(ROW()-MAX(COPIA!$BV$2,COPIA!$BW$2)-COPIA!$CC$2,136,4,,"COPIA"))),INDIRECT(ADDRESS(ROW()-MAX(COPIA!$BV$2,COPIA!$BW$2)-COPIA!$CC$2,95,4,,"COPIA"))),UPPER(COPIA!CC4))),"")
B10: =IF((ROW())>=MAX(COPIA!$BV$2,COPIA!$BW$2)+COPIA!$CB$2,CONCATENATE((INDIRECT(ADDRESS(ROW()-MAX(COPIA!$BV$2,COPIA!$BW$2)-COPIA!$CC$2,87,4,,"COPIA"))),INDIRECT(ADDRESS(ROW()-MAX(COPIA!$BV$2,COPIA!$BW$2)-COPIA!$CC$2,96,4,,"COPIA"))),IF(AND(COPIA!$EO$1=TRUE,UPPER(COPIA!BZ5)="SALDO ECONOMICO NEGATIVO"),SUBSTITUTE(COPIA!BZ5,"SALDO ECONOMICO NEGATIVO","PERDITA D'ESERCIZIO"),UPPER(COPIA!BZ5))) | C10: =IFERROR(VALUE(IF((ROW())>=MAX(COPIA!$BV$2,COPIA!$BW$2)+COPIA!$CB$2,CONCATENATE((INDIRECT(ADDRESS(ROW()-MAX(COPIA!$BV$2,COPIA!$BW$2)-COPIA!$CC$2,88,4,,"COPIA"))),INDIRECT(ADDRESS(ROW()-MAX(COPIA!$BV$2,COPIA!$BW$2)-COPIA!$CC$2,137,4,,"COPIA"))),UPPER(COPIA!CA5))),"") -> 0 | D10: =IF((ROW())>=MAX(COPIA!$BV$2,COPIA!$BW$2)+COPIA!$CB$2,CONCATENATE((INDIRECT(ADDRESS(ROW()-MAX(COPIA!$BV$2,COPIA!$BW$2)-COPIA!$CC$2,138,4,,"COPIA"))),INDIRECT(ADDRESS(ROW()-MAX(COPIA!$BV$2,COPIA!$BW$2)-COPIA!$CC$2,135,4,,"COPIA"))),IF(AND($EO$4=TRUE,UPPER(COPIA!CB5)="SALDO ECONOMICO POSITIVO"),SUBSTITUTE(COPIA!CB5,"SALDO ECONOMICO POSITIVO","UTILE D'ESERCIZIO"),UPPER(COPIA!CB5))) | E10: =IFERROR(VALUE(IF((ROW())>=MAX(COPIA!$BV$2,COPIA!$BW$2)+COPIA!$CB$2,CONCATENATE((INDIRECT(ADDRESS(ROW()-MAX(COPIA!$BV$2,COPIA!$BW$2)-COPIA!$CC$2,136,4,,"COPIA"))),INDIRECT(ADDRESS(ROW()-MAX(COPIA!$BV$2,COPIA!$BW$2)-COPIA!$CC$2,95,4,,"COPIA"))),UPPER(COPIA!CC5))),"")
B11: =IF((ROW())>=MAX(COPIA!$BV$2,COPIA!$BW$2)+COPIA!$CB$2,CONCATENATE((INDIRECT(ADDRESS(ROW()-MAX(COPIA!$BV$2,COPIA!$BW$2)-COPIA!$CC$2,87,4,,"COPIA"))),INDIRECT(ADDRESS(ROW()-MAX(COPIA!$BV$2,COPIA!$BW$2)-COPIA!$CC$2,96,4,,"COPIA"))),IF(AND(COPIA!$EO$1=TRUE,UPPER(COPIA!BZ6)="SALDO ECONOMICO NEGATIVO"),SUBSTITUTE(COPIA!BZ6,"SALDO ECONOMICO NEGATIVO","PERDITA D'ESERCIZIO"),UPPER(COPIA!BZ6))) | C11: =IFERROR(VALUE(IF((ROW())>=MAX(COPIA!$BV$2,COPIA!$BW$2)+COPIA!$CB$2,CONCATENATE((INDIRECT(ADDRESS(ROW()-MAX(COPIA!$BV$2,COPIA!$BW$2)-COPIA!$CC$2,88,4,,"COPIA"))),INDIRECT(ADDRESS(ROW()-MAX(COPIA!$BV$2,COPIA!$BW$2)-COPIA!$CC$2,137,4,,"COPIA"))),UPPER(COPIA!CA6))),"") -> 0 | D11: =IF((ROW())>=MAX(COPIA!$BV$2,COPIA!$BW$2)+COPIA!$CB$2,CONCATENATE((INDIRECT(ADDRESS(ROW()-MAX(COPIA!$BV$2,COPIA!$BW$2)-COPIA!$CC$2,138,4,,"COPIA"))),INDIRECT(ADDRESS(ROW()-MAX(COPIA!$BV$2,COPIA!$BW$2)-COPIA!$CC$2,135,4,,"COPIA"))),IF(AND($EO$4=TRUE,UPPER(COPIA!CB6)="SALDO ECONOMICO POSITIVO"),SUBSTITUTE(COPIA!CB6,"SALDO ECONOMICO POSITIVO","UTILE D'ESERCIZIO"),UPPER(COPIA!CB6))) | E11: =IFERROR(VALUE(IF((ROW())>=MAX(COPIA!$BV$2,COPIA!$BW$2)+COPIA!$CB$2,CONCATENATE((INDIRECT(ADDRESS(ROW()-MAX(COPIA!$BV$2,COPIA!$BW$2)-COPIA!$CC$2,136,4,,"COPIA"))),INDIRECT(ADDRESS(ROW()-MAX(COPIA!$BV$2,COPIA!$BW$2)-COPIA!$CC$2,95,4,,"COPIA"))),UPPER(COPIA!CC6))),"")
B12: =IF((ROW())>=MAX(COPIA!$BV$2,COPIA!$BW$2)+COPIA!$CB$2,CONCATENATE((INDIRECT(ADDRESS(ROW()-MAX(COPIA!$BV$2,COPIA!$BW$2)-COPIA!$CC$2,87,4,,"COPIA"))),INDIRECT(ADDRESS(ROW()-MAX(COPIA!$BV$2,COPIA!$BW$2)-COPIA!$CC$2,96,4,,"COPIA"))),IF(AND(COPIA!$EO$1=TRUE,UPPER(COPIA!BZ7)="SALDO ECONOMICO NEGATIVO"),SUBSTITUTE(COPIA!BZ7,"SALDO ECONOMICO NEGATIVO","PERDITA D'ESERCIZIO"),UPPER(COPIA!BZ7))) | C12: =IFERROR(VALUE(IF((ROW())>=MAX(COPIA!$BV$2,COPIA!$BW$2)+COPIA!$CB$2,CONCATENATE((INDIRECT(ADDRESS(ROW()-MAX(COPIA!$BV$2,COPIA!$BW$2)-COPIA!$CC$2,88,4,,"COPIA"))),INDIRECT(ADDRESS(ROW()-MAX(COPIA!$BV$2,COPIA!$BW$2)-COPIA!$CC$2,137,4,,"COPIA"))),UPPER(COPIA!CA7))),"") -> 0 | D12: =IF((ROW())>=MAX(COPIA!$BV$2,COPIA!$BW$2)+COPIA!$CB$2,CONCATENATE((INDIRECT(ADDRESS(ROW()-MAX(COPIA!$BV$2,COPIA!$BW$2)-COPIA!$CC$2,138,4,,"COPIA"))),INDIRECT(ADDRESS(ROW()-MAX(COPIA!$BV$2,COPIA!$BW$2)-COPIA!$CC$2,135,4,,"COPIA"))),IF(AND($EO$4=TRUE,UPPER(COPIA!CB7)="SALDO ECONOMICO POSITIVO"),SUBSTITUTE(COPIA!CB7,"SALDO ECONOMICO POSITIVO","UTILE D'ESERCIZIO"),UPPER(COPIA!CB7))) | E12: =IFERROR(VALUE(IF((ROW())>=MAX(COPIA!$BV$2,COPIA!$BW$2)+COPIA!$CB$2,CONCATENATE((INDIRECT(ADDRESS(ROW()-MAX(COPIA!$BV$2,COPIA!$BW$2)-COPIA!$CC$2,136,4,,"COPIA"))),INDIRECT(ADDRESS(ROW()-MAX(COPIA!$BV$2,COPIA!$BW$2)-COPIA!$CC$2,95,4,,"COPIA"))),UPPER(COPIA!CC7))),"")
B13: =IF((ROW())>=MAX(COPIA!$BV$2,COPIA!$BW$2)+COPIA!$CB$2,CONCATENATE((INDIRECT(ADDRESS(ROW()-MAX(COPIA!$BV$2,COPIA!$BW$2)-COPIA!$CC$2,87,4,,"COPIA"))),INDIRECT(ADDRESS(ROW()-MAX(COPIA!$BV$2,COPIA!$BW$2)-COPIA!$CC$2,96,4,,"COPIA"))),IF(AND(COPIA!$EO$1=TRUE,UPPER(COPIA!BZ8)="SALDO ECONOMICO NEGATIVO"),SUBSTITUTE(COPIA!BZ8,"SALDO ECONOMICO NEGATIVO","PERDITA D'ESERCIZIO"),UPPER(COPIA!BZ8))) | C13: =IFERROR(VALUE(IF((ROW())>=MAX(COPIA!$BV$2,COPIA!$BW$2)+COPIA!$CB$2,CONCATENATE((INDIRECT(ADDRESS(ROW()-MAX(COPIA!$BV$2,COPIA!$BW$2)-COPIA!$CC$2,88,4,,"COPIA"))),INDIRECT(ADDRESS(ROW()-MAX(COPIA!$BV$2,COPIA!$BW$2)-COPIA!$CC$2,137,4,,"COPIA"))),UPPER(COPIA!CA8))),"") | D13: =IF((ROW())>=MAX(COPIA!$BV$2,COPIA!$BW$2)+COPIA!$CB$2,CONCATENATE((INDIRECT(ADDRESS(ROW()-MAX(COPIA!$BV$2,COPIA!$BW$2)-COPIA!$CC$2,138,4,,"COPIA"))),INDIRECT(ADDRESS(ROW()-MAX(COPIA!$BV$2,COPIA!$BW$2)-COPIA!$CC$2,135,4,,"COPIA"))),IF(AND($EO$4=TRUE,UPPER(COPIA!CB8)="SALDO ECONOMICO POSITIVO"),SUBSTITUTE(COPIA!CB8,"SALDO ECONOMICO POSITIVO","UTILE D'ESERCIZIO"),UPPER(COPIA!CB8))) | E13: =IFERROR(VALUE(IF((ROW())>=MAX(COPIA!$BV$2,COPIA!$BW$2)+COPIA!$CB$2,CONCATENATE((INDIRECT(ADDRESS(ROW()-MAX(COPIA!$BV$2,COPIA!$BW$2)-COPIA!$CC$2,136,4,,"COPIA"))),INDIRECT(ADDRESS(ROW()-MAX(COPIA!$BV$2,COPIA!$BW$2)-COPIA!$CC$2,95,4,,"COPIA"))),UPPER(COPIA!CC8))),"")
B14: =IF((ROW())>=MAX(COPIA!$BV$2,COPIA!$BW$2)+COPIA!$CB$2,CONCATENATE((INDIRECT(ADDRESS(ROW()-MAX(COPIA!$BV$2,COPIA!$BW$2)-COPIA!$CC$2,87,4,,"COPIA"))),INDIRECT(ADDRESS(ROW()-MAX(COPIA!$BV$2,COPIA!$BW$2)-COPIA!$CC$2,96,4,,"COPIA"))),IF(AND(COPIA!$EO$1=TRUE,UPPER(COPIA!BZ9)="SALDO ECONOMICO NEGATIVO"),SUBSTITUTE(COPIA!BZ9,"SALDO ECONOMICO NEGATIVO","PERDITA D'ESERCIZIO"),UPPER(COPIA!BZ9))) | C14: =IFERROR(VALUE(IF((ROW())>=MAX(COPIA!$BV$2,COPIA!$BW$2)+COPIA!$CB$2,CONCATENATE((INDIRECT(ADDRESS(ROW()-MAX(COPIA!$BV$2,COPIA!$BW$2)-COPIA!$CC$2,88,4,,"COPIA"))),INDIRECT(ADDRESS(ROW()-MAX(COPIA!$BV$2,COPIA!$BW$2)-COPIA!$CC$2,137,4,,"COPIA"))),UPPER(COPIA!CA9))),"") | D14: =IF((ROW())>=MAX(COPIA!$BV$2,COPIA!$BW$2)+COPIA!$CB$2,CONCATENATE((INDIRECT(ADDRESS(ROW()-MAX(COPIA!$BV$2,COPIA!$BW$2)-COPIA!$CC$2,138,4,,"COPIA"))),INDIRECT(ADDRESS(ROW()-MAX(COPIA!$BV$2,COPIA!$BW$2)-COPIA!$CC$2,135,4,,"COPIA"))),IF(AND($EO$4=TRUE,UPPER(COPIA!CB9)="SALDO ECONOMICO POSITIVO"),SUBSTITUTE(COPIA!CB9,"SALDO ECONOMICO POSITIVO","UTILE D'ESERCIZIO"),UPPER(COPIA!CB9))) | E14: =IFERROR(VALUE(IF((ROW())>=MAX(COPIA!$BV$2,COPIA!$BW$2)+COPIA!$CB$2,CONCATENATE((INDIRECT(ADDRESS(ROW()-MAX(COPIA!$BV$2,COPIA!$BW$2)-COPIA!$CC$2,136,4,,"COPIA"))),INDIRECT(ADDRESS(ROW()-MAX(COPIA!$BV$2,COPIA!$BW$2)-COPIA!$CC$2,95,4,,"COPIA"))),UPPER(COPIA!CC9))),"")
B15: =IF((ROW())>=MAX(COPIA!$BV$2,COPIA!$BW$2)+COPIA!$CB$2,CONCATENATE((INDIRECT(ADDRESS(ROW()-MAX(COPIA!$BV$2,COPIA!$BW$2)-COPIA!$CC$2,87,4,,"COPIA"))),INDIRECT(ADDRESS(ROW()-MAX(COPIA!$BV$2,COPIA!$BW$2)-COPIA!$CC$2,96,4,,"COPIA"))),IF(AND(COPIA!$EO$1=TRUE,UPPER(COPIA!BZ10)="SALDO ECONOMICO NEGATIVO"),SUBSTITUTE(COPIA!BZ10,"SALDO ECONOMICO NEGATIVO","PERDITA D'ESERCIZIO"),UPPER(COPIA!BZ10))) | C15: =IFERROR(VALUE(IF((ROW())>=MAX(COPIA!$BV$2,COPIA!$BW$2)+COPIA!$CB$2,CONCATENATE((INDIRECT(ADDRESS(ROW()-MAX(COPIA!$BV$2,COPIA!$BW$2)-COPIA!$CC$2,88,4,,"COPIA"))),INDIRECT(ADDRESS(ROW()-MAX(COPIA!$BV$2,COPIA!$BW$2)-COPIA!$CC$2,137,4,,"COPIA"))),UPPER(COPIA!CA10))),"") | D15: =IF((ROW())>=MAX(COPIA!$BV$2,COPIA!$BW$2)+COPIA!$CB$2,CONCATENATE((INDIRECT(ADDRESS(ROW()-MAX(COPIA!$BV$2,COPIA!$BW$2)-COPIA!$CC$2,138,4,,"COPIA"))),INDIRECT(ADDRESS(ROW()-MAX(COPIA!$BV$2,COPIA!$BW$2)-COPIA!$CC$2,135,4,,"COPIA"))),IF(AND($EO$4=TRUE,UPPER(COPIA!CB10)="SALDO ECONOMICO POSITIVO"),SUBSTITUTE(COPIA!CB10,"SALDO ECONOMICO POSITIVO","UTILE D'ESERCIZIO"),UPPER(COPIA!CB10))) | E15: =IFERROR(VALUE(IF((ROW())>=MAX(COPIA!$BV$2,COPIA!$BW$2)+COPIA!$CB$2,CONCATENATE((INDIRECT(ADDRESS(ROW()-MAX(COPIA!$BV$2,COPIA!$BW$2)-COPIA!$CC$2,136,4,,"COPIA"))),INDIRECT(ADDRESS(ROW()-MAX(COPIA!$BV$2,COPIA!$BW$2)-COPIA!$CC$2,95,4,,"COPIA"))),UPPER(COPIA!CC10))),"")
B16: =IF((ROW())>=MAX(COPIA!$BV$2,COPIA!$BW$2)+COPIA!$CB$2,CONCATENATE((INDIRECT(ADDRESS(ROW()-MAX(COPIA!$BV$2,COPIA!$BW$2)-COPIA!$CC$2,87,4,,"COPIA"))),INDIRECT(ADDRESS(ROW()-MAX(COPIA!$BV$2,COPIA!$BW$2)-COPIA!$CC$2,96,4,,"COPIA"))),IF(AND(COPIA!$EO$1=TRUE,UPPER(COPIA!BZ11)="SALDO ECONOMICO NEGATIVO"),SUBSTITUTE(COPIA!BZ11,"SALDO ECONOMICO NEGATIVO","PERDITA D'ESERCIZIO"),UPPER(COPIA!BZ11))) | C16: =IFERROR(VALUE(IF((ROW())>=MAX(COPIA!$BV$2,COPIA!$BW$2)+COPIA!$CB$2,CONCATENATE((INDIRECT(ADDRESS(ROW()-MAX(COPIA!$BV$2,COPIA!$BW$2)-COPIA!$CC$2,88,4,,"COPIA"))),INDIRECT(ADDRESS(ROW()-MAX(COPIA!$BV$2,COPIA!$BW$2)-COPIA!$CC$2,137,4,,"COPIA"))),UPPER(COPIA!CA11))),"") | D16: =IF((ROW())>=MAX(COPIA!$BV$2,COPIA!$BW$2)+COPIA!$CB$2,CONCATENATE((INDIRECT(ADDRESS(ROW()-MAX(COPIA!$BV$2,COPIA!$BW$2)-COPIA!$CC$2,138,4,,"COPIA"))),INDIRECT(ADDRESS(ROW()-MAX(COPIA!$BV$2,COPIA!$BW$2)-COPIA!$CC$2,135,4,,"COPIA"))),IF(AND($EO$4=TRUE,UPPER(COPIA!CB11)="SALDO ECONOMICO POSITIVO"),SUBSTITUTE(COPIA!CB11,"SALDO ECONOMICO POSITIVO","UTILE D'ESERCIZIO"),UPPER(COPIA!CB11))) | E16: =IFERROR(VALUE(IF((ROW())>=MAX(COPIA!$BV$2,COPIA!$BW$2)+COPIA!$CB$2,CONCATENATE((INDIRECT(ADDRESS(ROW()-MAX(COPIA!$BV$2,COPIA!$BW$2)-COPIA!$CC$2,136,4,,"COPIA"))),INDIRECT(ADDRESS(ROW()-MAX(COPIA!$BV$2,COPIA!$BW$2)-COPIA!$CC$2,95,4,,"COPIA"))),UPPER(COPIA!CC11))),"")
B17: =IF((ROW())>=MAX(COPIA!$BV$2,COPIA!$BW$2)+COPIA!$CB$2,CONCATENATE((INDIRECT(ADDRESS(ROW()-MAX(COPIA!$BV$2,COPIA!$BW$2)-COPIA!$CC$2,87,4,,"COPIA"))),INDIRECT(ADDRESS(ROW()-MAX(COPIA!$BV$2,COPIA!$BW$2)-COPIA!$CC$2,96,4,,"COPIA"))),IF(AND(COPIA!$EO$1=TRUE,UPPER(COPIA!BZ12)="SALDO ECONOMICO NEGATIVO"),SUBSTITUTE(COPIA!BZ12,"SALDO ECONOMICO NEGATIVO","PERDITA D'ESERCIZIO"),UPPER(COPIA!BZ12))) | C17: =IFERROR(VALUE(IF((ROW())>=MAX(COPIA!$BV$2,COPIA!$BW$2)+COPIA!$CB$2,CONCATENATE((INDIRECT(ADDRESS(ROW()-MAX(COPIA!$BV$2,COPIA!$BW$2)-COPIA!$CC$2,88,4,,"COPIA"))),INDIRECT(ADDRESS(ROW()-MAX(COPIA!$BV$2,COPIA!$BW$2)-COPIA!$CC$2,137,4,,"COPIA"))),UPPER(COPIA!CA12))),"") | D17: =IF((ROW())>=MAX(COPIA!$BV$2,COPIA!$BW$2)+COPIA!$CB$2,CONCATENATE((INDIRECT(ADDRESS(ROW()-MAX(COPIA!$BV$2,COPIA!$BW$2)-COPIA!$CC$2,138,4,,"COPIA"))),INDIRECT(ADDRESS(ROW()-MAX(COPIA!$BV$2,COPIA!$BW$2)-COPIA!$CC$2,135,4,,"COPIA"))),IF(AND($EO$4=TRUE,UPPER(COPIA!CB12)="SALDO ECONOMICO POSITIVO"),SUBSTITUTE(COPIA!CB12,"SALDO ECONOMICO POSITIVO","UTILE D'ESERCIZIO"),UPPER(COPIA!CB12))) | E17: =IFERROR(VALUE(IF((ROW())>=MAX(COPIA!$BV$2,COPIA!$BW$2)+COPIA!$CB$2,CONCATENATE((INDIRECT(ADDRESS(ROW()-MAX(COPIA!$BV$2,COPIA!$BW$2)-COPIA!$CC$2,136,4,,"COPIA"))),INDIRECT(ADDRESS(ROW()-MAX(COPIA!$BV$2,COPIA!$BW$2)-COPIA!$CC$2,95,4,,"COPIA"))),UPPER(COPIA!CC12))),"")
B18: =IF((ROW())>=MAX(COPIA!$BV$2,COPIA!$BW$2)+COPIA!$CB$2,CONCATENATE((INDIRECT(ADDRESS(ROW()-MAX(COPIA!$BV$2,COPIA!$BW$2)-COPIA!$CC$2,87,4,,"COPIA"))),INDIRECT(ADDRESS(ROW()-MAX(COPIA!$BV$2,COPIA!$BW$2)-COPIA!$CC$2,96,4,,"COPIA"))),IF(AND(COPIA!$EO$1=TRUE,UPPER(COPIA!BZ13)="SALDO ECONOMICO NEGATIVO"),SUBSTITUTE(COPIA!BZ13,"SALDO ECONOMICO NEGATIVO","PERDITA D'ESERCIZIO"),UPPER(COPIA!BZ13))) | C18: =IFERROR(VALUE(IF((ROW())>=MAX(COPIA!$BV$2,COPIA!$BW$2)+COPIA!$CB$2,CONCATENATE((INDIRECT(ADDRESS(ROW()-MAX(COPIA!$BV$2,COPIA!$BW$2)-COPIA!$CC$2,88,4,,"COPIA"))),INDIRECT(ADDRESS(ROW()-MAX(COPIA!$BV$2,COPIA!$BW$2)-COPIA!$CC$2,137,4,,"COPIA"))),UPPER(COPIA!CA13))),"") | D18: =IF((ROW())>=MAX(COPIA!$BV$2,COPIA!$BW$2)+COPIA!$CB$2,CONCATENATE((INDIRECT(ADDRESS(ROW()-MAX(COPIA!$BV$2,COPIA!$BW$2)-COPIA!$CC$2,138,4,,"COPIA"))),INDIRECT(ADDRESS(ROW()-MAX(COPIA!$BV$2,COPIA!$BW$2)-COPIA!$CC$2,135,4,,"COPIA"))),IF(AND($EO$4=TRUE,UPPER(COPIA!CB13)="SALDO ECONOMICO POSITIVO"),SUBSTITUTE(COPIA!CB13,"SALDO ECONOMICO POSITIVO","UTILE D'ESERCIZIO"),UPPER(COPIA!CB13))) | E18: =IFERROR(VALUE(IF((ROW())>=MAX(COPIA!$BV$2,COPIA!$BW$2)+COPIA!$CB$2,CONCATENATE((INDIRECT(ADDRESS(ROW()-MAX(COPIA!$BV$2,COPIA!$BW$2)-COPIA!$CC$2,136,4,,"COPIA"))),INDIRECT(ADDRESS(ROW()-MAX(COPIA!$BV$2,COPIA!$BW$2)-COPIA!$CC$2,95,4,,"COPIA"))),UPPER(COPIA!CC13))),"")
B19: =IF((ROW())>=MAX(COPIA!$BV$2,COPIA!$BW$2)+COPIA!$CB$2,CONCATENATE((INDIRECT(ADDRESS(ROW()-MAX(COPIA!$BV$2,COPIA!$BW$2)-COPIA!$CC$2,87,4,,"COPIA"))),INDIRECT(ADDRESS(ROW()-MAX(COPIA!$BV$2,COPIA!$BW$2)-COPIA!$CC$2,96,4,,"COPIA"))),IF(AND(COPIA!$EO$1=TRUE,UPPER(COPIA!BZ14)="SALDO ECONOMICO NEGATIVO"),SUBSTITUTE(COPIA!BZ14,"SALDO ECONOMICO NEGATIVO","PERDITA D'ESERCIZIO"),UPPER(COPIA!BZ14))) | C19: =IFERROR(VALUE(IF((ROW())>=MAX(COPIA!$BV$2,COPIA!$BW$2)+COPIA!$CB$2,CONCATENATE((INDIRECT(ADDRESS(ROW()-MAX(COPIA!$BV$2,COPIA!$BW$2)-COPIA!$CC$2,88,4,,"COPIA"))),INDIRECT(ADDRESS(ROW()-MAX(COPIA!$BV$2,COPIA!$BW$2)-COPIA!$CC$2,137,4,,"COPIA"))),UPPER(COPIA!CA14))),"") | D19: =IF((ROW())>=MAX(COPIA!$BV$2,COPIA!$BW$2)+COPIA!$CB$2,CONCATENATE((INDIRECT(ADDRESS(ROW()-MAX(COPIA!$BV$2,COPIA!$BW$2)-COPIA!$CC$2,138,4,,"COPIA"))),INDIRECT(ADDRESS(ROW()-MAX(COPIA!$BV$2,COPIA!$BW$2)-COPIA!$CC$2,135,4,,"COPIA"))),IF(AND($EO$4=TRUE,UPPER(COPIA!CB14)="SALDO ECONOMICO POSITIVO"),SUBSTITUTE(COPIA!CB14,"SALDO ECONOMICO POSITIVO","UTILE D'ESERCIZIO"),UPPER(COPIA!CB14))) | E19: =IFERROR(VALUE(IF((ROW())>=MAX(COPIA!$BV$2,COPIA!$BW$2)+COPIA!$CB$2,CONCATENATE((INDIRECT(ADDRESS(ROW()-MAX(COPIA!$BV$2,COPIA!$BW$2)-COPIA!$CC$2,136,4,,"COPIA"))),INDIRECT(ADDRESS(ROW()-MAX(COPIA!$BV$2,COPIA!$BW$2)-COPIA!$CC$2,95,4,,"COPIA"))),UPPER(COPIA!CC14))),"")
... B124: =IF((ROW())>=MAX(COPIA!$BV$2,COPIA!$BW$2)+COPIA!$CB$2,CONCATENATE((INDIRECT(ADDRESS(ROW()-MAX(COPIA!$BV$2,COPIA!$BW$2)-COPIA!$CC$2,87,4,,"COPIA"))),INDIRECT(ADDRESS(ROW()-MAX(COPIA!$BV$2,COPIA!$BW$2)-COPIA!$CC$2,96,4,,"COPIA"))),IF(AND(COPIA!$EO$1=TRUE,UPPER(COPIA!BZ119)="SALDO ECONOMICO NEGATIVO"),SUBSTITUTE(COPIA!BZ119,"SALDO ECONOMICO NEGATIVO","PERDITA D'ESERCIZIO"),UPPER(COPIA!BZ119))) | C124: =IFERROR(VALUE(IF((ROW())>=MAX(COPIA!$BV$2,COPIA!$BW$2)+COPIA!$CB$2,CONCATENATE((INDIRECT(ADDRESS(ROW()-MAX(COPIA!$BV$2,COPIA!$BW$2)-COPIA!$CC$2,88,4,,"COPIA"))),INDIRECT(ADDRESS(ROW()-MAX(COPIA!$BV$2,COPIA!$BW$2)-COPIA!$CC$2,137,4,,"COPIA"))),UPPER(COPIA!CA119))),"") | D124: =IF((ROW())>=MAX(COPIA!$BV$2,COPIA!$BW$2)+COPIA!$CB$2,CONCATENATE((INDIRECT(ADDRESS(ROW()-MAX(COPIA!$BV$2,COPIA!$BW$2)-COPIA!$CC$2,138,4,,"COPIA"))),INDIRECT(ADDRESS(ROW()-MAX(COPIA!$BV$2,COPIA!$BW$2)-COPIA!$CC$2,135,4,,"COPIA"))),IF(AND($EO$4=TRUE,UPPER(COPIA!CB119)="SALDO ECONOMICO POSITIVO"),SUBSTITUTE(COPIA!CB119,"SALDO ECONOMICO POSITIVO","UTILE D'ESERCIZIO"),UPPER(COPIA!CB119))) | E124: =IFERROR(VALUE(IF((ROW())>=MAX(COPIA!$BV$2,COPIA!$BW$2)+COPIA!$CB$2,CONCATENATE((INDIRECT(ADDRESS(ROW()-MAX(COPIA!$BV$2,COPIA!$BW$2)-COPIA!$CC$2,136,4,,"COPIA"))),INDIRECT(ADDRESS(ROW()-MAX(COPIA!$BV$2,COPIA!$BW$2)-COPIA!$CC$2,95,4,,"COPIA"))),UPPER(COPIA!CC119))),"")

Sheet BILANCIO
A1: BILANCIO DI ESERCIZIO
B2: OPZIONI DI VISUALIZZAZIONE | C2: OPZIONI DI STAMPA | D2: RIQUADRI DI CONTROLLO: conti finanziari accesi alle imposte - conti con alternanza di saldo | E2: Informazioni di carattere finanziario relative ai:
B3: BILANCIO DELLE MICRO IMPRESE | C3: RIGHE TRA I PROSPETTI | D3: =IFERROR(COPIA!GZ1,"") | E3: CREDITI | F3: DEBITI
B4: =IFERROR(IF(COPIA!CJ1=0,"",COPIA!ES1),"") | D4: =IFERROR(COPIA!GW2,"")
A6: =COPIA!IH1 -> 0 | B6: =IF(INDIRECT(ADDRESS(8,6,,,"LIBRO_GIORNALE"))="","",INDIRECT(ADDRESS(8,6,,,"LIBRO_GIORNALE"))) | D6: =IF(INDIRECT(ADDRESS(8,7,,,"LIBRO_GIORNALE"))="","",INDIRECT(ADDRESS(8,7,,,"LIBRO_GIORNALE")))
A7: =COPIA!IG1 -> 1 | B7: =IFERROR(IF(A7>1,CONCATENATE("STATO PATRIMONIALE ","al", " ",COPIA!DS2,"/",COPIA!DT2,"/",COPIA!DU2),""),"")
B8: =IFERROR(IF($A$7>1,"ATTIVO",""),"") | C8: =IFERROR(IF($A$7>1,"importi",""),"") | D8: =IFERROR(IF($A$7>1,"PASSIVO E NETTO",""),"") | E8: =IFERROR(IF($A$7>1,"importi",""),"")
B9: =IFERROR(IF(ROW()-8<=COPIA!$IG$1,SUBSTITUTE(INDEX(COPIA!$IB$3:$IH$18,MATCH(ROWS($B$9:B9),COPIA!$IH$3:$IH$18,0),1),"_"," "),IF(ROW()-8>=COPIA!$IG$1+COPIA!$IH$1,SUBSTITUTE(INDEX(COPIA!$IB$37:$IH$93,MATCH(ROW()-8-COPIA!$IH$1,COPIA!$IH$37:$IH$93,0),1),"_"," "),"")),"") | C9: =IFERROR(IF(ROW()-8<=COPIA!$IG$1,INDEX(COPIA!$IB$3:$IH$18,MATCH(ROWS($B$9:B9),COPIA!$IH$3:$IH$18,0),6),IF(ROW()-8>=COPIA!$IG$1+2,INDEX(COPIA!$IB$37:$IH$93,MATCH(ROW()-8-COPIA!$IH$1,COPIA!$IH$37:$IH$93,0),6),"")),"") | D9: =IFERROR(SUBSTITUTE(INDEX(COPIA!$IB$19:$IH$34,MATCH(ROWS($D$9:D9),COPIA!$IH$19:$IH$34,0),1),"_"," "),"") | E9: =IFERROR(INDEX(COPIA!$IB$19:$IH$34,MATCH(ROWS($D$9:E9),COPIA!$IH$19:$IH$34,0),6),"")
B10: =IFERROR(IF(ROW()-8<=COPIA!$IG$1,SUBSTITUTE(INDEX(COPIA!$IB$3:$IH$18,MATCH(ROWS($B$9:B10),COPIA!$IH$3:$IH$18,0),1),"_"," "),IF(ROW()-8>=COPIA!$IG$1+COPIA!$IH$1,SUBSTITUTE(INDEX(COPIA!$IB$37:$IH$93,MATCH(ROW()-8-COPIA!$IH$1,COPIA!$IH$37:$IH$93,0),1),"_"," "),"")),"") | C10: =IFERROR(IF(ROW()-8<=COPIA!$IG$1,INDEX(COPIA!$IB$3:$IH$18,MATCH(ROWS($B$9:B10),COPIA!$IH$3:$IH$18,0),6),IF(ROW()-8>=COPIA!$IG$1+2,INDEX(COPIA!$IB$37:$IH$93,MATCH(ROW()-8-COPIA!$IH$1,COPIA!$IH$37:$IH$93,0),6),"")),"") | D10: =IFERROR(SUBSTITUTE(INDEX(COPIA!$IB$19:$IH$34,MATCH(ROWS($D$9:D10),COPIA!$IH$19:$IH$34,0),1),"_"," "),"") | E10: =IFERROR(INDEX(COPIA!$IB$19:$IH$34,MATCH(ROWS($D$9:E10),COPIA!$IH$19:$IH$34,0),6),"")
B11: =IFERROR(IF(ROW()-8<=COPIA!$IG$1,SUBSTITUTE(INDEX(COPIA!$IB$3:$IH$18,MATCH(ROWS($B$9:B11),COPIA!$IH$3:$IH$18,0),1),"_"," "),IF(ROW()-8>=COPIA!$IG$1+COPIA!$IH$1,SUBSTITUTE(INDEX(COPIA!$IB$37:$IH$93,MATCH(ROW()-8-COPIA!$IH$1,COPIA!$IH$37:$IH$93,0),1),"_"," "),"")),"") | C11: =IFERROR(IF(ROW()-8<=COPIA!$IG$1,INDEX(COPIA!$IB$3:$IH$18,MATCH(ROWS($B$9:B11),COPIA!$IH$3:$IH$18,0),6),IF(ROW()-8>=COPIA!$IG$1+2,INDEX(COPIA!$IB$37:$IH$93,MATCH(ROW()-8-COPIA!$IH$1,COPIA!$IH$37:$IH$93,0),6),"")),"") | D11: =IFERROR(SUBSTITUTE(INDEX(COPIA!$IB$19:$IH$34,MATCH(ROWS($D$9:D11),COPIA!$IH$19:$IH$34,0),1),"_"," "),"") | E11: =IFERROR(INDEX(COPIA!$IB$19:$IH$34,MATCH(ROWS($D$9:E11),COPIA!$IH$19:$IH$34,0),6),"")
B12: =IFERROR(IF(ROW()-8<=COPIA!$IG$1,SUBSTITUTE(INDEX(COPIA!$IB$3:$IH$18,MATCH(ROWS($B$9:B12),COPIA!$IH$3:$IH$18,0),1),"_"," "),IF(ROW()-8>=COPIA!$IG$1+COPIA!$IH$1,SUBSTITUTE(INDEX(COPIA!$IB$37:$IH$93,MATCH(ROW()-8-COPIA!$IH$1,COPIA!$IH$37:$IH$93,0),1),"_"," "),"")),"") | C12: =IFERROR(IF(ROW()-8<=COPIA!$IG$1,INDEX(COPIA!$IB$3:$IH$18,MATCH(ROWS($B$9:B12),COPIA!$IH$3:$IH$18,0),6),IF(ROW()-8>=COPIA!$IG$1+2,INDEX(COPIA!$IB$37:$IH$93,MATCH(ROW()-8-COPIA!$IH$1,COPIA!$IH$37:$IH$93,0),6),"")),"") | D12: =IFERROR(SUBSTITUTE(INDEX(COPIA!$IB$19:$IH$34,MATCH(ROWS($D$9:D12),COPIA!$IH$19:$IH$34,0),1),"_"," "),"") | E12: =IFERROR(INDEX(COPIA!$IB$19:$IH$34,MATCH(ROWS($D$9:E12),COPIA!$IH$19:$IH$34,0),6),"")
B13: =IFERROR(IF(ROW()-8<=COPIA!$IG$1,SUBSTITUTE(INDEX(COPIA!$IB$3:$IH$18,MATCH(ROWS($B$9:B13),COPIA!$IH$3:$IH$18,0),1),"_"," "),IF(ROW()-8>=COPIA!$IG$1+COPIA!$IH$1,SUBSTITUTE(INDEX(COPIA!$IB$37:$IH$93,MATCH(ROW()-8-COPIA!$IH$1,COPIA!$IH$37:$IH$93,0),1),"_"," "),"")),"") | C13: =IFERROR(IF(ROW()-8<=COPIA!$IG$1,INDEX(COPIA!$IB$3:$IH$18,MATCH(ROWS($B$9:B13),COPIA!$IH$3:$IH$18,0),6),IF(ROW()-8>=COPIA!$IG$1+2,INDEX(COPIA!$IB$37:$IH$93,MATCH(ROW()-8-COPIA!$IH$1,COPIA!$IH$37:$IH$93,0),6),"")),"") | D13: =IFERROR(SUBSTITUTE(INDEX(COPIA!$IB$19:$IH$34,MATCH(ROWS($D$9:D13),COPIA!$IH$19:$IH$34,0),1),"_"," "),"") | E13: =IFERROR(INDEX(COPIA!$IB$19:$IH$34,MATCH(ROWS($D$9:E13),COPIA!$IH$19:$IH$34,0),6),"")
B14: =IFERROR(IF(ROW()-8<=COPIA!$IG$1,SUBSTITUTE(INDEX(COPIA!$IB$3:$IH$18,MATCH(ROWS($B$9:B14),COPIA!$IH$3:$IH$18,0),1),"_"," "),IF(ROW()-8>=COPIA!$IG$1+COPIA!$IH$1,SUBSTITUTE(INDEX(COPIA!$IB$37:$IH$93,MATCH(ROW()-8-COPIA!$IH$1,COPIA!$IH$37:$IH$93,0),1),"_"," "),"")),"") | C14: =IFERROR(IF(ROW()-8<=COPIA!$IG$1,INDEX(COPIA!$IB$3:$IH$18,MATCH(ROWS($B$9:B14),COPIA!$IH$3:$IH$18,0),6),IF(ROW()-8>=COPIA!$IG$1+2,INDEX(COPIA!$IB$37:$IH$93,MATCH(ROW()-8-COPIA!$IH$1,COPIA!$IH$37:$IH$93,0),6),"")),"") | D14: =IFERROR(SUBSTITUTE(INDEX(COPIA!$IB$19:$IH$34,MATCH(ROWS($D$9:D14),COPIA!$IH$19:$IH$34,0),1),"_"," "),"") | E14: =IFERROR(INDEX(COPIA!$IB$19:$IH$34,MATCH(ROWS($D$9:E14),COPIA!$IH$19:$IH$34,0),6),"")
B15: =IFERROR(IF(ROW()-8<=COPIA!$IG$1,SUBSTITUTE(INDEX(COPIA!$IB$3:$IH$18,MATCH(ROWS($B$9:B15),COPIA!$IH$3:$IH$18,0),1),"_"," "),IF(ROW()-8>=COPIA!$IG$1+COPIA!$IH$1,SUBSTITUTE(INDEX(COPIA!$IB$37:$IH$93,MATCH(ROW()-8-COPIA!$IH$1,COPIA!$IH$37:$IH$93,0),1),"_"," "),"")),"") | C15: =IFERROR(IF(ROW()-8<=COPIA!$IG$1,INDEX(COPIA!$IB$3:$IH$18,MATCH(ROWS($B$9:B15),COPIA!$IH$3:$IH$18,0),6),IF(ROW()-8>=COPIA!$IG$1+2,INDEX(COPIA!$IB$37:$IH$93,MATCH(ROW()-8-COPIA!$IH$1,COPIA!$IH$37:$IH$93,0),6),"")),"") | D15: =IFERROR(SUBSTITUTE(INDEX(COPIA!$IB$19:$IH$34,MATCH(ROWS($D$9:D15),COPIA!$IH$19:$IH$34,0),1),"_"," "),"") | E15: =IFERROR(INDEX(COPIA!$IB$19:$IH$34,MATCH(ROWS($D$9:E15),COPIA!$IH$19:$IH$34,0),6),"")
B16: =IFERROR(IF(ROW()-8<=COPIA!$IG$1,SUBSTITUTE(INDEX(COPIA!$IB$3:$IH$18,MATCH(ROWS($B$9:B16),COPIA!$IH$3:$IH$18,0),1),"_"," "),IF(ROW()-8>=COPIA!$IG$1+COPIA!$IH$1,SUBSTITUTE(INDEX(COPIA!$IB$37:$IH$93,MATCH(ROW()-8-COPIA!$IH$1,COPIA!$IH$37:$IH$93,0),1),"_"," "),"")),"") | C16: =IFERROR(IF(ROW()-8<=COPIA!$IG$1,INDEX(COPIA!$IB$3:$IH$18,MATCH(ROWS($B$9:B16),COPIA!$IH$3:$IH$18,0),6),IF(ROW()-8>=COPIA!$IG$1+2,INDEX(COPIA!$IB$37:$IH$93,MATCH(ROW()-8-COPIA!$IH$1,COPIA!$IH$37:$IH$93,0),6),"")),"") | D16: =IFERROR(SUBSTITUTE(INDEX(COPIA!$IB$19:$IH$34,MATCH(ROWS($D$9:D16),COPIA!$IH$19:$IH$34,0),1),"_"," "),"") | E16: =IFERROR(INDEX(COPIA!$IB$19:$IH$34,MATCH(ROWS($D$9:E16),COPIA!$IH$19:$IH$34,0),6),"")
B17: =IFERROR(IF(ROW()-8<=COPIA!$IG$1,SUBSTITUTE(INDEX(COPIA!$IB$3:$IH$18,MATCH(ROWS($B$9:B17),COPIA!$IH$3:$IH$18,0),1),"_"," "),IF(ROW()-8>=COPIA!$IG$1+COPIA!$IH$1,SUBSTITUTE(INDEX(COPIA!$IB$37:$IH$93,MATCH(ROW()-8-COPIA!$IH$1,COPIA!$IH$37:$IH$93,0),1),"_"," "),"")),"") | C17: =IFERROR(IF(ROW()-8<=COPIA!$IG$1,INDEX(COPIA!$IB$3:$IH$18,MATCH(ROWS($B$9:B17),COPIA!$IH$3:$IH$18,0),6),IF(ROW()-8>=COPIA!$IG$1+2,INDEX(COPIA!$IB$37:$IH$93,MATCH(ROW()-8-COPIA!$IH$1,COPIA!$IH$37:$IH$93,0),6),"")),"") | D17: =IFERROR(SUBSTITUTE(INDEX(COPIA!$IB$19:$IH$34,MATCH(ROWS($D$9:D17),COPIA!$IH$19:$IH$34,0),1),"_"," "),"") | E17: =IFERROR(INDEX(COPIA!$IB$19:$IH$34,MATCH(ROWS($D$9:E17),COPIA!$IH$19:$IH$34,0),6),"")
B18: =IFERROR(IF(ROW()-8<=COPIA!$IG$1,SUBSTITUTE(INDEX(COPIA!$IB$3:$IH$18,MATCH(ROWS($B$9:B18),COPIA!$IH$3:$IH$18,0),1),"_"," "),IF(ROW()-8>=COPIA!$IG$1+COPIA!$IH$1,SUBSTITUTE(INDEX(COPIA!$IB$37:$IH$93,MATCH(ROW()-8-COPIA!$IH$1,COPIA!$IH$37:$IH$93,0),1),"_"," "),"")),"") | C18: =IFERROR(IF(ROW()-8<=COPIA!$IG$1,INDEX(COPIA!$IB$3:$IH$18,MATCH(ROWS($B$9:B18),COPIA!$IH$3:$IH$18,0),6),IF(ROW()-8>=COPIA!$IG$1+2,INDEX(COPIA!$IB$37:$IH$93,MATCH(ROW()-8-COPIA!$IH$1,COPIA!$IH$37:$IH$93,0),6),"")),"") | D18: =IFERROR(SUBSTITUTE(INDEX(COPIA!$IB$19:$IH$34,MATCH(ROWS($D$9:D18),COPIA!$IH$19:$IH$34,0),1),"_"," "),"") | E18: =IFERROR(INDEX(COPIA!$IB$19:$IH$34,MATCH(ROWS($D$9:E18),COPIA!$IH$19:$IH$34,0),6),"")
B19: =IFERROR(IF(ROW()-8<=COPIA!$IG$1,SUBSTITUTE(INDEX(COPIA!$IB$3:$IH$18,MATCH(ROWS($B$9:B19),COPIA!$IH$3:$IH$18,0),1),"_"," "),IF(ROW()-8>=COPIA!$IG$1+COPIA!$IH$1,SUBSTITUTE(INDEX(COPIA!$IB$37:$IH$93,MATCH(ROW()-8-COPIA!$IH$1,COPIA!$IH$37:$IH$93,0),1),"_"," "),"")),"") | C19: =IFERROR(IF(ROW()-8<=COPIA!$IG$1,INDEX(COPIA!$IB$3:$IH$18,MATCH(ROWS($B$9:B19),COPIA!$IH$3:$IH$18,0),6),IF(ROW()-8>=COPIA!$IG$1+2,INDEX(COPIA!$IB$37:$IH$93,MATCH(ROW()-8-COPIA!$IH$1,COPIA!$IH$37:$IH$93,0),6),"")),"") | D19: =IFERROR(SUBSTITUTE(INDEX(COPIA!$IB$19:$IH$34,MATCH(ROWS($D$9:D19),COPIA!$IH$19:$IH$34,0),1),"_"," "),"") | E19: =IFERROR(INDEX(COPIA!$IB$19:$IH$34,MATCH(ROWS($D$9:E19),COPIA!$IH$19:$IH$34,0),6),"")
B20: =IFERROR(IF(ROW()-8<=COPIA!$IG$1,SUBSTITUTE(INDEX(COPIA!$IB$3:$IH$18,MATCH(ROWS($B$9:B20),COPIA!$IH$3:$IH$18,0),1),"_"," "),IF(ROW()-8>=COPIA!$IG$1+COPIA!$IH$1,SUBSTITUTE(INDEX(COPIA!$IB$37:$IH$93,MATCH(ROW()-8-COPIA!$IH$1,COPIA!$IH$37:$IH$93,0),1),"_"," "),"")),"") | C20: =IFERROR(IF(ROW()-8<=COPIA!$IG$1,INDEX(COPIA!$IB$3:$IH$18,MATCH(ROWS($B$9:B20),COPIA!$IH$3:$IH$18,0),6),IF(ROW()-8>=COPIA!$IG$1+2,INDEX(COPIA!$IB$37:$IH$93,MATCH(ROW()-8-COPIA!$IH$1,COPIA!$IH$37:$IH$93,0),6),"")),"") | D20: =IFERROR(SUBSTITUTE(INDEX(COPIA!$IB$19:$IH$34,MATCH(ROWS($D$9:D20),COPIA!$IH$19:$IH$34,0),1),"_"," "),"") | E20: =IFERROR(INDEX(COPIA!$IB$19:$IH$34,MATCH(ROWS($D$9:E20),COPIA!$IH$19:$IH$34,0),6),"")
... B122: =IFERROR(IF(ROW()-8<=COPIA!$IG$1,SUBSTITUTE(INDEX(COPIA!$IB$3:$IH$18,MATCH(ROWS($B$9:B122),COPIA!$IH$3:$IH$18,0),1),"_"," "),IF(ROW()-8>=COPIA!$IG$1+COPIA!$IH$1,SUBSTITUTE(INDEX(COPIA!$IB$37:$IH$93,MATCH(ROW()-8-COPIA!$IH$1,COPIA!$IH$37:$IH$93,0),1),"_"," "),"")),"") | C122: =IFERROR(IF(ROW()-8<=COPIA!$IG$1,INDEX(COPIA!$IB$3:$IH$18,MATCH(ROWS($B$9:B122),COPIA!$IH$3:$IH$18,0),6),IF(ROW()-8>=COPIA!$IG$1+2,INDEX(COPIA!$IB$37:$IH$93,MATCH(ROW()-8-COPIA!$IH$1,COPIA!$IH$37:$IH$93,0),6),"")),"") | D122: =IFERROR(SUBSTITUTE(INDEX(COPIA!$IB$19:$IH$34,MATCH(ROWS($D$9:D122),COPIA!$IH$19:$IH$34,0),1),"_"," "),"") | E122: =IFERROR(INDEX(COPIA!$IB$19:$IH$34,MATCH(ROWS($D$9:E122),COPIA!$IH$19:$IH$34,0),6),"")

Sheet CHIUS.-APERT.
B1: SCRITTURE DI CHIUSURA E DI APERTURA
B2: VISUALIZZA: | E2: =IF(COPIA!CH1=0,"",COPIA!ES1) | F2: CONTROLLO: conti accesi alle imposte | G2: CONTROLLO: conti con alternanza di saldo
F3: =COPIA!GZ1 | G3: =COPIA!GW2
B4: SCRITTURE DI CHIUSURA
A9: =MAX(C12:C228)+3 -> 3 | B9: =IF(INDIRECT(ADDRESS(8,6,,,"LIBRO_GIORNALE"))="","",INDIRECT(ADDRESS(8,6,,,"LIBRO_GIORNALE"))) | F9: =IF(INDIRECT(ADDRESS(8,7,,,"LIBRO_GIORNALE"))="","",INDIRECT(ADDRESS(8,7,,,"LIBRO_GIORNALE")))
B10: =IF(COPIA!CH1=0,"",IF(COPIA!GP1=2,CONCATENATE("Scritture di apertura al 01/01/",COPIA!EW1),CONCATENATE("Scritture di epilogo e di chiusura al 31/12/",COPIA!EW1)))
B11: =IF(COPIA!CH1=0,"","Codice") | C11: =IF(COPIA!CH1=0,"","Nr. Riga") | D11: =IF(COPIA!CH1=0,"","DATA") | E11: =IF(COPIA!CH1=0,""," DENOMINAZIONE DEI CONTI") | F11: =IF(COPIA!CH1=0,"","DESCRIZIONE") | G11: =IF(COPIA!CH1=0,"","DARE") | H11: =IF(COPIA!CH1=0,"","AVERE")
B12: =IFERROR(INDEX(PIANO_DEI_CONTI,MATCH(E12,DENOMINAZIONE,0),1),"") | C12: =IF(B12<>"",ROW()-11,"") | D12: =IF(AND(COPIA!$EV$1=0,B12<>"",COPIA!$GP$1=1),CONCATENATE("31/12/",COPIA!$EW$1),IF(AND(COPIA!$EV$1=0,B12<>"",COPIA!$GP$1=2),CONCATENATE("01/01/",COPIA!$EW$1),"")) | E12: =IF(COPIA!$EV$1>0,"",IF(COPIA!$GP$1=1,COPIA!GN3,COPIA!HV3)) | F12: =IF(COPIA!$EV$1>0,"",IF(COPIA!$GP$1=1,COPIA!GT3,COPIA!IZ3)) | G12: =IF(COPIA!$EV$1>0,"",IF(COPIA!$GP$1=1,COPIA!GO3,COPIA!IX3)) | H12: =IF(COPIA!$EV$1>0,"",IF(COPIA!$GP$1=1,COPIA!GP3,COPIA!IY3)) | J12: =IF(AND(G12="",H12=""),"",ROUND(SUM(G$12:G12),2)-ROUND(SUM(H$12:H12),2))
B13: =IFERROR(INDEX(PIANO_DEI_CONTI,MATCH(E13,DENOMINAZIONE,0),1),"") | C13: =IF(B13<>"",ROW()-11,"") | D13: =IF(AND(COPIA!$EV$1=0,B13<>"",COPIA!$GP$1=1),CONCATENATE("31/12/",COPIA!$EW$1),IF(AND(COPIA!$EV$1=0,B13<>"",COPIA!$GP$1=2),CONCATENATE("01/01/",COPIA!$EW$1),"")) | E13: =IF(COPIA!$EV$1>0,"",IF(COPIA!$GP$1=1,COPIA!GN4,COPIA!HV4)) | F13: =IF(COPIA!$EV$1>0,"",IF(COPIA!$GP$1=1,COPIA!GT4,COPIA!IZ4)) | G13: =IF(COPIA!$EV$1>0,"",IF(COPIA!$GP$1=1,COPIA!GO4,COPIA!IX4)) | H13: =IF(COPIA!$EV$1>0,"",IF(COPIA!$GP$1=1,COPIA!GP4,COPIA!IY4)) | J13: =IF(AND(G13="",H13=""),"",ROUND(SUM(G$12:G13),2)-ROUND(SUM(H$12:H13),2))
B14: =IFERROR(INDEX(PIANO_DEI_CONTI,MATCH(E14,DENOMINAZIONE,0),1),"") | C14: =IF(B14<>"",ROW()-11,"") | D14: =IF(AND(COPIA!$EV$1=0,B14<>"",COPIA!$GP$1=1),CONCATENATE("31/12/",COPIA!$EW$1),IF(AND(COPIA!$EV$1=0,B14<>"",COPIA!$GP$1=2),CONCATENATE("01/01/",COPIA!$EW$1),"")) | E14: =IF(COPIA!$EV$1>0,"",IF(COPIA!$GP$1=1,COPIA!GN5,COPIA!HV5)) | F14: =IF(COPIA!$EV$1>0,"",IF(COPIA!$GP$1=1,COPIA!GT5,COPIA!IZ5)) | G14: =IF(COPIA!$EV$1>0,"",IF(COPIA!$GP$1=1,COPIA!GO5,COPIA!IX5)) | H14: =IF(COPIA!$EV$1>0,"",IF(COPIA!$GP$1=1,COPIA!GP5,COPIA!IY5)) | J14: =IF(AND(G14="",H14=""),"",ROUND(SUM(G$12:G14),2)-ROUND(SUM(H$12:H14),2))
B15: =IFERROR(INDEX(PIANO_DEI_CONTI,MATCH(E15,DENOMINAZIONE,0),1),"") | C15: =IF(B15<>"",ROW()-11,"") | D15: =IF(AND(COPIA!$EV$1=0,B15<>"",COPIA!$GP$1=1),CONCATENATE("31/12/",COPIA!$EW$1),IF(AND(COPIA!$EV$1=0,B15<>"",COPIA!$GP$1=2),CONCATENATE("01/01/",COPIA!$EW$1),"")) | E15: =IF(COPIA!$EV$1>0,"",IF(COPIA!$GP$1=1,COPIA!GN6,COPIA!HV6)) | F15: =IF(COPIA!$EV$1>0,"",IF(COPIA!$GP$1=1,COPIA!GT6,COPIA!IZ6)) | G15: =IF(COPIA!$EV$1>0,"",IF(COPIA!$GP$1=1,COPIA!GO6,COPIA!IX6)) | H15: =IF(COPIA!$EV$1>0,"",IF(COPIA!$GP$1=1,COPIA!GP6,COPIA!IY6)) | J15: =IF(AND(G15="",H15=""),"",ROUND(SUM(G$12:G15),2)-ROUND(SUM(H$12:H15),2))
B16: =IFERROR(INDEX(PIANO_DEI_CONTI,MATCH(E16,DENOMINAZIONE,0),1),"") | C16: =IF(B16<>"",ROW()-11,"") | D16: =IF(AND(COPIA!$EV$1=0,B16<>"",COPIA!$GP$1=1),CONCATENATE("31/12/",COPIA!$EW$1),IF(AND(COPIA!$EV$1=0,B16<>"",COPIA!$GP$1=2),CONCATENATE("01/01/",COPIA!$EW$1),"")) | E16: =IF(COPIA!$EV$1>0,"",IF(COPIA!$GP$1=1,COPIA!GN7,COPIA!HV7)) | F16: =IF(COPIA!$EV$1>0,"",IF(COPIA!$GP$1=1,COPIA!GT7,COPIA!IZ7)) | G16: =IF(COPIA!$EV$1>0,"",IF(COPIA!$GP$1=1,COPIA!GO7,COPIA!IX7)) | H16: =IF(COPIA!$EV$1>0,"",IF(COPIA!$GP$1=1,COPIA!GP7,COPIA!IY7)) | J16: =IF(AND(G16="",H16=""),"",ROUND(SUM(G$12:G16),2)-ROUND(SUM(H$12:H16),2))
B17: =IFERROR(INDEX(PIANO_DEI_CONTI,MATCH(E17,DENOMINAZIONE,0),1),"") | C17: =IF(B17<>"",ROW()-11,"") | D17: =IF(AND(COPIA!$EV$1=0,B17<>"",COPIA!$GP$1=1),CONCATENATE("31/12/",COPIA!$EW$1),IF(AND(COPIA!$EV$1=0,B17<>"",COPIA!$GP$1=2),CONCATENATE("01/01/",COPIA!$EW$1),"")) | E17: =IF(COPIA!$EV$1>0,"",IF(COPIA!$GP$1=1,COPIA!GN8,COPIA!HV8)) | F17: =IF(COPIA!$EV$1>0,"",IF(COPIA!$GP$1=1,COPIA!GT8,COPIA!IZ8)) | G17: =IF(COPIA!$EV$1>0,"",IF(COPIA!$GP$1=1,COPIA!GO8,COPIA!IX8)) | H17: =IF(COPIA!$EV$1>0,"",IF(COPIA!$GP$1=1,COPIA!GP8,COPIA!IY8)) | J17: =IF(AND(G17="",H17=""),"",ROUND(SUM(G$12:G17),2)-ROUND(SUM(H$12:H17),2))
B18: =IFERROR(INDEX(PIANO_DEI_CONTI,MATCH(E18,DENOMINAZIONE,0),1),"") | C18: =IF(B18<>"",ROW()-11,"") | D18: =IF(AND(COPIA!$EV$1=0,B18<>"",COPIA!$GP$1=1),CONCATENATE("31/12/",COPIA!$EW$1),IF(AND(COPIA!$EV$1=0,B18<>"",COPIA!$GP$1=2),CONCATENATE("01/01/",COPIA!$EW$1),"")) | E18: =IF(COPIA!$EV$1>0,"",IF(COPIA!$GP$1=1,COPIA!GN9,COPIA!HV9)) | F18: =IF(COPIA!$EV$1>0,"",IF(COPIA!$GP$1=1,COPIA!GT9,COPIA!IZ9)) | G18: =IF(COPIA!$EV$1>0,"",IF(COPIA!$GP$1=1,COPIA!GO9,COPIA!IX9)) | H18: =IF(COPIA!$EV$1>0,"",IF(COPIA!$GP$1=1,COPIA!GP9,COPIA!IY9)) | J18: =IF(AND(G18="",H18=""),"",ROUND(SUM(G$12:G18),2)-ROUND(SUM(H$12:H18),2))
B19: =IFERROR(INDEX(PIANO_DEI_CONTI,MATCH(E19,DENOMINAZIONE,0),1),"") | C19: =IF(B19<>"",ROW()-11,"") | D19: =IF(AND(COPIA!$EV$1=0,B19<>"",COPIA!$GP$1=1),CONCATENATE("31/12/",COPIA!$EW$1),IF(AND(COPIA!$EV$1=0,B19<>"",COPIA!$GP$1=2),CONCATENATE("01/01/",COPIA!$EW$1),"")) | E19: =IF(COPIA!$EV$1>0,"",IF(COPIA!$GP$1=1,COPIA!GN10,COPIA!HV10)) | F19: =IF(COPIA!$EV$1>0,"",IF(COPIA!$GP$1=1,COPIA!GT10,COPIA!IZ10)) | G19: =IF(COPIA!$EV$1>0,"",IF(COPIA!$GP$1=1,COPIA!GO10,COPIA!IX10)) | H19: =IF(COPIA!$EV$1>0,"",IF(COPIA!$GP$1=1,COPIA!GP10,COPIA!IY10)) | J19: =IF(AND(G19="",H19=""),"",ROUND(SUM(G$12:G19),2)-ROUND(SUM(H$12:H19),2))
B20: =IFERROR(INDEX(PIANO_DEI_CONTI,MATCH(E20,DENOMINAZIONE,0),1),"") | C20: =IF(B20<>"",ROW()-11,"") | D20: =IF(AND(COPIA!$EV$1=0,B20<>"",COPIA!$GP$1=1),CONCATENATE("31/12/",COPIA!$EW$1),IF(AND(COPIA!$EV$1=0,B20<>"",COPIA!$GP$1=2),CONCATENATE("01/01/",COPIA!$EW$1),"")) | E20: =IF(COPIA!$EV$1>0,"",IF(COPIA!$GP$1=1,COPIA!GN11,COPIA!HV11)) | F20: =IF(COPIA!$EV$1>0,"",IF(COPIA!$GP$1=1,COPIA!GT11,COPIA!IZ11)) | G20: =IF(COPIA!$EV$1>0,"",IF(COPIA!$GP$1=1,COPIA!GO11,COPIA!IX11)) | H20: =IF(COPIA!$EV$1>0,"",IF(COPIA!$GP$1=1,COPIA!GP11,COPIA!IY11)) | J20: =IF(AND(G20="",H20=""),"",ROUND(SUM(G$12:G20),2)-ROUND(SUM(H$12:H20),2))
B21: =IFERROR(INDEX(PIANO_DEI_CONTI,MATCH(E21,DENOMINAZIONE,0),1),"") | C21: =IF(B21<>"",ROW()-11,"") | D21: =IF(AND(COPIA!$EV$1=0,B21<>"",COPIA!$GP$1=1),CONCATENATE("31/12/",COPIA!$EW$1),IF(AND(COPIA!$EV$1=0,B21<>"",COPIA!$GP$1=2),CONCATENATE("01/01/",COPIA!$EW$1),"")) | E21: =IF(COPIA!$EV$1>0,"",IF(COPIA!$GP$1=1,COPIA!GN12,COPIA!HV12)) | F21: =IF(COPIA!$EV$1>0,"",IF(COPIA!$GP$1=1,COPIA!GT12,COPIA!IZ12)) | G21: =IF(COPIA!$EV$1>0,"",IF(COPIA!$GP$1=1,COPIA!GO12,COPIA!IX12)) | H21: =IF(COPIA!$EV$1>0,"",IF(COPIA!$GP$1=1,COPIA!GP12,COPIA!IY12)) | J21: =IF(AND(G21="",H21=""),"",ROUND(SUM(G$12:G21),2)-ROUND(SUM(H$12:H21),2))
B22: =IFERROR(INDEX(PIANO_DEI_CONTI,MATCH(E22,DENOMINAZIONE,0),1),"") | C22: =IF(B22<>"",ROW()-11,"") | D22: =IF(AND(COPIA!$EV$1=0,B22<>"",COPIA!$GP$1=1),CONCATENATE("31/12/",COPIA!$EW$1),IF(AND(COPIA!$EV$1=0,B22<>"",COPIA!$GP$1=2),CONCATENATE("01/01/",COPIA!$EW$1),"")) | E22: =IF(COPIA!$EV$1>0,"",IF(COPIA!$GP$1=1,COPIA!GN13,COPIA!HV13)) | F22: =IF(COPIA!$EV$1>0,"",IF(COPIA!$GP$1=1,COPIA!GT13,COPIA!IZ13)) | G22: =IF(COPIA!$EV$1>0,"",IF(COPIA!$GP$1=1,COPIA!GO13,COPIA!IX13)) | H22: =IF(COPIA!$EV$1>0,"",IF(COPIA!$GP$1=1,COPIA!GP13,COPIA!IY13)) | J22: =IF(AND(G22="",H22=""),"",ROUND(SUM(G$12:G22),2)-ROUND(SUM(H$12:H22),2))
B23: =IFERROR(INDEX(PIANO_DEI_CONTI,MATCH(E23,DENOMINAZIONE,0),1),"") | C23: =IF(B23<>"",ROW()-11,"") | D23: =IF(AND(COPIA!$EV$1=0,B23<>"",COPIA!$GP$1=1),CONCATENATE("31/12/",COPIA!$EW$1),IF(AND(COPIA!$EV$1=0,B23<>"",COPIA!$GP$1=2),CONCATENATE("01/01/",COPIA!$EW$1),"")) | E23: =IF(COPIA!$EV$1>0,"",IF(COPIA!$GP$1=1,COPIA!GN14,COPIA!HV14)) | F23: =IF(COPIA!$EV$1>0,"",IF(COPIA!$GP$1=1,COPIA!GT14,COPIA!IZ14)) | G23: =IF(COPIA!$EV$1>0,"",IF(COPIA!$GP$1=1,COPIA!GO14,COPIA!IX14)) | H23: =IF(COPIA!$EV$1>0,"",IF(COPIA!$GP$1=1,COPIA!GP14,COPIA!IY14)) | J23: =IF(AND(G23="",H23=""),"",ROUND(SUM(G$12:G23),2)-ROUND(SUM(H$12:H23),2))
... B227: =IFERROR(INDEX(PIANO_DEI_CONTI,MATCH(E227,DENOMINAZIONE,0),1),"") | C227: =IF(B227<>"",ROW()-11,"") | D227: =IF(AND(COPIA!$EV$1=0,B227<>"",COPIA!$GP$1=1),CONCATENATE("31/12/",COPIA!$EW$1),IF(AND(COPIA!$EV$1=0,B227<>"",COPIA!$GP$1=2),CONCATENATE("01/01/",COPIA!$EW$1),"")) | E227: =IF(COPIA!$EV$1>0,"",IF(COPIA!$GP$1=1,COPIA!GN218,COPIA!HV218)) | F227: =IF(COPIA!$EV$1>0,"",IF(COPIA!$GP$1=1,COPIA!GT218,COPIA!IZ218)) | G227: =IF(COPIA!$EV$1>0,"",IF(COPIA!$GP$1=1,COPIA!GO218,COPIA!IX218)) | H227: =IF(COPIA!$EV$1>0,"",IF(COPIA!$GP$1=1,COPIA!GP218,COPIA!IY218)) | J227: =IF(AND(G227="",H227=""),"",ROUND(SUM(G$12:G227),2)-ROUND(SUM(H$12:H227),2))

Sheet COPIA
A1: =INDIRECT(ADDRESS(ROW(),COLUMN()+3,,,"PIANO_DEI_CONTI")) -> 0 | B1: 1 | D1: TRUE | E1: TRUE | I1: =IF(INDIRECT(ADDRESS(3,6,,,"PIANO_DEI_CONTI"))="A - COSTITUZIONE - ACQUISTI - VENDITE",1,IF(INDIRECT(ADDRESS(3,6,,,"PIANO_DEI_CONTI"))="B - ALTRE OPERAZIONI DI GESTIONE",2,3)) -> 3 | J1: =IF(INDIRECT(ADDRESS(2,5,,,"LIBRO_GIORNALE"))="CONTI SUDDIVISI PER RAGGRUPPAMENTO",2,1) -> 2 | L1: =IF(INDIRECT(ADDRESS(3,2,,,"LIBRO_GIORNALE"))="DESKTOP: Office",IF(ISNUMBER(M1),INDEX($O$3:$P$48,MATCH($M$1,$P$3:$P$48,0),1),M1),N2) -> VISUALIZZA TUTTI I CONTI | M1: 1 | O1: =MAX($L$3:L$220) -> 171 | P1: =MAX($L$3:$L$220) -> 171 | Z1: 1 | AN1: N | AQ1: A | AR1: B | AS1: C | AT1: A | AU1: B | AV1: C | AW1: A | AX1: B | AY1: C | BP1: PATRIMONIO NETTO | BS1: PRELEVAMENTI EXTRAGESTIONE | BX1: =IFERROR(IF(INDEX($BI$3:$BJ$220,MATCH($BP$1,$BI$3:$BI$220,0),2)="",0,INDEX($BI$3:$BJ$220,MATCH($BP$1,$BI$3:$BI$220,0),2)),0) -> 0 | BY1: =IFERROR(MATCH($BS$1,$BL$3:BL220,0),0) -> 0 | BZ1: =IFERROR(MATCH($BS$2,$BL$3:$BL$220,0),0) -> 0 | CA1: =BR221 -> 0 | CB1: =BW221 -> 0 | CD1: SE COSTI | CE1: SE COSTI | CF1: SITUAZIONE ECONOMICA | CG1: SE COSTI | CH1: =IF(AND(CM1=0,CP1=0,CB1=0,CA1=0,LIBRO_GIORNALE!G4=0,LIBRO_GIORNALE!H4=0,VALORI_INIZIALI!H3=0,VALORI_INIZIALI!I3=0),0,1) -> 0 | CK1: SE RICAVI | CL1: TOT RICAVI | CM1: =IF(DU231<>$DV$231,0,SUM($CQ$3:$CQ$230)) -> 0 | CO1: TOT COSTI | CP1: =IF($DU$231<>$DV$231,0,SUM($CJ$3:$CJ$230)) -> 0 | CQ1: FINALE RICAVI | CR1: =IF(MAX($CM$2,$CP$2)=0,"","SITUAZIONE ECONOMICA") | CS1: mastri aperti | CU1: =TODAY() -> 46107 | CV1: 1 | CW1: =YEAR(CU1) -> 2026 | CX1: =DATE(CW1,CV1,CV1) -> 46023 | CY1: =FB1 -> 31 | CZ1: =FA1 -> 12 | DA1: =DATE(CW1,CZ1,CY1) -> 46387 | DB1: FILTRO VALORI INIZIALI | DC1: 15 | DD1: 1 | DE1: 1 | DF1: =IF(ISNUMBER(DE1),INDEX($O$3:$P$48,MATCH($DE$1,$P$3:$P$48,0),1),DE1) -> VISUALIZZA TUTTI I CONTI | DG1: =SUM(MAX(DF3:DF2300),1) -> 1 | DH1: =MAX($DH$3:$DH$220) -> 0 | DI1: =CX2-SUM(COUNTIFS($DE$3:$DE$2300,"="&"s*"),COUNTIFS($DD$3:$DD$2300,"="&"s*")) -> 0 | DJ1: SE ECCEDENZE | DM1: TOT DARE | DN1: TOT AVERE | DO1: ECC. DARE | DP1: ECC AVERE | DQ1: =IF($DU$1=1,"TOTALI",IF($DU$1=2,"ECCEDENZE",IF($DU$1=3,"TOTALI ED ECCEDENZE",""))) -> TOTALI ED ECCEDENZE | DS1: dare | DT1: avere | DU1: =IF(INDIRECT(ADDRESS(3,2,,,"SIT._CONTABILE"))="PER TOTALI",1,IF(INDIRECT(ADDRESS(3,2,,,"SIT._CONTABILE"))="PER ECCEDENZE",2,3)) -> 3 | DV1: MAX TOTALE | DW1: =MAX($DQ$3:$DQ$230) -> 0 | DX1: TOTALE | DY1: IMPORTO | EJ1: =IFERROR(IF((INDEX($EM$3:$EN$500,MATCH($EL$1,$EM$3:$EM$500,0),2)-1)=0,2,INDEX($EM$3:$EN$500,MATCH($EL$1,$EM$3:$EM$500,0),2)-1),0) -> 2 | EL1: =MAX($EM$3:EM500) -> 0 | EM1: =$DD$2 -> 46037 | EN1: =IF(INDIRECT(ADDRESS(5,7,,,"VALORI_INIZIALI"))="Riporta la descrizione valore iniziale",TRUE,FALSE) -> TRUE | EO1: =IF(INDIRECT(ADDRESS(2,2,,,"SIT.PATR._SIT.ECON."))="VISUALIZZA IL RISULTATO ECONOMICO",TRUE,FALSE) -> TRUE | EP1: CONTI SUDDIVISI PER CLASSIFICAZIONE | ES1: =IF(EV1>0,CONCATENATE("Verifica che: ",EW3,EW4,EW5,EW6),"") -> Verifica che: Il conto PATRIMONIO NETTO sia acceso | ET1: =CONCATENATE(ET3," ",ET4," ",ET5) | EU1: =IF(EV1>0,EV1,1) -> 1 | EV1: =COUNTIFS($EV$3:$EV$30,">"&0) -> 1 | EW1: =IF(EY1=1,"n","n+1") -> n | EX1: =IF(INDIRECT(ADDRESS(6,8,,,"LIBRO_GIORNALE"))="ATTIVA",1,INDIRECT(ADDRESS(6,8,,,"LIBRO_GIORNALE"))+1) -> 1 | EY1: =IF(INDIRECT(ADDRESS(6,4,,,"LIBRO_GIORNALE"))="N+1",2,1) -> 1 | EZ1: =CW1+EY1-1 -> 2026 | FA1: =IF(INDIRECT(ADDRESS(6,3,,,"LIBRO_GIORNALE"))=0,12,INDIRECT(ADDRESS(6,3,,,"LIBRO_GIORNALE"))) -> 12 | FB1: =IF(INDIRECT(ADDRESS(6,2,,,"LIBRO_GIORNALE"))=0,31,INDIRECT(ADDRESS(6,2,,,"LIBRO_GIORNALE"))) -> 31 | FC1: =DATE(EZ1,FA1,FB1) -> 46387 | FD1: =ROUND(SUMIFS(dare_grezzo,$FD$3:$FD$400,"="&"SE DARE",data_grezzo,">="&INIZIO_A_PC,data_grezzo,"<="&FINE_A_PC),2) -> 0 | FE1: =ROUND(SUMIFS(avere_grezzo,$FD$3:$FD$400,"="&"SE AVERE",data_grezzo,">="&INIZIO_A_PC,data_grezzo,"<="&FINE_A_PC),2) -> 0 | FF1: =IF(EY1=2,IF(AND(FD1>=FD2,FE1>=FE2),FE1+FD2-FD1-FE2,0),0) -> 0 | FM1: =MAX(FN3:FN400) -> 0 | FQ1: COSTI | FR1: RICAVI | FS1: PRELEVAMENTI EXTRAGESTIONE | FT1: TITOLARE C/RITENUTE SUBITE | FU1: PATRIMONIO NETTO | FX1: =MAX(FX3:FX400)+5 -> 178 | GB1: =BR222 | GC1: =MIN(FQ$3:FQ$400) -> 1 | GD1: =MIN(FR$3:FR$400) -> 22 | GE1: =MIN(FS$3:FS$400) -> 90 | GF1: =MIN(FT$3:FT$400) -> 132 | GK1: =MAX(FQ$3:FQ$400) -> 19 | GL1: =MAX(FR$3:FR$400) -> 76 | GM1: =MAX(FS$3:FS$400) -> 131 | GN1: =MAX(FT$3:FT$400) -> 173 | GO1: SCRITTURE DI CHIUSURA | GP1: =IF(INDIRECT(ADDRESS(4,2,,,"CHIUS.-APERT."))="SCRITTURE DI CHIUSURA",1,2) -> 1 | GT1: =IF(AND(GP1=1,GT2=0),"",IF(AND(GP1=2,IW1=0),"",CONCATENATE("Si segnala uno sbilancio pari a ",FIXED(IF(GP1=1,GT2,IW1),2,1)," euro"))) | GW1: =MAX(GU3:GU400) -> 0 | GX1: IVA | GZ1: =IF(GY2>0,CONCATENATE("Non sono stati girati i seguenti conti: ",GY3,GY4,GY5,GY6,GY7,GY8),"") | HL1: apertura | HW1: =SUMIFS(COPIA!$FB$103:$FB$400,COPIA!$EW$103:$EW$400,"&"=1,COPIA!$EY$103:$EY$400,"&">=INIZIO_AC,COPIA!$EY$103:$EY$400,"&"<=FINE_AC) -> 0 | HY1: =SUM(IG39:IG43,IG78,IG90,IG92)-SUM(IG48:IG65) -> 0 | IB1: =IG21+IG23+IG26+IG28+IG30+IG33 -> 0 | ID1: =IFERROR(IF(INDIRECT(ADDRESS(3,2,,,"BILANCIO"))="BILANCIO DELLE MICRO IMPRESE",1,2),2) -> 1 | IE1: =MAX(IH3:IH17) -> 0 | IF1: =MAX(IH20:IH33) -> 0 | IG1: =MAX(IE1,IF1)+1 -> 1 | IH1: =-1+IJ1 -> 0 | IJ1: =IF(INDIRECT(ADDRESS(3,3,,,"BILANCIO"))="RIGHE TRA I PROSPETTI",1,INDIRECT(ADDRESS(3,3,,,"BILANCIO"))+1) -> 1 | IK1: =SUM(MAX(IH3:IH34),MAX(IH35:IH93),IH1) -> 5 | IQ1: =MAX(IQ3:IQ200) -> 0 | IW1: =ABS(IX1-IY1) -> 0 | IX1: =SUM(IX3:IX200) -> 0 | IY1: =SUM(IY3:IY200) -> 0 | JA1: anno | JG1: =IF(INDIRECT(ADDRESS(5,5,,,"CONTI_DI_MASTRO"))="VISUALIZZA PRIMA I CONTI DELL'ULTIMO ARTICOLO",1,0) -> 0 | JL1: =IF(CX2>0,CONCATENATE("Numero dei conti visualizzati: ",CX2),"Nessun conto visualizzato") -> Nessun conto visualizzato | JM1: =IF(JM2>0,"I movimenti non sono in ordine cronologico","")
N2: =INDIRECT(ADDRESS(3,5,,,"LIBRO_GIORNALE")) | R2: =MAX(P3:P150) -> 31 | Z2: CODICE | AA2: DENOMINAZIONE | AB2: NATURA | AC2: ECCEDENZA | AD2: CLASSIFICAZIONE | AE2: DESTINAZIONE | AF2: RAGRUPPAMENTO | AG2: BLOCCO-A | AH2: BLOCCO-B | AI2: BLOCCO-C | AN2: N+1 | BS2: TITOLARE C/RITENUTE SUBITE | BV2: =IF(AND($BY$1>0,$BZ$1>0),(MAX($V$3:$V$220))-2,IF(AND($BY$1=0,$BZ$1=0),MAX($V$3:$V$220),IF(AND($BY$1=0,$BZ$1>0),MAX($V$3:$V$220)-1,IF(AND($BZ$1=0,$BY$1>0),MAX($V$3:$V$220)-1,0)))) -> 0 | BW2: =MAX($BK$3:$BK$220)-1 -> -1 | BX2: =IF(BX1>=0,BP1,"") -> PATRIMONIO NETTO | BY2: =IF(BY1>0,BS1,"") | BZ2: =IF(INDIRECT(ADDRESS(3,8,,,"SIT.PATR._SIT.ECON."))="RIGHE TRA I PROSPETTI",1,INDIRECT(ADDRESS(3,8,,,"SIT.PATR._SIT.ECON."))+1) -> 1 | CA2: 13 | CB2: =BZ2-1+CA2 -> 13 | CC2: =CB2-1 -> 12 | CM2: =MAX($CO$3:$CO$230) -> 0 | CP2: =MAX($CH$3:$CH$230) -> 0 | CR2: =IF(MAX($CM$2,$CP$2)=0,"","COSTI") | CS2: dare | CT2: avere | CV2: VISUALIZZA UN CONTO IN EVIDENZA | CW2: 0 | CX2: =MAX(CW3:CW220) -> 0 | CY2: mastro | CZ2: =CONTI_DI_MASTRO!D5 -> VISUALIZZA UN CONTO IN EVIDENZA | DA2: =IF(INDIRECT(ADDRESS(5,9,,,"CONTI_DI_MASTRO"))="VISUALIZZA I MOVIMENTI DEI CONTI E IL SALDO",TRUE,FALSE) -> TRUE | DB2: =IF(OR($DC$1=0,$DD$1=0),$CW$1-1,$CW$1) -> 2026 | DC2: data mastri | DD2: =DATE($DB$2,$DD$1,$DC$1) -> 46037 | DE2: =IFERROR(INDEX($CV$2:$CW$220,MATCH($CZ$2,$CV$2:$CV$220,0),2),0) -> 0 | DF2: =IF(DE2>0,MAX(DF2163:DF2300)+1,0) -> 0 | DM2: =FB1 -> 31 | DN2: =FA1 -> 12 | DO2: =IF(OR($DM$2=0,$DN$2=0),$CW$1-1,$CW$1) -> 2026 | DS2: =IF(FB1<10,CONCATENATE(0,FB1),FB1) -> 31 | DT2: =IF(FA1<10,CONCATENATE(0,FA1),FA1) -> 12 | DU2: =EW1 -> n | DW2: FORMATTAZIONE | DY2: TOT O ECC | DZ2: TOT E ECC | EA2: ordine mastri | EE2: =IF(MAX($CM$2,$CP$2)>0,"RICAVI","") | EO2: =DATE(CW1,12,31) -> 46387 | EP2: CONTI SUDDIVISI PER RAGGRUPPAMENTO | EQ2: =MAX(ER3:ER500) -> 0 | EU2: I TOTALI SONO CORRETTAMENTE VISUALIZZATI | EV2: =IF(EV1=0,1,0) -> 0 | EW2: PIENA | EX2: =DATE(CW1,12,31) -> 46387 | EY2: =DATE(CW1,1,1) -> 46023 | EZ2: =EZ1 -> 2026 | FA2: 1 | FB2: 1 | FC2: =DATE(EZ2,FA2,FB2) -> 46023 | FD2: =ROUND(SUMIFS(avere_grezzo,$FD$3:$FD$400,"="&"SE DARE",data_grezzo,">="&INIZIO_A_PC,data_grezzo,"<="&FINE_A_PC),2) -> 0 | FE2: =ROUND(SUMIFS(dare_grezzo,$FD$3:$FD$400,"="&"SE AVERE",data_grezzo,">="&INIZIO_A_PC,data_grezzo,"<="&FINE_A_PC),2) -> 0 | FR2: =MAX(FQ3:FQ400)+2 -> 21 | FS2: =MAX(FR2:FR400)+13 -> 89 | FT2: =MAX(FS2:FS400) -> 131 | GG2: dare | GH2: avere | GI2: dare | GJ2: avere | GO2: SCRITTURE DI APERTURA | GR2: =SUM($GO$3:$GO$200) -> 0 | GS2: =SUM($GP$3:$GP$200) -> 0 | GT2: =ABS(GR2-GS2) -> 0 | GW2: =IF(GW1>0,CONCATENATE("Non sono stati girati i seguenti conti: ",GW3,GW4,GW5,GW6,GW7,GW8),"") | GY2: =MAX(GX3:GX400) -> 0 | HL2: =COUNTA(HL3:HL102)-COUNTBLANK(HL3:HL102) -> 0 | HM2: =COUNTA(HM3:HM102)-COUNTBLANK(HM3:HM102) -> 0 | HN2: =COUNTA(HN3:HN102)-COUNTBLANK(HN3:HN102) -> 0 | HP2: =IF(HM2=0,HL2+1,HL2+2) -> 1 | HQ2: =HP2+HM2+HN2 -> 1 | IB2: =IG18 | IX2: DARE | IY2: AVERE | IZ2: DESCRIZIONE | JM2: =SUM(JM103:JM400) -> 0
A3: =GZ3 -> 01.00 | B3: =HA3 -> IMMOBILIZZAZIONI IMMATERIALI | C3: =HB3 -> 0 | D3: =HC3 -> 0 | E3: =HD3 -> 0 | F3: =HE3 -> 0 | G3: =IF(EI3=TRUE,1,0) -> 0 | H3: =IF(EJ3=TRUE,1,0) -> 0 | I3: =IF(EK3=TRUE,1,0) -> 0 | J3: =IF(INDIRECT(ADDRESS(6,6,,,"LIBRO_GIORNALE"))="DELIMITAZIONE ARTICOLO ATTIVATA",TRUE,FALSE) -> TRUE | K3: =IFERROR(IF($I$1=1,INDEX($AA$3:$AS$220,MATCH(ROWS($K$3:K3),$AQ$3:$AQ$220,0),1),IF($I$1=2,INDEX($AA$3:$AS$220,MATCH(ROWS($K$3:K3),$AR$3:$AR$220,0),1),IF($I$1=3,INDEX($AA$3:$AS$220,MATCH(ROWS($K$3:K3),$AS$3:$AS$220,0),1),""))),"") -> COSTI DI IMPIANTO | L3: =IF(AND($L$1="VISUALIZZA TUTTI I CONTI",K3<>""),MAX(L2:L2)+1,IFERROR(IF($J$1=1,IF(INDEX(PIANO_DEI_CONTI,MATCH($K3,DENOMINAZIONE,0),5)=$L$1,MAX($L$2:L2)+1,0),IF($J$1=2,IF(INDEX(PIANO_DEI_CONTI,MATCH($K3,DENOMINAZIONE,0),7)=$L$1,MAX($L$2:L2)+1,0))),0)) -> 1 | M3: =IFERROR(INDEX($K$3:$K$220,MATCH(ROWS($M$3:M3),$L$3:$L$220,0),1),"") -> COSTI DI IMPIANTO | N3: VISUALIZZA TUTTI I CONTI | O3: VISUALIZZA TUTTI I CONTI | P3: =IF(AND(N3=O3,O3<>""),MAX(P$2:P2)+1,0) -> 1 | Q3: =IF(IFERROR(INDEX($O$3:$P$220,MATCH(ROWS(Q$3:Q3),$P$3:$P$220,0),1),"")=0,"",IFERROR(INDEX($O$3:$P$220,MATCH(ROWS(Q$3:Q3),$P$3:$P$220,0),1),"")) -> VISUALIZZA TUTTI I CONTI | R3: =IF(OR(INDEX(PIANO_DEI_CONTI,MATCH(AA3,DENOMINAZIONE,0),6)="SP DARE",INDEX(PIANO_DEI_CONTI,MATCH(AA3,DENOMINAZIONE,0),6)="SP DARE/AVERE"),AA3,"") -> COSTI DI IMPIANTO | S3: =IF(IFERROR(MATCH(R3,DENOMINAZIONE_GIORNALE,0),0)>0,MAX(S$2:S2)+1,0) -> 0 | T3: =IFERROR(INDEX($R$3:$S$220,MATCH(ROWS($T$3:T3),$S$3:$S$220,0),1),"") | U3: =IFERROR(IF(IF(AND(OR(INDEX(PIANO_DEI_CONTI,MATCH(T3,DENOMINAZIONE,0),6)="SP DARE",INDEX(PIANO_DEI_CONTI,MATCH(T3,DENOMINAZIONE,0),6)="SP DARE/AVERE"),SUMIFS(DARE,DENOMINAZIONE_GIORNALE,T3,DARE,">"&0)>SUMIFS(AVERE,DENOMINAZIONE_GIORNALE,T3,AVERE,">"&0)),SUMIFS(DARE,DENOMINAZIONE_GIORNALE,T3,DARE,">"&0)-SUMIFS(AVERE,DENOMINAZIONE_GIORNALE,T3,AVERE,">"&0),0)<>0,IF(AND(OR(INDEX(PIANO_DEI_CONTI,MATCH(T3,DENOMINAZIONE,0),6)="SP DARE",INDEX(PIANO_DEI_CONTI,MATCH(T3,DENOMINAZIONE,0),6)="SP DARE/AVERE"),SUMIFS(DARE,DENOMINAZIONE_GIORNALE,T3,DARE,">"&0)>SUMIFS(AVERE,DENOMINAZIONE_GIORNALE,T3,AVERE,">"&0)),SUMIFS(DARE,DENOMINAZIONE_GIORNALE,T3,DARE,">"&0)-SUMIFS(AVERE,DENOMINAZIONE_GIORNALE,T3,AVERE,">"&0),0),0),0) -> 0 | V3: =IF(IF(U3<>0,MAX($V$2:V2)+1,0)=0,0,IF(U3<>0,MAX($V$2:V2)+1,0)) -> 0 | W3: =IF(MID(A3,3,3)=".00","",A3) | X3: =IFERROR(INDEX($A$3:$B$220,MATCH(W3,$A$3:$A$220,0),2),"") | Y3: =IF(W3="",0,MAX($Y$2:Y2)+1) -> 0 | Z3: =IFERROR(INDEX($W$3:$Y$220,MATCH(ROWS($Z$2:Z2),$Y$3:$Y$220,0),1),"") -> 01.01 | AA3: =IFERROR(INDEX($A$3:$I$220,MATCH($Z3,$A$3:$A$220,0),2),"") -> COSTI DI IMPIANTO | AB3: =IFERROR(INDEX($A$3:$I$220,MATCH($Z3,$A$3:$A$220,0),3),"") -> E | AC3: =IFERROR(INDEX($A$3:$I$220,MATCH($Z3,$A$3:$A$220,0),4),"") -> D | AD3: =IFERROR(INDEX($A$3:$I$220,MATCH($Z3,$A$3:$A$220,0),5),"") -> COSTI PLURIENNALI | AE3: =IFERROR(INDEX($A$3:$I$220,MATCH($Z3,$A$3:$A$220,0),6),"") -> SP DARE | AF3: =AP3 -> IMMOBILIZZAZIONI IMMATERIALI | AG3: =IFERROR(INDEX($A$3:$I$220,MATCH($Z3,$A$3:$A$220,0),7),"") -> 1 | AH3: =IFERROR(INDEX($A$3:$I$220,MATCH($Z3,$A$3:$A$220,0),8),"") -> 1 | AI3: =IFERROR(INDEX($A$3:$I$220,MATCH($Z3,$A$3:$A$220,0),9),"") -> 1 | AJ3: =MID(Z3,1,2) -> 01 | AK3: =IF(MID($A3,3,3)=".00",MID(A3,1,2),"") -> 01 | AL3: =IF(AK3<>"",MAX($AL$2:AL2)+1,0) -> 1 | AM3: =IFERROR(INDEX($AK$3:$AL$220,MATCH(ROWS($AM$3:AM3),$AL$3:$AL$220,0),1),"") -> 01 | AN3: =IF(AM3<>"",CONCATENATE(AM3,".00"),"") -> 01.00 | AO3: =IFERROR(INDEX($A$3:$B$220,MATCH(AN3,$A$3:$A$220,0),2),"") -> IMMOBILIZZAZIONI IMMATERIALI | AP3: =IFERROR(INDEX($AJ$3:$AP$220,MATCH(AJ3,$AM$3:$AM$220,0),6),"") -> IMMOBILIZZAZIONI IMMATERIALI | AQ3: =IF(OR(AG3=0,AG3=""),0,MAX(AQ$2:AQ2)+1) -> 1 | AR3: =IF(OR(AH3=0,AH3=""),0,MAX(AR$2:AR2)+1) -> 1 | AS3: =IF(OR(AI3=0,AI3=""),0,MAX(AS$2:AS2)+1) -> 1 | AT3: =IFERROR(INDEX($AD$3:$AS$220,MATCH(ROWS(AT$3:AT3),AQ$3:AQ$220,0),1),"") -> COSTI PLURIENNALI | AU3: =IFERROR(INDEX($AD$3:$AS$220,MATCH(ROWS(AU$3:AU3),AR$3:AR$220,0),1),"") -> COSTI PLURIENNALI | AV3: =IFERROR(INDEX($AD$3:$AS$220,MATCH(ROWS(AV$3:AV3),AS$3:AS$220,0),1),"") -> COSTI PLURIENNALI | AW3: =IFERROR(INDEX($AP$3:$AS$220,MATCH(ROWS(AW$3:AW3),AQ$3:AQ$220,0),1),"") -> IMMOBILIZZAZIONI IMMATERIALI | AX3: =IFERROR(INDEX($AP$3:$AS$220,MATCH(ROWS(AX$3:AX3),AR$3:AR$220,0),1),"") -> IMMOBILIZZAZIONI IMMATERIALI | AY3: =IFERROR(INDEX($AP$3:$AS$220,MATCH(ROWS(AY$3:AY3),AS$3:AS$220,0),1),"") -> IMMOBILIZZAZIONI IMMATERIALI | AZ3: =IF(BA3=0,"",CONCATENATE(ROW()-2," A.")) | BA3: =IF(BB3<>0,INIZIO_AC,0) -> 0 | BB3: =IFERROR(INDEX($FG$3:$FL$400,MATCH(ROWS($BB$3:BB3),$FL$3:$FL$400,0),1),0) -> 0 | BC3: =IF(BB3<>0,"apertura del conto","") | BD3: =IFERROR(INDEX($FG$3:$FL$400,MATCH(ROWS($BD$3:BD3),$FL$3:$FL$400,0),4),0) -> 0 | BE3: =IFERROR(INDEX($FG$3:$FL$400,MATCH(ROWS($BE$3:BE3),$FL$3:$FL$400,0),5),0) -> 0 | BF3: PER TOTALI | BG3: =IFERROR(IF(OR(INDEX(PIANO_DEI_CONTI,MATCH(AA3,DENOMINAZIONE,0),6)="SP AVERE",INDEX(PIANO_DEI_CONTI,MATCH(AA3,DENOMINAZIONE,0),6)="SP DARE/AVERE"),AA3,""),0) | BH3: =IF(IFERROR(MATCH(BG3,DENOMINAZIONE_GIORNALE,0),0)>0,MAX(BH$2:BH2)+1,0) -> 0 | BI3: =IFERROR(INDEX($BG$3:$BH$220,MATCH(ROWS($BI$3:BI3),$BH$3:$BH$220,0),1),"") | BJ3: =IF(IF(AND(OR(INDEX(PIANO_DEI_CONTI,MATCH(BI3,DENOMINAZIONE,0),6)="SP AVERE",INDEX(PIANO_DEI_CONTI,MATCH(BI3,DENOMINAZIONE,0),6)="SP DARE/AVERE"),SUMIFS(AVERE,DENOMINAZIONE_GIORNALE,BI3,AVERE,">"&0)>SUMIFS(DARE,DENOMINAZIONE_GIORNALE,BI3,DARE,">"&0)),SUMIFS(AVERE,DENOMINAZIONE_GIORNALE,BI3,AVERE,">"&0)-SUMIFS(DARE,DENOMINAZIONE_GIORNALE,BI3,DARE,">"&0),0)<>0,IF(AND(OR(INDEX(PIANO_DEI_CONTI,MATCH(BI3,DENOMINAZIONE,0),6)="SP AVERE",INDEX(PIANO_DEI_CONTI,MATCH(BI3,DENOMINAZIONE,0),6)="SP DARE/AVERE"),SUMIFS(AVERE,DENOMINAZIONE_GIORNALE,BI3,AVERE,">"&0)>SUMIFS(DARE,DENOMINAZIONE_GIORNALE,BI3,DARE,">"&0)),SUMIFS(AVERE,DENOMINAZIONE_GIORNALE,BI3,AVERE,">"&0)-SUMIFS(DARE,DENOMINAZIONE_GIORNALE,BI3,DARE,">"&0),0),"") | BK3: =IF(IF(BJ3<>"",MAX($BK$2:BK2)+1,0)=0,"",IF(BJ3<>"",MAX($BK$2:BK2)+1,0)) | BL3: =IFERROR(INDEX($T$3:$U$220, MATCH(ROWS(BL$3:BL3),$V$3:$V$220,0),1),"") | BM3: =IFERROR(INDEX($T$3:$U$220, MATCH(ROWS(BM$3:BM3),$V$3:$V$220,0),2),"") | BN3: =IF(IFERROR(INDEX($BI$3:$BJ$220,MATCH(ROWS(BN$3:BN3),$BK$3:$BK$220,0),1),"")="PATRIMONIO NETTO","",IFERROR(INDEX($BI$3:$BJ$220,MATCH(ROWS(BN$3:BN3),$BK$3:$BK$220,0),1),"")) | BO3: =IFERROR(INDEX($BI$3:$BJ$220,MATCH(ROWS(BO$3:BO3),$BK$3:$BK$220,0),2),"") | BP3: =IF(BN3<>"",MAX(BP$2:$BP2)+1,0) -> 0 | BQ3: =IFERROR(INDEX($BN$3:$BO$200,MATCH(ROWS(BQ$3:BQ3),$BP$3:$BP$220,0),1),"") | BR3: =IFERROR(INDEX($BN$3:$BO$220,MATCH(ROWS(BR$3:BR3),$BP$3:$BP$220,0),2),"") | BS3: =IFERROR(IF(OR(INDEX($T$3:$U$220,MATCH(ROWS(BL$3:BL3),$V$3:$V$220,0),1)="PRELEVAMENTI EXTRAGESTIONE",INDEX($T$3:$U$220,MATCH(ROWS(BL$3:BL3),$V$3:$V$220,0),1)="TITOLARE C/RITENUTE SUBITE"),"",INDEX($T$3:$U$220,MATCH(ROWS(BL$3:BL3),$V$3:$V$220,0),1)),"") | BT3: =INDEX($T$3:$U$220,MATCH(BS3,$T$3:$T$220,0),2) -> 0 | BU3: =IF(BS3<>"",MAX(BU$2:BU2)+1,0) -> 0 | BV3: =IFERROR(INDEX($BS$3:$BT$223,MATCH(ROWS(BV$3:BV3),$BU$3:$BU$223,0),1),"") | BW3: =INDEX($BS$3:$BT$220,MATCH(BV3,$BS$3:$BS$223,0),2) -> 0 | BX3: =IF($EV$1>0,"",IF($EO$1=TRUE,SUBSTITUTE(IF(OR($DS$231<>$DT$231,$DS$232<>$DT$232,$DU$231<>$DV$231),"",IF($BX$1=0,"",IF((ROW()-2)=MAX($BV$2:$BW$2)+1,"TOTALE PASSIVITÀ",IF((ROW()-2)=MAX($BV$2:$BW$2)+2,"PATRIMONIO NETTO",IF(AND((ROW()-2)=MAX($BV$2,$BW$2)+3,$CM$1>$CP$1,$DU$231=$DV$231),"SALDO ECONOMICO POSITIVO",IF(AND((ROW()-2)=MAX($BV$2,$BW$2)+4,$CM$1>$CP$1,$DU$231=$DV$231),"TOTALE",IF(AND((ROW()-2)=MAX($BV$2,$BW$2)+4,$CM$1<$CP$1,$DU$231=$DV$231,$BY$1=0,$BZ$1>0,$BX$1>0),"TOTALE",IF(AND((ROW()-2)=MAX($BV$2,$BW$2)+3,$CM$1=$CP$1,$DU$231=$DV$231,$BY$1>0,$BZ$1=0,$BX$1>0),"TOTALE",IF(AND((ROW()-2)=MAX($BV$2,$BW$2)+3,$CM$1=$CP$1,$DU$231=$DV$231,$BY$1=0,$BZ$1>0,$BX$1>0),"TOTALE",IF(AND((ROW()-2)=MAX($BV$2,$BW$2)+3,$CM$1=$CP$1,$DU$231=$DV$231,$BY$1=0,$BZ$1=0,$BX$1>0),"TOTALE A PAREGGIO",IF(AND((ROW()-2)=MAX($BV$2,$BW$2)+4,$CM$1=$CP$1,$DU$231=$DV$231,$BY$1>0,$BZ$1>0,$BX$1>0),"TOTALE",IF(AND((ROW()-2)=MAX($BV$2,$BW$2)+3,$CM$1=$CP$1,$DU$231=$DV$231,$BY$1=0,$BY$1>0,$BZ$1=0,$BX$1>0),"TOTALE",IF(AND((ROW()-2)=MAX($BV$2,$BW$2)+4,$CM$1<$CP$1,$DU$231=$DV$231,$BY$1>0,$BZ$1=0),"TOTALE",IF(AND((ROW()-2)=MAX($BV$2,$BW$2)+5,$CM$1<$CP$1,$DU$231=$DV$231,$BY$1>0,$BZ$1>0),"TOTALE",IF(AND((ROW()-2)=MAX($BV$2,$BW$2)+3,$CM$1<$CP$1,$DU$231=$DV$231,$BY$1=0,$BZ$1=0),"TOTALE",IF(AND((ROW()-2)=MAX($BV$2,$BW$2)+3,$CM$1=0,$CP$1=0,$DU$231=$DV$231,$BY$1=0,$BZ$1=0),"TOTALE",IF(AND((ROW()-2)=MAX($BV$2,$BW$2)+4,$CM$1=$CP$1,$DU$231=$DV$231,$BY$1>0,$BZ$1>0),"TOTALE",""))))))))))))))))),"SALDO ECONOMICO POSITIVO","UTILE D'ESERCIZIO"),IF(OR($DS$231<>$DT$231,$DS$232<>$DT$232,$DU$231<>$DV$231),"",IF($BX$1=0,"",IF((ROW()-2)=MAX($BV$2:$BW$2)+1,"TOTALE PASSIVITÀ",IF((ROW()-2)=MAX($BV$2:$BW$2)+2,"PATRIMONIO NETTO",IF(AND((ROW()-2)=MAX($BV$2,$BW$2)+3,$CM$1>$CP$1,$DU$231=$DV$231),"SALDO ECONOMICO POSITIVO",IF(AND((ROW()-2)=MAX($BV$2,$BW$2)+4,$CM$1>$CP$1,$DU$231=$DV$231),"TOTALE",IF(AND((ROW()-2)=MAX($BV$2,$BW$2)+4,$CM$1<$CP$1,$DU$231=$DV$231,$BY$1=0,$BZ$1>0,$BX$1>0),"TOTALE",IF(AND((ROW()-2)=MAX($BV$2,$BW$2)+3,$CM$1=$CP$1,$DU$231=$DV$231,$BY$1>0,$BZ$1=0,$BX$1>0),"TOTALE",IF(AND((ROW()-2)=MAX($BV$2,$BW$2)+3,$CM$1=$CP$1,$DU$231=$DV$231,$BY$1=0,$BZ$1>0,$BX$1>0),"TOTALE",IF(AND((ROW()-2)=MAX($BV$2,$BW$2)+3,$CM$1=$CP$1,$DU$231=$DV$231,$BY$1=0,$BZ$1=0,$BX$1>0),"TOTALE A PAREGGIO",IF(AND((ROW()-2)=MAX($BV$2,$BW$2)+4,$CM$1=$CP$1,$DU$231=$DV$231,$BY$1>0,$BZ$1>0,$BX$1>0),"TOTALE",IF(AND((ROW()-2)=MAX($BV$2,$BW$2)+3,$CM$1=$CP$1,$DU$231=$DV$231,$BY$1=0,$BY$1>0,$BZ$1=0,$BX$1>0),"TOTALE",IF(AND((ROW()-2)=MAX($BV$2,$BW$2)+4,$CM$1<$CP$1,$DU$231=$DV$231,$BY$1>0,$BZ$1=0),"TOTALE",IF(AND((ROW()-2)=MAX($BV$2,$BW$2)+5,$CM$1<$CP$1,$DU$231=$DV$231,$BY$1>0,$BZ$1>0),"TOTALE",IF(AND((ROW()-2)=MAX($BV$2,$BW$2)+3,$CM$1<$CP$1,$DU$231=$DV$231,$BY$1=0,$BZ$1=0),"TOTALE",IF(AND((ROW()-2)=MAX($BV$2,$BW$2)+3,$CM$1=0,$CP$1=0,$DU$231=$DV$231,$BY$1=0,$BZ$1=0),"TOTALE",IF(AND((ROW()-2)=MAX($BV$2,$BW$2)+4,$CM$1=$CP$1,$DU$231=$DV$231,$BY$1>0,$BZ$1>0),"TOTALE",""))))))))))))))))))) | BY3: =IF($EV$1>0,"",IF($EO$1=TRUE,SUBSTITUTE(IF(OR($BB$1<>$BD$1,$BC$1<>$BE$1,$DS$231<>$DT$231,$DS$232<>$DT$232,$DU$231<>$DV$231),"",IF($BX$1=0,"",IF(AND((ROW()-2)=MAX($BV$2:$BW$2)+1,OR($BY$1>0,$BZ$1>0,$CP$1>$CM$1)),"TOTALE ATTIVITÀ",IF(AND((ROW()-2)=MAX($BV$2:$BW$2)+2,$BY$1>0),"PRELEVAMENTI EXTRAGESTIONE",IF(AND((ROW()-2)=MAX($BV$2:$BW$2)+2,$BY$1=0,$BZ$1>0),"TITOLARE C/RITENUTE SUBITE",IF(AND((ROW()-2)=MAX($BV$2:$BW$2)+3,$BY$1>0,$BZ$1>0),"TITOLARE C/RITENUTE SUBITE",IF(AND((ROW()-2)=MAX($BV$2:$BW$2)+2,$BY$1=0,$BZ$1=0,$CP$1>$CM$1),"SALDO ECONOMICO NEGATIVO",IF(AND((ROW()-2)=MAX($BV$2:$BW$2)+3,$BY$1>0,$BZ$1=0,$CP$1>$CM$1),"SALDO ECONOMICO NEGATIVO",IF(AND((ROW()-2)=MAX($BV$2:$BW$2)+3,$BY$1=0,$BZ$1>0,$CP$1>$CM$1),"SALDO ECONOMICO NEGATIVO",IF(AND((ROW()-2)=MAX($BV$2:$BW$2)+4,$BY$1>0,$BZ$1>0,$CP$1>$CM$1),"SALDO ECONOMICO NEGATIVO",IF(AND((ROW()-2)=MAX($BV$2:$BW$2)+3,$BY$1=0,$BZ$1=0,$CP$1>$CM$1),"TOTALE",IF(AND((ROW()-2)=MAX($BV$2:$BW$2)+4,$BY$1>0,$BZ$1=0,$CP$1<$CM$1),"TOTALE",IF(AND((ROW()-2)=MAX($BV$2:$BW$2)+4,$BY$1=0,$BZ$1>0,$CP$1<$CM$1),"TOTALE",IF(AND((ROW()-2)=MAX($BV$2:$BW$2)+4,$BY$1>0,$BZ$1=0,$CP$1>$CM$1),"TOTALE",IF(AND((ROW()-2)=MAX($BV$2:$BW$2)+4,BX1>0,BY$1=0,$BZ$1>0,$CP$1>$CM$1),"TOTALE",IF(AND((ROW()-2)=MAX($BV$2:$BW$2)+3,BX1>0,BY$1=0,$BZ$1=0,$CP$1=$CM$1),"TOTALE ATTIVITÀ",IF(AND((ROW()-2)=MAX($BV$2:$BW$2)+4,$BX$1>0,$BY$1>0,$BZ$1>0,$CP$1=$CM$1),"TOTALE",IF(AND((ROW()-2)=MAX($BV$2:$BW$2)+3,$BX$1>0,$BY$1=0,$BZ$1>0,$CP$1=$CM$1),"TOTALE",IF(AND((ROW()-2)=MAX($BV$2:$BW$2)+3,$BX$1>0,$BY$1>0,$BZ$1=0,$CP$1=$CM$1),"TOTALE",IF(AND((ROW()-2)=MAX($BV$2:$BW$2)+4,$BX$1>0,$BY$1>0,$BZ$1>0,$CP$1<$CM$1),"TOTALE",IF(AND((ROW()-2)=MAX($BV$2:$BW$2)+4,$BY$1=0,$BZ$1=0,$CP$1<$CM$1),"TOTALE",IF(AND((ROW()-2)=MAX($BV$2:$BW$2)+5,$BY$1>0,$BZ$1>0,$CP$1>$CM$1),"TOTALE",IF(AND((ROW()-2)=MAX($BV$2:$BW$2)+3,$BY$1=0,$BZ$1=0,$CP$1=0,$CM$1=0),"TOTALE",IF(AND((ROW()-2)=MAX($BV$2:$BW$2)+4,$BY$1>0,$BZ$1>0,$CP$1>0,$CM$1>0,$CP$1=$CM$1),"TOTALE","")))))))))))))))))))))))),"SALDO ECONOMICO NEGATIVO","PERDITA D'ESERCIZIO"),IF(OR($BB$1<>$BD$1,$BC$1<>$BE$1,$DS$231<>$DT$231,$DS$232<>$DT$232,$DU$231<>$DV$231),"",IF($BX$1=0,"",IF(AND((ROW()-2)=MAX($BV$2:$BW$2)+1,OR($BY$1>0,$BZ$1>0,$CP$1>$CM$1)),"TOTALE ATTIVITÀ",IF(AND((ROW()-2)=MAX($BV$2:$BW$2)+2,$BY$1>0),"PRELEVAMENTI EXTRAGESTIONE",IF(AND((ROW()-2)=MAX($BV$2:$BW$2)+2,$BY$1=0,$BZ$1>0),"TITOLARE C/RITENUTE SUBITE",IF(AND((ROW()-2)=MAX($BV$2:$BW$2)+3,$BY$1>0,$BZ$1>0),"TITOLARE C/RITENUTE SUBITE",IF(AND((ROW()-2)=MAX($BV$2:$BW$2)+2,$BY$1=0,$BZ$1=0,$CP$1>$CM$1),"SALDO ECONOMICO NEGATIVO",IF(AND((ROW()-2)=MAX($BV$2:$BW$2)+3,$BY$1>0,$BZ$1=0,$CP$1>$CM$1),"SALDO ECONOMICO NEGATIVO",IF(AND((ROW()-2)=MAX($BV$2:$BW$2)+3,$BY$1=0,$BZ$1>0,$CP$1>$CM$1),"SALDO ECONOMICO NEGATIVO",IF(AND((ROW()-2)=MAX($BV$2:$BW$2)+4,$BY$1>0,$BZ$1>0,$CP$1>$CM$1),"SALDO ECONOMICO NEGATIVO",IF(AND((ROW()-2)=MAX($BV$2:$BW$2)+3,$BY$1=0,$BZ$1=0,$CP$1>$CM$1),"TOTALE",IF(AND((ROW()-2)=MAX($BV$2:$BW$2)+4,$BY$1>0,$BZ$1=0,$CP$1<$CM$1),"TOTALE",IF(AND((ROW()-2)=MAX($BV$2:$BW$2)+4,$BY$1=0,$BZ$1>0,$CP$1<$CM$1),"TOTALE",IF(AND((ROW()-2)=MAX($BV$2:$BW$2)+4,$BY$1>0,$BZ$1=0,$CP$1>$CM$1),"TOTALE",IF(AND((ROW()-2)=MAX($BV$2:$BW$2)+4,BX1>0,BY$1=0,$BZ$1>0,$CP$1>$CM$1),"TOTALE",IF(AND((ROW()-2)=MAX($BV$2:$BW$2)+3,BX1>0,BY$1=0,$BZ$1=0,$CP$1=$CM$1),"TOTALE ATTIVITÀ",IF(AND((ROW()-2)=MAX($BV$2:$BW$2)+4,$BX$1>0,$BY$1>0,$BZ$1>0,$CP$1=$CM$1),"TOTALE",IF(AND((ROW()-2)=MAX($BV$2:$BW$2)+3,$BX$1>0,$BY$1=0,$BZ$1>0,$CP$1=$CM$1),"TOTALE",IF(AND((ROW()-2)=MAX($BV$2:$BW$2)+3,$BX$1>0,$BY$1>0,$BZ$1=0,$CP$1=$CM$1),"TOTALE",IF(AND((ROW()-2)=MAX($BV$2:$BW$2)+4,$BX$1>0,$BY$1>0,$BZ$1>0,$CP$1<$CM$1),"TOTALE",IF(AND((ROW()-2)=MAX($BV$2:$BW$2)+4,$BY$1=0,$BZ$1=0,$CP$1<$CM$1),"TOTALE",IF(AND((ROW()-2)=MAX($BV$2:$BW$2)+5,$BY$1>0,$BZ$1>0,$CP$1>$CM$1),"TOTALE",IF(AND((ROW()-2)=MAX($BV$2:$BW$2)+3,$BY$1=0,$BZ$1=0,$CP$1=0,$CM$1=0),"TOTALE",IF(AND((ROW()-2)=MAX($BV$2:$BW$2)+4,$BY$1>0,$BZ$1>0,$CP$1>0,$CM$1>0,$CP$1=$CM$1),"TOTALE","")))))))))))))))))))))))))) | BZ3: =IFERROR(IF(OR($DS$231<>$DT$231,$DU$231<>$DV$231,$EO$25<>0,$EO$26<>0),INDEX($T$3:$V$220,MATCH(ROWS($BV$3:BV3),$V$3:$V$220,0),1),CONCATENATE(BV3,BY3)),"") | CA3: =IFERROR(INDEX($BV$3:$BW$225,MATCH(BZ3,$BV$3:$BV$225,0),2),INDEX($BL$3:$BW$225,MATCH(BZ3,$BL$3:$BL$225,0),2)) -> 0 | CB3: =IFERROR(IF(OR($BB$1<>$BD$1,$BC$1<>$BE$1,$DS$231<>$DT$231,$DU$231<>$DV$231,$EO$25<>0,$EO$26<>0),INDEX($BI$3:$BK$220,MATCH(ROWS($CB$3:CB3),$BK$3:$BK$220,0),1),CONCATENATE(BQ3,BX3)),"") | CC3: =INDEX($BQ$3:$BR$225,MATCH(CB3,$BQ$3:$BQ$225,0),2) | CD3: =IF(INDEX(PIANO_DEI_CONTI,MATCH(AA3,DENOMINAZIONE,0),6)="SE DARE",AA3,"") | CE3: =IF(IFERROR(MATCH(CD3,DENOMINAZIONE_GIORNALE,0),0)>0,MAX(CE$2:CE2)+1,0) -> 0 | CF3: =IFERROR(INDEX($CD$3:$CE$220,MATCH(ROWS($CF$3:CF3),$CE$3:$CE$220,0),1),"") | CG3: =IF(AND(INDEX(PIANO_DEI_CONTI,MATCH(CF3,DENOMINAZIONE,0),6)="SE DARE",SUMIFS(DARE,DENOMINAZIONE_GIORNALE,CF3)>SUMIFS(AVERE,DENOMINAZIONE_GIORNALE,CF3)),SUMIFS(DARE,DENOMINAZIONE_GIORNALE,CF3)-SUMIFS(AVERE,DENOMINAZIONE_GIORNALE,CF3),0) -> 0 | CH3: =IF(IF(CG3<>0,MAX($CH$2:CH2)+1,0)=0,"",IF(CG3<>"",MAX($CH$2:CH2)+1,0)) | CI3: =IFERROR(INDEX($CF$3:$CG$220,MATCH(ROWS($CI$3:CI3),$CH$3:$CH$220,0),1),"") | CJ3: =IFERROR(IF(INDEX($CF$3:$CG$220,MATCH(CI3,$CF$3:$CF$220,0),2)=0,"",INDEX($CF$3:$CG$220,MATCH(CI3,$CF$3:$CF$220,0),2)),"") | CK3: =IF(INDEX(PIANO_DEI_CONTI,MATCH(AA3,DENOMINAZIONE,0),6)="SE AVERE",AA3,"") | CL3: =IF(IFERROR(MATCH(CK3,DENOMINAZIONE_GIORNALE,0),0)>0,MAX(CL$2:CL2)+1,0) -> 0 | CM3: =IFERROR(INDEX($CK$3:$CL$220,MATCH(ROWS($CM$3:CM3),$CL$3:$CL$220,0),1),"") | CN3: =IF(AND(INDEX(PIANO_DEI_CONTI,MATCH(CM3,DENOMINAZIONE,0),6)="SE AVERE",SUMIFS(AVERE,DENOMINAZIONE_GIORNALE,CM3,DATA,">="&$CX$1)>SUMIFS(DARE,DENOMINAZIONE_GIORNALE,CM3)),SUMIFS(AVERE,DENOMINAZIONE_GIORNALE,CM3)-SUMIFS(DARE,DENOMINAZIONE_GIORNALE,CM3),"") | CO3: =IF(IF(CN3<>0,MAX($CO$2:CO2)+1,0)=0,"",IF(CN3<>"",MAX($CO$2:CO2)+1,0)) -> 0 | CP3: =IFERROR(INDEX($CM$3:$CN$220,MATCH(ROWS(CP$3:CP3),$CO$3:$CO$220,0),1),"") | CQ3: =IFERROR(INDEX($CM$3:$CN$220,MATCH(ROWS(CQ$3:CQ3),$CO$3:$CO$220,0),2),"") | CR3: =IF($EV$1>0,"",IF($EO$1=TRUE,SUBSTITUTE(IF(OR($BX$1=0,$BB$1<>$BD$1,$BC$1<>$BE$1,$DS$232<>$DT$232,$EO$25<>0,$EO$26<>0),"",IFERROR(IF(AND(MATCH($BP$1,DENOMINAZIONE_GIORNALE,0)>0,$DU$231=$DV$231,$DS$231=$DT$231),IF(AND($CP$1>$CM$1,$CP$2>$CM$2,(ROW()-2)=$CP$2+3),"TOTALE COSTI",IF(AND($CP$1>$CM$1,$CM$2>=$CP$2,(ROW()-2)=$CM$2+3),"TOTALE COSTI",IF(AND($CP$1<$CM$1,$CP$2>=$CM$2,(ROW()-2)=$CP$2+1),"TOTALE COSTI",IF(AND($CP$1<$CM$1,$CP$2<$CM$2,ROW()-2=$CM$2+1),"TOTALE COSTI",IF(AND($CP$1=$CM$1,$DU$231=$DV$231,OR($CM$2>0,$CP$2>0),(ROW()-2)=MAX($CP$2,$CM$2)+1),"TOTALE COSTI",IF(AND($CM$1>$CP$1,$CP$2>$CM$2,(ROW()-2)=$CP$2+2),"SALDO ECONOMICO POSITIVO",IF(AND($CM$1>$CP$1,$CM$2>=$CP$2,(ROW()-2)=$CM$2+2),"SALDO ECONOMICO POSITIVO",IF(AND($CM$1>$CP$1,$CP$2>$CM$2,(ROW()-2)=$CP$2+3),"TOTALE A PAREGGIO",IF(AND($CM$1>$CP$1,$CM$2>=$CP$2,(ROW()-2)=$CM$2+3),"TOTALE A PAREGGIO",""))))))))),""),"")),"SALDO ECONOMICO POSITIVO","UTILE D'ESERCIZIO"),IF(OR($BX$1=0,$BB$1<>$BD$1,$BC$1<>$BE$1,$DS$232<>$DT$232,$EO$25<>0,$EO$26<>0),"",IFERROR(IF(AND(MATCH($BP$1,DENOMINAZIONE_GIORNALE,0)>0,$DU$231=$DV$231,$DS$231=$DT$231),IF(AND($CP$1>$CM$1,$CP$2>$CM$2,(ROW()-2)=$CP$2+3),"TOTALE COSTI",IF(AND($CP$1>$CM$1,$CM$2>=$CP$2,(ROW()-2)=$CM$2+3),"TOTALE COSTI",IF(AND($CP$1<$CM$1,$CP$2>=$CM$2,(ROW()-2)=$CP$2+1),"TOTALE COSTI",IF(AND($CP$1<$CM$1,$CP$2<$CM$2,ROW()-2=$CM$2+1),"TOTALE COSTI",IF(AND($CP$1=$CM$1,$DU$231=$DV$231,OR($CM$2>0,$CP$2>0),(ROW()-2)=MAX($CP$2,$CM$2)+1),"TOTALE COSTI",IF(AND($CM$1>$CP$1,$CP$2>$CM$2,(ROW()-2)=$CP$2+2),"SALDO ECONOMICO POSITIVO",IF(AND($CM$1>$CP$1,$CM$2>=$CP$2,(ROW()-2)=$CM$2+2),"SALDO ECONOMICO POSITIVO",IF(AND($CM$1>$CP$1,$CP$2>$CM$2,(ROW()-2)=$CP$2+3),"TOTALE A PAREGGIO",IF(AND($CM$1>$CP$1,$CM$2>=$CP$2,(ROW()-2)=$CM$2+3),"TOTALE A PAREGGIO",""))))))))),""),"")))) | CS3: =SUMIFS(DARE,DENOMINAZIONE_GIORNALE,AA3,DARE,">"&0) -> 0 | CT3: =SUMIFS(AVERE,DENOMINAZIONE_GIORNALE,AA3,AVERE,">"&0) -> 0 | CU3: =IF(OR(CS3>0,CT3>0),MAX($CU$2:CU2)+1,0) -> 0 | CV3: =IFERROR(INDEX(PIANO_DEI_CONTI,MATCH(ROWS($CV$3:CV3),$CU$3:$CU$200,0),2),"") | CW3: =IFERROR(IF(CV3<>"",MAX($CW$2:CW2)+1,0),0) -> 0 | CX3: =$EA$3 -> 1 | CY3: =IF(ISERROR(INDEX($CV$3:$CX$2300,MATCH(CX3,$CW$3:$CW$2300,0),1)),"MASTRO",INDEX($CV$3:$CX$2300,MATCH(CX3,$CW$3:$CW$2300,0),1)) -> MASTRO | DA3: =IF(CY2="MASTRO","Conto n.","") -> Conto n. | DB3: =IF(CY3=0,"",INDEX(PIANO_DEI_CONTI,MATCH(DC3,DENOMINAZIONE,0),1)) | DC3: =IF(OR(CY3=0,CY3="mastro"),"",CY3) | DD3: =IF(AND($DA$2=TRUE,OR(INDEX(PIANO_DEI_CONTI,MATCH($DC3,DENOMINAZIONE,0),4)="A",INDEX(PIANO_DEI_CONTI,MATCH($DC3,DENOMINAZIONE,0),4)="D/A"),SUMIFS(AVERE,DENOMINAZIONE_GIORNALE,"="&$DC3)>SUMIFS(DARE,DENOMINAZIONE_GIORNALE,"="&$DC3)),CONCATENATE("s ",FIXED(ABS(SUMIFS(AVERE,DENOMINAZIONE_GIORNALE,"="&$DC3)-SUMIFS(DARE,DENOMINAZIONE_GIORNALE,"="&$DC3)),2)),"") | DE3: =IF(AND($DA$2=TRUE,OR(INDEX(PIANO_DEI_CONTI,MATCH($DC3,DENOMINAZIONE,0),4)="D",INDEX(PIANO_DEI_CONTI,MATCH($DC3,DENOMINAZIONE,0),4)="D/A"),SUMIFS(DARE,DENOMINAZIONE_GIORNALE,"="&$DC3)>SUMIFS(AVERE,DENOMINAZIONE_GIORNALE,"="&$DC3)),CONCATENATE("s ",FIXED(ABS(SUMIFS(DARE,DENOMINAZIONE_GIORNALE,"="&$DC3)-SUMIFS(AVERE,DENOMINAZIONE_GIORNALE,"="&$DC3)),2)),"") | DF3: =IF(AND(CX3=$DE$2,$DF$2<>0),0,IF(AND(DB3<>"",OR(DB2<>"",DB4<>"")),MAX($DF$2:DF2)+1,0)) -> 0 | DG3: =IF(OR(VALORI_INIZIALI!E8="",AND(VALORI_INIZIALI!E8<>"",VALORI_INIZIALI!H8=0,VALORI_INIZIALI!I8=0)),"",IFERROR(INDEX(PIANO_DEI_CONTI,MATCH(BB3,DENOMINAZIONE,0),1),0)) | DH3: =IFERROR(IF($J$1=1,IF(INDEX(PIANO_DEI_CONTI,MATCH($K3,DENOMINAZIONE,0),5)=$DF$1,MAX($DH$2:DH2)+1,0),IF($J$1=2,IF(INDEX(PIANO_DEI_CONTI,MATCH($K3,DENOMINAZIONE,0),7)=$DF$1,MAX($DH$2:DH2)+1,0))),0) -> 0 | DI3: =IFERROR(INDEX($K$3:$K$220,MATCH(ROWS($DI$3:DI3),$DH$3:$DH$220,0),1),0) -> 0 | DJ3: =IF(IFERROR(MATCH(AA3,DENOMINAZIONE_GIORNALE,0),0)<>0,ROW()-2,0) -> 0 | DK3: =IF(DJ3=0,0,MAX(DK$2:DK2)+1) -> 0 | DL3: =IFERROR(INDEX(PIANO_DEI_CONTI,MATCH(ROWS(DL$3:DL3),$DK$3:DK230,0),2),0) -> 0 | DM3: =IFERROR(IF(AND(INDEX(PIANO_DEI_CONTI,MATCH($DL3,DENOMINAZIONE,0),4)="D",SUMIFS(DARE,DENOMINAZIONE_GIORNALE,$DL3)>=SUMIFS(AVERE,DENOMINAZIONE_GIORNALE,$DL3)),SUMIFS(DARE,DENOMINAZIONE_GIORNALE,$DL3),IF(AND(INDEX(PIANO_DEI_CONTI,MATCH($DL3,DENOMINAZIONE,0),4)="A",SUMIFS(AVERE,DENOMINAZIONE_GIORNALE,$DL3)>=SUMIFS(DARE,DENOMINAZIONE_GIORNALE,$DL3)),SUMIFS(DARE,DENOMINAZIONE_GIORNALE,$DL3),IF(INDEX(PIANO_DEI_CONTI,MATCH($DL3,DENOMINAZIONE,0),4)="D/A",SUMIFS(DARE,DENOMINAZIONE_GIORNALE,$DL3),0))),0) -> 0 | DN3: =IFERROR(IF(AND(INDEX(PIANO_DEI_CONTI,MATCH($DL3,DENOMINAZIONE,0),4)="D",SUMIFS(DARE,DENOMINAZIONE_GIORNALE,$DL3)>=SUMIFS(AVERE,DENOMINAZIONE_GIORNALE,$DL3)),SUMIFS(AVERE,DENOMINAZIONE_GIORNALE,$DL3),IF(AND(INDEX(PIANO_DEI_CONTI,MATCH($DL3,DENOMINAZIONE,0),4)="A",SUMIFS(AVERE,DENOMINAZIONE_GIORNALE,$DL3)>=SUMIFS(DARE,DENOMINAZIONE_GIORNALE,$DL3)),SUMIFS(AVERE,DENOMINAZIONE_GIORNALE,$DL3),IF(INDEX(PIANO_DEI_CONTI,MATCH($DL3,DENOMINAZIONE,0),4)="D/A",SUMIFS(AVERE,DENOMINAZIONE_GIORNALE,$DL3),0))),0) -> 0 | DO3: =IF(AND(DL3<>"",$DM3>$DN3,OR($DM3>0,$DN3>0)),$DM3-$DN3,0) -> 0 | DP3: =IF(AND(DL3<>"",$DM3<$DN3,OR($DM3>0,$DN3>0)),$DN3-$DM3,0) -> 0 | DQ3: =IF(OR($DQ$1="TOTALI",$DQ$1="TOTALI ED ECCEDENZE"),IF(OR(DM3>0,DN3>0),MAX(DQ$2:DQ2)+1,0),IF($DQ$1="ECCEDENZE",IF(OR(DO3>0,DP3>0),MAX(DQ$2:DQ2)+1,0),"")) -> 0 | DR3: =IFERROR(INDEX($DL$3:$DQ$230,MATCH(ROWS(DR$3:DR3),$DQ$3:$DQ$230,0),1),"") | DS3: =IFERROR(IF($DQ$1="eccedenze",INDEX($DL$3:$DP$230,MATCH($DR3,$DL$3:$DL$230,0),4),IF(OR($DQ$1="totali",$DQ$1="TOTALI ED ECCEDENZE"),INDEX($DL$3:$DP$230,MATCH($DR3,$DL$3:$DL$230,0),2),"")),"") | DT3: =IFERROR(IF($DQ$1="eccedenze",INDEX($DL$3:$DP$230,MATCH($DR3,$DL$3:$DL$230,0),5),IF(OR($DQ$1="totali",$DQ$1="TOTALI ED ECCEDENZE"),INDEX($DL$3:$DP$230,MATCH($DR3,$DL$3:$DL$230,0),3),"")),"") | DU3: =IF(AND($DR3<>"",$DS3>$DT3,$DQ$1="TOTALI ED ECCEDENZE",OR($DS3>0,$DT3>0)),$DS3-$DT3,IF(DS3=DT3,"","")) | DV3: =IF(AND($DR3<>"",$DS3<$DT3,$DQ$1="TOTALI ED ECCEDENZE",OR($DS3>0,$DT3>0)),$DT3-$DS3,IF(DT3=DS3,"","")) | DW3: =IF(OR(AND(DR3<>"",$DQ$1="TOTALI ED ECCEDENZE"),AND(DX3="TOTALI",$DQ$1="TOTALI ED ECCEDENZE")),1,0) -> 0 | DX3: =IF($EV$1>0,"",IF((ROW()-2)=$DW$1+1,IF(AND(MATCH("PATRIMONIO NETTO",$DR$3:$DR$230,0)>0,$BB$1=$BD$1,$BC$1=$BE$1,$DS$231=$DT$231,$EO$25=0,$EO$26=0),"TOTALI",""),"")) | DY3: =IF($DX3="TOTALI",$DS$231,"") | DZ3: =IF(IF($DX3="TOTALI",$DU$231,"")=0,"",IF($DX3="TOTALI",$DU$231,"")) | EA3: =SUM(JJ3,JL3) -> 1 | EB3: pab1 | ED3: =IFERROR(INDEX(PIANO_DEI_CONTI,MATCH(BB3,DENOMINAZIONE,0),5),"") -> 0 | EE3: =IF($EV$1>0,"",IF(AND(IF(OR($BX$1=0,$BB$1<>$BD$1,$BC$1<>$BE$1,$DS$232<>$DT$232,$EO$25<>0,$EO$26<>0),"",IFERROR(IF(AND(MATCH($BP$1,DENOMINAZIONE_GIORNALE,0)>0,$DU$231=$DV$231,$DS$231=$DT$231),IF(AND($CP$1>$CM$1,$CP$2>$CM$2,(ROW()-2)=$CP$2+3),"TOTALE A PAREGGIO",IF(AND($CP$1>$CM$1,$CM$2>=$CP$2,(ROW()-2)=$CM$2+3),"TOTALE A PAREGGIO",IF(AND($CP$1>$CM$1,$CM$2>=$CP$2,(ROW()-2)=$CM$2+1),"TOTALE RICAVI",IF(AND($CP$1>$CM$1,$CP$2>=$CM$2,(ROW()-2)=$CP$2+1),"TOTALE RICAVI",IF(AND($CP$1>$CM$1,$CP$2<$CM$2,ROW()-2=$CM$2+3),"TOTALE RICAVI",IF(AND($DU$231=$DV$231,$CP$1=$CM$1,OR($CM$2>0,$CP$2>0),(ROW()-2)=MAX($CM$2,$CP$2)+1),"TOTALE RICAVI",IF(AND($CM$1<$CP$1,$CP$2>$CM$2,(ROW()-2)=$CP$2+2),"SALDO ECONOMICO NEGATIVO",IF(AND($CM$1<$CP$1,$CM$2>=$CP$2,(ROW()-2)=$CM$2+2),"SALDO ECONOMICO NEGATIVO",IF(AND($CM$1>$CP$1,$CP$2>$CM$2,(ROW()-2)=$CP$2+3),"TOTALE RICAVI",IF(AND($CM$1>$CP$1,$CM$2>=$CP$2,(ROW()-2)=$CM$2+3),"TOTALE RICAVI","")))))))))),""),""))="SALDO ECONOMICO NEGATIVO",$EO$1=TRUE),SUBSTITUTE(IF($DS$232<>$DT$232,"",IFERROR(IF(AND(MATCH($BP$1,DENOMINAZIONE_GIORNALE,0)>0,$DU$231=$DV$231,$DS$231=$DT$231),IF(AND($CP$1>$CM$1,$CP$2>$CM$2,(ROW()-2)=$CP$2+3),"TOTALE A PAREGGIO",IF(AND($CP$1>$CM$1,$CM$2>=$CP$2,(ROW()-2)=$CM$2+3),"TOTALE A PAREGGIO",IF(AND($CP$1>$CM$1,$CM$2>=$CP$2,(ROW()-2)=$CM$2+1),"TOTALE RICAVI",IF(AND($CP$1>$CM$1,$CP$2>=$CM$2,(ROW()-2)=$CP$2+1),"TOTALE RICAVI",IF(AND($CP$1>$CM$1,$CP$2<$CM$2,ROW()-2=$CM$2+3),"TOTALE RICAVI",IF(AND($DU$231=$DV$231,$CP$1=$CM$1,OR($CM$2>0,$CP$2>0),(ROW()-2)=MAX($CP$2,$CM$2)+1),"TOTALE RICAVI",IF(AND($CM$1<$CP$1,$CP$2>$CM$2,(ROW()-2)=$CP$2+2),"SALDO ECONOMICO NEGATIVO",IF(AND($CM$1<$CP$1,$CM$2>=$CP$2,(ROW()-2)=$CM$2+2),"SALDO ECONOMICO NEGATIVO",IF(AND($CM$1>$CP$1,$CP$2>$CM$2,(ROW()-2)=$CP$2+3),"TOTALE RICAVI",IF(AND($CM$1>$CP$1,$CM$2>=$CP$2,(ROW()-2)=$CM$2+3),"TOTALE RICAVI","")))))))))),""),"")),"SALDO ECONOMICO NEGATIVO","PERDITA D'ESERCIZIO"),IF(OR($BX$1=0,$BB$1<>$BD$1,$BC$1<>$BE$1,$DS$232<>$DT$232,$EO$25<>0,$EO$26<>0),"",IFERROR(IF(AND(MATCH($BP$1,DENOMINAZIONE_GIORNALE,0)>0,$DU$231=$DV$231,$DS$231=$DT$231),IF(AND($CP$1>$CM$1,$CP$2>$CM$2,(ROW()-2)=$CP$2+3),"TOTALE A PAREGGIO",IF(AND($CP$1>$CM$1,$CM$2>=$CP$2,(ROW()-2)=$CM$2+3),"TOTALE A PAREGGIO",IF(AND($CP$1>$CM$1,$CM$2>=$CP$2,(ROW()-2)=$CM$2+1),"TOTALE RICAVI",IF(AND($CP$1>$CM$1,$CP$2>=$CM$2,(ROW()-2)=$CP$2+1),"TOTALE RICAVI",IF(AND($CP$1>$CM$1,$CP$2<$CM$2,ROW()-2=$CM$2+3),"TOTALE RICAVI",IF(AND($DU$231=$DV$231,$CP$1=$CM$1,OR($CM$2>0,$CP$2>0),(ROW()-2)=MAX($CP$2,$CM$2)+1),"TOTALE RICAVI",IF(AND($CM$1<$CP$1,$CP$2>$CM$2,(ROW()-2)=$CP$2+2),"SALDO ECONOMICO NEGATIVO",IF(AND($CM$1<$CP$1,$CM$2>=$CP$2,(ROW()-2)=$CM$2+2),"SALDO ECONOMICO NEGATIVO",IF(AND($CM$1>$CP$1,$CP$2>$CM$2,(ROW()-2)=$CP$2+3),"TOTALE RICAVI",IF(AND($CM$1>$CP$1,$CM$2>=$CP$2,(ROW()-2)=$CM$2+3),"TOTALE RICAVI","")))))))))),""),"")))) | EF3: =IF(EE3="TOTALE RICAVI",$CM$1,IF(EE3="PERDITA D'ESERCIZIO",$CP$1-$CM$1,IF(EE3="SALDO ECONOMICO NEGATIVO",$CP$1-$CM$1,IF(EE3="TOTALE A PAREGGIO",$CP$1,"")))) | EG3: =IF(CR3="TOTALE COSTI",$CP$1,IF(CR3="TOTALE A PAREGGIO",$CM$1,IF(CR3="SALDO ECONOMICO POSITIVO",$CM$1-$CP$1,""))) | EH3: =CP3 | EL3: =ROW()-2 -> 1 | EM3: =IF(AND(BA3>0,BA3<=$EM$1),MAX($EM$2:EM2)+1,0) -> 0 | EN3: =IF(EM3=$EL$1,(ROW()-2),0) -> 1 | EP3: =IFERROR(INDEX(PIANO_DEI_CONTI,MATCH(EZ3,DENOMINAZIONE,0),7),"") | EQ3: =IF(AND(EZ3<>0,EY3<=FINE_AC),INDEX(PIANO_DEI_CONTI,MATCH(EZ3,DENOMINAZIONE,0),1),0) -> 0 | ER3: =IF(ISNA(EQ3),MAX(ER$2:ER2)+1,0) -> 0 | ES3: =IF(ER3>=1,EZ3,"") | ET3: =IFERROR(UPPER(INDEX($ER$3:$ES$500,MATCH(ROWS(ET$3:ET3),$ER$3:$ER$500,0),2)),"") | EU3: Tutti i conti presentino un'eccedenza corretta | EV3: =IF(FM1>0,1,0) -> 0 | EW3: =IF(AND(IFERROR(INDEX($EU$3:$EV$30,MATCH(ROWS($EX$3:EX3),$EV$3:$EV$30,0),1),"")<>"",EW4<>""),CONCATENATE(IFERROR(INDEX($EU$3:$EV$30,MATCH(ROWS($EX$3:EX3),$EV$3:$EV$30,0),1),"")," - "),IFERROR(INDEX($EU$3:$EV$30,MATCH(ROWS($EX$3:EX3),$EV$3:$EV$30,0),1),"")) -> Il conto PATRIMONIO NETTO sia acceso | EX3: =EX1-1 -> 0 | EY3: =INDIRECT(ADDRESS(ROW()+5,COLUMN()-151,,,"VALORI_INIZIALI")) -> 0 | EZ3: =INDIRECT(ADDRESS(ROW()+5,COLUMN()-151,,,"VALORI_INIZIALI")) -> 0 | FA3: =IF(AND(CONCATENATE(INDIRECT(ADDRESS(ROW()+5,6,,,"VALORI_INIZIALI")),INDIRECT(ADDRESS(ROW()+5,7,,,"VALORI_INIZIALI")))="",EZ3<>0),"manca la descrizione dell'operazione",CONCATENATE(INDIRECT(ADDRESS(ROW()+5,6,,,"VALORI_INIZIALI")),INDIRECT(ADDRESS(ROW()+5,7,,,"VALORI_INIZIALI")))) | FB3: =IF(EZ3=0,0,ROUND(INDIRECT(ADDRESS(ROW()+5,COLUMN()-150,,,"VALORI_INIZIALI")),2)) -> 0 | FC3: =IF(EZ3=0,0,ROUND(INDIRECT(ADDRESS(ROW()+5,COLUMN()-150,,,"VALORI_INIZIALI")),2)) -> 0 | FD3: =IFERROR(INDEX(PIANO_DEI_CONTI,MATCH(EZ3,DENOMINAZIONE,0),6),"") -> 0 | FE3: =IFERROR(IF(EZ3<>0,INDEX(PIANO_DEI_CONTI,MATCH(EZ3,DENOMINAZIONE,0),1),""),"") | FF3: =IF(EZ3<>0,CONCATENATE(ROW()-2," V.I."),"") | FG3: =IF(AND(MID(AE3,1,2)="SP",AA3<>"PATRIMONIO NETTO",AA3<>"TITOLARE C/RITENUTE SUBITE",AA3<>"PRELEVAMENTI EXTRAGESTIONE"),AA3,"") -> COSTI DI IMPIANTO | FH3: =IF(AND(INDEX(PIANO_DEI_CONTI,MATCH($FG3,DENOMINAZIONE,0),4)="D",SUMIFS(dare_grezzo,den_grezzo,$FG3,data_grezzo,"<"&INIZIO_AC,data_grezzo,">="&INIZIO_A_PC)>=SUMIFS(avere_grezzo,den_grezzo,$FG3,data_grezzo,"<"&INIZIO_AC,data_grezzo,">="&INIZIO_A_PC)),SUMIFS(dare_grezzo,den_grezzo,$FG3,data_grezzo,"<"&INIZIO_AC,data_grezzo,">="&INIZIO_A_PC),IF(AND(INDEX(PIANO_DEI_CONTI,MATCH($FG3,DENOMINAZIONE,0),4)="A",SUMIFS(avere_grezzo,den_grezzo,$FG3,data_grezzo,"<"&INIZIO_AC,data_grezzo,">="&INIZIO_A_PC)>=SUMIFS(dare_grezzo,den_grezzo,$FG3,data_grezzo,"<"&INIZIO_AC,data_grezzo,">="&INIZIO_A_PC)),SUMIFS(dare_grezzo,den_grezzo,$FG3,data_grezzo,"<"&INIZIO_AC,data_grezzo,">="&INIZIO_A_PC),IF(INDEX(PIANO_DEI_CONTI,MATCH($FG3,DENOMINAZIONE,0),4)="D/A",SUMIFS(dare_grezzo,den_grezzo,$FG3,data_grezzo,"<"&INIZIO_AC,data_grezzo,">="&INIZIO_A_PC),0))) -> 0 | FI3: =IFERROR(IF(AND(INDEX(PIANO_DEI_CONTI,MATCH($FG3,DENOMINAZIONE,0),4)="D",SUMIFS(dare_grezzo,den_grezzo,$FG3,data_grezzo,"<"&INIZIO_AC,data_grezzo,">="&INIZIO_A_PC)>=SUMIFS(avere_grezzo,den_grezzo,$FG3,data_grezzo,"<"&INIZIO_AC,data_grezzo,">="&INIZIO_A_PC)),SUMIFS(avere_grezzo,den_grezzo,$FG3,data_grezzo,"<"&INIZIO_AC,data_grezzo,">="&INIZIO_A_PC),IF(AND(INDEX(PIANO_DEI_CONTI,MATCH($FG3,DENOMINAZIONE,0),4)="A",SUMIFS(avere_grezzo,den_grezzo,$FG3,data_grezzo,"<"&INIZIO_AC,data_grezzo,">="&INIZIO_A_PC)>=SUMIFS(dare_grezzo,den_grezzo,$FG3,data_grezzo,"<"&INIZIO_AC,data_grezzo,">="&INIZIO_A_PC)),SUMIFS(avere_grezzo,den_grezzo,$FG3,data_grezzo,"<"&INIZIO_AC,data_grezzo,">="&INIZIO_A_PC),IF(INDEX(PIANO_DEI_CONTI,MATCH($FG3,DENOMINAZIONE,0),4)="D/A",SUMIFS(avere_grezzo,den_grezzo,$FG3,data_grezzo,"<"&INIZIO_AC,data_grezzo,">="&INIZIO_A_PC),0))),0) -> 0 | FJ3: =IF(AND(FG3<>"",$FH3>$FI3,OR($FH3>0,$FI3>0)),$FH3-$FI3,0) -> 0 | FK3: =IF(AND($FG3<>"",$FI3>$FH3,OR($FH3>0,$FI3>0)),$FI3-$FH3,0) -> 0 | FL3: =IF(OR(FJ3>0,FK3>0),MAX($FL$2:FL2)+1,0) -> 0 | FM3: =IF(AND(AC3="d",AE3="SP DARE"),SUMIFS(dare_grezzo,den_grezzo,AA3,data_grezzo,"<="&FINE_AC,data_grezzo,">="&INIZIO_A_PC)-SUMIFS(avere_grezzo,den_grezzo,AA3,data_grezzo,"<="&FINE_AC,data_grezzo,">="&INIZIO_A_PC),IF(AND(AC3="a",AE3="SP AVERE"),SUMIFS(avere_grezzo,den_grezzo,AA3,data_grezzo,"<="&FINE_AC,data_grezzo,">="&INIZIO_A_PC)-SUMIFS(dare_grezzo,den_grezzo,AA3,data_grezzo,"<="&FINE_AC,data_grezzo,">="&INIZIO_A_PC),IF(AND(AC3="d",AE3="SE DARE"),SUMIFS(dare_grezzo,den_grezzo,AA3,data_grezzo,"<="&FINE_AC,data_grezzo,">="&INIZIO_A_PC)-SUMIFS(avere_grezzo,den_grezzo,AA3,data_grezzo,"<="&FINE_AC,data_grezzo,">="&INIZIO_A_PC),IF(AND(AC3="a",AE3="SE AVERE"),SUMIFS(avere_grezzo,den_grezzo,AA3,data_grezzo,"<="&FINE_AC,data_grezzo,">="&INIZIO_A_PC)-SUMIFS(dare_grezzo,den_grezzo,AA3,data_grezzo,"<="&FINE_AC,data_grezzo,">="&INIZIO_A_PC),0)))) -> 0 | FN3: =IF(FM3<0,MAX($FN$2:FN2)+1,0) -> 0 | FO3: =IF(FM3<0,AA3,"") | FP3: =IFERROR(INDEX($FN$3:$FO$400,MATCH(ROWS($FP$3:FP3),$FN$3:$FN$400,0),2),"") | FQ3: =IF(AE3="SE AVERE",MAX($FQ$2:FQ2)+1,"") | FR3: =IF(AE3="SE DARE",MAX($FR$2:FR2)+1,"") | FS3: =IF(AND(AE3="SP DARE",AA3<>$FS$1,AA3<>$FT$1),MAX($FS$2:FS2)+1,IF(AND(GQ3="SP DARE",AA3<>$FS$1,AA3<>$FT$1),MAX($FS$2:FS2)+1,"")) -> 90 | FT3: =IF(AND(AE3="SP AVERE",AA3<>$FU$1),MAX($FT$2:FT2)+1,IF(AND(GQ3="SP AVERE",AA3<>$FU$1),MAX($FT$2:FT2)+1,"")) | FU3: =SUM(FQ3:FT3) -> 90 | FV3: =AA3 -> COSTI DI IMPIANTO | FW3: =IFERROR(INDEX($FU$3:$FV$500,MATCH(ROWS($FW$3:FW3),$FU$3:$FU$500,0),2),0) -> MERCI C/VENDITE | FX3: =IF(FW3<>0,ROW()-2,0) -> 1 | FY3: =IF(AND(ROW()<=$FX$1,FX3=0),ROW()-2,0) -> 0 | FZ3: =IF(FY3>0,MAX($FZ$2:FZ2)+1,0) -> 0 | GA3: =IFERROR(INDEX($FY$3:$FZ$500,MATCH(ROWS($GA$3:GA3),$FZ$3:$FZ$500,0),1),0) -> 20 | GB3: CONTO DI RISULTATO ECONOMICO | GC3: =FX3+FY3 -> 1 | GD3: =IFERROR(IF(FX3>0,FW3,INDEX($GA$3:$GB$400,MATCH(ROW()-2,$GA$3:$GA$400,0),2)),0) -> MERCI C/VENDITE | GF3: =CM1 -> 0 | GG3: =IFERROR(INDEX($GA$3:$GF$400,MATCH(ROW()-2,$GA$3:$GA$400,0),5),0) -> 0 | GH3: =IFERROR(INDEX($GA$3:$GF$400,MATCH(ROW()-2,$GA$3:$GA$400,0),6),0) -> 0 | GI3: =IFERROR(INDEX($DL$3:$DP$400,MATCH($FW3,$DL$3:$DL$400,0),5),0) -> 0 | GJ3: =IFERROR(INDEX($DL$3:$DP$400,MATCH($FW3,$DL$3:$DL$400,0),4),0) -> 0 | GK3: =GG3+GI3 -> 0 | GL3: =GH3+GJ3 -> 0 | GM3: =IF(OR(GK3>0,GL3>0),MAX($GM$2:GM2)+1,0) -> 0 | GN3: =IFERROR(INDEX($GD$3:$GM$400,MATCH(ROWS($GN$3:GN3),$GM$3:$GM$400,0),1),"") | GO3: =IFERROR(INDEX($GD$3:$GM$400,MATCH(ROWS($GO$3:GO3),$GM$3:$GM$400,0),8),"") | GP3: =IFERROR(INDEX($GD$3:$GM$400,MATCH(ROWS($GP$3:GP3),$GM$3:$GM$400,0),9),"") | GQ3: =IF(AND(AE3="sp dare/avere",SUMIFS(dare_grezzo,den_grezzo,"="&AA3,data_grezzo,">="&INIZIO_A_PC,data_grezzo,"<="&FINE_AC)>SUMIFS(avere_grezzo,den_grezzo,"="&AA3,data_grezzo,">="&INIZIO_A_PC,data_grezzo,"<="&FINE_AC)),"SP DARE",IF(AND(AE3="sp dare/avere",SUMIFS(dare_grezzo,den_grezzo,"="&AA3,data_grezzo,">="&INIZIO_A_PC,data_grezzo,"<="&FINE_AC)<SUMIFS(avere_grezzo,den_grezzo,"="&AA3,data_grezzo,">="&INIZIO_A_PC,data_grezzo,"<="&FINE_AC)),"SP AVERE",0)) -> 0 | GR3: =IF(AND(FQ3>0,ROW()=FU3),"epilogo a Conto economico",0) -> 0 | GS3: =IF(AND(ROW()-2>=$GC$1,ROW()-2<=$GK$1),"epilogo a Conto economico",IF(AND(ROW()-2>=$GD$1,ROW()-2<=$GL$1),"epilogo a Conto economico",IF(AND(ROW()-2>=$GE$1,ROW()-2<=$GN$1),"chiusura del conto",IF(AND(ROW()-2>=$GF$1,ROW()-2<=$GL$1),"epilogo a Conto economico",IF(ROW()-2=$GA$3,"epilogo componenti positivi",IF(ROW()-2=$GA$4,"epilogo componenti negativi",IF(AND(ROW()-2>=$GA$7,ROW()-2<=$GA$8),"rilevato utile d'esercizio",IF(AND(ROW()-2>=$GA$5,ROW()-2<=$GA$6),"rilevata perdita d'esercizio",IF(AND(ROW()-2>=$GA$9,ROW()-2<=$GA$10),"capitalizzato l'utile conseguito",IF(AND(ROW()-2>=$GA$11,ROW()-2<=$GA$12),"coperta perdita d'esercizio",IF(ROW()-2=$GA$13,"prelevamenti extragestione",IF(ROW()-2=$GA$15,"giro ritenute subite",IF(OR(ROW()-2=$GA$14,ROW()-2=$GA$16),"giro a patrimonio netto",IF(ROW()-2=$GA$17,"totale attività",IF(ROW()-2=$GA$18,"totale passività",IF(ROW()-2=$GA$19,"chiusura del conto",IF(ROW()-2=$GA$20,"patrimonio netto finale",""))))))))))))))))) -> epilogo a Conto economico | GT3: =IFERROR(INDEX($GD$3:$GS$400,MATCH(ROWS($GT$3:GT3),$GM$3:$GM$400,0),16),"") | GU3: =IF(GQ3<>0,MAX($GU$2:$GU2)+1,0) -> 0 | GV3: =IF(GU3<>0,AA3,0) -> 0 | GW3: =IF(AND(IFERROR(INDEX($GU$3:$GV$400,MATCH(ROWS($GW$3:GW3),$GU$3:$GU$400,0),2),"")<>"",GW4<>""),CONCATENATE(IFERROR(INDEX($GU$3:$GV$400,MATCH(ROWS($GW$3:GW3),$GU$3:$GU$400,0),2),"")," - "),IFERROR(INDEX($GU$3:$GV$400,MATCH(ROWS($GW$3:GW3),$GU$3:$GU$400,0),2),"")) | GX3: =IF(OR(GN3="IVA NS/CREDITO",GN3="IVA NS/DEBITO",GN3="IVA C/ACCONTO",GN3="IMPOSTE C/ACCONTO"),MAX($GX$2:GX2)+1,0) -> 0 | GY3: =IF(AND(IFERROR(INDEX($GN$3:$GX$200,MATCH(ROWS($GY$3:GY3),$GX$3:$GX$200,0),1),"")<>"",GY4<>""),CONCATENATE(IFERROR(INDEX($GN$3:$GX$200,MATCH(ROWS($GY$3:GY3),$GX$3:$GX$200,0),1),"")," - "),IFERROR(INDEX($GN$3:$GX$200,MATCH(ROWS($GY$3:GY3),$GX$3:$GX$200,0),1),"")) | GZ3: 01.00 | HA3: IMMOBILIZZAZIONI IMMATERIALI | HL3: =IFERROR(IF(INDEX(PIANO_DEI_CONTI,MATCH($BB3,DENOMINAZIONE,0),6)="SP dare",$BB3,IF(AND(INDEX(PIANO_DEI_CONTI,MATCH($BB3,DENOMINAZIONE,0),6)="SP DARE/AVERE",$BD3>=$BE3),$BB3,"")),"") | HM3: =IFERROR(IF(AND(INDEX(PIANO_DEI_CONTI,MATCH($BB3,DENOMINAZIONE,0),6)="SP AVERE",$BB3<>"PATRIMONIO NETTO"),$BB3,IF(AND(INDEX(PIANO_DEI_CONTI,MATCH($BB3,DENOMINAZIONE,0),6)="SP DARE/AVERE",$BD3<=$BE3),$BB3,"")),"") | HN3: =IFERROR(IF(AND(INDEX(PIANO_DEI_CONTI,MATCH($BB3,DENOMINAZIONE,0),6)="SP AVERE",$BB3="PATRIMONIO NETTO"),$BB3,""),"") | HO3: =IF(HL3<>"",MAX($HO$2:HO2)+1,0) -> 0 | HP3: =IF(HM3<>"",MAX($HP$2:HP2)+1,0) -> 0 | HQ3: =IF(HN3<>"",MAX($HQ$2:HQ2)+1,0) -> 0 | HR3: =IF($HL$2=0,"",IF(AND(ROW()-2=$HL$2+1,$HL$2<>0),"BILANCIO DI APERTURA",IF(AND(ROW()-2=$HL$2+2,$HL$2<>0,$HM$2>0),"BILANCIO DI APERTURA",IF(AND(ROW()-2=$HL$2+2+$HM$2+1,$HM$2<>0),"BILANCIO DI APERTURA",IF(AND(ROW()-2=$HL$2+2,$HM$2=0),"BILANCIO DI APERTURA",""))))) | HS3: =CONCATENATE(HL3,HM3,HN3) | HT3: =HO3+HP3+HQ3 -> 0 | HU3: =IF(HR3="BILANCIO DI APERTURA",ROW()-2,0) -> 0 | HV3: =CONCATENATE(IFERROR(INDEX($HS$3:$HT$102,MATCH(ROWS($HV$3:HV3),$HT$3:$HT$102,0),1),""),HR3) | IA3: pab | IB3: B)_Immobilizzazioni | IC3: =IFERROR(INDEX(PIANO_DEI_CONTI,MATCH(ROWS(DL$3:DL3),$DK$3:DK230,0),2),0) -> 0 | ID3: =IFERROR(IF(AND(DL3<>"",$DM3>$DN3,OR($DM3>0,$DN3>0)),$DM3-$DN3,0),0) -> 0 | IE3: =IFERROR(IF(AND(DL3<>"",$DM3<$DN3,OR($DM3>0,$DN3>0)),$DN3-$DM3,0),0) -> 0 | IF3: =IFERROR(INDEX($AA$3:$EC$200,MATCH(IC3,$AA$3:$AA$200,0),106),"") -> 0 | IG3: =IF(IG7>0,"",0) -> 0 | IH3: =IF(IG3<>0,MAX($IH$2:IH2)+1,0) -> 0 | II3: =IF($AD3="costi pluriennali",MAX($II$2:II2)+1,0) -> 1 | IJ3: =IF($AD3="rettifiche costi pluriennali",MAX($IJ$2:IJ2)+1,0) -> 0 | IK3: =MAX(II3,IJ3) -> 1 | IL3: =IF(IK3>0,AA3,"") -> COSTI DI IMPIANTO | IM3: =IFERROR(INDEX($IC$3:$IK$200,MATCH(IL3,$IC$3:$IC$200,0),2),0) -> 0 | IN3: =IFERROR(INDEX($IC$3:$IK$200,MATCH(IL3,$IC$3:$IC$200,0),3),0) -> 0 | IO3: =SUMIFS($IM$3:$IM$200,$IK$3:$IK$200,ROWS($IO$3:IO3))-SUMIFS($IN$3:$IN$200,$IK$3:$IK$200,ROWS($IO$3:IO3)) -> 0 | IP3: =IF(IO3<0,INDEX($IJ$3:$IL$200,MATCH(ROWS($IP$3:IP3),$IJ$3:$IJ$200,0),3),"") | IQ3: =IF(IP3<>"",MAX($IQ$2:IQ2)+1,0) -> 0 | IR3: =IFERROR(INDEX($IP$3:$IQ$200,MATCH(ROWS($IR$3:IR3),$IQ$3:$IQ$200,0),1),"") | IS3: =IF(AND($HM$2>0,SUM($FJ$3:$FJ$120)<>0,ROW()-2=$HP$2-1),SUM($FJ$3:$FJ$120),IF(AND($HM$2=0,SUM($FJ$3:$FJ$120)<>0,ROW()-2=$HP$2),SUM($FJ$3:$FJ$120),"")) | IT3: =IF(AND(ROW()-2=$HP$2,SUM($FK$3:$FK$120)<>0),SUM($FK$3:$FK$120),"") | IU3: =IF(ROW()-2=$HQ$2,SUM($IS$3:$IS$200)-SUM($IT$3:$IT$200),"") -> 0 | IV3: =IFERROR(IF(INDEX($FG$3:$HV$200,MATCH($HV3,$FG$3:$FG$200,0),4)=0,"",INDEX($FG$3:$HV$200,MATCH($HV3,$FG$3:$FG$200,0),4)),"") | IW3: =IFERROR(IF(INDEX($FG$3:$HV$200,MATCH($HV3,$FG$3:$FG$200,0),5)=0,"",INDEX($FG$3:$HV$200,MATCH($HV3,$FG$3:$FG$200,0),5)),"") | IX3: =IF(SUM(IV3,IT3,IU3)=0,"",SUM(IV3,IT3,IU3)) | IY3: =IF(SUM(IW3,IS3)=0,"",SUM(IW3,IS3)) | IZ3: =IF(AND(IX3="",IY3=""),"",IF(OR(IV3<>"",IW3<>""),"apertura del conto",IF(IS3<>"","totale attività",IF(IT3<>"","totale passività",IF(IU3<>"","patrimonio netto iniziale",""))))) | JA3: =IF(EY3>0,YEAR(EY3),"") | JB3: =IFERROR(INDEX(PIANO_DEI_CONTI,MATCH(EZ3,DENOMINAZIONE,0),5),"") -> 0 | JC3: =IF(OR(AND(FB3<0,FC3<0),FB3<0,FC3<0),1,0) -> 0 | JE3: =IFERROR(INDEX(LIBRO_GIORNALE!$N$11:$O$408,MATCH(ROWS($JE$2:JE2),LIBRO_GIORNALE!$O$11:$O$408,0),1),0) -> 0 | JF3: =UPPER(IFERROR(INDEX($EX$103:$EZ$400,MATCH(JE3,$EX$103:$EX$400,0),3),0)) -> 0 | JG3: =IF(EXACT(JF3,JF2),0,IF($JG$1=1,IFERROR(MATCH($JF3,$CV$3:$CV$220,0),0),0)) -> 0 | JH3: =IF(JJ3>0,0,MAX($JH$2:JH2)+1) -> 1 | JI3: =IF(JG3>0,MAX($JI$2:JI2)+1,0) -> 0 | JJ3: =IFERROR(INDEX($JG$3:$JI$124,MATCH(ROWS($JJ$3:JJ3),$JI$3:$JI$124,0),1),0) -> 0 | JK3: =IFERROR(IF(JH3>0,MATCH(JH3,$JJ$3:$JJ$124,0),0),0) -> 0 | JL3: =IF(JK3=0,JH3,0) -> 1 | JM3: RIGHE TRA I PROSPETTI
A4: =GZ4 -> 01.01 | B4: =HA4 -> COSTI DI IMPIANTO | C4: =HB4 -> E | D4: =HC4 -> D | E4: =HD4 -> COSTI PLURIENNALI | F4: =HE4 -> SP DARE | G4: =IF(EI4=TRUE,1,0) -> 1 | H4: =IF(EJ4=TRUE,1,0) -> 1 | I4: =IF(EK4=TRUE,1,0) -> 1 | J4: 1 | K4: =IFERROR(IF($I$1=1,INDEX($AA$3:$AS$220,MATCH(ROWS($K$3:K4),$AQ$3:$AQ$220,0),1),IF($I$1=2,INDEX($AA$3:$AS$220,MATCH(ROWS($K$3:K4),$AR$3:$AR$220,0),1),IF($I$1=3,INDEX($AA$3:$AS$220,MATCH(ROWS($K$3:K4),$AS$3:$AS$220,0),1),""))),"") -> BREVETTI | L4: =IF(AND($L$1="VISUALIZZA TUTTI I CONTI",K4<>""),MAX(L3:L3)+1,IFERROR(IF($J$1=1,IF(INDEX(PIANO_DEI_CONTI,MATCH($K4,DENOMINAZIONE,0),5)=$L$1,MAX($L$2:L3)+1,0),IF($J$1=2,IF(INDEX(PIANO_DEI_CONTI,MATCH($K4,DENOMINAZIONE,0),7)=$L$1,MAX($L$2:L3)+1,0))),0)) -> 2 | M4: =IFERROR(INDEX($K$3:$K$220,MATCH(ROWS($M$3:M4),$L$3:$L$220,0),1),"") -> BREVETTI | N4: COSTI PLURIENNALI | O4: =IFERROR(IF(AND($J$1=1,$I$1=3,INDEX($AV$3:$AV$220,MATCH(N4,$AV$3:$AV$220,0),1)=N4),N4,IF(AND($J$1=1,$I$1=2,INDEX($AU$3:$AU$220,MATCH(N4,$AU$3:$AU$220,0),1)=N4),N4,IF(AND($J$1=1,$I$1=1,INDEX($AT$3:$AT$220,MATCH(N4,$AT$3:$AT$220,0),1)=N4),N4,""))),"") | P4: =IF(AND(N4=O4,O4<>""),MAX(P$2:P3)+1,0) -> 0 | Q4: =IF(IFERROR(INDEX($O$3:$P$220,MATCH(ROWS(Q$3:Q4),$P$3:$P$220,0),1),"")=0,"",IFERROR(INDEX($O$3:$P$220,MATCH(ROWS(Q$3:Q4),$P$3:$P$220,0),1),"")) -> IMMOBILIZZAZIONI IMMATERIALI | R4: =IF(OR(INDEX(PIANO_DEI_CONTI,MATCH(AA4,DENOMINAZIONE,0),6)="SP DARE",INDEX(PIANO_DEI_CONTI,MATCH(AA4,DENOMINAZIONE,0),6)="SP DARE/AVERE"),AA4,"") -> BREVETTI | S4: =IF(IFERROR(MATCH(R4,DENOMINAZIONE_GIORNALE,0),0)>0,MAX(S$2:S3)+1,0) -> 0 | T4: =IFERROR(INDEX($R$3:$S$220,MATCH(ROWS($T$3:T4),$S$3:$S$220,0),1),"") | U4: =IFERROR(IF(IF(AND(OR(INDEX(PIANO_DEI_CONTI,MATCH(T4,DENOMINAZIONE,0),6)="SP DARE",INDEX(PIANO_DEI_CONTI,MATCH(T4,DENOMINAZIONE,0),6)="SP DARE/AVERE"),SUMIFS(DARE,DENOMINAZIONE_GIORNALE,T4,DARE,">"&0)>SUMIFS(AVERE,DENOMINAZIONE_GIORNALE,T4,AVERE,">"&0)),SUMIFS(DARE,DENOMINAZIONE_GIORNALE,T4,DARE,">"&0)-SUMIFS(AVERE,DENOMINAZIONE_GIORNALE,T4,AVERE,">"&0),0)<>0,IF(AND(OR(INDEX(PIANO_DEI_CONTI,MATCH(T4,DENOMINAZIONE,0),6)="SP DARE",INDEX(PIANO_DEI_CONTI,MATCH(T4,DENOMINAZIONE,0),6)="SP DARE/AVERE"),SUMIFS(DARE,DENOMINAZIONE_GIORNALE,T4,DARE,">"&0)>SUMIFS(AVERE,DENOMINAZIONE_GIORNALE,T4,AVERE,">"&0)),SUMIFS(DARE,DENOMINAZIONE_GIORNALE,T4,DARE,">"&0)-SUMIFS(AVERE,DENOMINAZIONE_GIORNALE,T4,AVERE,">"&0),0),0),0) -> 0 | V4: =IF(IF(U4<>0,MAX($V$2:V3)+1,0)=0,0,IF(U4<>0,MAX($V$2:V3)+1,0)) -> 0 | W4: =IF(MID(A4,3,3)=".00","",A4) -> 01.01 | X4: =IFERROR(INDEX($A$3:$B$220,MATCH(W4,$A$3:$A$220,0),2),"") -> COSTI DI IMPIANTO | Y4: =IF(W4="",0,MAX($Y$2:Y3)+1) -> 1 | Z4: =IFERROR(INDEX($W$3:$Y$220,MATCH(ROWS($Z$2:Z3),$Y$3:$Y$220,0),1),"") -> 01.03 | AA4: =IFERROR(INDEX($A$3:$I$220,MATCH($Z4,$A$3:$A$220,0),2),"") -> BREVETTI | AB4: =IFERROR(INDEX($A$3:$I$220,MATCH($Z4,$A$3:$A$220,0),3),"") -> E | AC4: =IFERROR(INDEX($A$3:$I$220,MATCH($Z4,$A$3:$A$220,0),4),"") -> D | AD4: =IFERROR(INDEX($A$3:$I$220,MATCH($Z4,$A$3:$A$220,0),5),"") -> COSTI PLURIENNALI | AE4: =IFERROR(INDEX($A$3:$I$220,MATCH($Z4,$A$3:$A$220,0),6),"") -> SP DARE | AF4: =AP4 -> IMMOBILIZZAZIONI IMMATERIALI | AG4: =IFERROR(INDEX($A$3:$I$220,MATCH($Z4,$A$3:$A$220,0),7),"") -> 1 | AH4: =IFERROR(INDEX($A$3:$I$220,MATCH($Z4,$A$3:$A$220,0),8),"") -> 1 | AI4: =IFERROR(INDEX($A$3:$I$220,MATCH($Z4,$A$3:$A$220,0),9),"") -> 1 | AJ4: =MID(Z4,1,2) -> 01 | AK4: =IF(MID($A4,3,3)=".00",MID(A4,1,2),"") | AL4: =IF(AK4<>"",MAX($AL$2:AL3)+1,0) -> 0 | AM4: =IFERROR(INDEX($AK$3:$AL$220,MATCH(ROWS($AM$3:AM4),$AL$3:$AL$220,0),1),"") -> 02 | AN4: =IF(AM4<>"",CONCATENATE(AM4,".00"),"") -> 02.00 | AO4: =IFERROR(INDEX($A$3:$B$220,MATCH(AN4,$A$3:$A$220,0),2),"") -> IMMOBILIZZAZIONI MATERIALI | AP4: =IFERROR(INDEX($AJ$3:$AP$220,MATCH(AJ4,$AM$3:$AM$220,0),6),"") -> IMMOBILIZZAZIONI IMMATERIALI | AQ4: =IF(OR(AG4=0,AG4=""),0,MAX(AQ$2:AQ3)+1) -> 2 | AR4: =IF(OR(AH4=0,AH4=""),0,MAX(AR$2:AR3)+1) -> 2 | AS4: =IF(OR(AI4=0,AI4=""),0,MAX(AS$2:AS3)+1) -> 2 | AT4: =IFERROR(INDEX($AD$3:$AS$220,MATCH(ROWS(AT$3:AT4),AQ$3:AQ$220,0),1),"") -> COSTI PLURIENNALI | AU4: =IFERROR(INDEX($AD$3:$AS$220,MATCH(ROWS(AU$3:AU4),AR$3:AR$220,0),1),"") -> COSTI PLURIENNALI | AV4: =IFERROR(INDEX($AD$3:$AS$220,MATCH(ROWS(AV$3:AV4),AS$3:AS$220,0),1),"") -> COSTI PLURIENNALI | AW4: =IFERROR(INDEX($AP$3:$AS$220,MATCH(ROWS(AW$3:AW4),AQ$3:AQ$220,0),1),"") -> IMMOBILIZZAZIONI IMMATERIALI | AX4: =IFERROR(INDEX($AP$3:$AS$220,MATCH(ROWS(AX$3:AX4),AR$3:AR$220,0),1),"") -> IMMOBILIZZAZIONI IMMATERIALI | AY4: =IFERROR(INDEX($AP$3:$AS$220,MATCH(ROWS(AY$3:AY4),AS$3:AS$220,0),1),"") -> IMMOBILIZZAZIONI IMMATERIALI | AZ4: =IF(BA4=0,"",CONCATENATE(ROW()-2," A.")) | BA4: =IF(BB4<>0,INIZIO_AC,0) -> 0 | BB4: =IFERROR(INDEX($FG$3:$FL$400,MATCH(ROWS($BB$3:BB4),$FL$3:$FL$400,0),1),0) -> 0 | BC4: =IF(BB4<>0,"apertura del conto","") | BD4: =IFERROR(INDEX($FG$3:$FL$400,MATCH(ROWS($BD$3:BD4),$FL$3:$FL$400,0),4),0) -> 0 | BE4: =IFERROR(INDEX($FG$3:$FL$400,MATCH(ROWS($BE$3:BE4),$FL$3:$FL$400,0),5),0) -> 0 | BF4: PER ECCEDENZE | BG4: =IFERROR(IF(OR(INDEX(PIANO_DEI_CONTI,MATCH(AA4,DENOMINAZIONE,0),6)="SP AVERE",INDEX(PIANO_DEI_CONTI,MATCH(AA4,DENOMINAZIONE,0),6)="SP DARE/AVERE"),AA4,""),0) | BH4: =IF(IFERROR(MATCH(BG4,DENOMINAZIONE_GIORNALE,0),0)>0,MAX(BH$2:BH3)+1,0) -> 0 | BI4: =IFERROR(INDEX($BG$3:$BH$220,MATCH(ROWS($BI$3:BI4),$BH$3:$BH$220,0),1),"") | BJ4: =IF(IF(AND(OR(INDEX(PIANO_DEI_CONTI,MATCH(BI4,DENOMINAZIONE,0),6)="SP AVERE",INDEX(PIANO_DEI_CONTI,MATCH(BI4,DENOMINAZIONE,0),6)="SP DARE/AVERE"),SUMIFS(AVERE,DENOMINAZIONE_GIORNALE,BI4,AVERE,">"&0)>SUMIFS(DARE,DENOMINAZIONE_GIORNALE,BI4,DARE,">"&0)),SUMIFS(AVERE,DENOMINAZIONE_GIORNALE,BI4,AVERE,">"&0)-SUMIFS(DARE,DENOMINAZIONE_GIORNALE,BI4,DARE,">"&0),0)<>0,IF(AND(OR(INDEX(PIANO_DEI_CONTI,MATCH(BI4,DENOMINAZIONE,0),6)="SP AVERE",INDEX(PIANO_DEI_CONTI,MATCH(BI4,DENOMINAZIONE,0),6)="SP DARE/AVERE"),SUMIFS(AVERE,DENOMINAZIONE_GIORNALE,BI4,AVERE,">"&0)>SUMIFS(DARE,DENOMINAZIONE_GIORNALE,BI4,DARE,">"&0)),SUMIFS(AVERE,DENOMINAZIONE_GIORNALE,BI4,AVERE,">"&0)-SUMIFS(DARE,DENOMINAZIONE_GIORNALE,BI4,DARE,">"&0),0),"") | BK4: =IF(IF(BJ4<>"",MAX($BK$2:BK3)+1,0)=0,"",IF(BJ4<>"",MAX($BK$2:BK3)+1,0)) | BL4: =IFERROR(INDEX($T$3:$U$220, MATCH(ROWS(BL$3:BL4),$V$3:$V$220,0),1),"") | BM4: =IFERROR(INDEX($T$3:$U$220, MATCH(ROWS(BM$3:BM4),$V$3:$V$220,0),2),"") | BN4: =IF(IFERROR(INDEX($BI$3:$BJ$220,MATCH(ROWS(BN$3:BN4),$BK$3:$BK$220,0),1),"")="PATRIMONIO NETTO","",IFERROR(INDEX($BI$3:$BJ$220,MATCH(ROWS(BN$3:BN4),$BK$3:$BK$220,0),1),"")) | BO4: =IFERROR(INDEX($BI$3:$BJ$220,MATCH(ROWS(BO$3:BO4),$BK$3:$BK$220,0),2),"") | BP4: =IF(BN4<>"",MAX(BP$2:$BP3)+1,0) -> 0 | BQ4: =IFERROR(INDEX($BN$3:$BO$200,MATCH(ROWS(BQ$3:BQ4),$BP$3:$BP$220,0),1),"") | BR4: =IFERROR(INDEX($BN$3:$BO$220,MATCH(ROWS(BR$3:BR4),$BP$3:$BP$220,0),2),"") | BS4: =IFERROR(IF(OR(INDEX($T$3:$U$220,MATCH(ROWS(BL$3:BL4),$V$3:$V$220,0),1)="PRELEVAMENTI EXTRAGESTIONE",INDEX($T$3:$U$220,MATCH(ROWS(BL$3:BL4),$V$3:$V$220,0),1)="TITOLARE C/RITENUTE SUBITE"),"",INDEX($T$3:$U$220,MATCH(ROWS(BL$3:BL4),$V$3:$V$220,0),1)),"") | BT4: =INDEX($T$3:$U$220,MATCH(BS4,$T$3:$T$220,0),2) -> 0 | BU4: =IF(BS4<>"",MAX(BU$2:BU3)+1,0) -> 0 | BV4: =IFERROR(INDEX($BS$3:$BT$223,MATCH(ROWS(BV$3:BV4),$BU$3:$BU$223,0),1),"") | BW4: =INDEX($BS$3:$BT$220,MATCH(BV4,$BS$3:$BS$223,0),2) -> 0 | BX4: =IF($EV$1>0,"",IF($EO$1=TRUE,SUBSTITUTE(IF(OR($DS$231<>$DT$231,$DS$232<>$DT$232,$DU$231<>$DV$231),"",IF($BX$1=0,"",IF((ROW()-2)=MAX($BV$2:$BW$2)+1,"TOTALE PASSIVITÀ",IF((ROW()-2)=MAX($BV$2:$BW$2)+2,"PATRIMONIO NETTO",IF(AND((ROW()-2)=MAX($BV$2,$BW$2)+3,$CM$1>$CP$1,$DU$231=$DV$231),"SALDO ECONOMICO POSITIVO",IF(AND((ROW()-2)=MAX($BV$2,$BW$2)+4,$CM$1>$CP$1,$DU$231=$DV$231),"TOTALE",IF(AND((ROW()-2)=MAX($BV$2,$BW$2)+4,$CM$1<$CP$1,$DU$231=$DV$231,$BY$1=0,$BZ$1>0,$BX$1>0),"TOTALE",IF(AND((ROW()-2)=MAX($BV$2,$BW$2)+3,$CM$1=$CP$1,$DU$231=$DV$231,$BY$1>0,$BZ$1=0,$BX$1>0),"TOTALE",IF(AND((ROW()-2)=MAX($BV$2,$BW$2)+3,$CM$1=$CP$1,$DU$231=$DV$231,$BY$1=0,$BZ$1>0,$BX$1>0),"TOTALE",IF(AND((ROW()-2)=MAX($BV$2,$BW$2)+3,$CM$1=$CP$1,$DU$231=$DV$231,$BY$1=0,$BZ$1=0,$BX$1>0),"TOTALE A PAREGGIO",IF(AND((ROW()-2)=MAX($BV$2,$BW$2)+4,$CM$1=$CP$1,$DU$231=$DV$231,$BY$1>0,$BZ$1>0,$BX$1>0),"TOTALE",IF(AND((ROW()-2)=MAX($BV$2,$BW$2)+3,$CM$1=$CP$1,$DU$231=$DV$231,$BY$1=0,$BY$1>0,$BZ$1=0,$BX$1>0),"TOTALE",IF(AND((ROW()-2)=MAX($BV$2,$BW$2)+4,$CM$1<$CP$1,$DU$231=$DV$231,$BY$1>0,$BZ$1=0),"TOTALE",IF(AND((ROW()-2)=MAX($BV$2,$BW$2)+5,$CM$1<$CP$1,$DU$231=$DV$231,$BY$1>0,$BZ$1>0),"TOTALE",IF(AND((ROW()-2)=MAX($BV$2,$BW$2)+3,$CM$1<$CP$1,$DU$231=$DV$231,$BY$1=0,$BZ$1=0),"TOTALE",IF(AND((ROW()-2)=MAX($BV$2,$BW$2)+3,$CM$1=0,$CP$1=0,$DU$231=$DV$231,$BY$1=0,$BZ$1=0),"TOTALE",IF(AND((ROW()-2)=MAX($BV$2,$BW$2)+4,$CM$1=$CP$1,$DU$231=$DV$231,$BY$1>0,$BZ$1>0),"TOTALE",""))))))))))))))))),"SALDO ECONOMICO POSITIVO","UTILE D'ESERCIZIO"),IF(OR($DS$231<>$DT$231,$DS$232<>$DT$232,$DU$231<>$DV$231),"",IF($BX$1=0,"",IF((ROW()-2)=MAX($BV$2:$BW$2)+1,"TOTALE PASSIVITÀ",IF((ROW()-2)=MAX($BV$2:$BW$2)+2,"PATRIMONIO NETTO",IF(AND((ROW()-2)=MAX($BV$2,$BW$2)+3,$CM$1>$CP$1,$DU$231=$DV$231),"SALDO ECONOMICO POSITIVO",IF(AND((ROW()-2)=MAX($BV$2,$BW$2)+4,$CM$1>$CP$1,$DU$231=$DV$231),"TOTALE",IF(AND((ROW()-2)=MAX($BV$2,$BW$2)+4,$CM$1<$CP$1,$DU$231=$DV$231,$BY$1=0,$BZ$1>0,$BX$1>0),"TOTALE",IF(AND((ROW()-2)=MAX($BV$2,$BW$2)+3,$CM$1=$CP$1,$DU$231=$DV$231,$BY$1>0,$BZ$1=0,$BX$1>0),"TOTALE",IF(AND((ROW()-2)=MAX($BV$2,$BW$2)+3,$CM$1=$CP$1,$DU$231=$DV$231,$BY$1=0,$BZ$1>0,$BX$1>0),"TOTALE",IF(AND((ROW()-2)=MAX($BV$2,$BW$2)+3,$CM$1=$CP$1,$DU$231=$DV$231,$BY$1=0,$BZ$1=0,$BX$1>0),"TOTALE A PAREGGIO",IF(AND((ROW()-2)=MAX($BV$2,$BW$2)+4,$CM$1=$CP$1,$DU$231=$DV$231,$BY$1>0,$BZ$1>0,$BX$1>0),"TOTALE",IF(AND((ROW()-2)=MAX($BV$2,$BW$2)+3,$CM$1=$CP$1,$DU$231=$DV$231,$BY$1=0,$BY$1>0,$BZ$1=0,$BX$1>0),"TOTALE",IF(AND((ROW()-2)=MAX($BV$2,$BW$2)+4,$CM$1<$CP$1,$DU$231=$DV$231,$BY$1>0,$BZ$1=0),"TOTALE",IF(AND((ROW()-2)=MAX($BV$2,$BW$2)+5,$CM$1<$CP$1,$DU$231=$DV$231,$BY$1>0,$BZ$1>0),"TOTALE",IF(AND((ROW()-2)=MAX($BV$2,$BW$2)+3,$CM$1<$CP$1,$DU$231=$DV$231,$BY$1=0,$BZ$1=0),"TOTALE",IF(AND((ROW()-2)=MAX($BV$2,$BW$2)+3,$CM$1=0,$CP$1=0,$DU$231=$DV$231,$BY$1=0,$BZ$1=0),"TOTALE",IF(AND((ROW()-2)=MAX($BV$2,$BW$2)+4,$CM$1=$CP$1,$DU$231=$DV$231,$BY$1>0,$BZ$1>0),"TOTALE",""))))))))))))))))))) | BY4: =IF($EV$1>0,"",IF($EO$1=TRUE,SUBSTITUTE(IF(OR($BB$1<>$BD$1,$BC$1<>$BE$1,$DS$231<>$DT$231,$DS$232<>$DT$232,$DU$231<>$DV$231),"",IF($BX$1=0,"",IF(AND((ROW()-2)=MAX($BV$2:$BW$2)+1,OR($BY$1>0,$BZ$1>0,$CP$1>$CM$1)),"TOTALE ATTIVITÀ",IF(AND((ROW()-2)=MAX($BV$2:$BW$2)+2,$BY$1>0),"PRELEVAMENTI EXTRAGESTIONE",IF(AND((ROW()-2)=MAX($BV$2:$BW$2)+2,$BY$1=0,$BZ$1>0),"TITOLARE C/RITENUTE SUBITE",IF(AND((ROW()-2)=MAX($BV$2:$BW$2)+3,$BY$1>0,$BZ$1>0),"TITOLARE C/RITENUTE SUBITE",IF(AND((ROW()-2)=MAX($BV$2:$BW$2)+2,$BY$1=0,$BZ$1=0,$CP$1>$CM$1),"SALDO ECONOMICO NEGATIVO",IF(AND((ROW()-2)=MAX($BV$2:$BW$2)+3,$BY$1>0,$BZ$1=0,$CP$1>$CM$1),"SALDO ECONOMICO NEGATIVO",IF(AND((ROW()-2)=MAX($BV$2:$BW$2)+3,$BY$1=0,$BZ$1>0,$CP$1>$CM$1),"SALDO ECONOMICO NEGATIVO",IF(AND((ROW()-2)=MAX($BV$2:$BW$2)+4,$BY$1>0,$BZ$1>0,$CP$1>$CM$1),"SALDO ECONOMICO NEGATIVO",IF(AND((ROW()-2)=MAX($BV$2:$BW$2)+3,$BY$1=0,$BZ$1=0,$CP$1>$CM$1),"TOTALE",IF(AND((ROW()-2)=MAX($BV$2:$BW$2)+4,$BY$1>0,$BZ$1=0,$CP$1<$CM$1),"TOTALE",IF(AND((ROW()-2)=MAX($BV$2:$BW$2)+4,$BY$1=0,$BZ$1>0,$CP$1<$CM$1),"TOTALE",IF(AND((ROW()-2)=MAX($BV$2:$BW$2)+4,$BY$1>0,$BZ$1=0,$CP$1>$CM$1),"TOTALE",IF(AND((ROW()-2)=MAX($BV$2:$BW$2)+4,BX2>0,BY$1=0,$BZ$1>0,$CP$1>$CM$1),"TOTALE",IF(AND((ROW()-2)=MAX($BV$2:$BW$2)+3,BX2>0,BY$1=0,$BZ$1=0,$CP$1=$CM$1),"TOTALE ATTIVITÀ",IF(AND((ROW()-2)=MAX($BV$2:$BW$2)+4,$BX$1>0,$BY$1>0,$BZ$1>0,$CP$1=$CM$1),"TOTALE",IF(AND((ROW()-2)=MAX($BV$2:$BW$2)+3,$BX$1>0,$BY$1=0,$BZ$1>0,$CP$1=$CM$1),"TOTALE",IF(AND((ROW()-2)=MAX($BV$2:$BW$2)+3,$BX$1>0,$BY$1>0,$BZ$1=0,$CP$1=$CM$1),"TOTALE",IF(AND((ROW()-2)=MAX($BV$2:$BW$2)+4,$BX$1>0,$BY$1>0,$BZ$1>0,$CP$1<$CM$1),"TOTALE",IF(AND((ROW()-2)=MAX($BV$2:$BW$2)+4,$BY$1=0,$BZ$1=0,$CP$1<$CM$1),"TOTALE",IF(AND((ROW()-2)=MAX($BV$2:$BW$2)+5,$BY$1>0,$BZ$1>0,$CP$1>$CM$1),"TOTALE",IF(AND((ROW()-2)=MAX($BV$2:$BW$2)+3,$BY$1=0,$BZ$1=0,$CP$1=0,$CM$1=0),"TOTALE",IF(AND((ROW()-2)=MAX($BV$2:$BW$2)+4,$BY$1>0,$BZ$1>0,$CP$1>0,$CM$1>0,$CP$1=$CM$1),"TOTALE","")))))))))))))))))))))))),"SALDO ECONOMICO NEGATIVO","PERDITA D'ESERCIZIO"),IF(OR($BB$1<>$BD$1,$BC$1<>$BE$1,$DS$231<>$DT$231,$DS$232<>$DT$232,$DU$231<>$DV$231),"",IF($BX$1=0,"",IF(AND((ROW()-2)=MAX($BV$2:$BW$2)+1,OR($BY$1>0,$BZ$1>0,$CP$1>$CM$1)),"TOTALE ATTIVITÀ",IF(AND((ROW()-2)=MAX($BV$2:$BW$2)+2,$BY$1>0),"PRELEVAMENTI EXTRAGESTIONE",IF(AND((ROW()-2)=MAX($BV$2:$BW$2)+2,$BY$1=0,$BZ$1>0),"TITOLARE C/RITENUTE SUBITE",IF(AND((ROW()-2)=MAX($BV$2:$BW$2)+3,$BY$1>0,$BZ$1>0),"TITOLARE C/RITENUTE SUBITE",IF(AND((ROW()-2)=MAX($BV$2:$BW$2)+2,$BY$1=0,$BZ$1=0,$CP$1>$CM$1),"SALDO ECONOMICO NEGATIVO",IF(AND((ROW()-2)=MAX($BV$2:$BW$2)+3,$BY$1>0,$BZ$1=0,$CP$1>$CM$1),"SALDO ECONOMICO NEGATIVO",IF(AND((ROW()-2)=MAX($BV$2:$BW$2)+3,$BY$1=0,$BZ$1>0,$CP$1>$CM$1),"SALDO ECONOMICO NEGATIVO",IF(AND((ROW()-2)=MAX($BV$2:$BW$2)+4,$BY$1>0,$BZ$1>0,$CP$1>$CM$1),"SALDO ECONOMICO NEGATIVO",IF(AND((ROW()-2)=MAX($BV$2:$BW$2)+3,$BY$1=0,$BZ$1=0,$CP$1>$CM$1),"TOTALE",IF(AND((ROW()-2)=MAX($BV$2:$BW$2)+4,$BY$1>0,$BZ$1=0,$CP$1<$CM$1),"TOTALE",IF(AND((ROW()-2)=MAX($BV$2:$BW$2)+4,$BY$1=0,$BZ$1>0,$CP$1<$CM$1),"TOTALE",IF(AND((ROW()-2)=MAX($BV$2:$BW$2)+4,$BY$1>0,$BZ$1=0,$CP$1>$CM$1),"TOTALE",IF(AND((ROW()-2)=MAX($BV$2:$BW$2)+4,BX2>0,BY$1=0,$BZ$1>0,$CP$1>$CM$1),"TOTALE",IF(AND((ROW()-2)=MAX($BV$2:$BW$2)+3,BX2>0,BY$1=0,$BZ$1=0,$CP$1=$CM$1),"TOTALE ATTIVITÀ",IF(AND((ROW()-2)=MAX($BV$2:$BW$2)+4,$BX$1>0,$BY$1>0,$BZ$1>0,$CP$1=$CM$1),"TOTALE",IF(AND((ROW()-2)=MAX($BV$2:$BW$2)+3,$BX$1>0,$BY$1=0,$BZ$1>0,$CP$1=$CM$1),"TOTALE",IF(AND((ROW()-2)=MAX($BV$2:$BW$2)+3,$BX$1>0,$BY$1>0,$BZ$1=0,$CP$1=$CM$1),"TOTALE",IF(AND((ROW()-2)=MAX($BV$2:$BW$2)+4,$BX$1>0,$BY$1>0,$BZ$1>0,$CP$1<$CM$1),"TOTALE",IF(AND((ROW()-2)=MAX($BV$2:$BW$2)+4,$BY$1=0,$BZ$1=0,$CP$1<$CM$1),"TOTALE",IF(AND((ROW()-2)=MAX($BV$2:$BW$2)+5,$BY$1>0,$BZ$1>0,$CP$1>$CM$1),"TOTALE",IF(AND((ROW()-2)=MAX($BV$2:$BW$2)+3,$BY$1=0,$BZ$1=0,$CP$1=0,$CM$1=0),"TOTALE",IF(AND((ROW()-2)=MAX($BV$2:$BW$2)+4,$BY$1>0,$BZ$1>0,$CP$1>0,$CM$1>0,$CP$1=$CM$1),"TOTALE","")))))))))))))))))))))))))) | BZ4: =IFERROR(IF(OR($DS$231<>$DT$231,$DU$231<>$DV$231,$EO$25<>0,$EO$26<>0),INDEX($T$3:$V$220,MATCH(ROWS($BV$3:BV4),$V$3:$V$220,0),1),CONCATENATE(BV4,BY4)),"") | CA4: =IFERROR(INDEX($BV$3:$BW$225,MATCH(BZ4,$BV$3:$BV$225,0),2),INDEX($BL$3:$BW$225,MATCH(BZ4,$BL$3:$BL$225,0),2)) -> 0 | CB4: =IFERROR(IF(OR($BB$1<>$BD$1,$BC$1<>$BE$1,$DS$231<>$DT$231,$DU$231<>$DV$231,$EO$25<>0,$EO$26<>0),INDEX($BI$3:$BK$220,MATCH(ROWS($CB$3:CB4),$BK$3:$BK$220,0),1),CONCATENATE(BQ4,BX4)),"") | CC4: =INDEX($BQ$3:$BR$225,MATCH(CB4,$BQ$3:$BQ$225,0),2) | CD4: =IF(INDEX(PIANO_DEI_CONTI,MATCH(AA4,DENOMINAZIONE,0),6)="SE DARE",AA4,"") | CE4: =IF(IFERROR(MATCH(CD4,DENOMINAZIONE_GIORNALE,0),0)>0,MAX(CE$2:CE3)+1,0) -> 0 | CF4: =IFERROR(INDEX($CD$3:$CE$220,MATCH(ROWS($CF$3:CF4),$CE$3:$CE$220,0),1),"") | CG4: =IF(AND(INDEX(PIANO_DEI_CONTI,MATCH(CF4,DENOMINAZIONE,0),6)="SE DARE",SUMIFS(DARE,DENOMINAZIONE_GIORNALE,CF4)>SUMIFS(AVERE,DENOMINAZIONE_GIORNALE,CF4)),SUMIFS(DARE,DENOMINAZIONE_GIORNALE,CF4)-SUMIFS(AVERE,DENOMINAZIONE_GIORNALE,CF4),0) -> 0 | CH4: =IF(IF(CG4<>0,MAX($CH$2:CH3)+1,0)=0,"",IF(CG4<>"",MAX($CH$2:CH3)+1,0)) | CI4: =IFERROR(INDEX($CF$3:$CG$220,MATCH(ROWS($CI$3:CI4),$CH$3:$CH$220,0),1),"") | CJ4: =IFERROR(IF(INDEX($CF$3:$CG$220,MATCH(CI4,$CF$3:$CF$220,0),2)=0,"",INDEX($CF$3:$CG$220,MATCH(CI4,$CF$3:$CF$220,0),2)),"") | CK4: =IF(INDEX(PIANO_DEI_CONTI,MATCH(AA4,DENOMINAZIONE,0),6)="SE AVERE",AA4,"") | CL4: =IF(IFERROR(MATCH(CK4,DENOMINAZIONE_GIORNALE,0),0)>0,MAX(CL$2:CL3)+1,0) -> 0 | CM4: =IFERROR(INDEX($CK$3:$CL$220,MATCH(ROWS($CM$3:CM4),$CL$3:$CL$220,0),1),"") | CN4: =IF(AND(INDEX(PIANO_DEI_CONTI,MATCH(CM4,DENOMINAZIONE,0),6)="SE AVERE",SUMIFS(AVERE,DENOMINAZIONE_GIORNALE,CM4,DATA,">="&$CX$1)>SUMIFS(DARE,DENOMINAZIONE_GIORNALE,CM4)),SUMIFS(AVERE,DENOMINAZIONE_GIORNALE,CM4)-SUMIFS(DARE,DENOMINAZIONE_GIORNALE,CM4),"") | CO4: =IF(IF(CN4<>0,MAX($CO$2:CO3)+1,0)=0,"",IF(CN4<>"",MAX($CO$2:CO3)+1,0)) -> 0 | CP4: =IFERROR(INDEX($CM$3:$CN$220,MATCH(ROWS(CP$3:CP4),$CO$3:$CO$220,0),1),"") | CQ4: =IFERROR(INDEX($CM$3:$CN$220,MATCH(ROWS(CQ$3:CQ4),$CO$3:$CO$220,0),2),"") | CR4: =IF($EV$1>0,"",IF($EO$1=TRUE,SUBSTITUTE(IF(OR($BX$1=0,$BB$1<>$BD$1,$BC$1<>$BE$1,$DS$232<>$DT$232,$EO$25<>0,$EO$26<>0),"",IFERROR(IF(AND(MATCH($BP$1,DENOMINAZIONE_GIORNALE,0)>0,$DU$231=$DV$231,$DS$231=$DT$231),IF(AND($CP$1>$CM$1,$CP$2>$CM$2,(ROW()-2)=$CP$2+3),"TOTALE COSTI",IF(AND($CP$1>$CM$1,$CM$2>=$CP$2,(ROW()-2)=$CM$2+3),"TOTALE COSTI",IF(AND($CP$1<$CM$1,$CP$2>=$CM$2,(ROW()-2)=$CP$2+1),"TOTALE COSTI",IF(AND($CP$1<$CM$1,$CP$2<$CM$2,ROW()-2=$CM$2+1),"TOTALE COSTI",IF(AND($CP$1=$CM$1,$DU$231=$DV$231,OR($CM$2>0,$CP$2>0),(ROW()-2)=MAX($CP$2,$CM$2)+1),"TOTALE COSTI",IF(AND($CM$1>$CP$1,$CP$2>$CM$2,(ROW()-2)=$CP$2+2),"SALDO ECONOMICO POSITIVO",IF(AND($CM$1>$CP$1,$CM$2>=$CP$2,(ROW()-2)=$CM$2+2),"SALDO ECONOMICO POSITIVO",IF(AND($CM$1>$CP$1,$CP$2>$CM$2,(ROW()-2)=$CP$2+3),"TOTALE A PAREGGIO",IF(AND($CM$1>$CP$1,$CM$2>=$CP$2,(ROW()-2)=$CM$2+3),"TOTALE A PAREGGIO",""))))))))),""),"")),"SALDO ECONOMICO POSITIVO","UTILE D'ESERCIZIO"),IF(OR($BX$1=0,$BB$1<>$BD$1,$BC$1<>$BE$1,$DS$232<>$DT$232,$EO$25<>0,$EO$26<>0),"",IFERROR(IF(AND(MATCH($BP$1,DENOMINAZIONE_GIORNALE,0)>0,$DU$231=$DV$231,$DS$231=$DT$231),IF(AND($CP$1>$CM$1,$CP$2>$CM$2,(ROW()-2)=$CP$2+3),"TOTALE COSTI",IF(AND($CP$1>$CM$1,$CM$2>=$CP$2,(ROW()-2)=$CM$2+3),"TOTALE COSTI",IF(AND($CP$1<$CM$1,$CP$2>=$CM$2,(ROW()-2)=$CP$2+1),"TOTALE COSTI",IF(AND($CP$1<$CM$1,$CP$2<$CM$2,ROW()-2=$CM$2+1),"TOTALE COSTI",IF(AND($CP$1=$CM$1,$DU$231=$DV$231,OR($CM$2>0,$CP$2>0),(ROW()-2)=MAX($CP$2,$CM$2)+1),"TOTALE COSTI",IF(AND($CM$1>$CP$1,$CP$2>$CM$2,(ROW()-2)=$CP$2+2),"SALDO ECONOMICO POSITIVO",IF(AND($CM$1>$CP$1,$CM$2>=$CP$2,(ROW()-2)=$CM$2+2),"SALDO ECONOMICO POSITIVO",IF(AND($CM$1>$CP$1,$CP$2>$CM$2,(ROW()-2)=$CP$2+3),"TOTALE A PAREGGIO",IF(AND($CM$1>$CP$1,$CM$2>=$CP$2,(ROW()-2)=$CM$2+3),"TOTALE A PAREGGIO",""))))))))),""),"")))) | CS4: =SUMIFS(DARE,DENOMINAZIONE_GIORNALE,AA4,DARE,">"&0) -> 0 | CT4: =SUMIFS(AVERE,DENOMINAZIONE_GIORNALE,AA4,AVERE,">"&0) -> 0 | CU4: =IF(OR(CS4>0,CT4>0),MAX($CU$2:CU3)+1,0) -> 0 | CV4: =IFERROR(INDEX(PIANO_DEI_CONTI,MATCH(ROWS($CV$3:CV4),$CU$3:$CU$200,0),2),"") | CW4: =IFERROR(IF(CV4<>"",MAX($CW$2:CW3)+1,0),0) -> 0 | CX4: =$EA$3 -> 1 | CY4: =IF(ISERROR(INDEX($CV$3:$CX$2300,MATCH(CX4,$CW$3:$CW$2300,0),1)),"MASTRO",INDEX($CV$3:$CX$2300,MATCH(CX4,$CW$3:$CW$2300,0),1)) -> MASTRO | DA4: =IF(DB3="","","Num. riga") | DB4: =IF(DB3="","","Data") | DC4: =IF(DB3="","","Operazioni") | DD4: =IF(DB3="","","Dare ") | DE4: =IF(DB3="","","Avere ") | DF4: =IF(AND(CX4=$DE$2,$DF$2<>0),0,IF(AND(DB4<>"",OR(DB3<>"",DB5<>"")),MAX($DF$2:DF3)+1,0)) -> 0 | DG4: =IF(OR(VALORI_INIZIALI!E9="",AND(VALORI_INIZIALI!E9<>"",VALORI_INIZIALI!H9=0,VALORI_INIZIALI!I9=0)),"",IFERROR(INDEX(PIANO_DEI_CONTI,MATCH(BB4,DENOMINAZIONE,0),1),0)) | DH4: =IFERROR(IF($J$1=1,IF(INDEX(PIANO_DEI_CONTI,MATCH($K4,DENOMINAZIONE,0),5)=$DF$1,MAX($DH$2:DH3)+1,0),IF($J$1=2,IF(INDEX(PIANO_DEI_CONTI,MATCH($K4,DENOMINAZIONE,0),7)=$DF$1,MAX($DH$2:DH3)+1,0))),0) -> 0 | DI4: =IFERROR(INDEX($K$3:$K$220,MATCH(ROWS($DI$3:DI4),$DH$3:$DH$220,0),1),0) -> 0 | DJ4: =IF(IFERROR(MATCH(AA4,DENOMINAZIONE_GIORNALE,0),0)<>0,ROW()-2,0) -> 0 | DK4: =IF(DJ4=0,0,MAX(DK$2:DK3)+1) -> 0 | DL4: =IFERROR(INDEX(PIANO_DEI_CONTI,MATCH(ROWS(DL$3:DL4),$DK$3:DK231,0),2),0) -> 0 | DM4: =IFERROR(IF(AND(INDEX(PIANO_DEI_CONTI,MATCH($DL4,DENOMINAZIONE,0),4)="D",SUMIFS(DARE,DENOMINAZIONE_GIORNALE,$DL4)>=SUMIFS(AVERE,DENOMINAZIONE_GIORNALE,$DL4)),SUMIFS(DARE,DENOMINAZIONE_GIORNALE,$DL4),IF(AND(INDEX(PIANO_DEI_CONTI,MATCH($DL4,DENOMINAZIONE,0),4)="A",SUMIFS(AVERE,DENOMINAZIONE_GIORNALE,$DL4)>=SUMIFS(DARE,DENOMINAZIONE_GIORNALE,$DL4)),SUMIFS(DARE,DENOMINAZIONE_GIORNALE,$DL4),IF(INDEX(PIANO_DEI_CONTI,MATCH($DL4,DENOMINAZIONE,0),4)="D/A",SUMIFS(DARE,DENOMINAZIONE_GIORNALE,$DL4),0))),0) -> 0 | DN4: =IFERROR(IF(AND(INDEX(PIANO_DEI_CONTI,MATCH($DL4,DENOMINAZIONE,0),4)="D",SUMIFS(DARE,DENOMINAZIONE_GIORNALE,$DL4)>=SUMIFS(AVERE,DENOMINAZIONE_GIORNALE,$DL4)),SUMIFS(AVERE,DENOMINAZIONE_GIORNALE,$DL4),IF(AND(INDEX(PIANO_DEI_CONTI,MATCH($DL4,DENOMINAZIONE,0),4)="A",SUMIFS(AVERE,DENOMINAZIONE_GIORNALE,$DL4)>=SUMIFS(DARE,DENOMINAZIONE_GIORNALE,$DL4)),SUMIFS(AVERE,DENOMINAZIONE_GIORNALE,$DL4),IF(INDEX(PIANO_DEI_CONTI,MATCH($DL4,DENOMINAZIONE,0),4)="D/A",SUMIFS(AVERE,DENOMINAZIONE_GIORNALE,$DL4),0))),0) -> 0 | DO4: =IF(AND(DL4<>"",$DM4>$DN4,OR($DM4>0,$DN4>0)),$DM4-$DN4,0) -> 0 | DP4: =IF(AND(DL4<>"",$DM4<$DN4,OR($DM4>0,$DN4>0)),$DN4-$DM4,0) -> 0 | DQ4: =IF(OR($DQ$1="TOTALI",$DQ$1="TOTALI ED ECCEDENZE"),IF(OR(DM4>0,DN4>0),MAX(DQ$2:DQ3)+1,0),IF($DQ$1="ECCEDENZE",IF(OR(DO4>0,DP4>0),MAX(DQ$2:DQ3)+1,0),"")) -> 0 | DR4: =IFERROR(INDEX($DL$3:$DQ$230,MATCH(ROWS(DR$3:DR4),$DQ$3:$DQ$230,0),1),"") | DS4: =IFERROR(IF($DQ$1="eccedenze",INDEX($DL$3:$DP$230,MATCH($DR4,$DL$3:$DL$230,0),4),IF(OR($DQ$1="totali",$DQ$1="TOTALI ED ECCEDENZE"),INDEX($DL$3:$DP$230,MATCH($DR4,$DL$3:$DL$230,0),2),"")),"") | DT4: =IFERROR(IF($DQ$1="eccedenze",INDEX($DL$3:$DP$230,MATCH($DR4,$DL$3:$DL$230,0),5),IF(OR($DQ$1="totali",$DQ$1="TOTALI ED ECCEDENZE"),INDEX($DL$3:$DP$230,MATCH($DR4,$DL$3:$DL$230,0),3),"")),"") | DU4: =IF(AND($DR4<>"",$DS4>$DT4,$DQ$1="TOTALI ED ECCEDENZE",OR($DS4>0,$DT4>0)),$DS4-$DT4,IF(DS4=DT4,"","")) | DV4: =IF(AND($DR4<>"",$DS4<$DT4,$DQ$1="TOTALI ED ECCEDENZE",OR($DS4>0,$DT4>0)),$DT4-$DS4,IF(DT4=DS4,"","")) | DW4: =IF(OR(AND(DR4<>"",$DQ$1="TOTALI ED ECCEDENZE"),AND(DX4="TOTALI",$DQ$1="TOTALI ED ECCEDENZE")),1,0) -> 0 | DX4: =IF($EV$1>0,"",IF((ROW()-2)=$DW$1+1,IF(AND(MATCH("PATRIMONIO NETTO",$DR$3:$DR$230,0)>0,$BB$1=$BD$1,$BC$1=$BE$1,$DS$231=$DT$231,$EO$25=0,$EO$26=0),"TOTALI",""),"")) | DY4: =IF($DX4="TOTALI",$DS$231,"") | DZ4: =IF(IF($DX4="TOTALI",$DU$231,"")=0,"",IF($DX4="TOTALI",$DU$231,"")) | EA4: =SUM(JJ4,JL4) -> 2 | EB4: pab1 | ED4: =IFERROR(INDEX(PIANO_DEI_CONTI,MATCH(BB4,DENOMINAZIONE,0),5),"") -> 0 | EE4: =IF($EV$1>0,"",IF(AND(IF(OR($BX$1=0,$BB$1<>$BD$1,$BC$1<>$BE$1,$DS$232<>$DT$232,$EO$25<>0,$EO$26<>0),"",IFERROR(IF(AND(MATCH($BP$1,DENOMINAZIONE_GIORNALE,0)>0,$DU$231=$DV$231,$DS$231=$DT$231),IF(AND($CP$1>$CM$1,$CP$2>$CM$2,(ROW()-2)=$CP$2+3),"TOTALE A PAREGGIO",IF(AND($CP$1>$CM$1,$CM$2>=$CP$2,(ROW()-2)=$CM$2+3),"TOTALE A PAREGGIO",IF(AND($CP$1>$CM$1,$CM$2>=$CP$2,(ROW()-2)=$CM$2+1),"TOTALE RICAVI",IF(AND($CP$1>$CM$1,$CP$2>=$CM$2,(ROW()-2)=$CP$2+1),"TOTALE RICAVI",IF(AND($CP$1>$CM$1,$CP$2<$CM$2,ROW()-2=$CM$2+3),"TOTALE RICAVI",IF(AND($DU$231=$DV$231,$CP$1=$CM$1,OR($CM$2>0,$CP$2>0),(ROW()-2)=MAX($CM$2,$CP$2)+1),"TOTALE RICAVI",IF(AND($CM$1<$CP$1,$CP$2>$CM$2,(ROW()-2)=$CP$2+2),"SALDO ECONOMICO NEGATIVO",IF(AND($CM$1<$CP$1,$CM$2>=$CP$2,(ROW()-2)=$CM$2+2),"SALDO ECONOMICO NEGATIVO",IF(AND($CM$1>$CP$1,$CP$2>$CM$2,(ROW()-2)=$CP$2+3),"TOTALE RICAVI",IF(AND($CM$1>$CP$1,$CM$2>=$CP$2,(ROW()-2)=$CM$2+3),"TOTALE RICAVI","")))))))))),""),""))="SALDO ECONOMICO NEGATIVO",$EO$1=TRUE),SUBSTITUTE(IF($DS$232<>$DT$232,"",IFERROR(IF(AND(MATCH($BP$1,DENOMINAZIONE_GIORNALE,0)>0,$DU$231=$DV$231,$DS$231=$DT$231),IF(AND($CP$1>$CM$1,$CP$2>$CM$2,(ROW()-2)=$CP$2+3),"TOTALE A PAREGGIO",IF(AND($CP$1>$CM$1,$CM$2>=$CP$2,(ROW()-2)=$CM$2+3),"TOTALE A PAREGGIO",IF(AND($CP$1>$CM$1,$CM$2>=$CP$2,(ROW()-2)=$CM$2+1),"TOTALE RICAVI",IF(AND($CP$1>$CM$1,$CP$2>=$CM$2,(ROW()-2)=$CP$2+1),"TOTALE RICAVI",IF(AND($CP$1>$CM$1,$CP$2<$CM$2,ROW()-2=$CM$2+3),"TOTALE RICAVI",IF(AND($DU$231=$DV$231,$CP$1=$CM$1,OR($CM$2>0,$CP$2>0),(ROW()-2)=MAX($CP$2,$CM$2)+1),"TOTALE RICAVI",IF(AND($CM$1<$CP$1,$CP$2>$CM$2,(ROW()-2)=$CP$2+2),"SALDO ECONOMICO NEGATIVO",IF(AND($CM$1<$CP$1,$CM$2>=$CP$2,(ROW()-2)=$CM$2+2),"SALDO ECONOMICO NEGATIVO",IF(AND($CM$1>$CP$1,$CP$2>$CM$2,(ROW()-2)=$CP$2+3),"TOTALE RICAVI",IF(AND($CM$1>$CP$1,$CM$2>=$CP$2,(ROW()-2)=$CM$2+3),"TOTALE RICAVI","")))))))))),""),"")),"SALDO ECONOMICO NEGATIVO","PERDITA D'ESERCIZIO"),IF(OR($BX$1=0,$BB$1<>$BD$1,$BC$1<>$BE$1,$DS$232<>$DT$232,$EO$25<>0,$EO$26<>0),"",IFERROR(IF(AND(MATCH($BP$1,DENOMINAZIONE_GIORNALE,0)>0,$DU$231=$DV$231,$DS$231=$DT$231),IF(AND($CP$1>$CM$1,$CP$2>$CM$2,(ROW()-2)=$CP$2+3),"TOTALE A PAREGGIO",IF(AND($CP$1>$CM$1,$CM$2>=$CP$2,(ROW()-2)=$CM$2+3),"TOTALE A PAREGGIO",IF(AND($CP$1>$CM$1,$CM$2>=$CP$2,(ROW()-2)=$CM$2+1),"TOTALE RICAVI",IF(AND($CP$1>$CM$1,$CP$2>=$CM$2,(ROW()-2)=$CP$2+1),"TOTALE RICAVI",IF(AND($CP$1>$CM$1,$CP$2<$CM$2,ROW()-2=$CM$2+3),"TOTALE RICAVI",IF(AND($DU$231=$DV$231,$CP$1=$CM$1,OR($CM$2>0,$CP$2>0),(ROW()-2)=MAX($CP$2,$CM$2)+1),"TOTALE RICAVI",IF(AND($CM$1<$CP$1,$CP$2>$CM$2,(ROW()-2)=$CP$2+2),"SALDO ECONOMICO NEGATIVO",IF(AND($CM$1<$CP$1,$CM$2>=$CP$2,(ROW()-2)=$CM$2+2),"SALDO ECONOMICO NEGATIVO",IF(AND($CM$1>$CP$1,$CP$2>$CM$2,(ROW()-2)=$CP$2+3),"TOTALE RICAVI",IF(AND($CM$1>$CP$1,$CM$2>=$CP$2,(ROW()-2)=$CM$2+3),"TOTALE RICAVI","")))))))))),""),"")))) | EF4: =IF(EE4="TOTALE RICAVI",$CM$1,IF(EE4="PERDITA D'ESERCIZIO",$CP$1-$CM$1,IF(EE4="SALDO ECONOMICO NEGATIVO",$CP$1-$CM$1,IF(EE4="TOTALE A PAREGGIO",$CP$1,"")))) | EG4: =IF(CR4="TOTALE COSTI",$CP$1,IF(CR4="TOTALE A PAREGGIO",$CM$1,IF(OR(CR4="SALDO ECONOMICO POSITIVO",CR4="UTILE D'ESERCIZIO"),$CM$1-$CP$1,""))) | EH4: =CP4 | EI4: =IF(INDIRECT(ADDRESS(ROW()+4,1,,,"PIANO_DEI_CONTI"))="X",TRUE,FALSE) -> TRUE | EJ4: =IF(INDIRECT(ADDRESS(ROW()+4,2,,,"PIANO_DEI_CONTI"))="X",TRUE,FALSE) -> TRUE | EK4: =IF(INDIRECT(ADDRESS(ROW()+4,3,,,"PIANO_DEI_CONTI"))="X",TRUE,FALSE) -> TRUE | EL4: =ROW()-2 -> 2 | EM4: =IF(AND(BA4>0,BA4<=$EM$1),MAX($EM$2:EM3)+1,0) -> 0 | EN4: =IF(EM4=$EL$1,ROW(),0) -> 4 | EP4: =IFERROR(INDEX(PIANO_DEI_CONTI,MATCH(EZ4,DENOMINAZIONE,0),7),"") | EQ4: =IF(AND(EZ4<>0,EY4<=FINE_AC),INDEX(PIANO_DEI_CONTI,MATCH(EZ4,DENOMINAZIONE,0),1),0) -> 0 | ER4: =IF(ISNA(EQ4),MAX(ER$2:ER3)+1,0) -> 0 | ES4: =IF(ER4>=1,EZ4,"") | ET4: =IFERROR(UPPER(INDEX($ER$3:$ES$500,MATCH(ROWS(ET$3:ET4),$ER$3:$ER$500,0),2)),"") | EU4: La denominazione di tutti i conti sia corretta | EV4: =IF(EQ2>0,MAX($EV$3:EV3)+1,0) -> 0 | EW4: =IF(AND(IFERROR(INDEX($EU$3:$EV$30,MATCH(ROWS($EX$3:EX4),$EV$3:$EV$30,0),1),"")<>"",EW5<>""),CONCATENATE(IFERROR(INDEX($EU$3:$EV$30,MATCH(ROWS($EX$3:EX4),$EV$3:$EV$30,0),1),"")," - "),IFERROR(INDEX($EU$3:$EV$30,MATCH(ROWS($EX$3:EX4),$EV$3:$EV$30,0),1),"")) | EY4: =INDIRECT(ADDRESS(ROW()+5,COLUMN()-151,,,"VALORI_INIZIALI")) -> 0 | EZ4: =INDIRECT(ADDRESS(ROW()+5,COLUMN()-151,,,"VALORI_INIZIALI")) -> 0 | FA4: =IF(AND(CONCATENATE(INDIRECT(ADDRESS(ROW()+5,6,,,"VALORI_INIZIALI")),INDIRECT(ADDRESS(ROW()+5,7,,,"VALORI_INIZIALI")))="",EZ4<>0),"manca la descrizione dell'operazione",CONCATENATE(INDIRECT(ADDRESS(ROW()+5,6,,,"VALORI_INIZIALI")),INDIRECT(ADDRESS(ROW()+5,7,,,"VALORI_INIZIALI")))) | FB4: =IF(EZ4=0,0,ROUND(INDIRECT(ADDRESS(ROW()+5,COLUMN()-150,,,"VALORI_INIZIALI")),2)) -> 0 | FC4: =IF(EZ4=0,0,ROUND(INDIRECT(ADDRESS(ROW()+5,COLUMN()-150,,,"VALORI_INIZIALI")),2)) -> 0 | FD4: =IFERROR(INDEX(PIANO_DEI_CONTI,MATCH(EZ4,DENOMINAZIONE,0),6),"") -> 0 | FE4: =IFERROR(IF(EZ4<>0,INDEX(PIANO_DEI_CONTI,MATCH(EZ4,DENOMINAZIONE,0),1),""),"") | FF4: =IF(EZ4<>0,CONCATENATE(ROW()-2," V.I."),"") | FG4: =IF(AND(MID(AE4,1,2)="SP",AA4<>"PATRIMONIO NETTO",AA4<>"TITOLARE C/RITENUTE SUBITE",AA4<>"PRELEVAMENTI EXTRAGESTIONE"),AA4,"") -> BREVETTI | FH4: =IF(AND(INDEX(PIANO_DEI_CONTI,MATCH($FG4,DENOMINAZIONE,0),4)="D",SUMIFS(dare_grezzo,den_grezzo,$FG4,data_grezzo,"<"&INIZIO_AC,data_grezzo,">="&INIZIO_A_PC)>=SUMIFS(avere_grezzo,den_grezzo,$FG4,data_grezzo,"<"&INIZIO_AC,data_grezzo,">="&INIZIO_A_PC)),SUMIFS(dare_grezzo,den_grezzo,$FG4,data_grezzo,"<"&INIZIO_AC,data_grezzo,">="&INIZIO_A_PC),IF(AND(INDEX(PIANO_DEI_CONTI,MATCH($FG4,DENOMINAZIONE,0),4)="A",SUMIFS(avere_grezzo,den_grezzo,$FG4,data_grezzo,"<"&INIZIO_AC,data_grezzo,">="&INIZIO_A_PC)>=SUMIFS(dare_grezzo,den_grezzo,$FG4,data_grezzo,"<"&INIZIO_AC,data_grezzo,">="&INIZIO_A_PC)),SUMIFS(dare_grezzo,den_grezzo,$FG4,data_grezzo,"<"&INIZIO_AC,data_grezzo,">="&INIZIO_A_PC),IF(INDEX(PIANO_DEI_CONTI,MATCH($FG4,DENOMINAZIONE,0),4)="D/A",SUMIFS(dare_grezzo,den_grezzo,$FG4,data_grezzo,"<"&INIZIO_AC,data_grezzo,">="&INIZIO_A_PC),0))) -> 0 | FI4: =IFERROR(IF(AND(INDEX(PIANO_DEI_CONTI,MATCH($FG4,DENOMINAZIONE,0),4)="D",SUMIFS(dare_grezzo,den_grezzo,$FG4,data_grezzo,"<"&INIZIO_AC,data_grezzo,">="&INIZIO_A_PC)>=SUMIFS(avere_grezzo,den_grezzo,$FG4,data_grezzo,"<"&INIZIO_AC,data_grezzo,">="&INIZIO_A_PC)),SUMIFS(avere_grezzo,den_grezzo,$FG4,data_grezzo,"<"&INIZIO_AC,data_grezzo,">="&INIZIO_A_PC),IF(AND(INDEX(PIANO_DEI_CONTI,MATCH($FG4,DENOMINAZIONE,0),4)="A",SUMIFS(avere_grezzo,den_grezzo,$FG4,data_grezzo,"<"&INIZIO_AC,data_grezzo,">="&INIZIO_A_PC)>=SUMIFS(dare_grezzo,den_grezzo,$FG4,data_grezzo,"<"&INIZIO_AC,data_grezzo,">="&INIZIO_A_PC)),SUMIFS(avere_grezzo,den_grezzo,$FG4,data_grezzo,"<"&INIZIO_AC,data_grezzo,">="&INIZIO_A_PC),IF(INDEX(PIANO_DEI_CONTI,MATCH($FG4,DENOMINAZIONE,0),4)="D/A",SUMIFS(avere_grezzo,den_grezzo,$FG4,data_grezzo,"<"&INIZIO_AC,data_grezzo,">="&INIZIO_A_PC),0))),0) -> 0 | FJ4: =IF(AND(FG4<>"",$FH4>$FI4,OR($FH4>0,$FI4>0)),$FH4-$FI4,0) -> 0 | FK4: =IF(AND($FG4<>"",$FI4>$FH4,OR($FH4>0,$FI4>0)),$FI4-$FH4,0) -> 0 | FL4: =IF(OR(FJ4>0,FK4>0),MAX($FL$2:FL3)+1,0) -> 0 | FM4: =IF(AND(AC4="d",AE4="SP DARE"),SUMIFS(dare_grezzo,den_grezzo,AA4,data_grezzo,"<="&FINE_AC,data_grezzo,">="&INIZIO_A_PC)-SUMIFS(avere_grezzo,den_grezzo,AA4,data_grezzo,"<="&FINE_AC,data_grezzo,">="&INIZIO_A_PC),IF(AND(AC4="a",AE4="SP AVERE"),SUMIFS(avere_grezzo,den_grezzo,AA4,data_grezzo,"<="&FINE_AC,data_grezzo,">="&INIZIO_A_PC)-SUMIFS(dare_grezzo,den_grezzo,AA4,data_grezzo,"<="&FINE_AC,data_grezzo,">="&INIZIO_A_PC),IF(AND(AC4="d",AE4="SE DARE"),SUMIFS(dare_grezzo,den_grezzo,AA4,data_grezzo,"<="&FINE_AC,data_grezzo,">="&INIZIO_A_PC)-SUMIFS(avere_grezzo,den_grezzo,AA4,data_grezzo,"<="&FINE_AC,data_grezzo,">="&INIZIO_A_PC),IF(AND(AC4="a",AE4="SE AVERE"),SUMIFS(avere_grezzo,den_grezzo,AA4,data_grezzo,"<="&FINE_AC,data_grezzo,">="&INIZIO_A_PC)-SUMIFS(dare_grezzo,den_grezzo,AA4,data_grezzo,"<="&FINE_AC,data_grezzo,">="&INIZIO_A_PC),0)))) -> 0 | FN4: =IF(FM4<0,MAX($FN$2:FN3)+1,0) -> 0 | FO4: =IF(FM4<0,AA4,"") | FP4: =IFERROR(INDEX($FN$3:$FO$400,MATCH(ROWS($FP$3:FP4),$FN$3:$FN$400,0),2),"") | FQ4: =IF(AE4="SE AVERE",MAX($FQ$2:FQ3)+1,"") | FR4: =IF(AE4="SE DARE",MAX($FR$2:FR3)+1,"") | FS4: =IF(AND(AE4="SP DARE",AA4<>$FS$1,AA4<>$FT$1),MAX($FS$2:FS3)+1,IF(AND(GQ4="SP DARE",AA4<>$FS$1,AA4<>$FT$1),MAX($FS$2:FS3)+1,"")) -> 91 | FT4: =IF(AND(AE4="SP AVERE",AA4<>$FU$1),MAX($FT$2:FT3)+1,IF(AND(GQ4="SP AVERE",AA4<>$FU$1),MAX($FT$2:FT3)+1,"")) | FU4: =SUM(FQ4:FT4) -> 91 | FV4: =AA4 -> BREVETTI | FW4: =IFERROR(INDEX($FU$3:$FV$500,MATCH(ROWS($FW$3:FW4),$FU$3:$FU$500,0),2),0) -> MERCI C/VENDITE ON LINE | FX4: =IF(FW4<>0,ROW()-2,0) -> 2 | FY4: =IF(AND(ROW()<=$FX$1,FX4=0),ROW()-2,0) -> 0 | FZ4: =IF(FY4>0,MAX($FZ$2:FZ3)+1,0) -> 0 | GA4: =IFERROR(INDEX($FY$3:$FZ$500,MATCH(ROWS($GA$3:GA4),$FZ$3:$FZ$500,0),1),0) -> 21 | GB4: CONTO DI RISULTATO ECONOMICO | GC4: =FX4+FY4 -> 2 | GD4: =IFERROR(IF(FX4>0,FW4,INDEX($GA$3:$GB$400,MATCH(ROW()-2,$GA$3:$GA$400,0),2)),0) -> MERCI C/VENDITE ON LINE | GE4: =CP1 -> 0 | GG4: =IFERROR(INDEX($GA$3:$GF$400,MATCH(ROW()-2,$GA$3:$GA$400,0),5),0) -> 0 | GH4: =IFERROR(INDEX($GA$3:$GF$400,MATCH(ROW()-2,$GA$3:$GA$400,0),6),0) -> 0 | GI4: =IFERROR(INDEX($DL$3:$DP$400,MATCH($FW4,$DL$3:$DL$400,0),5),0) -> 0 | GJ4: =IFERROR(INDEX($DL$3:$DP$400,MATCH($FW4,$DL$3:$DL$400,0),4),0) -> 0 | GK4: =GG4+GI4 -> 0 | GL4: =GH4+GJ4 -> 0 | GM4: =IF(OR(GK4>0,GL4>0),MAX($GM$2:GM3)+1,0) -> 0 | GN4: =IFERROR(INDEX($GD$3:$GM$400,MATCH(ROWS($GN$3:GN4),$GM$3:$GM$400,0),1),"") | GO4: =IFERROR(INDEX($GD$3:$GM$400,MATCH(ROWS($GO$3:GO4),$GM$3:$GM$400,0),8),"") | GP4: =IFERROR(INDEX($GD$3:$GM$400,MATCH(ROWS($GP$3:GP4),$GM$3:$GM$400,0),9),"") | GQ4: =IF(AND(AE4="sp dare/avere",SUMIFS(dare_grezzo,den_grezzo,"="&AA4,data_grezzo,">="&INIZIO_A_PC,data_grezzo,"<="&FINE_AC)>SUMIFS(avere_grezzo,den_grezzo,"="&AA4,data_grezzo,">="&INIZIO_A_PC,data_grezzo,"<="&FINE_AC)),"SP DARE",IF(AND(AE4="sp dare/avere",SUMIFS(dare_grezzo,den_grezzo,"="&AA4,data_grezzo,">="&INIZIO_A_PC,data_grezzo,"<="&FINE_AC)<SUMIFS(avere_grezzo,den_grezzo,"="&AA4,data_grezzo,">="&INIZIO_A_PC,data_grezzo,"<="&FINE_AC)),"SP AVERE",0)) -> 0 | GR4: =IF(AND(FQ4>0,ROW()=FU4),"epilogo a Conto economico",0) -> 0 | GS4: =IF(AND(ROW()-2>=$GC$1,ROW()-2<=$GK$1),"epilogo a Conto economico",IF(AND(ROW()-2>=$GD$1,ROW()-2<=$GL$1),"epilogo a Conto economico",IF(AND(ROW()-2>=$GE$1,ROW()-2<=$GN$1),"chiusura del conto",IF(AND(ROW()-2>=$GF$1,ROW()-2<=$GL$1),"epilogo a Conto economico",IF(ROW()-2=$GA$3,"epilogo componenti positivi",IF(ROW()-2=$GA$4,"epilogo componenti negativi",IF(AND(ROW()-2>=$GA$7,ROW()-2<=$GA$8),"rilevato utile d'esercizio",IF(AND(ROW()-2>=$GA$5,ROW()-2<=$GA$6),"rilevata perdita d'esercizio",IF(AND(ROW()-2>=$GA$9,ROW()-2<=$GA$10),"capitalizzato l'utile conseguito",IF(AND(ROW()-2>=$GA$11,ROW()-2<=$GA$12),"coperta perdita d'esercizio",IF(ROW()-2=$GA$13,"prelevamenti extragestione",IF(ROW()-2=$GA$15,"giro ritenute subite",IF(OR(ROW()-2=$GA$14,ROW()-2=$GA$16),"giro a patrimonio netto",IF(ROW()-2=$GA$17,"totale attività",IF(ROW()-2=$GA$18,"totale passività",IF(ROW()-2=$GA$19,"chiusura del conto",IF(ROW()-2=$GA$20,"patrimonio netto finale",""))))))))))))))))) -> epilogo a Conto economico | GT4: =IFERROR(INDEX($GD$3:$GS$400,MATCH(ROWS($GT$3:GT4),$GM$3:$GM$400,0),16),"") | GU4: =IF(GQ4<>0,MAX($GU$2:$GU3)+1,0) -> 0 | GV4: =IF(GU4<>0,AA4,0) -> 0 | GW4: =IF(AND(IFERROR(INDEX($GU$3:$GV$400,MATCH(ROWS($GW$3:GW4),$GU$3:$GU$400,0),2),"")<>"",GW5<>""),CONCATENATE(IFERROR(INDEX($GU$3:$GV$400,MATCH(ROWS($GW$3:GW4),$GU$3:$GU$400,0),2),"")," - "),IFERROR(INDEX($GU$3:$GV$400,MATCH(ROWS($GW$3:GW4),$GU$3:$GU$400,0),2),"")) | GX4: =IF(OR(GN4="IVA NS/CREDITO",GN4="IVA NS/DEBITO",GN4="IVA C/ACCONTO",GN4="IMPOSTE C/ACCONTO"),MAX($GX$2:GX3)+1,0) -> 0 | GY4: =IF(AND(IFERROR(INDEX($GN$3:$GX$200,MATCH(ROWS($GY$3:GY4),$GX$3:$GX$200,0),1),"")<>"",GY5<>""),CONCATENATE(IFERROR(INDEX($GN$3:$GX$200,MATCH(ROWS($GY$3:GY4),$GX$3:$GX$200,0),1),"")," - "),IFERROR(INDEX($GN$3:$GX$200,MATCH(ROWS($GY$3:GY4),$GX$3:$GX$200,0),1),"")) | GZ4: 01.01 | HA4: COSTI DI IMPIANTO | HB4: E | HC4: D | HD4: COSTI PLURIENNALI | HE4: SP DARE | HL4: =IFERROR(IF(INDEX(PIANO_DEI_CONTI,MATCH($BB4,DENOMINAZIONE,0),6)="SP dare",$BB4,IF(AND(INDEX(PIANO_DEI_CONTI,MATCH($BB4,DENOMINAZIONE,0),6)="SP DARE/AVERE",$BD4>=$BE4),$BB4,"")),"") | HM4: =IFERROR(IF(AND(INDEX(PIANO_DEI_CONTI,MATCH($BB4,DENOMINAZIONE,0),6)="SP AVERE",$BB4<>"PATRIMONIO NETTO"),$BB4,IF(AND(INDEX(PIANO_DEI_CONTI,MATCH($BB4,DENOMINAZIONE,0),6)="SP DARE/AVERE",$BD4<=$BE4),$BB4,"")),"") | HN4: =IFERROR(IF(AND(INDEX(PIANO_DEI_CONTI,MATCH($BB4,DENOMINAZIONE,0),6)="SP AVERE",$BB4="PATRIMONIO NETTO"),$BB4,""),"") | HO4: =IF(HL4<>"",MAX($HO$2:HO3)+1,0) -> 0 | HP4: =IF(HM4<>"",MAX($HP$2:HP3)+1,0) -> 0 | HQ4: =IF(HN4<>"",MAX($HQ$2:HQ3)+1,0) -> 0 | HR4: =IF($HL$2=0,"",IF(AND(ROW()-2=$HL$2+1,$HL$2<>0),"BILANCIO DI APERTURA",IF(AND(ROW()-2=$HL$2+2,$HL$2<>0,$HM$2>0),"BILANCIO DI APERTURA",IF(AND(ROW()-2=$HL$2+2+$HM$2+1,$HM$2<>0),"BILANCIO DI APERTURA",IF(AND(ROW()-2=$HL$2+2,$HM$2=0),"BILANCIO DI APERTURA",""))))) | HS4: =CONCATENATE(HL4,HM4,HN4) | HT4: =HO4+HP4+HQ4 -> 0 | HU4: =IF(HR4="BILANCIO DI APERTURA",ROW()-2,0) -> 0 | HV4: =CONCATENATE(IFERROR(INDEX($HS$3:$HT$102,MATCH(ROWS($HV$3:HV4),$HT$3:$HT$102,0),1),""),HR4) | IA4: pab1 | IB4: _I___-_Immobilizzazioni immateriali | IC4: =IFERROR(INDEX(PIANO_DEI_CONTI,MATCH(ROWS(DL$3:DL4),$DK$3:DK231,0),2),0) -> 0 | ID4: =IFERROR(IF(AND(DL4<>"",$DM4>$DN4,OR($DM4>0,$DN4>0)),$DM4-$DN4,0),0) -> 0 | IE4: =IFERROR(IF(AND(DL4<>"",$DM4<$DN4,OR($DM4>0,$DN4>0)),$DN4-$DM4,0),0) -> 0 | IF4: =IFERROR(INDEX($AA$3:$EC$200,MATCH(IC4,$AA$3:$AA$200,0),106),"") -> 0 | IG4: =IF(SUMIFS($ID$3:$ID$200,$IF$3:$IF$200,IA4)>=SUMIFS($IE$3:$IE$200,$IF$3:$IF$200,IA4),ROUND(SUMIFS($ID$3:$ID$200,$IF$3:$IF$200,IA4)-SUMIFS($IE$3:$IE$200,$IF$3:$IF$200,IA4),0),0) -> 0 | IH4: =IF(IG4<>0,MAX($IH$2:IH3)+1,0) -> 0 | II4: =IF(AD4="costi pluriennali",MAX($II$2:II3)+1,0) -> 2 | IJ4: =IF($AD4="rettifiche costi pluriennali",MAX($IJ$2:IJ3)+1,0) -> 0 | IK4: =MAX(II4,IJ4) -> 2 | IL4: =IF(IK4>0,AA4,"") -> BREVETTI | IM4: =IFERROR(INDEX($IC$3:$IK$200,MATCH(IL4,$IC$3:$IC$200,0),2),0) -> 0 | IN4: =IFERROR(INDEX($IC$3:$IK$200,MATCH(IL4,$IC$3:$IC$200,0),3),0) -> 0 | IO4: =SUMIFS($IM$3:$IM$200,$IK$3:$IK$200,ROWS($IO$3:IO4))-SUMIFS($IN$3:$IN$200,$IK$3:$IK$200,ROWS($IO$3:IO4)) -> 0 | IP4: =IF(IO4<0,INDEX($IJ$3:$IL$200,MATCH(ROWS($IP$3:IP4),$IJ$3:$IJ$200,0),3),"") | IQ4: =IF(IP4<>"",MAX($IQ$2:IQ3)+1,0) -> 0 | IR4: =IFERROR(INDEX($IP$3:$IQ$200,MATCH(ROWS($IR$3:IR4),$IQ$3:$IQ$200,0),1),"") | IS4: =IF(AND($HM$2>0,SUM($FJ$3:$FJ$120)<>0,ROW()-2=$HP$2-1),SUM($FJ$3:$FJ$120),IF(AND($HM$2=0,SUM($FJ$3:$FJ$120)<>0,ROW()-2=$HP$2),SUM($FJ$3:$FJ$120),"")) | IT4: =IF(AND(ROW()-2=$HP$2,SUM($FK$3:$FK$120)<>0),SUM($FK$3:$FK$120),"") | IU4: =IF(ROW()-2=$HQ$2,SUM($IS$3:$IS$200)-SUM($IT$3:$IT$200),"") | IV4: =IFERROR(IF(INDEX($FG$3:$HV$200,MATCH($HV4,$FG$3:$FG$200,0),4)=0,"",INDEX($FG$3:$HV$200,MATCH($HV4,$FG$3:$FG$200,0),4)),"") | IW4: =IFERROR(IF(INDEX($FG$3:$HV$200,MATCH($HV4,$FG$3:$FG$200,0),5)=0,"",INDEX($FG$3:$HV$200,MATCH($HV4,$FG$3:$FG$200,0),5)),"") | IX4: =IF(SUM(IV4,IT4,IU4)=0,"",SUM(IV4,IT4,IU4)) | IY4: =IF(SUM(IW4,IS4)=0,"",SUM(IW4,IS4)) | IZ4: =IF(AND(IX4="",IY4=""),"",IF(OR(IV4<>"",IW4<>""),"apertura del conto",IF(IS4<>"","totale attività",IF(IT4<>"","totale passività",IF(IU4<>"","patrimonio netto iniziale",""))))) | JA4: =IF(EY4>0,YEAR(EY4),"") | JB4: =IFERROR(INDEX(PIANO_DEI_CONTI,MATCH(EZ4,DENOMINAZIONE,0),5),"") -> 0 | JC4: =IF(OR(AND(FB4<0,FC4<0),FB4<0,FC4<0),1,0) -> 0 | JE4: =IFERROR(INDEX(LIBRO_GIORNALE!$N$11:$O$408,MATCH(ROWS($JE$2:JE3),LIBRO_GIORNALE!$O$11:$O$408,0),1),0) -> 0 | JF4: =UPPER(IFERROR(INDEX($EX$103:$EZ$400,MATCH(JE4,$EX$103:$EX$400,0),3),0)) -> 0 | JG4: =IF(EXACT(JF4,JF3),0,IF($JG$1=1,IFERROR(MATCH($JF4,$CV$3:$CV$220,0),0),0)) -> 0 | JH4: =IF(JJ4>0,0,MAX($JH$2:JH3)+1) -> 2 | JI4: =IF(JG4>0,MAX($JI$2:JI3)+1,0) -> 0 | JJ4: =IFERROR(INDEX($JG$3:$JI$124,MATCH(ROWS($JJ$3:JJ4),$JI$3:$JI$124,0),1),0) -> 0 | JK4: =IFERROR(IF(JH4>0,MATCH(JH4,$JJ$3:$JJ$124,0),0),0) -> 0 | JL4: =IF(JK4=0,JH4,0) -> 2 | JM4: 1
